Workbook

Sheet 本版更新
A1: R2.00 更新重點
A2: 1 | B2: R2.00：核心條件改為四項 —— ① 21EMA 向上（EMA21 高過前一日同 5 日前）② 9EMA 在 21EMA 上方 ③ 一底高於一底（樞軸底遞升、最後一底 ≤30 日前）④ 形態接近上升三角：25 日重心 ≥0.5、低位斜率 >0、高位平至微升。「回到 9/21EMA」唔再係核心門檻，改為分頁條件。
A3: 2 | B3: 三個分頁（都係第一梯隊嘅子集、引用總表）：a 剛黃金交叉（5 日內金叉）15 隻；b 回到 21EMA（離 EMA21 ≤3% 兼 ≤0.75 ATR 或近 3 日觸及）10 隻；c 回到 9EMA（同樣口徑對 EMA9，離兩條都近就歸較近嗰條）76 隻。總表加咗 a／b／c 三欄 ✓。
A4: 3 | B4: 數據更新至 2026-10-01 收市（192 個交易日，2025-12-26 起；Yahoo 日線由 GitHub Actions 抓取）。
A5: 4 | B5: 合資格 2,791 隻 → C1 573 → C2 542 → C3 322 → C4 第一梯隊 100 隻（大型 26／中型 30／小型 43；平頂上升三角 30 隻）。第二梯隊（差一項）99 隻。
A6: 5 | B6: 排名：綜合分數 = 0.25 趨勢 + 0.25 回調質素 + 0.2 底部結構 + 0.3 三角形（每項 0–100，總表全部係公式）。頭五位：JILL（79）、PPIH（77）、MG（74）、HNGE（74）、TTMI（74）。
A7: 6 | B7: 市況：指數企喺高位、闊度極弱；加息周期中段，長債息 24 年新高、油價 $90 樓上 —— 偏防守，只做高 RS 嘅 9/21EMA 回調（市況頁有指數／ETF／商品／債息嘅 EMA 狀態、合資格股票池闊度、四大力量周期對標同領先指標觀察表）。
A8: 7 | B8: 頁：總表（兩個梯隊）、a 剛黃金交叉、b 回到21EMA、c 回到9EMA、大型股／中型股／小型股（引用總表）、差一項、樞軸底頂、篩選規則、市況、數據核對。所有代號連 TradingView；藍字係量度值、黑字係公式。
A9: 8 | B9: 產出：9EMA-Uptrend_Watchlist_R2.00_claudefable51xhigh_10.02_1658.xlsx（claudefable51xhigh = Claude Fable 5.1，effort xhigh；2026-10-02 16:58 香港時間）。

Sheet 總表
A1: 梯隊 | B1: 排名 | C1: 代號 | D1: 公司 | E1: 交易所 | F1: 板塊 | G1: 行業 | H1: 市值(十億美元) | I1: 市值組 | J1: 收市價 | K1: 前收 | L1: 當日% | M1: 當日高 | N1: 當日低 | O1: 成交量 | P1: 20日均量 | Q1: 量比 | R1: EMA9 | S1: EMA21 | T1: EMA21（5日前） | U1: EMA21 5日斜率% | V1: EMA21 10步上升比例 | W1: 距EMA9% | X1: 距EMA21% | Y1: ATR14 | Z1: ATR14% | AA1: 距EMA9（ATR倍） | AB1: 距EMA21（ATR倍） | AC1: 最接近 | AD1: 近3日低位觸及 | AE1: 9/21狀態 | AF1: a 剛金叉 | AG1: b 回到21EMA | AH1: c 回到9EMA | AI1: 金叉日期 | AJ1: 金叉後日數 | AK1: 連續上升底數目 | AL1: 最後一底日期 | AM1: 最後一底價 | AN1: 上一底價 | AO1: 底較底升% | AP1: 最後一底距今（日） | AQ1: 距最後一底% | AR1: 15日最高收市 | AS1: 距15日高% | AT1: 形態（25日） | AU1: 高位斜率（%/日） | AV1: 低位斜率（%/日） | AW1: 重心（VWAP在25日高低區間位置） | AX1: 重心（收市範圍） | AY1: 頂部觸及次數 | AZ1: 25日最高 | BA1: 25日最低 | BB1: 25日VWAP | BC1: 跌日／升日量比（10日） | BD1: 收市在當日區間位置 | BE1: RS21（對全池中位數）% | BF1: 21日回報% | BG1: 趨勢分數 | BH1: 回調質素 | BI1: 底部結構 | BJ1: 三角形分數 | BK1: 綜合分數 | BL1: 唔過嘅條件 | BM1: 備註
A2: 1 | B2: 1 | C2: JILL | D2: J. Jill Inc. | E2: NYSE | F2: 非必需消費 | G2: Apparel | H2: 0.362 | I2: 小型 | J2: 24.4 | K2: 24.37 | L2: =J2/K2-1 | M2: 24.77 | N2: 24.22 | O2: 390800 | P2: 248770 | Q2: =O2/P2 | R2: 24.1815 | S2: 23.1877 | T2: 22.4388 | U2: =S2/T2-1 | V2: 1 | W2: =J2/R2-1 | X2: =J2/S2-1 | Y2: 0.9668 | Z2: =Y2/J2 | AA2: =(J2-R2)/Y2 | AB2: =(J2-S2)/Y2 | AC2: =IF(ABS(AA2)<=ABS(AB2),"9EMA","21EMA") | AD2: 9EMA | AE2: 持續在上方 | AH2: ✓ | AI2: 2026-05-28 | AJ2: 87 | AK2: 6 | AL2: 2026-09-24 | AM2: 22.86 | AN2: 18.49 | AO2: =IF(ISNUMBER(AN2),AM2/AN2-1,"") | AP2: 5 | AQ2: =IF(ISNUMBER(AM2),J2/AM2-1,"") | AR2: 24.63 | AS2: =J2/AR2-1 | AT2: 上傾收窄（楔形） | AU2: 0.998 | AV2: 1.2793 | AW2: 0.7068 | AX2: 0.7182 | AY2: 5 | AZ2: 25 | BA2: 18.49 | BB2: 23.0913 | BC2: 0.8074 | BD2: =IF(M2=N2,0.5,(J2-N2)/(M2-N2)) | BE2: 30.333 | BF2: 25.579 | BG2: =100*(0.4*MIN(1,MAX(0,((U2*100)-(0.0))/((2.5)-(0.0))))+0.3*MIN(1,MAX(0,((V2)-(0.6))/((1.0)-(0.6))))+0.3*MIN(1,MAX(0,((BE2)-(0.0))/((15.0)-(0.0))))) | BH2: =100*(0.4*MIN(1,MAX(0,((MIN(ABS(AA2),ABS(AB2)))-(0.75))/((0.0)-(0.75))))+0.3*MIN(1,MAX(0,((BC2)-(1.2))/((0.6)-(1.2))))+0.3*BD2) | BI2: =100*(0.5*MIN(1,MAX(0,((AK2)-(1.0))/((4.0)-(1.0))))+0.3*MIN(1,MAX(0,((IF(ISNUMBER(AO2),AO2,0)*100)-(0.0))/((8.0)-(0.0))))+0.2*MIN(1,MAX(0,((IF(ISNUMBER(AP2),AP2,0))-(25.0))/((5.0)-(25.0))))) | BJ2: =100*(0.35*MIN(1,MAX(0,((ABS(AU2))-(0.3))/((0.05)-(0.3))))+0.3*MIN(1,MAX(0,((AV2)-(0.0))/((0.3)-(0.0))))+0.25*MIN(1,MAX(0,((AW2)-(0.4))/((0.7)-(0.4))))+0.1*IF(AY2>=2,1,0.5)) | BK2: =0.25*BG2+0.25*BH2+0.2*BI2+0.3*BJ2 | BL2: 全部通過
A3: 1 | B3: 2 | C3: PPIH | D3: Perma-Pipe International Holdings Inc. | E3: NASDAQ | F3: 工業 | G3: Pollution Control Equipment | H3: 0.252 | I3: 小型 | J3: 31.32 | K3: 30.76 | L3: =J3/K3-1 | M3: 32.09 | N3: 30.5 | O3: 119300 | P3: 97670 | Q3: =O3/P3 | R3: 30.9909 | S3: 30.0983 | T3: 29.3367 | U3: =S3/T3-1 | V3: 1 | W3: =J3/R3-1 | X3: =J3/S3-1 | Y3: 1.0388 | Z3: =Y3/J3 | AA3: =(J3-R3)/Y3 | AB3: =(J3-S3)/Y3 | AC3: =IF(ABS(AA3)<=ABS(AB3),"9EMA","21EMA") | AD3: 9EMA | AE3: 持續在上方 | AH3: ✓ | AI3: 2026-08-10 | AJ3: 37 | AK3: 4 | AL3: 2026-09-23 | AM3: 29.77 | AN3: 26.24 | AO3: =IF(ISNUMBER(AN3),AM3/AN3-1,"") | AP3: 6 | AQ3: =IF(ISNUMBER(AM3),J3/AM3-1,"") | AR3: 31.88 | AS3: =J3/AR3-1 | AT3: 上升通道 | AU3: 0.6924 | AV3: 0.663 | AW3: 0.5652 | AX3: 0.5654 | AY3: 4 | AZ3: 32.19 | BA3: 26.24 | BB3: 29.6027 | BC3: 0.6571 | BD3: =IF(M3=N3,0.5,(J3-N3)/(M3-N3)) | BE3: 20.754 | BF3: 16 | BG3: =100*(0.4*MIN(1,MAX(0,((U3*100)-(0.0))/((2.5)-(0.0))))+0.3*MIN(1,MAX(0,((V3)-(0.6))/((1.0)-(0.6))))+0.3*MIN(1,MAX(0,((BE3)-(0.0))/((15.0)-(0.0))))) | BH3: =100*(0.4*MIN(1,MAX(0,((MIN(ABS(AA3),ABS(AB3)))-(0.75))/((0.0)-(0.75))))+0.3*MIN(1,MAX(0,((BC3)-(1.2))/((0.6)-(1.2))))+0.3*BD3) | BI3: =100*(0.5*MIN(1,MAX(0,((AK3)-(1.0))/((4.0)-(1.0))))+0.3*MIN(1,MAX(0,((IF(ISNUMBER(AO3),AO3,0)*100)-(0.0))/((8.0)-(0.0))))+0.2*MIN(1,MAX(0,((IF(ISNUMBER(AP3),AP3,0))-(25.0))/((5.0)-(25.0))))) | BJ3: =100*(0.35*MIN(1,MAX(0,((ABS(AU3))-(0.3))/((0.05)-(0.3))))+0.3*MIN(1,MAX(0,((AV3)-(0.0))/((0.3)-(0.0))))+0.25*MIN(1,MAX(0,((AW3)-(0.4))/((0.7)-(0.4))))+0.1*IF(AY3>=2,1,0.5)) | BK3: =0.25*BG3+0.25*BH3+0.2*BI3+0.3*BJ3 | BL3: 全部通過
A4: 1 | B4: 3 | C4: MG | D4: Mistras Group Inc | E4: NYSE | F4: 非必需消費 | G4: Military/Government/Technical | H4: 0.671 | I4: 小型 | J4: 20.63 | K4: 21.06 | L4: =J4/K4-1 | M4: 21.37 | N4: 20.5 | O4: 483000 | P4: 513160 | Q4: =O4/P4 | R4: 20.9314 | S4: 20.319 | T4: 19.7914 | U4: =S4/T4-1 | V4: 1 | W4: =J4/R4-1 | X4: =J4/S4-1 | Y4: 0.6681 | Z4: =Y4/J4 | AA4: =(J4-R4)/Y4 | AB4: =(J4-S4)/Y4 | AC4: =IF(ABS(AA4)<=ABS(AB4),"9EMA","21EMA") | AD4: 9EMA | AE4: 持續在上方 | AH4: ✓ | AI4: 2026-08-11 | AJ4: 36 | AK4: 4 | AL4: 2026-09-23 | AM4: 20.51 | AN4: 19.15 | AO4: =IF(ISNUMBER(AN4),AM4/AN4-1,"") | AP4: 6 | AQ4: =IF(ISNUMBER(AM4),J4/AM4-1,"") | AR4: 21.59 | AS4: =J4/AR4-1 | AT4: 上升通道 | AU4: 0.6921 | AV4: 0.7005 | AW4: 0.6205 | AX4: 0.6173 | AY4: 4 | AZ4: 21.77 | BA4: 18.17 | BB4: 20.4037 | BC4: 0.5202 | BD4: =IF(M4=N4,0.5,(J4-N4)/(M4-N4)) | BE4: 15.907 | BF4: 11.153 | BG4: =100*(0.4*MIN(1,MAX(0,((U4*100)-(0.0))/((2.5)-(0.0))))+0.3*MIN(1,MAX(0,((V4)-(0.6))/((1.0)-(0.6))))+0.3*MIN(1,MAX(0,((BE4)-(0.0))/((15.0)-(0.0))))) | BH4: =100*(0.4*MIN(1,MAX(0,((MIN(ABS(AA4),ABS(AB4)))-(0.75))/((0.0)-(0.75))))+0.3*MIN(1,MAX(0,((BC4)-(1.2))/((0.6)-(1.2))))+0.3*BD4) | BI4: =100*(0.5*MIN(1,MAX(0,((AK4)-(1.0))/((4.0)-(1.0))))+0.3*MIN(1,MAX(0,((IF(ISNUMBER(AO4),AO4,0)*100)-(0.0))/((8.0)-(0.0))))+0.2*MIN(1,MAX(0,((IF(ISNUMBER(AP4),AP4,0))-(25.0))/((5.0)-(25.0))))) | BJ4: =100*(0.35*MIN(1,MAX(0,((ABS(AU4))-(0.3))/((0.05)-(0.3))))+0.3*MIN(1,MAX(0,((AV4)-(0.0))/((0.3)-(0.0))))+0.25*MIN(1,MAX(0,((AW4)-(0.4))/((0.7)-(0.4))))+0.1*IF(AY4>=2,1,0.5)) | BK4: =0.25*BG4+0.25*BH4+0.2*BI4+0.3*BJ4 | BL4: 全部通過
A5: 1 | B5: 4 | C5: HNGE | D5: Hinge Health Inc. | E5: NYSE | F5: 科技 | G5: EDP Services | H5: 7.847 | I5: 中型 | J5: 97.94 | K5: 97.24 | L5: =J5/K5-1 | M5: 98.46 | N5: 96.325 | O5: 1415700 | P5: 1814210 | Q5: =O5/P5 | R5: 95.0834 | S5: 93.257 | T5: 91.6624 | U5: =S5/T5-1 | V5: 1 | W5: =J5/R5-1 | X5: =J5/S5-1 | Y5: 4.1291 | Z5: =Y5/J5 | AA5: =(J5-R5)/Y5 | AB5: =(J5-S5)/Y5 | AC5: =IF(ABS(AA5)<=ABS(AB5),"9EMA","21EMA") | AD5: 9+21EMA | AE5: 持續在上方 | AI5: 2026-08-07 | AJ5: 38 | AK5: 5 | AL5: 2026-09-23 | AM5: 89.75 | AN5: 86.29 | AO5: =IF(ISNUMBER(AN5),AM5/AN5-1,"") | AP5: 6 | AQ5: =IF(ISNUMBER(AM5),J5/AM5-1,"") | AR5: 97.94 | AS5: =J5/AR5-1 | AT5: 上升三角（平頂） | AU5: 0.0795 | AV5: 0.2553 | AW5: 0.5456 | AX5: 0.5037 | AY5: 3 | AZ5: 98.46 | BA5: 85.75 | BB5: 92.6847 | BC5: 0.721 | BD5: =IF(M5=N5,0.5,(J5-N5)/(M5-N5)) | BE5: 13.552 | BF5: 8.798 | BG5: =100*(0.4*MIN(1,MAX(0,((U5*100)-(0.0))/((2.5)-(0.0))))+0.3*MIN(1,MAX(0,((V5)-(0.6))/((1.0)-(0.6))))+0.3*MIN(1,MAX(0,((BE5)-(0.0))/((15.0)-(0.0))))) | BH5: =100*(0.4*MIN(1,MAX(0,((MIN(ABS(AA5),ABS(AB5)))-(0.75))/((0.0)-(0.75))))+0.3*MIN(1,MAX(0,((BC5)-(1.2))/((0.6)-(1.2))))+0.3*BD5) | BI5: =100*(0.5*MIN(1,MAX(0,((AK5)-(1.0))/((4.0)-(1.0))))+0.3*MIN(1,MAX(0,((IF(ISNUMBER(AO5),AO5,0)*100)-(0.0))/((8.0)-(0.0))))+0.2*MIN(1,MAX(0,((IF(ISNUMBER(AP5),AP5,0))-(25.0))/((5.0)-(25.0))))) | BJ5: =100*(0.35*MIN(1,MAX(0,((ABS(AU5))-(0.3))/((0.05)-(0.3))))+0.3*MIN(1,MAX(0,((AV5)-(0.0))/((0.3)-(0.0))))+0.25*MIN(1,MAX(0,((AW5)-(0.4))/((0.7)-(0.4))))+0.1*IF(AY5>=2,1,0.5)) | BK5: =0.25*BG5+0.25*BH5+0.2*BI5+0.3*BJ5 | BL5: 全部通過
A6: 1 | B6: 5 | C6: TTMI | D6: TTM Technologies Inc. | E6: NASDAQ | F6: 科技 | G6: Electrical Products | H6: 12.941 | I6: 大型 | J6: 126.5 | K6: 122.84 | L6: =J6/K6-1 | M6: 127.31 | N6: 119.77 | O6: 1783400 | P6: 1904120 | Q6: =O6/P6 | R6: 124.182 | S6: 123.1791 | T6: 122.0737 | U6: =S6/T6-1 | V6: 0.7 | W6: =J6/R6-1 | X6: =J6/S6-1 | Y6: 7.73 | Z6: =Y6/J6 | AA6: =(J6-R6)/Y6 | AB6: =(J6-S6)/Y6 | AC6: =IF(ABS(AA6)<=ABS(AB6),"9EMA","21EMA") | AD6: 9+21EMA | AE6: 持續在上方 | AH6: ✓ | AI6: 2026-09-23 | AJ6: 6 | AK6: 5 | AL6: 2026-09-28 | AM6: 119.02 | AN6: 109.94 | AO6: =IF(ISNUMBER(AN6),AM6/AN6-1,"") | AP6: 3 | AQ6: =IF(ISNUMBER(AM6),J6/AM6-1,"") | AR6: 129.17 | AS6: =J6/AR6-1 | AT6: 上升三角（平頂） | AU6: 0.0437 | AV6: 0.4842 | AW6: 0.5077 | AX6: 0.5551 | AY6: 1 | AZ6: 133.77 | BA6: 109.53 | BB6: 121.8359 | BC6: 0.8119 | BD6: =IF(M6=N6,0.5,(J6-N6)/(M6-N6)) | BE6: 14.439 | BF6: 9.685 | BG6: =100*(0.4*MIN(1,MAX(0,((U6*100)-(0.0))/((2.5)-(0.0))))+0.3*MIN(1,MAX(0,((V6)-(0.6))/((1.0)-(0.6))))+0.3*MIN(1,MAX(0,((BE6)-(0.0))/((15.0)-(0.0))))) | BH6: =100*(0.4*MIN(1,MAX(0,((MIN(ABS(AA6),ABS(AB6)))-(0.75))/((0.0)-(0.75))))+0.3*MIN(1,MAX(0,((BC6)-(1.2))/((0.6)-(1.2))))+0.3*BD6) | BI6: =100*(0.5*MIN(1,MAX(0,((AK6)-(1.0))/((4.0)-(1.0))))+0.3*MIN(1,MAX(0,((IF(ISNUMBER(AO6),AO6,0)*100)-(0.0))/((8.0)-(0.0))))+0.2*MIN(1,MAX(0,((IF(ISNUMBER(AP6),AP6,0))-(25.0))/((5.0)-(25.0))))) | BJ6: =100*(0.35*MIN(1,MAX(0,((ABS(AU6))-(0.3))/((0.05)-(0.3))))+0.3*MIN(1,MAX(0,((AV6)-(0.0))/((0.3)-(0.0))))+0.25*MIN(1,MAX(0,((AW6)-(0.4))/((0.7)-(0.4))))+0.1*IF(AY6>=2,1,0.5)) | BK6: =0.25*BG6+0.25*BH6+0.2*BI6+0.3*BJ6 | BL6: 全部通過
A7: 1 | B7: 6 | C7: NVAX | D7: Novavax Inc. | E7: NASDAQ | F7: 醫療保健 | G7: Biotechnology: Biological Products (No Diagnostic Substances) | H7: 1.783 | I7: 小型 | J7: 10.6 | K7: 10.81 | L7: =J7/K7-1 | M7: 10.98 | N7: 10.55 | O7: 3147200 | P7: 5277710 | Q7: =O7/P7 | R7: 10.5668 | S7: 10.1617 | T7: 9.8145 | U7: =S7/T7-1 | V7: 1 | W7: =J7/R7-1 | X7: =J7/S7-1 | Y7: 0.5687 | Z7: =Y7/J7 | AA7: =(J7-R7)/Y7 | AB7: =(J7-S7)/Y7 | AC7: =IF(ABS(AA7)<=ABS(AB7),"9EMA","21EMA") | AD7: 9EMA | AE7: 持續在上方 | AH7: ✓ | AI7: 2026-08-19 | AJ7: 30 | AK7: 5 | AL7: 2026-09-28 | AM7: 10.26 | AN7: 9.11 | AO7: =IF(ISNUMBER(AN7),AM7/AN7-1,"") | AP7: 3 | AQ7: =IF(ISNUMBER(AM7),J7/AM7-1,"") | AR7: 10.83 | AS7: =J7/AR7-1 | AT7: 上傾收窄（楔形） | AU7: 0.2916 | AV7: 0.6666 | AW7: 0.5422 | AX7: 0.5863 | AY7: 6 | AZ7: 11.11 | BA7: 8.89 | BB7: 10.0936 | BC7: 0.7553 | BD7: =IF(M7=N7,0.5,(J7-N7)/(M7-N7)) | BE7: 9.497 | BF7: 4.743 | BG7: =100*(0.4*MIN(1,MAX(0,((U7*100)-(0.0))/((2.5)-(0.0))))+0.3*MIN(1,MAX(0,((V7)-(0.6))/((1.0)-(0.6))))+0.3*MIN(1,MAX(0,((BE7)-(0.0))/((15.0)-(0.0))))) | BH7: =100*(0.4*MIN(1,MAX(0,((MIN(ABS(AA7),ABS(AB7)))-(0.75))/((0.0)-(0.75))))+0.3*MIN(1,MAX(0,((BC7)-(1.2))/((0.6)-(1.2))))+0.3*BD7) | BI7: =100*(0.5*MIN(1,MAX(0,((AK7)-(1.0))/((4.0)-(1.0))))+0.3*MIN(1,MAX(0,((IF(ISNUMBER(AO7),AO7,0)*100)-(0.0))/((8.0)-(0.0))))+0.2*MIN(1,MAX(0,((IF(ISNUMBER(AP7),AP7,0))-(25.0))/((5.0)-(25.0))))) | BJ7: =100*(0.35*MIN(1,MAX(0,((ABS(AU7))-(0.3))/((0.05)-(0.3))))+0.3*MIN(1,MAX(0,((AV7)-(0.0))/((0.3)-(0.0))))+0.25*MIN(1,MAX(0,((AW7)-(0.4))/((0.7)-(0.4))))+0.1*IF(AY7>=2,1,0.5)) | BK7: =0.25*BG7+0.25*BH7+0.2*BI7+0.3*BJ7 | BL7: 全部通過
A8: 1 | B8: 7 | C8: FRNM | D8: Freenome Inc. Common stock | E8: NASDAQ | F8: 醫療保健 | G8: Medical Specialities | H8: 1.692 | I8: 小型 | J8: 15.64 | K8: 15.75 | L8: =J8/K8-1 | M8: 16.4 | N8: 15.6 | O8: 586000 | P8: 861365 | Q8: =O8/P8 | R8: 15.8676 | S8: 15.5117 | T8: 15.2893 | U8: =S8/T8-1 | V8: 1 | W8: =J8/R8-1 | X8: =J8/S8-1 | Y8: 0.8875 | Z8: =Y8/J8 | AA8: =(J8-R8)/Y8 | AB8: =(J8-S8)/Y8 | AC8: =IF(ABS(AA8)<=ABS(AB8),"9EMA","21EMA") | AD8: 9+21EMA | AE8: 持續在上方 | AG8: ✓ | AI8: 2026-08-11 | AJ8: 36 | AK8: 4 | AL8: 2026-09-24 | AM8: 15.28 | AN8: 14.25 | AO8: =IF(ISNUMBER(AN8),AM8/AN8-1,"") | AP8: 5 | AQ8: =IF(ISNUMBER(AM8),J8/AM8-1,"") | AR8: 17.11 | AS8: =J8/AR8-1 | AT8: 上傾收窄（楔形） | AU8: 0.2078 | AV8: 0.8232 | AW8: 0.588 | AX8: 0.637 | AY8: 2 | AZ8: 17.5 | BA8: 13.76 | BB8: 15.9592 | BC8: 0.237 | BD8: =IF(M8=N8,0.5,(J8-N8)/(M8-N8)) | BE8: 7.312 | BF8: 2.557 | BG8: =100*(0.4*MIN(1,MAX(0,((U8*100)-(0.0))/((2.5)-(0.0))))+0.3*MIN(1,MAX(0,((V8)-(0.6))/((1.0)-(0.6))))+0.3*MIN(1,MAX(0,((BE8)-(0.0))/((15.0)-(0.0))))) | BH8: =100*(0.4*MIN(1,MAX(0,((MIN(ABS(AA8),ABS(AB8)))-(0.75))/((0.0)-(0.75))))+0.3*MIN(1,MAX(0,((BC8)-(1.2))/((0.6)-(1.2))))+0.3*BD8) | BI8: =100*(0.5*MIN(1,MAX(0,((AK8)-(1.0))/((4.0)-(1.0))))+0.3*MIN(1,MAX(0,((IF(ISNUMBER(AO8),AO8,0)*100)-(0.0))/((8.0)-(0.0))))+0.2*MIN(1,MAX(0,((IF(ISNUMBER(AP8),AP8,0))-(25.0))/((5.0)-(25.0))))) | BJ8: =100*(0.35*MIN(1,MAX(0,((ABS(AU8))-(0.3))/((0.05)-(0.3))))+0.3*MIN(1,MAX(0,((AV8)-(0.0))/((0.3)-(0.0))))+0.25*MIN(1,MAX(0,((AW8)-(0.4))/((0.7)-(0.4))))+0.1*IF(AY8>=2,1,0.5)) | BK8: =0.25*BG8+0.25*BH8+0.2*BI8+0.3*BJ8 | BL8: 全部通過
A9: 1 | B9: 8 | C9: NET | D9: Cloudflare Inc. | E9: NYSE | F9: 科技 | G9: Computer Software: Prepackaged Software | H9: 123.659 | I9: 大型 | J9: 351 | K9: 347.28 | L9: =J9/K9-1 | M9: 353.84 | N9: 342.11 | O9: 2774300 | P9: 3118820 | Q9: =O9/P9 | R9: 346.9575 | S9: 332.7633 | T9: 321.8414 | U9: =S9/T9-1 | V9: 1 | W9: =J9/R9-1 | X9: =J9/S9-1 | Y9: 16.4744 | Z9: =Y9/J9 | AA9: =(J9-R9)/Y9 | AB9: =(J9-S9)/Y9 | AC9: =IF(ABS(AA9)<=ABS(AB9),"9EMA","21EMA") | AD9: 9EMA | AE9: 持續在上方 | AH9: ✓ | AI9: 2026-09-09 | AJ9: 16 | AK9: 3 | AL9: 2026-09-28 | AM9: 338.67 | AN9: 313.5 | AO9: =IF(ISNUMBER(AN9),AM9/AN9-1,"") | AP9: 3 | AQ9: =IF(ISNUMBER(AM9),J9/AM9-1,"") | AR9: 358.82 | AS9: =J9/AR9-1 | AT9: 上傾收窄（楔形） | AU9: 0.8682 | AV9: 1.1604 | AW9: 0.5481 | AX9: 0.5848 | AY9: 3 | AZ9: 367.43 | BA9: 269.3 | BB9: 323.0821 | BC9: 0.9639 | BD9: =IF(M9=N9,0.5,(J9-N9)/(M9-N9)) | BE9: 27.692 | BF9: 22.938 | BG9: =100*(0.4*MIN(1,MAX(0,((U9*100)-(0.0))/((2.5)-(0.0))))+0.3*MIN(1,MAX(0,((V9)-(0.6))/((1.0)-(0.6))))+0.3*MIN(1,MAX(0,((BE9)-(0.0))/((15.0)-(0.0))))) | BH9: =100*(0.4*MIN(1,MAX(0,((MIN(ABS(AA9),ABS(AB9)))-(0.75))/((0.0)-(0.75))))+0.3*MIN(1,MAX(0,((BC9)-(1.2))/((0.6)-(1.2))))+0.3*BD9) | BI9: =100*(0.5*MIN(1,MAX(0,((AK9)-(1.0))/((4.0)-(1.0))))+0.3*MIN(1,MAX(0,((IF(ISNUMBER(AO9),AO9,0)*100)-(0.0))/((8.0)-(0.0))))+0.2*MIN(1,MAX(0,((IF(ISNUMBER(AP9),AP9,0))-(25.0))/((5.0)-(25.0))))) | BJ9: =100*(0.35*MIN(1,MAX(0,((ABS(AU9))-(0.3))/((0.05)-(0.3))))+0.3*MIN(1,MAX(0,((AV9)-(0.0))/((0.3)-(0.0))))+0.25*MIN(1,MAX(0,((AW9)-(0.4))/((0.7)-(0.4))))+0.1*IF(AY9>=2,1,0.5)) | BK9: =0.25*BG9+0.25*BH9+0.2*BI9+0.3*BJ9 | BL9: 全部通過
A10: 1 | B10: 9 | C10: MTSI | D10: MACOM Technology Solutions Holdings Inc. | E10: NASDAQ | F10: 科技 | G10: Semiconductors | H10: 21.752 | I10: 大型 | J10: 301.63 | K10: 284.82 | L10: =J10/K10-1 | M10: 304.29 | N10: 283.59 | O10: 1174700 | P10: 1335305 | Q10: =O10/P10 | R10: 283.7348 | S10: 277.7225 | T10: 271.6084 | U10: =S10/T10-1 | V10: 1 | W10: =J10/R10-1 | X10: =J10/S10-1 | Y10: 14.0183 | Z10: =Y10/J10 | AA10: =(J10-R10)/Y10 | AB10: =(J10-S10)/Y10 | AC10: =IF(ABS(AA10)<=ABS(AB10),"9EMA","21EMA") | AD10: 9EMA | AE10: 持續在上方 | AI10: 2026-09-23 | AJ10: 6 | AK10: 2 | AL10: 2026-09-24 | AM10: 266.42 | AN10: 235.63 | AO10: =IF(ISNUMBER(AN10),AM10/AN10-1,"") | AP10: 5 | AQ10: =IF(ISNUMBER(AM10),J10/AM10-1,"") | AR10: 301.63 | AS10: =J10/AR10-1 | AT10: 上升三角（平頂） | AU10: 0.0303 | AV10: 0.5106 | AW10: 0.5158 | AX10: 0.5068 | AY10: 1 | AZ10: 304.29 | BA10: 235.63 | BB10: 271.0477 | BC10: 0.8119 | BD10: =IF(M10=N10,0.5,(J10-N10)/(M10-N10)) | BE10: 19.876 | BF10: 15.122 | BG10: =100*(0.4*MIN(1,MAX(0,((U10*100)-(0.0))/((2.5)-(0.0))))+0.3*MIN(1,MAX(0,((V10)-(0.6))/((1.0)-(0.6))))+0.3*MIN(1,MAX(0,((BE10)-(0.0))/((15.0)-(0.0))))) | BH10: =100*(0.4*MIN(1,MAX(0,((MIN(ABS(AA10),ABS(AB10)))-(0.75))/((0.0)-(0.75))))+0.3*MIN(1,MAX(0,((BC10)-(1.2))/((0.6)-(1.2))))+0.3*BD10) | BI10: =100*(0.5*MIN(1,MAX(0,((AK10)-(1.0))/((4.0)-(1.0))))+0.3*MIN(1,MAX(0,((IF(ISNUMBER(AO10),AO10,0)*100)-(0.0))/((8.0)-(0.0))))+0.2*MIN(1,MAX(0,((IF(ISNUMBER(AP10),AP10,0))-(25.0))/((5.0)-(25.0))))) | BJ10: =100*(0.35*MIN(1,MAX(0,((ABS(AU10))-(0.3))/((0.05)-(0.3))))+0.3*MIN(1,MAX(0,((AV10)-(0.0))/((0.3)-(0.0))))+0.25*MIN(1,MAX(0,((AW10)-(0.4))/((0.7)-(0.4))))+0.1*IF(AY10>=2,1,0.5)) | BK10: =0.25*BG10+0.25*BH10+0.2*BI10+0.3*BJ10 | BL10: 全部通過
A11: 1 | B11: 10 | C11: ACVA | D11: ACV Auctions Inc. | E11: NYSE | F11: 非必需消費 | G11: Business Services | H11: 1.771 | I11: 小型 | J11: 10.45 | K11: 10.43 | L11: =J11/K11-1 | M11: 10.47 | N11: 10.44 | O11: 6423300 | P11: 15693280 | Q11: =O11/P11 | R11: 10.3306 | S11: 9.6783 | T11: 9.2089 | U11: =S11/T11-1 | V11: 1 | W11: =J11/R11-1 | X11: =J11/S11-1 | Y11: 0.2471 | Z11: =Y11/J11 | AA11: =(J11-R11)/Y11 | AB11: =(J11-S11)/Y11 | AC11: =IF(ABS(AA11)<=ABS(AB11),"9EMA","21EMA") | AD11: — | AE11: 持續在上方 | AH11: ✓ | AI11: 2026-09-11 | AJ11: 14 | AK11: 2 | AL11: 2026-09-23 | AM11: 10.41 | AN11: 6.6 | AO11: =IF(ISNUMBER(AN11),AM11/AN11-1,"") | AP11: 6 | AQ11: =IF(ISNUMBER(AM11),J11/AM11-1,"") | AR11: 10.48 | AS11: =J11/AR11-1 | AT11: 上升三角（平頂） | AU11: 0.0957 | AV11: 3.0383 | AW11: 0.8595 | AX11: 0.8604 | AY11: 15 | AZ11: 10.5 | BA11: 6.6 | BB11: 9.9522 | BC11: 2.1707 | BD11: =IF(M11=N11,0.5,(J11-N11)/(M11-N11)) | BE11: 59.34 | BF11: 54.586 | BG11: =100*(0.4*MIN(1,MAX(0,((U11*100)-(0.0))/((2.5)-(0.0))))+0.3*MIN(1,MAX(0,((V11)-(0.6))/((1.0)-(0.6))))+0.3*MIN(1,MAX(0,((BE11)-(0.0))/((15.0)-(0.0))))) | BH11: =100*(0.4*MIN(1,MAX(0,((MIN(ABS(AA11),ABS(AB11)))-(0.75))/((0.0)-(0.75))))+0.3*MIN(1,MAX(0,((BC11)-(1.2))/((0.6)-(1.2))))+0.3*BD11) | BI11: =100*(0.5*MIN(1,MAX(0,((AK11)-(1.0))/((4.0)-(1.0))))+0.3*MIN(1,MAX(0,((IF(ISNUMBER(AO11),AO11,0)*100)-(0.0))/((8.0)-(0.0))))+0.2*MIN(1,MAX(0,((IF(ISNUMBER(AP11),AP11,0))-(25.0))/((5.0)-(25.0))))) | BJ11: =100*(0.35*MIN(1,MAX(0,((ABS(AU11))-(0.3))/((0.05)-(0.3))))+0.3*MIN(1,MAX(0,((AV11)-(0.0))/((0.3)-(0.0))))+0.25*MIN(1,MAX(0,((AW11)-(0.4))/((0.7)-(0.4))))+0.1*IF(AY11>=2,1,0.5)) | BK11: =0.25*BG11+0.25*BH11+0.2*BI11+0.3*BJ11 | BL11: 全部通過
A12: 1 | B12: 11 | C12: LTC | D12: LTC Properties Inc. | E12: NYSE | F12: 房地產 | G12: Real Estate Investment Trusts | H12: 2.311 | I12: 中型 | J12: 42.67 | K12: 42.87 | L12: =J12/K12-1 | M12: 42.81 | N12: 42.08 | O12: 633200 | P12: 654050 | Q12: =O12/P12 | R12: 42.8522 | S12: 42.4586 | T12: 42.1776 | U12: =S12/T12-1 | V12: 1 | W12: =J12/R12-1 | X12: =J12/S12-1 | Y12: 0.8352 | Z12: =Y12/J12 | AA12: =(J12-R12)/Y12 | AB12: =(J12-S12)/Y12 | AC12: =IF(ABS(AA12)<=ABS(AB12),"9EMA","21EMA") | AD12: 9+21EMA | AE12: 持續在上方 | AH12: ✓ | AI12: 2026-08-20 | AJ12: 29 | AK12: 5 | AL12: 2026-09-21 | AM12: 42.06 | AN12: 40.82 | AO12: =IF(ISNUMBER(AN12),AM12/AN12-1,"") | AP12: 8 | AQ12: =IF(ISNUMBER(AM12),J12/AM12-1,"") | AR12: 43.5 | AS12: =J12/AR12-1 | AT12: 上升三角（平頂） | AU12: -0.0146 | AV12: 0.3172 | AW12: 0.6696 | AX12: 0.6751 | AY12: 12 | AZ12: 43.6 | BA12: 40.17 | BB12: 42.4667 | BC12: 1.2972 | BD12: =IF(M12=N12,0.5,(J12-N12)/(M12-N12)) | BE12: 7.822 | BF12: 3.068 | BG12: =100*(0.4*MIN(1,MAX(0,((U12*100)-(0.0))/((2.5)-(0.0))))+0.3*MIN(1,MAX(0,((V12)-(0.6))/((1.0)-(0.6))))+0.3*MIN(1,MAX(0,((BE12)-(0.0))/((15.0)-(0.0))))) | BH12: =100*(0.4*MIN(1,MAX(0,((MIN(ABS(AA12),ABS(AB12)))-(0.75))/((0.0)-(0.75))))+0.3*MIN(1,MAX(0,((BC12)-(1.2))/((0.6)-(1.2))))+0.3*BD12) | BI12: =100*(0.5*MIN(1,MAX(0,((AK12)-(1.0))/((4.0)-(1.0))))+0.3*MIN(1,MAX(0,((IF(ISNUMBER(AO12),AO12,0)*100)-(0.0))/((8.0)-(0.0))))+0.2*MIN(1,MAX(0,((IF(ISNUMBER(AP12),AP12,0))-(25.0))/((5.0)-(25.0))))) | BJ12: =100*(0.35*MIN(1,MAX(0,((ABS(AU12))-(0.3))/((0.05)-(0.3))))+0.3*MIN(1,MAX(0,((AV12)-(0.0))/((0.3)-(0.0))))+0.25*MIN(1,MAX(0,((AW12)-(0.4))/((0.7)-(0.4))))+0.1*IF(AY12>=2,1,0.5)) | BK12: =0.25*BG12+0.25*BH12+0.2*BI12+0.3*BJ12 | BL12: 全部通過
A13: 1 | B13: 12 | C13: PANW | D13: Palo Alto Networks Inc. | E13: NASDAQ | F13: 科技 | G13: Computer peripheral equipment | H13: 325 | I13: 大型 | J13: 396.25 | K13: 397.31 | L13: =J13/K13-1 | M13: 398.58 | N13: 387.02 | O13: 5309000 | P13: 6369485 | Q13: =O13/P13 | R13: 386.2583 | S13: 374.9784 | T13: 365.4081 | U13: =S13/T13-1 | V13: 1 | W13: =J13/R13-1 | X13: =J13/S13-1 | Y13: 17.56 | Z13: =Y13/J13 | AA13: =(J13-R13)/Y13 | AB13: =(J13-S13)/Y13 | AC13: =IF(ABS(AA13)<=ABS(AB13),"9EMA","21EMA") | AD13: 9EMA | AE13: 持續在上方 | AH13: ✓ | AI13: 2026-09-15 | AJ13: 12 | AK13: 3 | AL13: 2026-09-28 | AM13: 367.27 | AN13: 356 | AO13: =IF(ISNUMBER(AN13),AM13/AN13-1,"") | AP13: 3 | AQ13: =IF(ISNUMBER(AM13),J13/AM13-1,"") | AR13: 397.31 | AS13: =J13/AR13-1 | AT13: 上升三角（平頂） | AU13: 0.0769 | AV13: 0.695 | AW13: 0.5354 | AX13: 0.545 | AY13: 1 | AZ13: 404.69 | BA13: 321.39 | BB13: 365.992 | BC13: 1.0372 | BD13: =IF(M13=N13,0.5,(J13-N13)/(M13-N13)) | BE13: 14.188 | BF13: 9.434 | BG13: =100*(0.4*MIN(1,MAX(0,((U13*100)-(0.0))/((2.5)-(0.0))))+0.3*MIN(1,MAX(0,((V13)-(0.6))/((1.0)-(0.6))))+0.3*MIN(1,MAX(0,((BE13)-(0.0))/((15.0)-(0.0))))) | BH13: =100*(0.4*MIN(1,MAX(0,((MIN(ABS(AA13),ABS(AB13)))-(0.75))/((0.0)-(0.75))))+0.3*MIN(1,MAX(0,((BC13)-(1.2))/((0.6)-(1.2))))+0.3*BD13) | BI13: =100*(0.5*MIN(1,MAX(0,((AK13)-(1.0))/((4.0)-(1.0))))+0.3*MIN(1,MAX(0,((IF(ISNUMBER(AO13),AO13,0)*100)-(0.0))/((8.0)-(0.0))))+0.2*MIN(1,MAX(0,((IF(ISNUMBER(AP13),AP13,0))-(25.0))/((5.0)-(25.0))))) | BJ13: =100*(0.35*MIN(1,MAX(0,((ABS(AU13))-(0.3))/((0.05)-(0.3))))+0.3*MIN(1,MAX(0,((AV13)-(0.0))/((0.3)-(0.0))))+0.25*MIN(1,MAX(0,((AW13)-(0.4))/((0.7)-(0.4))))+0.1*IF(AY13>=2,1,0.5)) | BK13: =0.25*BG13+0.25*BH13+0.2*BI13+0.3*BJ13 | BL13: 全部通過
A14: 1 | B14: 13 | C14: PENG | D14: Penguin Solutions Inc. | E14: NASDAQ | F14: 科技 | G14: Semiconductors | H14: 2.802 | I14: 中型 | J14: 54.98 | K14: 54.69 | L14: =J14/K14-1 | M14: 55.67 | N14: 53.44 | O14: 1157400 | P14: 1358460 | Q14: =O14/P14 | R14: 54.4126 | S14: 53.4053 | T14: 52.2605 | U14: =S14/T14-1 | V14: 1 | W14: =J14/R14-1 | X14: =J14/S14-1 | Y14: 3.0785 | Z14: =Y14/J14 | AA14: =(J14-R14)/Y14 | AB14: =(J14-S14)/Y14 | AC14: =IF(ABS(AA14)<=ABS(AB14),"9EMA","21EMA") | AD14: 9+21EMA | AE14: 持續在上方 | AH14: ✓ | AI14: 2026-09-22 | AJ14: 7 | AK14: 3 | AL14: 2026-09-24 | AM14: 51.31 | AN14: 46.19 | AO14: =IF(ISNUMBER(AN14),AM14/AN14-1,"") | AP14: 5 | AQ14: =IF(ISNUMBER(AM14),J14/AM14-1,"") | AR14: 56.58 | AS14: =J14/AR14-1 | AT14: 上傾收窄（楔形） | AU14: 0.3647 | AV14: 0.7392 | AW14: 0.514 | AX14: 0.5141 | AY14: 3 | AZ14: 57.5 | BA14: 45.62 | BB14: 51.7262 | BC14: 0.9476 | BD14: =IF(M14=N14,0.5,(J14-N14)/(M14-N14)) | BE14: 20.283 | BF14: 15.528 | BG14: =100*(0.4*MIN(1,MAX(0,((U14*100)-(0.0))/((2.5)-(0.0))))+0.3*MIN(1,MAX(0,((V14)-(0.6))/((1.0)-(0.6))))+0.3*MIN(1,MAX(0,((BE14)-(0.0))/((15.0)-(0.0))))) | BH14: =100*(0.4*MIN(1,MAX(0,((MIN(ABS(AA14),ABS(AB14)))-(0.75))/((0.0)-(0.75))))+0.3*MIN(1,MAX(0,((BC14)-(1.2))/((0.6)-(1.2))))+0.3*BD14) | BI14: =100*(0.5*MIN(1,MAX(0,((AK14)-(1.0))/((4.0)-(1.0))))+0.3*MIN(1,MAX(0,((IF(ISNUMBER(AO14),AO14,0)*100)-(0.0))/((8.0)-(0.0))))+0.2*MIN(1,MAX(0,((IF(ISNUMBER(AP14),AP14,0))-(25.0))/((5.0)-(25.0))))) | BJ14: =100*(0.35*MIN(1,MAX(0,((ABS(AU14))-(0.3))/((0.05)-(0.3))))+0.3*MIN(1,MAX(0,((AV14)-(0.0))/((0.3)-(0.0))))+0.25*MIN(1,MAX(0,((AW14)-(0.4))/((0.7)-(0.4))))+0.1*IF(AY14>=2,1,0.5)) | BK14: =0.25*BG14+0.25*BH14+0.2*BI14+0.3*BJ14 | BL14: 全部通過
A15: 1 | B15: 14 | C15: DT | D15: Dynatrace Inc. | E15: NYSE | F15: 科技 | G15: Computer Software: Prepackaged Software | H15: 16.687 | I15: 大型 | J15: 59.26 | K15: 57.74 | L15: =J15/K15-1 | M15: 59.42 | N15: 58.26 | O15: 5248200 | P15: 6901235 | Q15: =O15/P15 | R15: 57.5596 | S15: 55.5806 | T15: 54.0331 | U15: =S15/T15-1 | V15: 1 | W15: =J15/R15-1 | X15: =J15/S15-1 | Y15: 1.7535 | Z15: =Y15/J15 | AA15: =(J15-R15)/Y15 | AB15: =(J15-S15)/Y15 | AC15: =IF(ABS(AA15)<=ABS(AB15),"9EMA","21EMA") | AD15: 9EMA | AE15: 持續在上方 | AH15: ✓ | AI15: 2026-07-29 | AJ15: 45 | AK15: 4 | AL15: 2026-09-28 | AM15: 55.644 | AN15: 49.56 | AO15: =IF(ISNUMBER(AN15),AM15/AN15-1,"") | AP15: 3 | AQ15: =IF(ISNUMBER(AM15),J15/AM15-1,"") | AR15: 59.26 | AS15: =J15/AR15-1 | AT15: 上傾收窄（楔形） | AU15: 0.4541 | AV15: 0.7897 | AW15: 0.5627 | AX15: 0.5372 | AY15: 5 | AZ15: 59.42 | BA15: 49.56 | BB15: 55.1085 | BC15: 0.9148 | BD15: =IF(M15=N15,0.5,(J15-N15)/(M15-N15)) | BE15: 16.862 | BF15: 12.107 | BG15: =100*(0.4*MIN(1,MAX(0,((U15*100)-(0.0))/((2.5)-(0.0))))+0.3*MIN(1,MAX(0,((V15)-(0.6))/((1.0)-(0.6))))+0.3*MIN(1,MAX(0,((BE15)-(0.0))/((15.0)-(0.0))))) | BH15: =100*(0.4*MIN(1,MAX(0,((MIN(ABS(AA15),ABS(AB15)))-(0.75))/((0.0)-(0.75))))+0.3*MIN(1,MAX(0,((BC15)-(1.2))/((0.6)-(1.2))))+0.3*BD15) | BI15: =100*(0.5*MIN(1,MAX(0,((AK15)-(1.0))/((4.0)-(1.0))))+0.3*MIN(1,MAX(0,((IF(ISNUMBER(AO15),AO15,0)*100)-(0.0))/((8.0)-(0.0))))+0.2*MIN(1,MAX(0,((IF(ISNUMBER(AP15),AP15,0))-(25.0))/((5.0)-(25.0))))) | BJ15: =100*(0.35*MIN(1,MAX(0,((ABS(AU15))-(0.3))/((0.05)-(0.3))))+0.3*MIN(1,MAX(0,((AV15)-(0.0))/((0.3)-(0.0))))+0.25*MIN(1,MAX(0,((AW15)-(0.4))/((0.7)-(0.4))))+0.1*IF(AY15>=2,1,0.5)) | BK15: =0.25*BG15+0.25*BH15+0.2*BI15+0.3*BJ15 | BL15: 全部通過
A16: 1 | B16: 15 | C16: NUTX | D16: Nutex Health Inc. | E16: NASDAQ | F16: 非必需消費 | G16: Business Services | H16: 1.449 | I16: 小型 | J16: 212.31 | K16: 211.66 | L16: =J16/K16-1 | M16: 219.94 | N16: 210.195 | O16: 122500 | P16: 155030 | Q16: =O16/P16 | R16: 210.3854 | S16: 205.1014 | T16: 200.2276 | U16: =S16/T16-1 | V16: 1 | W16: =J16/R16-1 | X16: =J16/S16-1 | Y16: 10.5554 | Z16: =Y16/J16 | AA16: =(J16-R16)/Y16 | AB16: =(J16-S16)/Y16 | AC16: =IF(ABS(AA16)<=ABS(AB16),"9EMA","21EMA") | AD16: 9EMA | AE16: 持續在上方 | AH16: ✓ | AI16: 2026-08-10 | AJ16: 37 | AK16: 5 | AL16: 2026-09-24 | AM16: 198.25 | AN16: 184 | AO16: =IF(ISNUMBER(AN16),AM16/AN16-1,"") | AP16: 5 | AQ16: =IF(ISNUMBER(AM16),J16/AM16-1,"") | AR16: 220.11 | AS16: =J16/AR16-1 | AT16: 上傾擴張 | AU16: 0.6755 | AV16: 0.4838 | AW16: 0.5032 | AX16: 0.4963 | AY16: 4 | AZ16: 224.28 | BA16: 182.66 | BB16: 203.6045 | BC16: 1.0121 | BD16: =IF(M16=N16,0.5,(J16-N16)/(M16-N16)) | BE16: 18.083 | BF16: 13.329 | BG16: =100*(0.4*MIN(1,MAX(0,((U16*100)-(0.0))/((2.5)-(0.0))))+0.3*MIN(1,MAX(0,((V16)-(0.6))/((1.0)-(0.6))))+0.3*MIN(1,MAX(0,((BE16)-(0.0))/((15.0)-(0.0))))) | BH16: =100*(0.4*MIN(1,MAX(0,((MIN(ABS(AA16),ABS(AB16)))-(0.75))/((0.0)-(0.75))))+0.3*MIN(1,MAX(0,((BC16)-(1.2))/((0.6)-(1.2))))+0.3*BD16) | BI16: =100*(0.5*MIN(1,MAX(0,((AK16)-(1.0))/((4.0)-(1.0))))+0.3*MIN(1,MAX(0,((IF(ISNUMBER(AO16),AO16,0)*100)-(0.0))/((8.0)-(0.0))))+0.2*MIN(1,MAX(0,((IF(ISNUMBER(AP16),AP16,0))-(25.0))/((5.0)-(25.0))))) | BJ16: =100*(0.35*MIN(1,MAX(0,((ABS(AU16))-(0.3))/((0.05)-(0.3))))+0.3*MIN(1,MAX(0,((AV16)-(0.0))/((0.3)-(0.0))))+0.25*MIN(1,MAX(0,((AW16)-(0.4))/((0.7)-(0.4))))+0.1*IF(AY16>=2,1,0.5)) | BK16: =0.25*BG16+0.25*BH16+0.2*BI16+0.3*BJ16 | BL16: 全部通過
A17: 1 | B17: 16 | C17: DDD | D17: 3D Systems Corporation | E17: NYSE | F17: 科技 | G17: Computer Software: Prepackaged Software | H17: 0.598 | I17: 小型 | J17: 3.54 | K17: 3.6 | L17: =J17/K17-1 | M17: 3.57 | N17: 3.44 | O17: 2659000 | P17: 2217730 | Q17: =O17/P17 | R17: 3.5163 | S17: 3.449 | T17: 3.3871 | U17: =S17/T17-1 | V17: 1 | W17: =J17/R17-1 | X17: =J17/S17-1 | Y17: 0.2003 | Z17: =Y17/J17 | AA17: =(J17-R17)/Y17 | AB17: =(J17-S17)/Y17 | AC17: =IF(ABS(AA17)<=ABS(AB17),"9EMA","21EMA") | AD17: 9+21EMA | AE17: 持續在上方 | AH17: ✓ | AI17: 2026-09-17 | AJ17: 10 | AK17: 2 | AL17: 2026-09-25 | AM17: 3.35 | AN17: 3.1 | AO17: =IF(ISNUMBER(AN17),AM17/AN17-1,"") | AP17: 4 | AQ17: =IF(ISNUMBER(AM17),J17/AM17-1,"") | AR17: 3.63 | AS17: =J17/AR17-1 | AT17: 上傾收窄（楔形） | AU17: 0.3329 | AV17: 1.0089 | AW17: 0.5249 | AX17: 0.6039 | AY17: 3 | AZ17: 3.74 | BA17: 3.1 | BB17: 3.4359 | BC17: 0.6653 | BD17: =IF(M17=N17,0.5,(J17-N17)/(M17-N17)) | BE17: 12.353 | BF17: 7.599 | BG17: =100*(0.4*MIN(1,MAX(0,((U17*100)-(0.0))/((2.5)-(0.0))))+0.3*MIN(1,MAX(0,((V17)-(0.6))/((1.0)-(0.6))))+0.3*MIN(1,MAX(0,((BE17)-(0.0))/((15.0)-(0.0))))) | BH17: =100*(0.4*MIN(1,MAX(0,((MIN(ABS(AA17),ABS(AB17)))-(0.75))/((0.0)-(0.75))))+0.3*MIN(1,MAX(0,((BC17)-(1.2))/((0.6)-(1.2))))+0.3*BD17) | BI17: =100*(0.5*MIN(1,MAX(0,((AK17)-(1.0))/((4.0)-(1.0))))+0.3*MIN(1,MAX(0,((IF(ISNUMBER(AO17),AO17,0)*100)-(0.0))/((8.0)-(0.0))))+0.2*MIN(1,MAX(0,((IF(ISNUMBER(AP17),AP17,0))-(25.0))/((5.0)-(25.0))))) | BJ17: =100*(0.35*MIN(1,MAX(0,((ABS(AU17))-(0.3))/((0.05)-(0.3))))+0.3*MIN(1,MAX(0,((AV17)-(0.0))/((0.3)-(0.0))))+0.25*MIN(1,MAX(0,((AW17)-(0.4))/((0.7)-(0.4))))+0.1*IF(AY17>=2,1,0.5)) | BK17: =0.25*BG17+0.25*BH17+0.2*BI17+0.3*BJ17 | BL17: 全部通過
A18: 1 | B18: 17 | C18: MTW | D18: Manitowoc Company Inc. (The) | E18: NYSE | F18: 工業 | G18: Construction/Ag Equipment/Trucks | H18: 0.774 | I18: 小型 | J18: 22.4 | K18: 21.46 | L18: =J18/K18-1 | M18: 22.7 | N18: 21.14 | O18: 551400 | P18: 498695 | Q18: =O18/P18 | R18: 21.9569 | S18: 21.3218 | T18: 20.8739 | U18: =S18/T18-1 | V18: 1 | W18: =J18/R18-1 | X18: =J18/S18-1 | Y18: 0.9582 | Z18: =Y18/J18 | AA18: =(J18-R18)/Y18 | AB18: =(J18-S18)/Y18 | AC18: =IF(ABS(AA18)<=ABS(AB18),"9EMA","21EMA") | AD18: 9+21EMA | AE18: 持續在上方 | AH18: ✓ | AI18: 2026-07-16 | AJ18: 54 | AK18: 5 | AL18: 2026-09-24 | AM18: 21.19 | AN18: 19.63 | AO18: =IF(ISNUMBER(AN18),AM18/AN18-1,"") | AP18: 5 | AQ18: =IF(ISNUMBER(AM18),J18/AM18-1,"") | AR18: 22.76 | AS18: =J18/AR18-1 | AT18: 上升通道 | AU18: 0.6778 | AV18: 0.6864 | AW18: 0.5851 | AX18: 0.6232 | AY18: 3 | AZ18: 23.17 | BA18: 18.73 | BB18: 21.3281 | BC18: 1.292 | BD18: =IF(M18=N18,0.5,(J18-N18)/(M18-N18)) | BE18: 22.898 | BF18: 18.143 | BG18: =100*(0.4*MIN(1,MAX(0,((U18*100)-(0.0))/((2.5)-(0.0))))+0.3*MIN(1,MAX(0,((V18)-(0.6))/((1.0)-(0.6))))+0.3*MIN(1,MAX(0,((BE18)-(0.0))/((15.0)-(0.0))))) | BH18: =100*(0.4*MIN(1,MAX(0,((MIN(ABS(AA18),ABS(AB18)))-(0.75))/((0.0)-(0.75))))+0.3*MIN(1,MAX(0,((BC18)-(1.2))/((0.6)-(1.2))))+0.3*BD18) | BI18: =100*(0.5*MIN(1,MAX(0,((AK18)-(1.0))/((4.0)-(1.0))))+0.3*MIN(1,MAX(0,((IF(ISNUMBER(AO18),AO18,0)*100)-(0.0))/((8.0)-(0.0))))+0.2*MIN(1,MAX(0,((IF(ISNUMBER(AP18),AP18,0))-(25.0))/((5.0)-(25.0))))) | BJ18: =100*(0.35*MIN(1,MAX(0,((ABS(AU18))-(0.3))/((0.05)-(0.3))))+0.3*MIN(1,MAX(0,((AV18)-(0.0))/((0.3)-(0.0))))+0.25*MIN(1,MAX(0,((AW18)-(0.4))/((0.7)-(0.4))))+0.1*IF(AY18>=2,1,0.5)) | BK18: =0.25*BG18+0.25*BH18+0.2*BI18+0.3*BJ18 | BL18: 全部通過
A19: 1 | B19: 18 | C19: ISRG | D19: Intuitive Surgical Inc. | E19: NASDAQ | F19: 醫療保健 | G19: Industrial Specialties | H19: 143.653 | I19: 大型 | J19: 401.24 | K19: 406.63 | L19: =J19/K19-1 | M19: 410.52 | N19: 399.25 | O19: 1511300 | P19: 2411950 | Q19: =O19/P19 | R19: 401.8931 | S19: 392.5062 | T19: 383.2484 | U19: =S19/T19-1 | V19: 1 | W19: =J19/R19-1 | X19: =J19/S19-1 | Y19: 10.9654 | Z19: =Y19/J19 | AA19: =(J19-R19)/Y19 | AB19: =(J19-S19)/Y19 | AC19: =IF(ABS(AA19)<=ABS(AB19),"9EMA","21EMA") | AD19: 9EMA | AE19: 持續在上方 | AH19: ✓ | AI19: 2026-09-17 | AJ19: 10 | AK19: 2 | AL19: 2026-09-25 | AM19: 391.92 | AN19: 345.25 | AO19: =IF(ISNUMBER(AN19),AM19/AN19-1,"") | AP19: 4 | AQ19: =IF(ISNUMBER(AM19),J19/AM19-1,"") | AR19: 414.79 | AS19: =J19/AR19-1 | AT19: 上升通道 | AU19: 0.4999 | AV19: 0.4297 | AW19: 0.5212 | AX19: 0.4986 | AY19: 4 | AZ19: 416.51 | BA19: 345.25 | BB19: 382.3872 | BC19: 0.6169 | BD19: =IF(M19=N19,0.5,(J19-N19)/(M19-N19)) | BE19: 13.418 | BF19: 8.664 | BG19: =100*(0.4*MIN(1,MAX(0,((U19*100)-(0.0))/((2.5)-(0.0))))+0.3*MIN(1,MAX(0,((V19)-(0.6))/((1.0)-(0.6))))+0.3*MIN(1,MAX(0,((BE19)-(0.0))/((15.0)-(0.0))))) | BH19: =100*(0.4*MIN(1,MAX(0,((MIN(ABS(AA19),ABS(AB19)))-(0.75))/((0.0)-(0.75))))+0.3*MIN(1,MAX(0,((BC19)-(1.2))/((0.6)-(1.2))))+0.3*BD19) | BI19: =100*(0.5*MIN(1,MAX(0,((AK19)-(1.0))/((4.0)-(1.0))))+0.3*MIN(1,MAX(0,((IF(ISNUMBER(AO19),AO19,0)*100)-(0.0))/((8.0)-(0.0))))+0.2*MIN(1,MAX(0,((IF(ISNUMBER(AP19),AP19,0))-(25.0))/((5.0)-(25.0))))) | BJ19: =100*(0.35*MIN(1,MAX(0,((ABS(AU19))-(0.3))/((0.05)-(0.3))))+0.3*MIN(1,MAX(0,((AV19)-(0.0))/((0.3)-(0.0))))+0.25*MIN(1,MAX(0,((AW19)-(0.4))/((0.7)-(0.4))))+0.1*IF(AY19>=2,1,0.5)) | BK19: =0.25*BG19+0.25*BH19+0.2*BI19+0.3*BJ19 | BL19: 全部通過
A20: 1 | B20: 19 | C20: SEI | D20: Solaris Energy Infrastructure Inc. | E20: NYSE | F20: 非必需消費 | G20: Oil and Gas Field Machinery | H20: 5.45 | I20: 中型 | J20: 71.38 | K20: 71.18 | L20: =J20/K20-1 | M20: 72.5 | N20: 70.23 | O20: 1718800 | P20: 2796590 | Q20: =O20/P20 | R20: 69.1653 | S20: 65.9819 | T20: 63.367 | U20: =S20/T20-1 | V20: 1 | W20: =J20/R20-1 | X20: =J20/S20-1 | Y20: 4.0993 | Z20: =Y20/J20 | AA20: =(J20-R20)/Y20 | AB20: =(J20-S20)/Y20 | AC20: =IF(ABS(AA20)<=ABS(AB20),"9EMA","21EMA") | AD20: 9EMA | AE20: 持續在上方 | AI20: 2026-09-09 | AJ20: 16 | AK20: 3 | AL20: 2026-09-23 | AM20: 64.23 | AN20: 60.59 | AO20: =IF(ISNUMBER(AN20),AM20/AN20-1,"") | AP20: 6 | AQ20: =IF(ISNUMBER(AM20),J20/AM20-1,"") | AR20: 71.38 | AS20: =J20/AR20-1 | AT20: 上傾收窄（楔形） | AU20: 0.2498 | AV20: 1.6431 | AW20: 0.6585 | AX20: 0.6637 | AY20: 5 | AZ20: 72.5 | BA20: 47.81 | BB20: 64.0693 | BC20: 0.9737 | BD20: =IF(M20=N20,0.5,(J20-N20)/(M20-N20)) | BE20: 48.549 | BF20: 43.795 | BG20: =100*(0.4*MIN(1,MAX(0,((U20*100)-(0.0))/((2.5)-(0.0))))+0.3*MIN(1,MAX(0,((V20)-(0.6))/((1.0)-(0.6))))+0.3*MIN(1,MAX(0,((BE20)-(0.0))/((15.0)-(0.0))))) | BH20: =100*(0.4*MIN(1,MAX(0,((MIN(ABS(AA20),ABS(AB20)))-(0.75))/((0.0)-(0.75))))+0.3*MIN(1,MAX(0,((BC20)-(1.2))/((0.6)-(1.2))))+0.3*BD20) | BI20: =100*(0.5*MIN(1,MAX(0,((AK20)-(1.0))/((4.0)-(1.0))))+0.3*MIN(1,MAX(0,((IF(ISNUMBER(AO20),AO20,0)*100)-(0.0))/((8.0)-(0.0))))+0.2*MIN(1,MAX(0,((IF(ISNUMBER(AP20),AP20,0))-(25.0))/((5.0)-(25.0))))) | BJ20: =100*(0.35*MIN(1,MAX(0,((ABS(AU20))-(0.3))/((0.05)-(0.3))))+0.3*MIN(1,MAX(0,((AV20)-(0.0))/((0.3)-(0.0))))+0.25*MIN(1,MAX(0,((AW20)-(0.4))/((0.7)-(0.4))))+0.1*IF(AY20>=2,1,0.5)) | BK20: =0.25*BG20+0.25*BH20+0.2*BI20+0.3*BJ20 | BL20: 全部通過
A21: 1 | B21: 20 | C21: FTNT | D21: Fortinet Inc. | E21: NASDAQ | F21: 科技 | G21: Computer peripheral equipment | H21: 131.159 | I21: 大型 | J21: 178.72 | K21: 178.76 | L21: =J21/K21-1 | M21: 180 | N21: 175.02 | O21: 2962800 | P21: 3961810 | Q21: =O21/P21 | R21: 175.8128 | S21: 171.1716 | T21: 167.6807 | U21: =S21/T21-1 | V21: 1 | W21: =J21/R21-1 | X21: =J21/S21-1 | Y21: 6.4558 | Z21: =Y21/J21 | AA21: =(J21-R21)/Y21 | AB21: =(J21-S21)/Y21 | AC21: =IF(ABS(AA21)<=ABS(AB21),"9EMA","21EMA") | AD21: 9EMA | AE21: 持續在上方 | AH21: ✓ | AI21: 2026-09-14 | AJ21: 13 | AK21: 4 | AL21: 2026-09-28 | AM21: 169.56 | AN21: 166.09 | AO21: =IF(ISNUMBER(AN21),AM21/AN21-1,"") | AP21: 3 | AQ21: =IF(ISNUMBER(AM21),J21/AM21-1,"") | AR21: 178.76 | AS21: =J21/AR21-1 | AT21: 上傾收窄（楔形） | AU21: 0.1917 | AV21: 0.6021 | AW21: 0.573 | AX21: 0.5865 | AY21: 4 | AZ21: 181.37 | BA21: 151.8 | BB21: 168.7443 | BC21: 1.52 | BD21: =IF(M21=N21,0.5,(J21-N21)/(M21-N21)) | BE21: 15.177 | BF21: 10.423 | BG21: =100*(0.4*MIN(1,MAX(0,((U21*100)-(0.0))/((2.5)-(0.0))))+0.3*MIN(1,MAX(0,((V21)-(0.6))/((1.0)-(0.6))))+0.3*MIN(1,MAX(0,((BE21)-(0.0))/((15.0)-(0.0))))) | BH21: =100*(0.4*MIN(1,MAX(0,((MIN(ABS(AA21),ABS(AB21)))-(0.75))/((0.0)-(0.75))))+0.3*MIN(1,MAX(0,((BC21)-(1.2))/((0.6)-(1.2))))+0.3*BD21) | BI21: =100*(0.5*MIN(1,MAX(0,((AK21)-(1.0))/((4.0)-(1.0))))+0.3*MIN(1,MAX(0,((IF(ISNUMBER(AO21),AO21,0)*100)-(0.0))/((8.0)-(0.0))))+0.2*MIN(1,MAX(0,((IF(ISNUMBER(AP21),AP21,0))-(25.0))/((5.0)-(25.0))))) | BJ21: =100*(0.35*MIN(1,MAX(0,((ABS(AU21))-(0.3))/((0.05)-(0.3))))+0.3*MIN(1,MAX(0,((AV21)-(0.0))/((0.3)-(0.0))))+0.25*MIN(1,MAX(0,((AW21)-(0.4))/((0.7)-(0.4))))+0.1*IF(AY21>=2,1,0.5)) | BK21: =0.25*BG21+0.25*BH21+0.2*BI21+0.3*BJ21 | BL21: 全部通過
A22: 1 | B22: 21 | C22: AVT | D22: Avnet Inc. | E22: NASDAQ | F22: 科技 | G22: Electronic Components | H22: 8.203 | I22: 中型 | J22: 102.24 | K22: 99.95 | L22: =J22/K22-1 | M22: 103.46 | N22: 98.55 | O22: 1203700 | P22: 1365340 | Q22: =O22/P22 | R22: 100.1881 | S22: 97.3309 | T22: 94.6101 | U22: =S22/T22-1 | V22: 1 | W22: =J22/R22-1 | X22: =J22/S22-1 | Y22: 3.8317 | Z22: =Y22/J22 | AA22: =(J22-R22)/Y22 | AB22: =(J22-S22)/Y22 | AC22: =IF(ABS(AA22)<=ABS(AB22),"9EMA","21EMA") | AD22: 9EMA | AE22: 持續在上方 | AH22: ✓ | AI22: 2026-09-08 | AJ22: 17 | AK22: 5 | AL22: 2026-09-16 | AM22: 90.9 | AN22: 86.71 | AO22: =IF(ISNUMBER(AN22),AM22/AN22-1,"") | AP22: 11 | AQ22: =IF(ISNUMBER(AM22),J22/AM22-1,"") | AR22: 103.08 | AS22: =J22/AR22-1 | AT22: 上升通道 | AU22: 0.6087 | AV22: 0.5123 | AW22: 0.5054 | AX22: 0.4921 | AY22: 4 | AZ22: 104.58 | BA22: 86.71 | BB22: 95.7408 | BC22: 0.8726 | BD22: =IF(M22=N22,0.5,(J22-N22)/(M22-N22)) | BE22: 19.129 | BF22: 14.375 | BG22: =100*(0.4*MIN(1,MAX(0,((U22*100)-(0.0))/((2.5)-(0.0))))+0.3*MIN(1,MAX(0,((V22)-(0.6))/((1.0)-(0.6))))+0.3*MIN(1,MAX(0,((BE22)-(0.0))/((15.0)-(0.0))))) | BH22: =100*(0.4*MIN(1,MAX(0,((MIN(ABS(AA22),ABS(AB22)))-(0.75))/((0.0)-(0.75))))+0.3*MIN(1,MAX(0,((BC22)-(1.2))/((0.6)-(1.2))))+0.3*BD22) | BI22: =100*(0.5*MIN(1,MAX(0,((AK22)-(1.0))/((4.0)-(1.0))))+0.3*MIN(1,MAX(0,((IF(ISNUMBER(AO22),AO22,0)*100)-(0.0))/((8.0)-(0.0))))+0.2*MIN(1,MAX(0,((IF(ISNUMBER(AP22),AP22,0))-(25.0))/((5.0)-(25.0))))) | BJ22: =100*(0.35*MIN(1,MAX(0,((ABS(AU22))-(0.3))/((0.05)-(0.3))))+0.3*MIN(1,MAX(0,((AV22)-(0.0))/((0.3)-(0.0))))+0.25*MIN(1,MAX(0,((AW22)-(0.4))/((0.7)-(0.4))))+0.1*IF(AY22>=2,1,0.5)) | BK22: =0.25*BG22+0.25*BH22+0.2*BI22+0.3*BJ22 | BL22: 全部通過
A23: 1 | B23: 22 | C23: MRVL | D23: Marvell Technology Inc. | E23: NASDAQ | F23: 科技 | G23: Semiconductors | H23: 231.686 | I23: 大型 | J23: 268.08 | K23: 264.21 | L23: =J23/K23-1 | M23: 270.28 | N23: 257.58 | O23: 18986300 | P23: 17834650 | Q23: =O23/P23 | R23: 258.2212 | S23: 247 | T23: 237.6213 | U23: =S23/T23-1 | V23: 1 | W23: =J23/R23-1 | X23: =J23/S23-1 | Y23: 13.0892 | Z23: =Y23/J23 | AA23: =(J23-R23)/Y23 | AB23: =(J23-S23)/Y23 | AC23: =IF(ABS(AA23)<=ABS(AB23),"9EMA","21EMA") | AD23: 9EMA | AE23: 持續在上方 | AI23: 2026-09-09 | AJ23: 16 | AK23: 3 | AL23: 2026-09-28 | AM23: 248.14 | AN23: 213.63 | AO23: =IF(ISNUMBER(AN23),AM23/AN23-1,"") | AP23: 3 | AQ23: =IF(ISNUMBER(AM23),J23/AM23-1,"") | AR23: 268.08 | AS23: =J23/AR23-1 | AT23: 上傾收窄（楔形） | AU23: 0.2841 | AV23: 0.9972 | AW23: 0.5018 | AX23: 0.4723 | AY23: 2 | AZ23: 270.28 | BA23: 200.62 | BB23: 235.5757 | BC23: 0.8184 | BD23: =IF(M23=N23,0.5,(J23-N23)/(M23-N23)) | BE23: 32.175 | BF23: 27.421 | BG23: =100*(0.4*MIN(1,MAX(0,((U23*100)-(0.0))/((2.5)-(0.0))))+0.3*MIN(1,MAX(0,((V23)-(0.6))/((1.0)-(0.6))))+0.3*MIN(1,MAX(0,((BE23)-(0.0))/((15.0)-(0.0))))) | BH23: =100*(0.4*MIN(1,MAX(0,((MIN(ABS(AA23),ABS(AB23)))-(0.75))/((0.0)-(0.75))))+0.3*MIN(1,MAX(0,((BC23)-(1.2))/((0.6)-(1.2))))+0.3*BD23) | BI23: =100*(0.5*MIN(1,MAX(0,((AK23)-(1.0))/((4.0)-(1.0))))+0.3*MIN(1,MAX(0,((IF(ISNUMBER(AO23),AO23,0)*100)-(0.0))/((8.0)-(0.0))))+0.2*MIN(1,MAX(0,((IF(ISNUMBER(AP23),AP23,0))-(25.0))/((5.0)-(25.0))))) | BJ23: =100*(0.35*MIN(1,MAX(0,((ABS(AU23))-(0.3))/((0.05)-(0.3))))+0.3*MIN(1,MAX(0,((AV23)-(0.0))/((0.3)-(0.0))))+0.25*MIN(1,MAX(0,((AW23)-(0.4))/((0.7)-(0.4))))+0.1*IF(AY23>=2,1,0.5)) | BK23: =0.25*BG23+0.25*BH23+0.2*BI23+0.3*BJ23 | BL23: 全部通過
A24: 1 | B24: 23 | C24: CVLT | D24: Commvault Systems Inc. | E24: NASDAQ | F24: 科技 | G24: Computer Software: Prepackaged Software | H24: 6.213 | I24: 中型 | J24: 147.77 | K24: 149.92 | L24: =J24/K24-1 | M24: 151.5 | N24: 145.69 | O24: 706300 | P24: 592410 | Q24: =O24/P24 | R24: 146.9838 | S24: 143.7918 | T24: 141.4376 | U24: =S24/T24-1 | V24: 1 | W24: =J24/R24-1 | X24: =J24/S24-1 | Y24: 5.7889 | Z24: =Y24/J24 | AA24: =(J24-R24)/Y24 | AB24: =(J24-S24)/Y24 | AC24: =IF(ABS(AA24)<=ABS(AB24),"9EMA","21EMA") | AD24: 9EMA | AE24: 持續在上方 | AH24: ✓ | AI24: 2026-09-15 | AJ24: 12 | AK24: 3 | AL24: 2026-09-28 | AM24: 141.1 | AN24: 129.5 | AO24: =IF(ISNUMBER(AN24),AM24/AN24-1,"") | AP24: 3 | AQ24: =IF(ISNUMBER(AM24),J24/AM24-1,"") | AR24: 150 | AS24: =J24/AR24-1 | AT24: 上傾收窄（楔形） | AU24: 0.343 | AV24: 0.6185 | AW24: 0.6215 | AX24: 0.6098 | AY24: 8 | AZ24: 151.62 | BA24: 125.9 | BB24: 141.8847 | BC24: 1.1136 | BD24: =IF(M24=N24,0.5,(J24-N24)/(M24-N24)) | BE24: 19.127 | BF24: 14.373 | BG24: =100*(0.4*MIN(1,MAX(0,((U24*100)-(0.0))/((2.5)-(0.0))))+0.3*MIN(1,MAX(0,((V24)-(0.6))/((1.0)-(0.6))))+0.3*MIN(1,MAX(0,((BE24)-(0.0))/((15.0)-(0.0))))) | BH24: =100*(0.4*MIN(1,MAX(0,((MIN(ABS(AA24),ABS(AB24)))-(0.75))/((0.0)-(0.75))))+0.3*MIN(1,MAX(0,((BC24)-(1.2))/((0.6)-(1.2))))+0.3*BD24) | BI24: =100*(0.5*MIN(1,MAX(0,((AK24)-(1.0))/((4.0)-(1.0))))+0.3*MIN(1,MAX(0,((IF(ISNUMBER(AO24),AO24,0)*100)-(0.0))/((8.0)-(0.0))))+0.2*MIN(1,MAX(0,((IF(ISNUMBER(AP24),AP24,0))-(25.0))/((5.0)-(25.0))))) | BJ24: =100*(0.35*MIN(1,MAX(0,((ABS(AU24))-(0.3))/((0.05)-(0.3))))+0.3*MIN(1,MAX(0,((AV24)-(0.0))/((0.3)-(0.0))))+0.25*MIN(1,MAX(0,((AW24)-(0.4))/((0.7)-(0.4))))+0.1*IF(AY24>=2,1,0.5)) | BK24: =0.25*BG24+0.25*BH24+0.2*BI24+0.3*BJ24 | BL24: 全部通過
A25: 1 | B25: 24 | C25: ADPT | D25: Adaptive Biotechnologies Corporation | E25: NASDAQ | F25: 醫療保健 | G25: Biotechnology: Biological Products (No Diagnostic Substances) | H25: 4.612 | I25: 中型 | J25: 27.37 | K25: 28.9 | L25: =J25/K25-1 | M25: 29 | N25: 27.145 | O25: 6018700 | P25: 2499620 | Q25: =O25/P25 | R25: 28.197 | S25: 27.2931 | T25: 26.5416 | U25: =S25/T25-1 | V25: 1 | W25: =J25/R25-1 | X25: =J25/S25-1 | Y25: 1.272 | Z25: =Y25/J25 | AA25: =(J25-R25)/Y25 | AB25: =(J25-S25)/Y25 | AC25: =IF(ABS(AA25)<=ABS(AB25),"9EMA","21EMA") | AD25: 9+21EMA | AE25: 持續在上方 | AG25: ✓ | AI25: 2026-09-15 | AJ25: 12 | AK25: 2 | AL25: 2026-09-22 | AM25: 26.733 | AN25: 23.53 | AO25: =IF(ISNUMBER(AN25),AM25/AN25-1,"") | AP25: 7 | AQ25: =IF(ISNUMBER(AM25),J25/AM25-1,"") | AR25: 29.57 | AS25: =J25/AR25-1 | AT25: 上傾收窄（楔形） | AU25: 0.6928 | AV25: 1.4628 | AW25: 0.5473 | AX25: 0.5305 | AY25: 5 | AZ25: 29.96 | BA25: 23.53 | BB25: 27.049 | BC25: 0.8816 | BD25: =IF(M25=N25,0.5,(J25-N25)/(M25-N25)) | BE25: 17.203 | BF25: 12.449 | BG25: =100*(0.4*MIN(1,MAX(0,((U25*100)-(0.0))/((2.5)-(0.0))))+0.3*MIN(1,MAX(0,((V25)-(0.6))/((1.0)-(0.6))))+0.3*MIN(1,MAX(0,((BE25)-(0.0))/((15.0)-(0.0))))) | BH25: =100*(0.4*MIN(1,MAX(0,((MIN(ABS(AA25),ABS(AB25)))-(0.75))/((0.0)-(0.75))))+0.3*MIN(1,MAX(0,((BC25)-(1.2))/((0.6)-(1.2))))+0.3*BD25) | BI25: =100*(0.5*MIN(1,MAX(0,((AK25)-(1.0))/((4.0)-(1.0))))+0.3*MIN(1,MAX(0,((IF(ISNUMBER(AO25),AO25,0)*100)-(0.0))/((8.0)-(0.0))))+0.2*MIN(1,MAX(0,((IF(ISNUMBER(AP25),AP25,0))-(25.0))/((5.0)-(25.0))))) | BJ25: =100*(0.35*MIN(1,MAX(0,((ABS(AU25))-(0.3))/((0.05)-(0.3))))+0.3*MIN(1,MAX(0,((AV25)-(0.0))/((0.3)-(0.0))))+0.25*MIN(1,MAX(0,((AW25)-(0.4))/((0.7)-(0.4))))+0.1*IF(AY25>=2,1,0.5)) | BK25: =0.25*BG25+0.25*BH25+0.2*BI25+0.3*BJ25 | BL25: 全部通過
A26: 1 | B26: 25 | C26: DELL | D26: Dell Technologies Inc. Class C | E26: NYSE | F26: 科技 | G26: Computer Manufacturing | H26: 342.035 | I26: 大型 | J26: 541.74 | K26: 537.95 | L26: =J26/K26-1 | M26: 550.29 | N26: 520.18 | O26: 6669200 | P26: 9281610 | Q26: =O26/P26 | R26: 545.0722 | S26: 533.3966 | T26: 526.7666 | U26: =S26/T26-1 | V26: 1 | W26: =J26/R26-1 | X26: =J26/S26-1 | Y26: 29.1657 | Z26: =Y26/J26 | AA26: =(J26-R26)/Y26 | AB26: =(J26-S26)/Y26 | AC26: =IF(ABS(AA26)<=ABS(AB26),"9EMA","21EMA") | AD26: 9+21EMA | AE26: 持續在上方 | AH26: ✓ | AI26: 2026-08-04 | AJ26: 41 | AK26: 3 | AL26: 2026-09-24 | AM26: 530.45 | AN26: 506.25 | AO26: =IF(ISNUMBER(AN26),AM26/AN26-1,"") | AP26: 5 | AQ26: =IF(ISNUMBER(AM26),J26/AM26-1,"") | AR26: 588.4 | AS26: =J26/AR26-1 | AT26: 上傾收窄（楔形） | AU26: 0.7022 | AV26: 1.1702 | AW26: 0.5963 | AX26: 0.6145 | AY26: 3 | AZ26: 595.51 | BA26: 421.89 | BB26: 525.4152 | BC26: 0.9982 | BD26: =IF(M26=N26,0.5,(J26-N26)/(M26-N26)) | BE26: 32.222 | BF26: 27.468 | BG26: =100*(0.4*MIN(1,MAX(0,((U26*100)-(0.0))/((2.5)-(0.0))))+0.3*MIN(1,MAX(0,((V26)-(0.6))/((1.0)-(0.6))))+0.3*MIN(1,MAX(0,((BE26)-(0.0))/((15.0)-(0.0))))) | BH26: =100*(0.4*MIN(1,MAX(0,((MIN(ABS(AA26),ABS(AB26)))-(0.75))/((0.0)-(0.75))))+0.3*MIN(1,MAX(0,((BC26)-(1.2))/((0.6)-(1.2))))+0.3*BD26) | BI26: =100*(0.5*MIN(1,MAX(0,((AK26)-(1.0))/((4.0)-(1.0))))+0.3*MIN(1,MAX(0,((IF(ISNUMBER(AO26),AO26,0)*100)-(0.0))/((8.0)-(0.0))))+0.2*MIN(1,MAX(0,((IF(ISNUMBER(AP26),AP26,0))-(25.0))/((5.0)-(25.0))))) | BJ26: =100*(0.35*MIN(1,MAX(0,((ABS(AU26))-(0.3))/((0.05)-(0.3))))+0.3*MIN(1,MAX(0,((AV26)-(0.0))/((0.3)-(0.0))))+0.25*MIN(1,MAX(0,((AW26)-(0.4))/((0.7)-(0.4))))+0.1*IF(AY26>=2,1,0.5)) | BK26: =0.25*BG26+0.25*BH26+0.2*BI26+0.3*BJ26 | BL26: 全部通過
A27: 1 | B27: 26 | C27: STX | D27: Seagate Technology Holdings PLC | E27: NASDAQ | F27: 科技 | G27: Electronic Components | H27: 210.956 | I27: 大型 | J27: 945.57 | K27: 922.34 | L27: =J27/K27-1 | M27: 946.36 | N27: 893.75 | O27: 2480800 | P27: 3764645 | Q27: =O27/P27 | R27: 909.5021 | S27: 882.858 | T27: 857.0708 | U27: =S27/T27-1 | V27: 1 | W27: =J27/R27-1 | X27: =J27/S27-1 | Y27: 48.238 | Z27: =Y27/J27 | AA27: =(J27-R27)/Y27 | AB27: =(J27-S27)/Y27 | AC27: =IF(ABS(AA27)<=ABS(AB27),"9EMA","21EMA") | AD27: 9EMA | AE27: 持續在上方 | AI27: 2026-09-22 | AJ27: 7 | AK27: 2 | AL27: 2026-09-28 | AM27: 870.38 | AN27: 758.35 | AO27: =IF(ISNUMBER(AN27),AM27/AN27-1,"") | AP27: 3 | AQ27: =IF(ISNUMBER(AM27),J27/AM27-1,"") | AR27: 945.57 | AS27: =J27/AR27-1 | AT27: 上傾收窄（楔形） | AU27: 0.3629 | AV27: 0.7348 | AW27: 0.5406 | AX27: 0.5075 | AY27: 4 | AZ27: 946.36 | BA27: 758.35 | BB27: 859.9854 | BC27: 0.7204 | BD27: =IF(M27=N27,0.5,(J27-N27)/(M27-N27)) | BE27: 20.542 | BF27: 15.788 | BG27: =100*(0.4*MIN(1,MAX(0,((U27*100)-(0.0))/((2.5)-(0.0))))+0.3*MIN(1,MAX(0,((V27)-(0.6))/((1.0)-(0.6))))+0.3*MIN(1,MAX(0,((BE27)-(0.0))/((15.0)-(0.0))))) | BH27: =100*(0.4*MIN(1,MAX(0,((MIN(ABS(AA27),ABS(AB27)))-(0.75))/((0.0)-(0.75))))+0.3*MIN(1,MAX(0,((BC27)-(1.2))/((0.6)-(1.2))))+0.3*BD27) | BI27: =100*(0.5*MIN(1,MAX(0,((AK27)-(1.0))/((4.0)-(1.0))))+0.3*MIN(1,MAX(0,((IF(ISNUMBER(AO27),AO27,0)*100)-(0.0))/((8.0)-(0.0))))+0.2*MIN(1,MAX(0,((IF(ISNUMBER(AP27),AP27,0))-(25.0))/((5.0)-(25.0))))) | BJ27: =100*(0.35*MIN(1,MAX(0,((ABS(AU27))-(0.3))/((0.05)-(0.3))))+0.3*MIN(1,MAX(0,((AV27)-(0.0))/((0.3)-(0.0))))+0.25*MIN(1,MAX(0,((AW27)-(0.4))/((0.7)-(0.4))))+0.1*IF(AY27>=2,1,0.5)) | BK27: =0.25*BG27+0.25*BH27+0.2*BI27+0.3*BJ27 | BL27: 全部通過
A28: 1 | B28: 27 | C28: OBIO | D28: Orchestra BioMed Holdings Inc. | E28: NASDAQ | F28: 醫療保健 | G28: Medicinal Chemicals and Botanical Products | H28: 0.374 | I28: 小型 | J28: 6.35 | K28: 6.22 | L28: =J28/K28-1 | M28: 6.5 | N28: 6.23 | O28: 389900 | P28: 382525 | Q28: =O28/P28 | R28: 6.0841 | S28: 5.8318 | T28: 5.656 | U28: =S28/T28-1 | V28: 1 | W28: =J28/R28-1 | X28: =J28/S28-1 | Y28: 0.3362 | Z28: =Y28/J28 | AA28: =(J28-R28)/Y28 | AB28: =(J28-S28)/Y28 | AC28: =IF(ABS(AA28)<=ABS(AB28),"9EMA","21EMA") | AD28: 9EMA | AE28: 持續在上方 | AI28: 2026-08-03 | AJ28: 42 | AK28: 4 | AL28: 2026-09-24 | AM28: 5.75 | AN28: 5.71 | AO28: =IF(ISNUMBER(AN28),AM28/AN28-1,"") | AP28: 5 | AQ28: =IF(ISNUMBER(AM28),J28/AM28-1,"") | AR28: 6.35 | AS28: =J28/AR28-1 | AT28: 上傾收窄（楔形） | AU28: 0.8451 | AV28: 1.2477 | AW28: 0.5919 | AX28: 0.6395 | AY28: 2 | AZ28: 6.5 | BA28: 4.71 | BB28: 5.7695 | BC28: 0.5585 | BD28: =IF(M28=N28,0.5,(J28-N28)/(M28-N28)) | BE28: 34.346 | BF28: 29.592 | BG28: =100*(0.4*MIN(1,MAX(0,((U28*100)-(0.0))/((2.5)-(0.0))))+0.3*MIN(1,MAX(0,((V28)-(0.6))/((1.0)-(0.6))))+0.3*MIN(1,MAX(0,((BE28)-(0.0))/((15.0)-(0.0))))) | BH28: =100*(0.4*MIN(1,MAX(0,((MIN(ABS(AA28),ABS(AB28)))-(0.75))/((0.0)-(0.75))))+0.3*MIN(1,MAX(0,((BC28)-(1.2))/((0.6)-(1.2))))+0.3*BD28) | BI28: =100*(0.5*MIN(1,MAX(0,((AK28)-(1.0))/((4.0)-(1.0))))+0.3*MIN(1,MAX(0,((IF(ISNUMBER(AO28),AO28,0)*100)-(0.0))/((8.0)-(0.0))))+0.2*MIN(1,MAX(0,((IF(ISNUMBER(AP28),AP28,0))-(25.0))/((5.0)-(25.0))))) | BJ28: =100*(0.35*MIN(1,MAX(0,((ABS(AU28))-(0.3))/((0.05)-(0.3))))+0.3*MIN(1,MAX(0,((AV28)-(0.0))/((0.3)-(0.0))))+0.25*MIN(1,MAX(0,((AW28)-(0.4))/((0.7)-(0.4))))+0.1*IF(AY28>=2,1,0.5)) | BK28: =0.25*BG28+0.25*BH28+0.2*BI28+0.3*BJ28 | BL28: 全部通過
A29: 1 | B29: 28 | C29: ANET | D29: Arista Networks Inc. | E29: NYSE | F29: 電訊 | G29: Computer Communications Equipment | H29: 256.773 | I29: 大型 | J29: 204.49 | K29: 203.59 | L29: =J29/K29-1 | M29: 206.35 | N29: 200.771 | O29: 4106100 | P29: 4781150 | Q29: =O29/P29 | R29: 203.2534 | S29: 199.9286 | T29: 197.2075 | U29: =S29/T29-1 | V29: 1 | W29: =J29/R29-1 | X29: =J29/S29-1 | Y29: 7.0691 | Z29: =Y29/J29 | AA29: =(J29-R29)/Y29 | AB29: =(J29-S29)/Y29 | AC29: =IF(ABS(AA29)<=ABS(AB29),"9EMA","21EMA") | AD29: 9+21EMA | AE29: 持續在上方 | AH29: ✓ | AI29: 2026-07-31 | AJ29: 43 | AK29: 3 | AL29: 2026-09-24 | AM29: 198.757 | AN29: 186.11 | AO29: =IF(ISNUMBER(AN29),AM29/AN29-1,"") | AP29: 5 | AQ29: =IF(ISNUMBER(AM29),J29/AM29-1,"") | AR29: 206.55 | AS29: =J29/AR29-1 | AT29: 上傾收窄（楔形） | AU29: 0.1792 | AV29: 0.6196 | AW29: 0.5462 | AX29: 0.5846 | AY29: 1 | AZ29: 212 | BA29: 181.27 | BB29: 198.0549 | BC29: 1.2441 | BD29: =IF(M29=N29,0.5,(J29-N29)/(M29-N29)) | BE29: 12.801 | BF29: 8.047 | BG29: =100*(0.4*MIN(1,MAX(0,((U29*100)-(0.0))/((2.5)-(0.0))))+0.3*MIN(1,MAX(0,((V29)-(0.6))/((1.0)-(0.6))))+0.3*MIN(1,MAX(0,((BE29)-(0.0))/((15.0)-(0.0))))) | BH29: =100*(0.4*MIN(1,MAX(0,((MIN(ABS(AA29),ABS(AB29)))-(0.75))/((0.0)-(0.75))))+0.3*MIN(1,MAX(0,((BC29)-(1.2))/((0.6)-(1.2))))+0.3*BD29) | BI29: =100*(0.5*MIN(1,MAX(0,((AK29)-(1.0))/((4.0)-(1.0))))+0.3*MIN(1,MAX(0,((IF(ISNUMBER(AO29),AO29,0)*100)-(0.0))/((8.0)-(0.0))))+0.2*MIN(1,MAX(0,((IF(ISNUMBER(AP29),AP29,0))-(25.0))/((5.0)-(25.0))))) | BJ29: =100*(0.35*MIN(1,MAX(0,((ABS(AU29))-(0.3))/((0.05)-(0.3))))+0.3*MIN(1,MAX(0,((AV29)-(0.0))/((0.3)-(0.0))))+0.25*MIN(1,MAX(0,((AW29)-(0.4))/((0.7)-(0.4))))+0.1*IF(AY29>=2,1,0.5)) | BK29: =0.25*BG29+0.25*BH29+0.2*BI29+0.3*BJ29 | BL29: 全部通過
A30: 1 | B30: 29 | C30: ARW | D30: Arrow Electronics Inc. | E30: NYSE | F30: 科技 | G30: Electronic Components | H30: 11.556 | I30: 大型 | J30: 231.63 | K30: 227 | L30: =J30/K30-1 | M30: 232.95 | N30: 225.3 | O30: 471800 | P30: 538675 | Q30: =O30/P30 | R30: 227.1167 | S30: 221.875 | T30: 216.7168 | U30: =S30/T30-1 | V30: 1 | W30: =J30/R30-1 | X30: =J30/S30-1 | Y30: 7.3602 | Z30: =Y30/J30 | AA30: =(J30-R30)/Y30 | AB30: =(J30-S30)/Y30 | AC30: =IF(ABS(AA30)<=ABS(AB30),"9EMA","21EMA") | AD30: 9EMA | AE30: 持續在上方 | AH30: ✓ | AI30: 2026-09-08 | AJ30: 17 | AK30: 4 | AL30: 2026-09-16 | AM30: 207.88 | AN30: 200.99 | AO30: =IF(ISNUMBER(AN30),AM30/AN30-1,"") | AP30: 11 | AQ30: =IF(ISNUMBER(AM30),J30/AM30-1,"") | AR30: 232.8 | AS30: =J30/AR30-1 | AT30: 上傾擴張 | AU30: 0.5025 | AV30: 0.2975 | AW30: 0.5173 | AX30: 0.4888 | AY30: 6 | AZ30: 233.94 | BA30: 200.99 | BB30: 218.0354 | BC30: 0.8659 | BD30: =IF(M30=N30,0.5,(J30-N30)/(M30-N30)) | BE30: 17.207 | BF30: 12.453 | BG30: =100*(0.4*MIN(1,MAX(0,((U30*100)-(0.0))/((2.5)-(0.0))))+0.3*MIN(1,MAX(0,((V30)-(0.6))/((1.0)-(0.6))))+0.3*MIN(1,MAX(0,((BE30)-(0.0))/((15.0)-(0.0))))) | BH30: =100*(0.4*MIN(1,MAX(0,((MIN(ABS(AA30),ABS(AB30)))-(0.75))/((0.0)-(0.75))))+0.3*MIN(1,MAX(0,((BC30)-(1.2))/((0.6)-(1.2))))+0.3*BD30) | BI30: =100*(0.5*MIN(1,MAX(0,((AK30)-(1.0))/((4.0)-(1.0))))+0.3*MIN(1,MAX(0,((IF(ISNUMBER(AO30),AO30,0)*100)-(0.0))/((8.0)-(0.0))))+0.2*MIN(1,MAX(0,((IF(ISNUMBER(AP30),AP30,0))-(25.0))/((5.0)-(25.0))))) | BJ30: =100*(0.35*MIN(1,MAX(0,((ABS(AU30))-(0.3))/((0.05)-(0.3))))+0.3*MIN(1,MAX(0,((AV30)-(0.0))/((0.3)-(0.0))))+0.25*MIN(1,MAX(0,((AW30)-(0.4))/((0.7)-(0.4))))+0.1*IF(AY30>=2,1,0.5)) | BK30: =0.25*BG30+0.25*BH30+0.2*BI30+0.3*BJ30 | BL30: 全部通過
A31: 1 | B31: 30 | C31: FLGT | D31: Fulgent Genetics Inc. | E31: NASDAQ | F31: 醫療保健 | G31: Medical Specialities | H31: 0.606 | I31: 小型 | J31: 21.3 | K31: 22.02 | L31: =J31/K31-1 | M31: 22.05 | N31: 21.12 | O31: 338200 | P31: 330000 | Q31: =O31/P31 | R31: 21.6971 | S31: 21.196 | T31: 20.7358 | U31: =S31/T31-1 | V31: 1 | W31: =J31/R31-1 | X31: =J31/S31-1 | Y31: 0.6669 | Z31: =Y31/J31 | AA31: =(J31-R31)/Y31 | AB31: =(J31-S31)/Y31 | AC31: =IF(ABS(AA31)<=ABS(AB31),"9EMA","21EMA") | AD31: 9+21EMA | AE31: 持續在上方 | AG31: ✓ | AI31: 2026-08-20 | AJ31: 29 | AK31: 4 | AL31: 2026-09-21 | AM31: 21.01 | AN31: 19.04 | AO31: =IF(ISNUMBER(AN31),AM31/AN31-1,"") | AP31: 8 | AQ31: =IF(ISNUMBER(AM31),J31/AM31-1,"") | AR31: 22.36 | AS31: =J31/AR31-1 | AT31: 上升通道 | AU31: 0.5332 | AV31: 0.6606 | AW31: 0.5164 | AX31: 0.5028 | AY31: 2 | AZ31: 22.59 | BA31: 19.04 | BB31: 20.8733 | BC31: 1.2258 | BD31: =IF(M31=N31,0.5,(J31-N31)/(M31-N31)) | BE31: 13.483 | BF31: 8.729 | BG31: =100*(0.4*MIN(1,MAX(0,((U31*100)-(0.0))/((2.5)-(0.0))))+0.3*MIN(1,MAX(0,((V31)-(0.6))/((1.0)-(0.6))))+0.3*MIN(1,MAX(0,((BE31)-(0.0))/((15.0)-(0.0))))) | BH31: =100*(0.4*MIN(1,MAX(0,((MIN(ABS(AA31),ABS(AB31)))-(0.75))/((0.0)-(0.75))))+0.3*MIN(1,MAX(0,((BC31)-(1.2))/((0.6)-(1.2))))+0.3*BD31) | BI31: =100*(0.5*MIN(1,MAX(0,((AK31)-(1.0))/((4.0)-(1.0))))+0.3*MIN(1,MAX(0,((IF(ISNUMBER(AO31),AO31,0)*100)-(0.0))/((8.0)-(0.0))))+0.2*MIN(1,MAX(0,((IF(ISNUMBER(AP31),AP31,0))-(25.0))/((5.0)-(25.0))))) | BJ31: =100*(0.35*MIN(1,MAX(0,((ABS(AU31))-(0.3))/((0.05)-(0.3))))+0.3*MIN(1,MAX(0,((AV31)-(0.0))/((0.3)-(0.0))))+0.25*MIN(1,MAX(0,((AW31)-(0.4))/((0.7)-(0.4))))+0.1*IF(AY31>=2,1,0.5)) | BK31: =0.25*BG31+0.25*BH31+0.2*BI31+0.3*BJ31 | BL31: 全部通過
A32: 1 | B32: 31 | C32: CRSR | D32: Corsair Gaming Inc. | E32: NASDAQ | F32: 科技 | G32: Computer peripheral equipment | H32: 1.46 | I32: 小型 | J32: 13.85 | K32: 13.5 | L32: =J32/K32-1 | M32: 14.24 | N32: 13.385 | O32: 1396000 | P32: 1064355 | Q32: =O32/P32 | R32: 13.5283 | S32: 13.159 | T32: 12.8885 | U32: =S32/T32-1 | V32: 1 | W32: =J32/R32-1 | X32: =J32/S32-1 | Y32: 0.5997 | Z32: =Y32/J32 | AA32: =(J32-R32)/Y32 | AB32: =(J32-S32)/Y32 | AC32: =IF(ABS(AA32)<=ABS(AB32),"9EMA","21EMA") | AD32: 9EMA | AE32: 持續在上方 | AH32: ✓ | AI32: 2026-06-29 | AJ32: 66 | AK32: 6 | AL32: 2026-09-24 | AM32: 13.06 | AN32: 12.05 | AO32: =IF(ISNUMBER(AN32),AM32/AN32-1,"") | AP32: 5 | AQ32: =IF(ISNUMBER(AM32),J32/AM32-1,"") | AR32: 13.85 | AS32: =J32/AR32-1 | AT32: 上傾收窄（楔形） | AU32: 0.5091 | AV32: 0.6863 | AW32: 0.5308 | AX32: 0.6089 | AY32: 1 | AZ32: 14.24 | BA32: 11.55 | BB32: 12.9778 | BC32: 0.9966 | BD32: =IF(M32=N32,0.5,(J32-N32)/(M32-N32)) | BE32: 23.945 | BF32: 19.191 | BG32: =100*(0.4*MIN(1,MAX(0,((U32*100)-(0.0))/((2.5)-(0.0))))+0.3*MIN(1,MAX(0,((V32)-(0.6))/((1.0)-(0.6))))+0.3*MIN(1,MAX(0,((BE32)-(0.0))/((15.0)-(0.0))))) | BH32: =100*(0.4*MIN(1,MAX(0,((MIN(ABS(AA32),ABS(AB32)))-(0.75))/((0.0)-(0.75))))+0.3*MIN(1,MAX(0,((BC32)-(1.2))/((0.6)-(1.2))))+0.3*BD32) | BI32: =100*(0.5*MIN(1,MAX(0,((AK32)-(1.0))/((4.0)-(1.0))))+0.3*MIN(1,MAX(0,((IF(ISNUMBER(AO32),AO32,0)*100)-(0.0))/((8.0)-(0.0))))+0.2*MIN(1,MAX(0,((IF(ISNUMBER(AP32),AP32,0))-(25.0))/((5.0)-(25.0))))) | BJ32: =100*(0.35*MIN(1,MAX(0,((ABS(AU32))-(0.3))/((0.05)-(0.3))))+0.3*MIN(1,MAX(0,((AV32)-(0.0))/((0.3)-(0.0))))+0.25*MIN(1,MAX(0,((AW32)-(0.4))/((0.7)-(0.4))))+0.1*IF(AY32>=2,1,0.5)) | BK32: =0.25*BG32+0.25*BH32+0.2*BI32+0.3*BJ32 | BL32: 全部通過
A33: 1 | B33: 32 | C33: UCTT | D33: Ultra Clean Holdings Inc. | E33: NASDAQ | F33: 科技 | G33: Semiconductors | H33: 3.67 | I33: 中型 | J33: 78.64 | K33: 81.06 | L33: =J33/K33-1 | M33: 81.87 | N33: 77.76 | O33: 1264200 | P33: 872500 | Q33: =O33/P33 | R33: 77.3895 | S33: 75.6253 | T33: 73.4001 | U33: =S33/T33-1 | V33: 0.9 | W33: =J33/R33-1 | X33: =J33/S33-1 | Y33: 4.445 | Z33: =Y33/J33 | AA33: =(J33-R33)/Y33 | AB33: =(J33-S33)/Y33 | AC33: =IF(ABS(AA33)<=ABS(AB33),"9EMA","21EMA") | AD33: 9EMA | AE33: 剛黃金交叉 | AF33: ✓ | AH33: ✓ | AI33: 2026-09-25 | AJ33: 4 | AK33: 2 | AL33: 2026-09-15 | AM33: 64.77 | AN33: 62.68 | AO33: =IF(ISNUMBER(AN33),AM33/AN33-1,"") | AP33: 12 | AQ33: =IF(ISNUMBER(AM33),J33/AM33-1,"") | AR33: 81.06 | AS33: =J33/AR33-1 | AT33: 上升三角（平頂） | AU33: -0.0827 | AV33: 0.3797 | AW33: 0.5265 | AX33: 0.5043 | AY33: 3 | AZ33: 82.57 | BA33: 62.68 | BB33: 73.1529 | BC33: 0.9717 | BD33: =IF(M33=N33,0.5,(J33-N33)/(M33-N33)) | BE33: 25.534 | BF33: 20.78 | BG33: =100*(0.4*MIN(1,MAX(0,((U33*100)-(0.0))/((2.5)-(0.0))))+0.3*MIN(1,MAX(0,((V33)-(0.6))/((1.0)-(0.6))))+0.3*MIN(1,MAX(0,((BE33)-(0.0))/((15.0)-(0.0))))) | BH33: =100*(0.4*MIN(1,MAX(0,((MIN(ABS(AA33),ABS(AB33)))-(0.75))/((0.0)-(0.75))))+0.3*MIN(1,MAX(0,((BC33)-(1.2))/((0.6)-(1.2))))+0.3*BD33) | BI33: =100*(0.5*MIN(1,MAX(0,((AK33)-(1.0))/((4.0)-(1.0))))+0.3*MIN(1,MAX(0,((IF(ISNUMBER(AO33),AO33,0)*100)-(0.0))/((8.0)-(0.0))))+0.2*MIN(1,MAX(0,((IF(ISNUMBER(AP33),AP33,0))-(25.0))/((5.0)-(25.0))))) | BJ33: =100*(0.35*MIN(1,MAX(0,((ABS(AU33))-(0.3))/((0.05)-(0.3))))+0.3*MIN(1,MAX(0,((AV33)-(0.0))/((0.3)-(0.0))))+0.25*MIN(1,MAX(0,((AW33)-(0.4))/((0.7)-(0.4))))+0.1*IF(AY33>=2,1,0.5)) | BK33: =0.25*BG33+0.25*BH33+0.2*BI33+0.3*BJ33 | BL33: 全部通過
A34: 1 | B34: 33 | C34: NTAP | D34: NetApp Inc. | E34: NASDAQ | F34: 科技 | G34: Electronic Components | H34: 41.264 | I34: 大型 | J34: 215.05 | K34: 210.08 | L34: =J34/K34-1 | M34: 215.22 | N34: 208.03 | O34: 2348700 | P34: 2566565 | Q34: =O34/P34 | R34: 204.5743 | S34: 198.3394 | T34: 192.0695 | U34: =S34/T34-1 | V34: 1 | W34: =J34/R34-1 | X34: =J34/S34-1 | Y34: 7.7496 | Z34: =Y34/J34 | AA34: =(J34-R34)/Y34 | AB34: =(J34-S34)/Y34 | AC34: =IF(ABS(AA34)<=ABS(AB34),"9EMA","21EMA") | AD34: 9EMA | AE34: 持續在上方 | AI34: 2026-09-11 | AJ34: 14 | AK34: 2 | AL34: 2026-09-22 | AM34: 190.89 | AN34: 161 | AO34: =IF(ISNUMBER(AN34),AM34/AN34-1,"") | AP34: 7 | AQ34: =IF(ISNUMBER(AM34),J34/AM34-1,"") | AR34: 215.05 | AS34: =J34/AR34-1 | AT34: 上傾收窄（楔形） | AU34: 0.4592 | AV34: 1.1583 | AW34: 0.5816 | AX34: 0.3701 | AY34: 2 | AZ34: 216.81 | BA34: 161 | BB34: 193.4577 | BC34: 0.8843 | BD34: =IF(M34=N34,0.5,(J34-N34)/(M34-N34)) | BE34: 22.165 | BF34: 17.411 | BG34: =100*(0.4*MIN(1,MAX(0,((U34*100)-(0.0))/((2.5)-(0.0))))+0.3*MIN(1,MAX(0,((V34)-(0.6))/((1.0)-(0.6))))+0.3*MIN(1,MAX(0,((BE34)-(0.0))/((15.0)-(0.0))))) | BH34: =100*(0.4*MIN(1,MAX(0,((MIN(ABS(AA34),ABS(AB34)))-(0.75))/((0.0)-(0.75))))+0.3*MIN(1,MAX(0,((BC34)-(1.2))/((0.6)-(1.2))))+0.3*BD34) | BI34: =100*(0.5*MIN(1,MAX(0,((AK34)-(1.0))/((4.0)-(1.0))))+0.3*MIN(1,MAX(0,((IF(ISNUMBER(AO34),AO34,0)*100)-(0.0))/((8.0)-(0.0))))+0.2*MIN(1,MAX(0,((IF(ISNUMBER(AP34),AP34,0))-(25.0))/((5.0)-(25.0))))) | BJ34: =100*(0.35*MIN(1,MAX(0,((ABS(AU34))-(0.3))/((0.05)-(0.3))))+0.3*MIN(1,MAX(0,((AV34)-(0.0))/((0.3)-(0.0))))+0.25*MIN(1,MAX(0,((AW34)-(0.4))/((0.7)-(0.4))))+0.1*IF(AY34>=2,1,0.5)) | BK34: =0.25*BG34+0.25*BH34+0.2*BI34+0.3*BJ34 | BL34: 全部通過
A35: 1 | B35: 34 | C35: OSPN | D35: OneSpan Inc. | E35: NASDAQ | F35: 科技 | G35: EDP Services | H35: 0.66 | I35: 小型 | J35: 18.04 | K35: 17.91 | L35: =J35/K35-1 | M35: 18.25 | N35: 17.58 | O35: 514100 | P35: 584265 | Q35: =O35/P35 | R35: 17.7902 | S35: 17.3836 | T35: 17.0675 | U35: =S35/T35-1 | V35: 1 | W35: =J35/R35-1 | X35: =J35/S35-1 | Y35: 0.5678 | Z35: =Y35/J35 | AA35: =(J35-R35)/Y35 | AB35: =(J35-S35)/Y35 | AC35: =IF(ABS(AA35)<=ABS(AB35),"9EMA","21EMA") | AD35: 9EMA | AE35: 持續在上方 | AH35: ✓ | AI35: 2026-08-27 | AJ35: 24 | AK35: 3 | AL35: 2026-09-22 | AM35: 17.05 | AN35: 15.97 | AO35: =IF(ISNUMBER(AN35),AM35/AN35-1,"") | AP35: 7 | AQ35: =IF(ISNUMBER(AM35),J35/AM35-1,"") | AR35: 18.04 | AS35: =J35/AR35-1 | AT35: 上傾收窄（楔形） | AU35: 0.4796 | AV35: 0.7483 | AW35: 0.6649 | AX35: 0.683 | AY35: 6 | AZ35: 18.25 | BA35: 15.58 | BB35: 17.3552 | BC35: 2.0453 | BD35: =IF(M35=N35,0.5,(J35-N35)/(M35-N35)) | BE35: 18.356 | BF35: 13.602 | BG35: =100*(0.4*MIN(1,MAX(0,((U35*100)-(0.0))/((2.5)-(0.0))))+0.3*MIN(1,MAX(0,((V35)-(0.6))/((1.0)-(0.6))))+0.3*MIN(1,MAX(0,((BE35)-(0.0))/((15.0)-(0.0))))) | BH35: =100*(0.4*MIN(1,MAX(0,((MIN(ABS(AA35),ABS(AB35)))-(0.75))/((0.0)-(0.75))))+0.3*MIN(1,MAX(0,((BC35)-(1.2))/((0.6)-(1.2))))+0.3*BD35) | BI35: =100*(0.5*MIN(1,MAX(0,((AK35)-(1.0))/((4.0)-(1.0))))+0.3*MIN(1,MAX(0,((IF(ISNUMBER(AO35),AO35,0)*100)-(0.0))/((8.0)-(0.0))))+0.2*MIN(1,MAX(0,((IF(ISNUMBER(AP35),AP35,0))-(25.0))/((5.0)-(25.0))))) | BJ35: =100*(0.35*MIN(1,MAX(0,((ABS(AU35))-(0.3))/((0.05)-(0.3))))+0.3*MIN(1,MAX(0,((AV35)-(0.0))/((0.3)-(0.0))))+0.25*MIN(1,MAX(0,((AW35)-(0.4))/((0.7)-(0.4))))+0.1*IF(AY35>=2,1,0.5)) | BK35: =0.25*BG35+0.25*BH35+0.2*BI35+0.3*BJ35 | BL35: 全部通過
A36: 1 | B36: 35 | C36: TWIN | D36: Twin Disc Incorporated | E36: NASDAQ | F36: 工業 | G36: Industrial Machinery/Components | H36: 0.381 | I36: 小型 | J36: 26.86 | K36: 26.2 | L36: =J36/K36-1 | M36: 26.95 | N36: 25.25 | O36: 99100 | P36: 87610 | Q36: =O36/P36 | R36: 26.0685 | S36: 25.2963 | T36: 24.5961 | U36: =S36/T36-1 | V36: 1 | W36: =J36/R36-1 | X36: =J36/S36-1 | Y36: 1.0265 | Z36: =Y36/J36 | AA36: =(J36-R36)/Y36 | AB36: =(J36-S36)/Y36 | AC36: =IF(ABS(AA36)<=ABS(AB36),"9EMA","21EMA") | AD36: 9+21EMA | AE36: 持續在上方 | AI36: 2026-09-08 | AJ36: 17 | AK36: 3 | AL36: 2026-09-16 | AM36: 23.56 | AN36: 22.16 | AO36: =IF(ISNUMBER(AN36),AM36/AN36-1,"") | AP36: 11 | AQ36: =IF(ISNUMBER(AM36),J36/AM36-1,"") | AR36: 26.86 | AS36: =J36/AR36-1 | AT36: 上升通道 | AU36: 0.5939 | AV36: 0.5212 | AW36: 0.526 | AX36: 0.5101 | AY36: 5 | AZ36: 26.96 | BA36: 22.16 | BB36: 24.6848 | BC36: 0.8702 | BD36: =IF(M36=N36,0.5,(J36-N36)/(M36-N36)) | BE36: 24.558 | BF36: 19.804 | BG36: =100*(0.4*MIN(1,MAX(0,((U36*100)-(0.0))/((2.5)-(0.0))))+0.3*MIN(1,MAX(0,((V36)-(0.6))/((1.0)-(0.6))))+0.3*MIN(1,MAX(0,((BE36)-(0.0))/((15.0)-(0.0))))) | BH36: =100*(0.4*MIN(1,MAX(0,((MIN(ABS(AA36),ABS(AB36)))-(0.75))/((0.0)-(0.75))))+0.3*MIN(1,MAX(0,((BC36)-(1.2))/((0.6)-(1.2))))+0.3*BD36) | BI36: =100*(0.5*MIN(1,MAX(0,((AK36)-(1.0))/((4.0)-(1.0))))+0.3*MIN(1,MAX(0,((IF(ISNUMBER(AO36),AO36,0)*100)-(0.0))/((8.0)-(0.0))))+0.2*MIN(1,MAX(0,((IF(ISNUMBER(AP36),AP36,0))-(25.0))/((5.0)-(25.0))))) | BJ36: =100*(0.35*MIN(1,MAX(0,((ABS(AU36))-(0.3))/((0.05)-(0.3))))+0.3*MIN(1,MAX(0,((AV36)-(0.0))/((0.3)-(0.0))))+0.25*MIN(1,MAX(0,((AW36)-(0.4))/((0.7)-(0.4))))+0.1*IF(AY36>=2,1,0.5)) | BK36: =0.25*BG36+0.25*BH36+0.2*BI36+0.3*BJ36 | BL36: 全部通過
A37: 1 | B37: 36 | C37: CHPT | D37: ChargePoint Holdings Inc. | E37: NYSE | F37: 其他 | G37: Industrial Machinery/Components | H37: 0.271 | I37: 小型 | J37: 10.2 | K37: 10.08 | L37: =J37/K37-1 | M37: 10.435 | N37: 9.777 | O37: 1055500 | P37: 4420845 | Q37: =O37/P37 | R37: 9.522 | S37: 8.8907 | T37: 8.4773 | U37: =S37/T37-1 | V37: 1 | W37: =J37/R37-1 | X37: =J37/S37-1 | Y37: 0.7117 | Z37: =Y37/J37 | AA37: =(J37-R37)/Y37 | AB37: =(J37-S37)/Y37 | AC37: =IF(ABS(AA37)<=ABS(AB37),"9EMA","21EMA") | AD37: 9+21EMA | AE37: 持續在上方 | AI37: 2026-09-03 | AJ37: 19 | AK37: 3 | AL37: 2026-09-28 | AM37: 8.65 | AN37: 8.56 | AO37: =IF(ISNUMBER(AN37),AM37/AN37-1,"") | AP37: 3 | AQ37: =IF(ISNUMBER(AM37),J37/AM37-1,"") | AR37: 10.32 | AS37: =J37/AR37-1 | AT37: 上傾收窄（楔形） | AU37: 0.3554 | AV37: 1.6429 | AW37: 0.7195 | AX37: 0.7756 | AY37: 2 | AZ37: 10.72 | BA37: 5.19 | BB37: 9.1687 | BC37: 0.8345 | BD37: =IF(M37=N37,0.5,(J37-N37)/(M37-N37)) | BE37: 97.207 | BF37: 92.453 | BG37: =100*(0.4*MIN(1,MAX(0,((U37*100)-(0.0))/((2.5)-(0.0))))+0.3*MIN(1,MAX(0,((V37)-(0.6))/((1.0)-(0.6))))+0.3*MIN(1,MAX(0,((BE37)-(0.0))/((15.0)-(0.0))))) | BH37: =100*(0.4*MIN(1,MAX(0,((MIN(ABS(AA37),ABS(AB37)))-(0.75))/((0.0)-(0.75))))+0.3*MIN(1,MAX(0,((BC37)-(1.2))/((0.6)-(1.2))))+0.3*BD37) | BI37: =100*(0.5*MIN(1,MAX(0,((AK37)-(1.0))/((4.0)-(1.0))))+0.3*MIN(1,MAX(0,((IF(ISNUMBER(AO37),AO37,0)*100)-(0.0))/((8.0)-(0.0))))+0.2*MIN(1,MAX(0,((IF(ISNUMBER(AP37),AP37,0))-(25.0))/((5.0)-(25.0))))) | BJ37: =100*(0.35*MIN(1,MAX(0,((ABS(AU37))-(0.3))/((0.05)-(0.3))))+0.3*MIN(1,MAX(0,((AV37)-(0.0))/((0.3)-(0.0))))+0.25*MIN(1,MAX(0,((AW37)-(0.4))/((0.7)-(0.4))))+0.1*IF(AY37>=2,1,0.5)) | BK37: =0.25*BG37+0.25*BH37+0.2*BI37+0.3*BJ37 | BL37: 全部通過
A38: 1 | B38: 37 | C38: VRNS | D38: Varonis Systems Inc. | E38: NASDAQ | F38: 科技 | G38: Computer Software: Prepackaged Software | H38: 5.45 | I38: 中型 | J38: 47.45 | K38: 47.45 | L38: =J38/K38-1 | M38: 48.1 | N38: 46.55 | O38: 1440200 | P38: 1852255 | Q38: =O38/P38 | R38: 47.3604 | S38: 46.6515 | T38: 46.2728 | U38: =S38/T38-1 | V38: 0.9 | W38: =J38/R38-1 | X38: =J38/S38-1 | Y38: 1.9231 | Z38: =Y38/J38 | AA38: =(J38-R38)/Y38 | AB38: =(J38-S38)/Y38 | AC38: =IF(ABS(AA38)<=ABS(AB38),"9EMA","21EMA") | AD38: 9+21EMA | AE38: 持續在上方 | AH38: ✓ | AI38: 2026-08-31 | AJ38: 22 | AK38: 4 | AL38: 2026-09-28 | AM38: 44.62 | AN38: 44.172 | AO38: =IF(ISNUMBER(AN38),AM38/AN38-1,"") | AP38: 3 | AQ38: =IF(ISNUMBER(AM38),J38/AM38-1,"") | AR38: 48.455 | AS38: =J38/AR38-1 | AT38: 上升通道 | AU38: 0.4004 | AV38: 0.416 | AW38: 0.7111 | AX38: 0.681 | AY38: 12 | AZ38: 48.79 | BA38: 40.89 | BB38: 46.5078 | BC38: 1.1322 | BD38: =IF(M38=N38,0.5,(J38-N38)/(M38-N38)) | BE38: 16.797 | BF38: 12.043 | BG38: =100*(0.4*MIN(1,MAX(0,((U38*100)-(0.0))/((2.5)-(0.0))))+0.3*MIN(1,MAX(0,((V38)-(0.6))/((1.0)-(0.6))))+0.3*MIN(1,MAX(0,((BE38)-(0.0))/((15.0)-(0.0))))) | BH38: =100*(0.4*MIN(1,MAX(0,((MIN(ABS(AA38),ABS(AB38)))-(0.75))/((0.0)-(0.75))))+0.3*MIN(1,MAX(0,((BC38)-(1.2))/((0.6)-(1.2))))+0.3*BD38) | BI38: =100*(0.5*MIN(1,MAX(0,((AK38)-(1.0))/((4.0)-(1.0))))+0.3*MIN(1,MAX(0,((IF(ISNUMBER(AO38),AO38,0)*100)-(0.0))/((8.0)-(0.0))))+0.2*MIN(1,MAX(0,((IF(ISNUMBER(AP38),AP38,0))-(25.0))/((5.0)-(25.0))))) | BJ38: =100*(0.35*MIN(1,MAX(0,((ABS(AU38))-(0.3))/((0.05)-(0.3))))+0.3*MIN(1,MAX(0,((AV38)-(0.0))/((0.3)-(0.0))))+0.25*MIN(1,MAX(0,((AW38)-(0.4))/((0.7)-(0.4))))+0.1*IF(AY38>=2,1,0.5)) | BK38: =0.25*BG38+0.25*BH38+0.2*BI38+0.3*BJ38 | BL38: 全部通過
A39: 1 | B39: 38 | C39: INFU | D39: InfuSystems Holdings Inc. | E39: AMEX | F39: 醫療保健 | G39: Medical/Dental Instruments | H39: 0.257 | I39: 小型 | J39: 12.82 | K39: 12.89 | L39: =J39/K39-1 | M39: 13.06 | N39: 12.62 | O39: 111800 | P39: 142220 | Q39: =O39/P39 | R39: 12.7932 | S39: 12.5514 | T39: 12.3582 | U39: =S39/T39-1 | V39: 1 | W39: =J39/R39-1 | X39: =J39/S39-1 | Y39: 0.4053 | Z39: =Y39/J39 | AA39: =(J39-R39)/Y39 | AB39: =(J39-S39)/Y39 | AC39: =IF(ABS(AA39)<=ABS(AB39),"9EMA","21EMA") | AD39: 9EMA | AE39: 持續在上方 | AH39: ✓ | AI39: 2026-08-04 | AJ39: 41 | AK39: 2 | AL39: 2026-09-25 | AM39: 12.47 | AN39: 11.8 | AO39: =IF(ISNUMBER(AN39),AM39/AN39-1,"") | AP39: 4 | AQ39: =IF(ISNUMBER(AM39),J39/AM39-1,"") | AR39: 13.11 | AS39: =J39/AR39-1 | AT39: 上升通道 | AU39: 0.5112 | AV39: 0.4273 | AW39: 0.5098 | AX39: 0.5113 | AY39: 6 | AZ39: 13.2 | BA39: 11.8 | BB39: 12.5137 | BC39: 0.6457 | BD39: =IF(M39=N39,0.5,(J39-N39)/(M39-N39)) | BE39: 10.705 | BF39: 5.95 | BG39: =100*(0.4*MIN(1,MAX(0,((U39*100)-(0.0))/((2.5)-(0.0))))+0.3*MIN(1,MAX(0,((V39)-(0.6))/((1.0)-(0.6))))+0.3*MIN(1,MAX(0,((BE39)-(0.0))/((15.0)-(0.0))))) | BH39: =100*(0.4*MIN(1,MAX(0,((MIN(ABS(AA39),ABS(AB39)))-(0.75))/((0.0)-(0.75))))+0.3*MIN(1,MAX(0,((BC39)-(1.2))/((0.6)-(1.2))))+0.3*BD39) | BI39: =100*(0.5*MIN(1,MAX(0,((AK39)-(1.0))/((4.0)-(1.0))))+0.3*MIN(1,MAX(0,((IF(ISNUMBER(AO39),AO39,0)*100)-(0.0))/((8.0)-(0.0))))+0.2*MIN(1,MAX(0,((IF(ISNUMBER(AP39),AP39,0))-(25.0))/((5.0)-(25.0))))) | BJ39: =100*(0.35*MIN(1,MAX(0,((ABS(AU39))-(0.3))/((0.05)-(0.3))))+0.3*MIN(1,MAX(0,((AV39)-(0.0))/((0.3)-(0.0))))+0.25*MIN(1,MAX(0,((AW39)-(0.4))/((0.7)-(0.4))))+0.1*IF(AY39>=2,1,0.5)) | BK39: =0.25*BG39+0.25*BH39+0.2*BI39+0.3*BJ39 | BL39: 全部通過
A40: 1 | B40: 39 | C40: HPE | D40: Hewlett Packard Enterprise Company | E40: NYSE | F40: 科技 | G40: Retail: Computer Software & Peripheral Equipment | H40: 84.812 | I40: 大型 | J40: 64.58 | K40: 63.89 | L40: =J40/K40-1 | M40: 66.11 | N40: 61.76 | O40: 16428700 | P40: 25777965 | Q40: =O40/P40 | R40: 62.4052 | S40: 59.9405 | T40: 57.9522 | U40: =S40/T40-1 | V40: 1 | W40: =J40/R40-1 | X40: =J40/S40-1 | Y40: 3.6134 | Z40: =Y40/J40 | AA40: =(J40-R40)/Y40 | AB40: =(J40-S40)/Y40 | AC40: =IF(ABS(AA40)<=ABS(AB40),"9EMA","21EMA") | AD40: 9EMA | AE40: 持續在上方 | AI40: 2026-09-03 | AJ40: 19 | AK40: 2 | AL40: 2026-09-16 | AM40: 55.02 | AN40: 45.7 | AO40: =IF(ISNUMBER(AN40),AM40/AN40-1,"") | AP40: 11 | AQ40: =IF(ISNUMBER(AM40),J40/AM40-1,"") | AR40: 64.58 | AS40: =J40/AR40-1 | AT40: 上傾收窄（楔形） | AU40: 0.9856 | AV40: 1.804 | AW40: 0.5469 | AX40: 0.4766 | AY40: 2 | AZ40: 67.101 | BA40: 45.7 | BB40: 57.4038 | BC40: 0.8122 | BD40: =IF(M40=N40,0.5,(J40-N40)/(M40-N40)) | BE40: 31.705 | BF40: 26.951 | BG40: =100*(0.4*MIN(1,MAX(0,((U40*100)-(0.0))/((2.5)-(0.0))))+0.3*MIN(1,MAX(0,((V40)-(0.6))/((1.0)-(0.6))))+0.3*MIN(1,MAX(0,((BE40)-(0.0))/((15.0)-(0.0))))) | BH40: =100*(0.4*MIN(1,MAX(0,((MIN(ABS(AA40),ABS(AB40)))-(0.75))/((0.0)-(0.75))))+0.3*MIN(1,MAX(0,((BC40)-(1.2))/((0.6)-(1.2))))+0.3*BD40) | BI40: =100*(0.5*MIN(1,MAX(0,((AK40)-(1.0))/((4.0)-(1.0))))+0.3*MIN(1,MAX(0,((IF(ISNUMBER(AO40),AO40,0)*100)-(0.0))/((8.0)-(0.0))))+0.2*MIN(1,MAX(0,((IF(ISNUMBER(AP40),AP40,0))-(25.0))/((5.0)-(25.0))))) | BJ40: =100*(0.35*MIN(1,MAX(0,((ABS(AU40))-(0.3))/((0.05)-(0.3))))+0.3*MIN(1,MAX(0,((AV40)-(0.0))/((0.3)-(0.0))))+0.25*MIN(1,MAX(0,((AW40)-(0.4))/((0.7)-(0.4))))+0.1*IF(AY40>=2,1,0.5)) | BK40: =0.25*BG40+0.25*BH40+0.2*BI40+0.3*BJ40 | BL40: 全部通過
A41: 1 | B41: 40 | C41: NGVC | D41: Natural Grocers by Vitamin Cottage Inc. | E41: NYSE | F41: 必需消費 | G41: Food Chains | H41: 0.702 | I41: 小型 | J41: 30.48 | K41: 30.46 | L41: =J41/K41-1 | M41: 31.02 | N41: 30.27 | O41: 120400 | P41: 156870 | Q41: =O41/P41 | R41: 30.1577 | S41: 29.5914 | T41: 29.1153 | U41: =S41/T41-1 | V41: 1 | W41: =J41/R41-1 | X41: =J41/S41-1 | Y41: 1.0513 | Z41: =Y41/J41 | AA41: =(J41-R41)/Y41 | AB41: =(J41-S41)/Y41 | AC41: =IF(ABS(AA41)<=ABS(AB41),"9EMA","21EMA") | AD41: 9EMA | AE41: 持續在上方 | AH41: ✓ | AI41: 2026-09-16 | AJ41: 11 | AK41: 2 | AL41: 2026-09-25 | AM41: 29.48 | AN41: 26.5 | AO41: =IF(ISNUMBER(AN41),AM41/AN41-1,"") | AP41: 4 | AQ41: =IF(ISNUMBER(AM41),J41/AM41-1,"") | AR41: 30.98 | AS41: =J41/AR41-1 | AT41: 上傾擴張 | AU41: 0.7672 | AV41: 0.4556 | AW41: 0.5234 | AX41: 0.5464 | AY41: 3 | AZ41: 31.61 | BA41: 26.5 | BB41: 29.1745 | BC41: 0.688 | BD41: =IF(M41=N41,0.5,(J41-N41)/(M41-N41)) | BE41: 15.389 | BF41: 10.635 | BG41: =100*(0.4*MIN(1,MAX(0,((U41*100)-(0.0))/((2.5)-(0.0))))+0.3*MIN(1,MAX(0,((V41)-(0.6))/((1.0)-(0.6))))+0.3*MIN(1,MAX(0,((BE41)-(0.0))/((15.0)-(0.0))))) | BH41: =100*(0.4*MIN(1,MAX(0,((MIN(ABS(AA41),ABS(AB41)))-(0.75))/((0.0)-(0.75))))+0.3*MIN(1,MAX(0,((BC41)-(1.2))/((0.6)-(1.2))))+0.3*BD41) | BI41: =100*(0.5*MIN(1,MAX(0,((AK41)-(1.0))/((4.0)-(1.0))))+0.3*MIN(1,MAX(0,((IF(ISNUMBER(AO41),AO41,0)*100)-(0.0))/((8.0)-(0.0))))+0.2*MIN(1,MAX(0,((IF(ISNUMBER(AP41),AP41,0))-(25.0))/((5.0)-(25.0))))) | BJ41: =100*(0.35*MIN(1,MAX(0,((ABS(AU41))-(0.3))/((0.05)-(0.3))))+0.3*MIN(1,MAX(0,((AV41)-(0.0))/((0.3)-(0.0))))+0.25*MIN(1,MAX(0,((AW41)-(0.4))/((0.7)-(0.4))))+0.1*IF(AY41>=2,1,0.5)) | BK41: =0.25*BG41+0.25*BH41+0.2*BI41+0.3*BJ41 | BL41: 全部通過
A42: 1 | B42: 41 | C42: PI | D42: Impinj Inc. | E42: NASDAQ | F42: 科技 | G42: Industrial Machinery/Components | H42: 5.478 | I42: 中型 | J42: 183.87 | K42: 179.29 | L42: =J42/K42-1 | M42: 185.725 | N42: 177.895 | O42: 350400 | P42: 404785 | Q42: =O42/P42 | R42: 179.0438 | S42: 176.2224 | T42: 174.3888 | U42: =S42/T42-1 | V42: 1 | W42: =J42/R42-1 | X42: =J42/S42-1 | Y42: 7.3973 | Z42: =Y42/J42 | AA42: =(J42-R42)/Y42 | AB42: =(J42-S42)/Y42 | AC42: =IF(ABS(AA42)<=ABS(AB42),"9EMA","21EMA") | AD42: 9+21EMA | AE42: 持續在上方 | AH42: ✓ | AI42: 2026-07-30 | AJ42: 44 | AK42: 4 | AL42: 2026-09-24 | AM42: 172.4 | AN42: 161.17 | AO42: =IF(ISNUMBER(AN42),AM42/AN42-1,"") | AP42: 5 | AQ42: =IF(ISNUMBER(AM42),J42/AM42-1,"") | AR42: 184.045 | AS42: =J42/AR42-1 | AT42: 上傾收窄（楔形） | AU42: 0.2417 | AV42: 0.6108 | AW42: 0.5848 | AX42: 0.5769 | AY42: 3 | AZ42: 186.66 | BA42: 160.65 | BB42: 175.8599 | BC42: 1.2597 | BD42: =IF(M42=N42,0.5,(J42-N42)/(M42-N42)) | BE42: 14.077 | BF42: 9.323 | BG42: =100*(0.4*MIN(1,MAX(0,((U42*100)-(0.0))/((2.5)-(0.0))))+0.3*MIN(1,MAX(0,((V42)-(0.6))/((1.0)-(0.6))))+0.3*MIN(1,MAX(0,((BE42)-(0.0))/((15.0)-(0.0))))) | BH42: =100*(0.4*MIN(1,MAX(0,((MIN(ABS(AA42),ABS(AB42)))-(0.75))/((0.0)-(0.75))))+0.3*MIN(1,MAX(0,((BC42)-(1.2))/((0.6)-(1.2))))+0.3*BD42) | BI42: =100*(0.5*MIN(1,MAX(0,((AK42)-(1.0))/((4.0)-(1.0))))+0.3*MIN(1,MAX(0,((IF(ISNUMBER(AO42),AO42,0)*100)-(0.0))/((8.0)-(0.0))))+0.2*MIN(1,MAX(0,((IF(ISNUMBER(AP42),AP42,0))-(25.0))/((5.0)-(25.0))))) | BJ42: =100*(0.35*MIN(1,MAX(0,((ABS(AU42))-(0.3))/((0.05)-(0.3))))+0.3*MIN(1,MAX(0,((AV42)-(0.0))/((0.3)-(0.0))))+0.25*MIN(1,MAX(0,((AW42)-(0.4))/((0.7)-(0.4))))+0.1*IF(AY42>=2,1,0.5)) | BK42: =0.25*BG42+0.25*BH42+0.2*BI42+0.3*BJ42 | BL42: 全部通過
A43: 1 | B43: 42 | C43: CRWD | D43: CrowdStrike Holdings Inc. | E43: NASDAQ | F43: 科技 | G43: Computer Software: Prepackaged Software | H43: 271.087 | I43: 大型 | J43: 266.09 | K43: 264.75 | L43: =J43/K43-1 | M43: 269.3 | N43: 259.3 | O43: 6947000 | P43: 10898615 | Q43: =O43/P43 | R43: 256.9822 | S43: 243.0427 | T43: 231.7042 | U43: =S43/T43-1 | V43: 1 | W43: =J43/R43-1 | X43: =J43/S43-1 | Y43: 11.7506 | Z43: =Y43/J43 | AA43: =(J43-R43)/Y43 | AB43: =(J43-S43)/Y43 | AC43: =IF(ABS(AA43)<=ABS(AB43),"9EMA","21EMA") | AD43: — | AE43: 持續在上方 | AI43: 2026-08-27 | AJ43: 24 | AK43: 6 | AL43: 2026-09-28 | AM43: 246.51 | AN43: 230.85 | AO43: =IF(ISNUMBER(AN43),AM43/AN43-1,"") | AP43: 3 | AQ43: =IF(ISNUMBER(AM43),J43/AM43-1,"") | AR43: 266.09 | AS43: =J43/AR43-1 | AT43: 上升通道 | AU43: 0.8739 | AV43: 1.0747 | AW43: 0.5009 | AX43: 0.5041 | AY43: 3 | AZ43: 269.3 | BA43: 200.6 | BB43: 235.0099 | BC43: 1.2308 | BD43: =IF(M43=N43,0.5,(J43-N43)/(M43-N43)) | BE43: 28.477 | BF43: 23.723 | BG43: =100*(0.4*MIN(1,MAX(0,((U43*100)-(0.0))/((2.5)-(0.0))))+0.3*MIN(1,MAX(0,((V43)-(0.6))/((1.0)-(0.6))))+0.3*MIN(1,MAX(0,((BE43)-(0.0))/((15.0)-(0.0))))) | BH43: =100*(0.4*MIN(1,MAX(0,((MIN(ABS(AA43),ABS(AB43)))-(0.75))/((0.0)-(0.75))))+0.3*MIN(1,MAX(0,((BC43)-(1.2))/((0.6)-(1.2))))+0.3*BD43) | BI43: =100*(0.5*MIN(1,MAX(0,((AK43)-(1.0))/((4.0)-(1.0))))+0.3*MIN(1,MAX(0,((IF(ISNUMBER(AO43),AO43,0)*100)-(0.0))/((8.0)-(0.0))))+0.2*MIN(1,MAX(0,((IF(ISNUMBER(AP43),AP43,0))-(25.0))/((5.0)-(25.0))))) | BJ43: =100*(0.35*MIN(1,MAX(0,((ABS(AU43))-(0.3))/((0.05)-(0.3))))+0.3*MIN(1,MAX(0,((AV43)-(0.0))/((0.3)-(0.0))))+0.25*MIN(1,MAX(0,((AW43)-(0.4))/((0.7)-(0.4))))+0.1*IF(AY43>=2,1,0.5)) | BK43: =0.25*BG43+0.25*BH43+0.2*BI43+0.3*BJ43 | BL43: 全部通過
A44: 1 | B44: 43 | C44: NVDA | D44: NVIDIA Corporation | E44: NASDAQ | F44: 科技 | G44: Semiconductors | H44: 5503.958 | I44: 大型 | J44: 230.86 | K44: 228.38 | L44: =J44/K44-1 | M44: 232.29 | N44: 228.16 | O44: 98369800 | P44: 109930565 | Q44: =O44/P44 | R44: 226.7739 | S44: 223.7414 | T44: 220.9661 | U44: =S44/T44-1 | V44: 1 | W44: =J44/R44-1 | X44: =J44/S44-1 | Y44: 5.8247 | Z44: =Y44/J44 | AA44: =(J44-R44)/Y44 | AB44: =(J44-S44)/Y44 | AC44: =IF(ABS(AA44)<=ABS(AB44),"9EMA","21EMA") | AD44: — | AE44: 持續在上方 | AH44: ✓ | AI44: 2026-09-18 | AJ44: 9 | AK44: 2 | AL44: 2026-09-24 | AM44: 221.09 | AN44: 208.93 | AO44: =IF(ISNUMBER(AN44),AM44/AN44-1,"") | AP44: 5 | AQ44: =IF(ISNUMBER(AM44),J44/AM44-1,"") | AR44: 230.86 | AS44: =J44/AR44-1 | AT44: 上升三角（平頂） | AU44: 0.0046 | AV44: 0.1622 | AW44: 0.5614 | AX44: 0.6267 | AY44: 6 | AZ44: 234.76 | BA44: 208.93 | BB44: 223.4306 | BC44: 0.7386 | BD44: =IF(M44=N44,0.5,(J44-N44)/(M44-N44)) | BE44: 10.926 | BF44: 6.172 | BG44: =100*(0.4*MIN(1,MAX(0,((U44*100)-(0.0))/((2.5)-(0.0))))+0.3*MIN(1,MAX(0,((V44)-(0.6))/((1.0)-(0.6))))+0.3*MIN(1,MAX(0,((BE44)-(0.0))/((15.0)-(0.0))))) | BH44: =100*(0.4*MIN(1,MAX(0,((MIN(ABS(AA44),ABS(AB44)))-(0.75))/((0.0)-(0.75))))+0.3*MIN(1,MAX(0,((BC44)-(1.2))/((0.6)-(1.2))))+0.3*BD44) | BI44: =100*(0.5*MIN(1,MAX(0,((AK44)-(1.0))/((4.0)-(1.0))))+0.3*MIN(1,MAX(0,((IF(ISNUMBER(AO44),AO44,0)*100)-(0.0))/((8.0)-(0.0))))+0.2*MIN(1,MAX(0,((IF(ISNUMBER(AP44),AP44,0))-(25.0))/((5.0)-(25.0))))) | BJ44: =100*(0.35*MIN(1,MAX(0,((ABS(AU44))-(0.3))/((0.05)-(0.3))))+0.3*MIN(1,MAX(0,((AV44)-(0.0))/((0.3)-(0.0))))+0.25*MIN(1,MAX(0,((AW44)-(0.4))/((0.7)-(0.4))))+0.1*IF(AY44>=2,1,0.5)) | BK44: =0.25*BG44+0.25*BH44+0.2*BI44+0.3*BJ44 | BL44: 全部通過
A45: 1 | B45: 44 | C45: FTRE | D45: Fortrea Holdings Inc. | E45: NASDAQ | F45: 醫療保健 | G45: Medical Specialities | H45: 1.897 | I45: 小型 | J45: 19.4 | K45: 19.95 | L45: =J45/K45-1 | M45: 19.96 | N45: 19.05 | O45: 1942500 | P45: 1513795 | Q45: =O45/P45 | R45: 19.6936 | S45: 19.294 | T45: 18.9934 | U45: =S45/T45-1 | V45: 1 | W45: =J45/R45-1 | X45: =J45/S45-1 | Y45: 1.004 | Z45: =Y45/J45 | AA45: =(J45-R45)/Y45 | AB45: =(J45-S45)/Y45 | AC45: =IF(ABS(AA45)<=ABS(AB45),"9EMA","21EMA") | AD45: 9+21EMA | AE45: 持續在上方 | AG45: ✓ | AI45: 2026-09-16 | AJ45: 11 | AK45: 2 | AL45: 2026-09-24 | AM45: 19.25 | AN45: 16.072 | AO45: =IF(ISNUMBER(AN45),AM45/AN45-1,"") | AP45: 5 | AQ45: =IF(ISNUMBER(AM45),J45/AM45-1,"") | AR45: 20.43 | AS45: =J45/AR45-1 | AT45: 上傾收窄（楔形） | AU45: 0.436 | AV45: 0.6387 | AW45: 0.5957 | AX45: 0.6272 | AY45: 2 | AZ45: 21.11 | BA45: 16.072 | BB45: 19.0729 | BC45: 1.1604 | BD45: =IF(M45=N45,0.5,(J45-N45)/(M45-N45)) | BE45: 14.235 | BF45: 9.481 | BG45: =100*(0.4*MIN(1,MAX(0,((U45*100)-(0.0))/((2.5)-(0.0))))+0.3*MIN(1,MAX(0,((V45)-(0.6))/((1.0)-(0.6))))+0.3*MIN(1,MAX(0,((BE45)-(0.0))/((15.0)-(0.0))))) | BH45: =100*(0.4*MIN(1,MAX(0,((MIN(ABS(AA45),ABS(AB45)))-(0.75))/((0.0)-(0.75))))+0.3*MIN(1,MAX(0,((BC45)-(1.2))/((0.6)-(1.2))))+0.3*BD45) | BI45: =100*(0.5*MIN(1,MAX(0,((AK45)-(1.0))/((4.0)-(1.0))))+0.3*MIN(1,MAX(0,((IF(ISNUMBER(AO45),AO45,0)*100)-(0.0))/((8.0)-(0.0))))+0.2*MIN(1,MAX(0,((IF(ISNUMBER(AP45),AP45,0))-(25.0))/((5.0)-(25.0))))) | BJ45: =100*(0.35*MIN(1,MAX(0,((ABS(AU45))-(0.3))/((0.05)-(0.3))))+0.3*MIN(1,MAX(0,((AV45)-(0.0))/((0.3)-(0.0))))+0.25*MIN(1,MAX(0,((AW45)-(0.4))/((0.7)-(0.4))))+0.1*IF(AY45>=2,1,0.5)) | BK45: =0.25*BG45+0.25*BH45+0.2*BI45+0.3*BJ45 | BL45: 全部通過
A46: 1 | B46: 45 | C46: LQDT | D46: Liquidity Services Inc. | E46: NASDAQ | F46: 非必需消費 | G46: Business Services | H46: 1.342 | I46: 小型 | J46: 43.64 | K46: 42.83 | L46: =J46/K46-1 | M46: 44.53 | N46: 42.59 | O46: 350900 | P46: 230000 | Q46: =O46/P46 | R46: 43.1744 | S46: 42.7419 | T46: 42.3784 | U46: =S46/T46-1 | V46: 1 | W46: =J46/R46-1 | X46: =J46/S46-1 | Y46: 1.1662 | Z46: =Y46/J46 | AA46: =(J46-R46)/Y46 | AB46: =(J46-S46)/Y46 | AC46: =IF(ABS(AA46)<=ABS(AB46),"9EMA","21EMA") | AD46: 9+21EMA | AE46: 持續在上方 | AH46: ✓ | AI46: 2026-09-11 | AJ46: 14 | AK46: 3 | AL46: 2026-09-18 | AM46: 42.1 | AN46: 38.49 | AO46: =IF(ISNUMBER(AN46),AM46/AN46-1,"") | AP46: 9 | AQ46: =IF(ISNUMBER(AM46),J46/AM46-1,"") | AR46: 43.64 | AS46: =J46/AR46-1 | AT46: 上傾收窄（楔形） | AU46: 0.275 | AV46: 0.6894 | AW46: 0.6206 | AX46: 0.6748 | AY46: 2 | AZ46: 44.53 | BA46: 38.49 | BB46: 42.2384 | BC46: 1.0772 | BD46: =IF(M46=N46,0.5,(J46-N46)/(M46-N46)) | BE46: 15.713 | BF46: 10.959 | BG46: =100*(0.4*MIN(1,MAX(0,((U46*100)-(0.0))/((2.5)-(0.0))))+0.3*MIN(1,MAX(0,((V46)-(0.6))/((1.0)-(0.6))))+0.3*MIN(1,MAX(0,((BE46)-(0.0))/((15.0)-(0.0))))) | BH46: =100*(0.4*MIN(1,MAX(0,((MIN(ABS(AA46),ABS(AB46)))-(0.75))/((0.0)-(0.75))))+0.3*MIN(1,MAX(0,((BC46)-(1.2))/((0.6)-(1.2))))+0.3*BD46) | BI46: =100*(0.5*MIN(1,MAX(0,((AK46)-(1.0))/((4.0)-(1.0))))+0.3*MIN(1,MAX(0,((IF(ISNUMBER(AO46),AO46,0)*100)-(0.0))/((8.0)-(0.0))))+0.2*MIN(1,MAX(0,((IF(ISNUMBER(AP46),AP46,0))-(25.0))/((5.0)-(25.0))))) | BJ46: =100*(0.35*MIN(1,MAX(0,((ABS(AU46))-(0.3))/((0.05)-(0.3))))+0.3*MIN(1,MAX(0,((AV46)-(0.0))/((0.3)-(0.0))))+0.25*MIN(1,MAX(0,((AW46)-(0.4))/((0.7)-(0.4))))+0.1*IF(AY46>=2,1,0.5)) | BK46: =0.25*BG46+0.25*BH46+0.2*BI46+0.3*BJ46 | BL46: 全部通過
A47: 1 | B47: 46 | C47: AMN | D47: AMN Healthcare Services Inc | E47: NYSE | F47: 非必需消費 | G47: Professional Services | H47: 1.389 | I47: 小型 | J47: 35.86 | K47: 35.87 | L47: =J47/K47-1 | M47: 36.4 | N47: 35.18 | O47: 732800 | P47: 623210 | Q47: =O47/P47 | R47: 34.9538 | S47: 34.5472 | T47: 34.1605 | U47: =S47/T47-1 | V47: 0.9 | W47: =J47/R47-1 | X47: =J47/S47-1 | Y47: 1.2139 | Z47: =Y47/J47 | AA47: =(J47-R47)/Y47 | AB47: =(J47-S47)/Y47 | AC47: =IF(ABS(AA47)<=ABS(AB47),"9EMA","21EMA") | AD47: 9+21EMA | AE47: 持續在上方 | AH47: ✓ | AI47: 2026-09-16 | AJ47: 11 | AK47: 3 | AL47: 2026-09-24 | AM47: 33.41 | AN47: 32.66 | AO47: =IF(ISNUMBER(AN47),AM47/AN47-1,"") | AP47: 5 | AQ47: =IF(ISNUMBER(AM47),J47/AM47-1,"") | AR47: 35.87 | AS47: =J47/AR47-1 | AT47: 上升三角（平頂） | AU47: -0.0214 | AV47: 0.2622 | AW47: 0.5337 | AX47: 0.4653 | AY47: 2 | AZ47: 36.4 | BA47: 32.03 | BB47: 34.3622 | BC47: 0.7467 | BD47: =IF(M47=N47,0.5,(J47-N47)/(M47-N47)) | BE47: 11.671 | BF47: 6.917 | BG47: =100*(0.4*MIN(1,MAX(0,((U47*100)-(0.0))/((2.5)-(0.0))))+0.3*MIN(1,MAX(0,((V47)-(0.6))/((1.0)-(0.6))))+0.3*MIN(1,MAX(0,((BE47)-(0.0))/((15.0)-(0.0))))) | BH47: =100*(0.4*MIN(1,MAX(0,((MIN(ABS(AA47),ABS(AB47)))-(0.75))/((0.0)-(0.75))))+0.3*MIN(1,MAX(0,((BC47)-(1.2))/((0.6)-(1.2))))+0.3*BD47) | BI47: =100*(0.5*MIN(1,MAX(0,((AK47)-(1.0))/((4.0)-(1.0))))+0.3*MIN(1,MAX(0,((IF(ISNUMBER(AO47),AO47,0)*100)-(0.0))/((8.0)-(0.0))))+0.2*MIN(1,MAX(0,((IF(ISNUMBER(AP47),AP47,0))-(25.0))/((5.0)-(25.0))))) | BJ47: =100*(0.35*MIN(1,MAX(0,((ABS(AU47))-(0.3))/((0.05)-(0.3))))+0.3*MIN(1,MAX(0,((AV47)-(0.0))/((0.3)-(0.0))))+0.25*MIN(1,MAX(0,((AW47)-(0.4))/((0.7)-(0.4))))+0.1*IF(AY47>=2,1,0.5)) | BK47: =0.25*BG47+0.25*BH47+0.2*BI47+0.3*BJ47 | BL47: 全部通過
A48: 1 | B48: 47 | C48: CNXN | D48: PC Connection Inc. | E48: NASDAQ | F48: 非必需消費 | G48: Catalog/Specialty Distribution | H48: 2.277 | I48: 中型 | J48: 92.57 | K48: 90.23 | L48: =J48/K48-1 | M48: 93.46 | N48: 90.3 | O48: 184100 | P48: 145765 | Q48: =O48/P48 | R48: 89.348 | S48: 86.9072 | T48: 84.7749 | U48: =S48/T48-1 | V48: 1 | W48: =J48/R48-1 | X48: =J48/S48-1 | Y48: 2.348 | Z48: =Y48/J48 | AA48: =(J48-R48)/Y48 | AB48: =(J48-S48)/Y48 | AC48: =IF(ABS(AA48)<=ABS(AB48),"9EMA","21EMA") | AD48: 9EMA | AE48: 持續在上方 | AI48: 2026-09-03 | AJ48: 19 | AK48: 3 | AL48: 2026-09-18 | AM48: 84.11 | AN48: 77.98 | AO48: =IF(ISNUMBER(AN48),AM48/AN48-1,"") | AP48: 9 | AQ48: =IF(ISNUMBER(AM48),J48/AM48-1,"") | AR48: 92.57 | AS48: =J48/AR48-1 | AT48: 上升通道 | AU48: 0.559 | AV48: 0.5518 | AW48: 0.5168 | AX48: 0.4892 | AY48: 1 | AZ48: 93.46 | BA48: 77.98 | BB48: 85.9807 | BC48: 0.9434 | BD48: =IF(M48=N48,0.5,(J48-N48)/(M48-N48)) | BE48: 20.365 | BF48: 15.611 | BG48: =100*(0.4*MIN(1,MAX(0,((U48*100)-(0.0))/((2.5)-(0.0))))+0.3*MIN(1,MAX(0,((V48)-(0.6))/((1.0)-(0.6))))+0.3*MIN(1,MAX(0,((BE48)-(0.0))/((15.0)-(0.0))))) | BH48: =100*(0.4*MIN(1,MAX(0,((MIN(ABS(AA48),ABS(AB48)))-(0.75))/((0.0)-(0.75))))+0.3*MIN(1,MAX(0,((BC48)-(1.2))/((0.6)-(1.2))))+0.3*BD48) | BI48: =100*(0.5*MIN(1,MAX(0,((AK48)-(1.0))/((4.0)-(1.0))))+0.3*MIN(1,MAX(0,((IF(ISNUMBER(AO48),AO48,0)*100)-(0.0))/((8.0)-(0.0))))+0.2*MIN(1,MAX(0,((IF(ISNUMBER(AP48),AP48,0))-(25.0))/((5.0)-(25.0))))) | BJ48: =100*(0.35*MIN(1,MAX(0,((ABS(AU48))-(0.3))/((0.05)-(0.3))))+0.3*MIN(1,MAX(0,((AV48)-(0.0))/((0.3)-(0.0))))+0.25*MIN(1,MAX(0,((AW48)-(0.4))/((0.7)-(0.4))))+0.1*IF(AY48>=2,1,0.5)) | BK48: =0.25*BG48+0.25*BH48+0.2*BI48+0.3*BJ48 | BL48: 全部通過
A49: 1 | B49: 48 | C49: GNE | D49: Genie Energy Ltd. Class B | E49: NYSE | F49: 公用事業 | G49: Power Generation | H49: 0.421 | I49: 小型 | J49: 16.42 | K49: 15.98 | L49: =J49/K49-1 | M49: 16.48 | N49: 15.9 | O49: 97700 | P49: 78130 | Q49: =O49/P49 | R49: 16.0691 | S49: 15.8343 | T49: 15.6642 | U49: =S49/T49-1 | V49: 1 | W49: =J49/R49-1 | X49: =J49/S49-1 | Y49: 0.3762 | Z49: =Y49/J49 | AA49: =(J49-R49)/Y49 | AB49: =(J49-S49)/Y49 | AC49: =IF(ABS(AA49)<=ABS(AB49),"9EMA","21EMA") | AD49: 9+21EMA | AE49: 持續在上方 | AH49: ✓ | AI49: 2026-08-06 | AJ49: 39 | AK49: 4 | AL49: 2026-09-25 | AM49: 15.72 | AN49: 14.58 | AO49: =IF(ISNUMBER(AN49),AM49/AN49-1,"") | AP49: 4 | AQ49: =IF(ISNUMBER(AM49),J49/AM49-1,"") | AR49: 16.42 | AS49: =J49/AR49-1 | AT49: 上傾收窄（楔形） | AU49: 0.3065 | AV49: 0.3857 | AW49: 0.6104 | AX49: 0.5965 | AY49: 5 | AZ49: 16.55 | BA49: 14.58 | BB49: 15.7824 | BC49: 1.2242 | BD49: =IF(M49=N49,0.5,(J49-N49)/(M49-N49)) | BE49: 12.923 | BF49: 8.169 | BG49: =100*(0.4*MIN(1,MAX(0,((U49*100)-(0.0))/((2.5)-(0.0))))+0.3*MIN(1,MAX(0,((V49)-(0.6))/((1.0)-(0.6))))+0.3*MIN(1,MAX(0,((BE49)-(0.0))/((15.0)-(0.0))))) | BH49: =100*(0.4*MIN(1,MAX(0,((MIN(ABS(AA49),ABS(AB49)))-(0.75))/((0.0)-(0.75))))+0.3*MIN(1,MAX(0,((BC49)-(1.2))/((0.6)-(1.2))))+0.3*BD49) | BI49: =100*(0.5*MIN(1,MAX(0,((AK49)-(1.0))/((4.0)-(1.0))))+0.3*MIN(1,MAX(0,((IF(ISNUMBER(AO49),AO49,0)*100)-(0.0))/((8.0)-(0.0))))+0.2*MIN(1,MAX(0,((IF(ISNUMBER(AP49),AP49,0))-(25.0))/((5.0)-(25.0))))) | BJ49: =100*(0.35*MIN(1,MAX(0,((ABS(AU49))-(0.3))/((0.05)-(0.3))))+0.3*MIN(1,MAX(0,((AV49)-(0.0))/((0.3)-(0.0))))+0.25*MIN(1,MAX(0,((AW49)-(0.4))/((0.7)-(0.4))))+0.1*IF(AY49>=2,1,0.5)) | BK49: =0.25*BG49+0.25*BH49+0.2*BI49+0.3*BJ49 | BL49: 全部通過
A50: 1 | B50: 49 | C50: CRUS | D50: Cirrus Logic Inc. | E50: NASDAQ | F50: 科技 | G50: Semiconductors | H50: 6.013 | I50: 中型 | J50: 120.17 | K50: 119.97 | L50: =J50/K50-1 | M50: 121.3 | N50: 118.63 | O50: 509500 | P50: 873185 | Q50: =O50/P50 | R50: 119.704 | S50: 118.8168 | T50: 118.0364 | U50: =S50/T50-1 | V50: 1 | W50: =J50/R50-1 | X50: =J50/S50-1 | Y50: 3.4221 | Z50: =Y50/J50 | AA50: =(J50-R50)/Y50 | AB50: =(J50-S50)/Y50 | AC50: =IF(ABS(AA50)<=ABS(AB50),"9EMA","21EMA") | AD50: 9+21EMA | AE50: 持續在上方 | AH50: ✓ | AI50: 2026-09-17 | AJ50: 10 | AK50: 3 | AL50: 2026-09-28 | AM50: 116.94 | AN50: 108.21 | AO50: =IF(ISNUMBER(AN50),AM50/AN50-1,"") | AP50: 3 | AQ50: =IF(ISNUMBER(AM50),J50/AM50-1,"") | AR50: 122.21 | AS50: =J50/AR50-1 | AT50: 上升通道 | AU50: 0.4229 | AV50: 0.5068 | AW50: 0.5244 | AX50: 0.5445 | AY50: 2 | AZ50: 124.75 | BA50: 106.26 | BB50: 115.9565 | BC50: 1.816 | BD50: =IF(M50=N50,0.5,(J50-N50)/(M50-N50)) | BE50: 14.931 | BF50: 10.177 | BG50: =100*(0.4*MIN(1,MAX(0,((U50*100)-(0.0))/((2.5)-(0.0))))+0.3*MIN(1,MAX(0,((V50)-(0.6))/((1.0)-(0.6))))+0.3*MIN(1,MAX(0,((BE50)-(0.0))/((15.0)-(0.0))))) | BH50: =100*(0.4*MIN(1,MAX(0,((MIN(ABS(AA50),ABS(AB50)))-(0.75))/((0.0)-(0.75))))+0.3*MIN(1,MAX(0,((BC50)-(1.2))/((0.6)-(1.2))))+0.3*BD50) | BI50: =100*(0.5*MIN(1,MAX(0,((AK50)-(1.0))/((4.0)-(1.0))))+0.3*MIN(1,MAX(0,((IF(ISNUMBER(AO50),AO50,0)*100)-(0.0))/((8.0)-(0.0))))+0.2*MIN(1,MAX(0,((IF(ISNUMBER(AP50),AP50,0))-(25.0))/((5.0)-(25.0))))) | BJ50: =100*(0.35*MIN(1,MAX(0,((ABS(AU50))-(0.3))/((0.05)-(0.3))))+0.3*MIN(1,MAX(0,((AV50)-(0.0))/((0.3)-(0.0))))+0.25*MIN(1,MAX(0,((AW50)-(0.4))/((0.7)-(0.4))))+0.1*IF(AY50>=2,1,0.5)) | BK50: =0.25*BG50+0.25*BH50+0.2*BI50+0.3*BJ50 | BL50: 全部通過
A51: 1 | B51: 50 | C51: MAZE | D51: Maze Therapeutics Inc. | E51: NASDAQ | F51: 醫療保健 | G51: Biotechnology: Biological Products (No Diagnostic Substances) | H51: 1.51 | I51: 小型 | J51: 26.65 | K51: 27.18 | L51: =J51/K51-1 | M51: 27.79 | N51: 26.5 | O51: 589300 | P51: 875905 | Q51: =O51/P51 | R51: 26.4127 | S51: 26.2274 | T51: 25.892 | U51: =S51/T51-1 | V51: 0.8 | W51: =J51/R51-1 | X51: =J51/S51-1 | Y51: 1.806 | Z51: =Y51/J51 | AA51: =(J51-R51)/Y51 | AB51: =(J51-S51)/Y51 | AC51: =IF(ABS(AA51)<=ABS(AB51),"9EMA","21EMA") | AD51: 9EMA | AE51: 剛黃金交叉 | AF51: ✓ | AH51: ✓ | AI51: 2026-09-29 | AJ51: 2 | AK51: 2 | AL51: 2026-09-28 | AM51: 24.84 | AN51: 21.95 | AO51: =IF(ISNUMBER(AN51),AM51/AN51-1,"") | AP51: 3 | AQ51: =IF(ISNUMBER(AM51),J51/AM51-1,"") | AR51: 28.38 | AS51: =J51/AR51-1 | AT51: 上升三角（平頂） | AU51: 0.0515 | AV51: 0.1948 | AW51: 0.5358 | AX51: 0.616 | AY51: 1 | AZ51: 29.91 | BA51: 21.95 | BB51: 26.2152 | BC51: 0.6721 | BD51: =IF(M51=N51,0.5,(J51-N51)/(M51-N51)) | BE51: 5.206 | BF51: 0.452 | BG51: =100*(0.4*MIN(1,MAX(0,((U51*100)-(0.0))/((2.5)-(0.0))))+0.3*MIN(1,MAX(0,((V51)-(0.6))/((1.0)-(0.6))))+0.3*MIN(1,MAX(0,((BE51)-(0.0))/((15.0)-(0.0))))) | BH51: =100*(0.4*MIN(1,MAX(0,((MIN(ABS(AA51),ABS(AB51)))-(0.75))/((0.0)-(0.75))))+0.3*MIN(1,MAX(0,((BC51)-(1.2))/((0.6)-(1.2))))+0.3*BD51) | BI51: =100*(0.5*MIN(1,MAX(0,((AK51)-(1.0))/((4.0)-(1.0))))+0.3*MIN(1,MAX(0,((IF(ISNUMBER(AO51),AO51,0)*100)-(0.0))/((8.0)-(0.0))))+0.2*MIN(1,MAX(0,((IF(ISNUMBER(AP51),AP51,0))-(25.0))/((5.0)-(25.0))))) | BJ51: =100*(0.35*MIN(1,MAX(0,((ABS(AU51))-(0.3))/((0.05)-(0.3))))+0.3*MIN(1,MAX(0,((AV51)-(0.0))/((0.3)-(0.0))))+0.25*MIN(1,MAX(0,((AW51)-(0.4))/((0.7)-(0.4))))+0.1*IF(AY51>=2,1,0.5)) | BK51: =0.25*BG51+0.25*BH51+0.2*BI51+0.3*BJ51 | BL51: 全部通過
A52: 1 | B52: 51 | C52: KODK | D52: Eastman Kodak Company Common New | E52: NYSE | F52: 非必需消費 | G52: Industrial Machinery/Components | H52: 0.936 | I52: 小型 | J52: 9.85 | K52: 9.56 | L52: =J52/K52-1 | M52: 9.88 | N52: 9.49 | O52: 977500 | P52: 778140 | Q52: =O52/P52 | R52: 9.6093 | S52: 9.5041 | T52: 9.4256 | U52: =S52/T52-1 | V52: 1 | W52: =J52/R52-1 | X52: =J52/S52-1 | Y52: 0.3077 | Z52: =Y52/J52 | AA52: =(J52-R52)/Y52 | AB52: =(J52-S52)/Y52 | AC52: =IF(ABS(AA52)<=ABS(AB52),"9EMA","21EMA") | AD52: 9+21EMA | AE52: 持續在上方 | AH52: ✓ | AI52: 2026-09-17 | AJ52: 10 | AK52: 4 | AL52: 2026-09-28 | AM52: 9.36 | AN52: 8.85 | AO52: =IF(ISNUMBER(AN52),AM52/AN52-1,"") | AP52: 3 | AQ52: =IF(ISNUMBER(AM52),J52/AM52-1,"") | AR52: 9.85 | AS52: =J52/AR52-1 | AT52: 上傾收窄（楔形） | AU52: 0.2486 | AV52: 0.3759 | AW52: 0.5469 | AX52: 0.4623 | AY52: 6 | AZ52: 9.89 | BA52: 8.71 | BB52: 9.3554 | BC52: 1.2482 | BD52: =IF(M52=N52,0.5,(J52-N52)/(M52-N52)) | BE52: 14.933 | BF52: 10.179 | BG52: =100*(0.4*MIN(1,MAX(0,((U52*100)-(0.0))/((2.5)-(0.0))))+0.3*MIN(1,MAX(0,((V52)-(0.6))/((1.0)-(0.6))))+0.3*MIN(1,MAX(0,((BE52)-(0.0))/((15.0)-(0.0))))) | BH52: =100*(0.4*MIN(1,MAX(0,((MIN(ABS(AA52),ABS(AB52)))-(0.75))/((0.0)-(0.75))))+0.3*MIN(1,MAX(0,((BC52)-(1.2))/((0.6)-(1.2))))+0.3*BD52) | BI52: =100*(0.5*MIN(1,MAX(0,((AK52)-(1.0))/((4.0)-(1.0))))+0.3*MIN(1,MAX(0,((IF(ISNUMBER(AO52),AO52,0)*100)-(0.0))/((8.0)-(0.0))))+0.2*MIN(1,MAX(0,((IF(ISNUMBER(AP52),AP52,0))-(25.0))/((5.0)-(25.0))))) | BJ52: =100*(0.35*MIN(1,MAX(0,((ABS(AU52))-(0.3))/((0.05)-(0.3))))+0.3*MIN(1,MAX(0,((AV52)-(0.0))/((0.3)-(0.0))))+0.25*MIN(1,MAX(0,((AW52)-(0.4))/((0.7)-(0.4))))+0.1*IF(AY52>=2,1,0.5)) | BK52: =0.25*BG52+0.25*BH52+0.2*BI52+0.3*BJ52 | BL52: 全部通過
A53: 1 | B53: 52 | C53: NEU | D53: NewMarket Corp | E53: NYSE | F53: 工業 | G53: Major Chemicals | H53: 8.254 | I53: 中型 | J53: 921.14 | K53: 897.52 | L53: =J53/K53-1 | M53: 923.47 | N53: 893.05 | O53: 125100 | P53: 119955 | Q53: =O53/P53 | R53: 902.08 | S53: 897.3208 | T53: 891.1874 | U53: =S53/T53-1 | V53: 0.6 | W53: =J53/R53-1 | X53: =J53/S53-1 | Y53: 23.2389 | Z53: =Y53/J53 | AA53: =(J53-R53)/Y53 | AB53: =(J53-S53)/Y53 | AC53: =IF(ABS(AA53)<=ABS(AB53),"9EMA","21EMA") | AD53: 9+21EMA | AE53: 剛黃金交叉 | AF53: ✓ | AH53: ✓ | AI53: 2026-09-28 | AJ53: 3 | AK53: 4 | AL53: 2026-09-22 | AM53: 874.71 | AN53: 833.43 | AO53: =IF(ISNUMBER(AN53),AM53/AN53-1,"") | AP53: 7 | AQ53: =IF(ISNUMBER(AM53),J53/AM53-1,"") | AR53: 921.14 | AS53: =J53/AR53-1 | AT53: 上升三角（平頂） | AU53: -0.0398 | AV53: 0.4979 | AW53: 0.5851 | AX53: 0.5146 | AY53: 3 | AZ53: 936.77 | BA53: 833.43 | BB53: 893.8921 | BC53: 0.9019 | BD53: =IF(M53=N53,0.5,(J53-N53)/(M53-N53)) | BE53: 6.749 | BF53: 1.995 | BG53: =100*(0.4*MIN(1,MAX(0,((U53*100)-(0.0))/((2.5)-(0.0))))+0.3*MIN(1,MAX(0,((V53)-(0.6))/((1.0)-(0.6))))+0.3*MIN(1,MAX(0,((BE53)-(0.0))/((15.0)-(0.0))))) | BH53: =100*(0.4*MIN(1,MAX(0,((MIN(ABS(AA53),ABS(AB53)))-(0.75))/((0.0)-(0.75))))+0.3*MIN(1,MAX(0,((BC53)-(1.2))/((0.6)-(1.2))))+0.3*BD53) | BI53: =100*(0.5*MIN(1,MAX(0,((AK53)-(1.0))/((4.0)-(1.0))))+0.3*MIN(1,MAX(0,((IF(ISNUMBER(AO53),AO53,0)*100)-(0.0))/((8.0)-(0.0))))+0.2*MIN(1,MAX(0,((IF(ISNUMBER(AP53),AP53,0))-(25.0))/((5.0)-(25.0))))) | BJ53: =100*(0.35*MIN(1,MAX(0,((ABS(AU53))-(0.3))/((0.05)-(0.3))))+0.3*MIN(1,MAX(0,((AV53)-(0.0))/((0.3)-(0.0))))+0.25*MIN(1,MAX(0,((AW53)-(0.4))/((0.7)-(0.4))))+0.1*IF(AY53>=2,1,0.5)) | BK53: =0.25*BG53+0.25*BH53+0.2*BI53+0.3*BJ53 | BL53: 全部通過
A54: 1 | B54: 53 | C54: EXEL | D54: Exelixis Inc. | E54: NASDAQ | F54: 醫療保健 | G54: Biotechnology: Biological Products (No Diagnostic Substances) | H54: 14.473 | I54: 大型 | J54: 57.94 | K54: 58.41 | L54: =J54/K54-1 | M54: 59.28 | N54: 57.76 | O54: 1369400 | P54: 2131605 | Q54: =O54/P54 | R54: 58.0236 | S54: 57.4456 | T54: 56.926 | U54: =S54/T54-1 | V54: 0.9 | W54: =J54/R54-1 | X54: =J54/S54-1 | Y54: 1.6709 | Z54: =Y54/J54 | AA54: =(J54-R54)/Y54 | AB54: =(J54-S54)/Y54 | AC54: =IF(ABS(AA54)<=ABS(AB54),"9EMA","21EMA") | AD54: 9+21EMA | AE54: 持續在上方 | AH54: ✓ | AI54: 2026-08-25 | AJ54: 26 | AK54: 4 | AL54: 2026-09-23 | AM54: 56.26 | AN54: 54.55 | AO54: =IF(ISNUMBER(AN54),AM54/AN54-1,"") | AP54: 6 | AQ54: =IF(ISNUMBER(AM54),J54/AM54-1,"") | AR54: 58.65 | AS54: =J54/AR54-1 | AT54: 上升三角（平頂） | AU54: -0.0984 | AV54: 0.3053 | AW54: 0.5305 | AX54: 0.656 | AY54: 1 | AZ54: 61.14 | BA54: 53.43 | BB54: 57.5202 | BC54: 1.4208 | BD54: =IF(M54=N54,0.5,(J54-N54)/(M54-N54)) | BE54: 6.6 | BF54: 1.846 | BG54: =100*(0.4*MIN(1,MAX(0,((U54*100)-(0.0))/((2.5)-(0.0))))+0.3*MIN(1,MAX(0,((V54)-(0.6))/((1.0)-(0.6))))+0.3*MIN(1,MAX(0,((BE54)-(0.0))/((15.0)-(0.0))))) | BH54: =100*(0.4*MIN(1,MAX(0,((MIN(ABS(AA54),ABS(AB54)))-(0.75))/((0.0)-(0.75))))+0.3*MIN(1,MAX(0,((BC54)-(1.2))/((0.6)-(1.2))))+0.3*BD54) | BI54: =100*(0.5*MIN(1,MAX(0,((AK54)-(1.0))/((4.0)-(1.0))))+0.3*MIN(1,MAX(0,((IF(ISNUMBER(AO54),AO54,0)*100)-(0.0))/((8.0)-(0.0))))+0.2*MIN(1,MAX(0,((IF(ISNUMBER(AP54),AP54,0))-(25.0))/((5.0)-(25.0))))) | BJ54: =100*(0.35*MIN(1,MAX(0,((ABS(AU54))-(0.3))/((0.05)-(0.3))))+0.3*MIN(1,MAX(0,((AV54)-(0.0))/((0.3)-(0.0))))+0.25*MIN(1,MAX(0,((AW54)-(0.4))/((0.7)-(0.4))))+0.1*IF(AY54>=2,1,0.5)) | BK54: =0.25*BG54+0.25*BH54+0.2*BI54+0.3*BJ54 | BL54: 全部通過
A55: 1 | B55: 54 | C55: AZTA | D55: Azenta Inc. | E55: NASDAQ | F55: 科技 | G55: Industrial Machinery/Components | H55: 1.528 | I55: 小型 | J55: 34.48 | K55: 34.89 | L55: =J55/K55-1 | M55: 35.03 | N55: 34.19 | O55: 936000 | P55: 860225 | Q55: =O55/P55 | R55: 34.1241 | S55: 33.4234 | T55: 32.8192 | U55: =S55/T55-1 | V55: 1 | W55: =J55/R55-1 | X55: =J55/S55-1 | Y55: 1.1668 | Z55: =Y55/J55 | AA55: =(J55-R55)/Y55 | AB55: =(J55-S55)/Y55 | AC55: =IF(ABS(AA55)<=ABS(AB55),"9EMA","21EMA") | AD55: 9EMA | AE55: 持續在上方 | AH55: ✓ | AI55: 2026-09-16 | AJ55: 11 | AK55: 2 | AL55: 2026-09-28 | AM55: 33.28 | AN55: 29.64 | AO55: =IF(ISNUMBER(AN55),AM55/AN55-1,"") | AP55: 3 | AQ55: =IF(ISNUMBER(AM55),J55/AM55-1,"") | AR55: 34.89 | AS55: =J55/AR55-1 | AT55: 上傾收窄（楔形） | AU55: 0.3487 | AV55: 0.4999 | AW55: 0.5617 | AX55: 0.5561 | AY55: 5 | AZ55: 35.24 | BA55: 29.64 | BB55: 32.7857 | BC55: 1.1195 | BD55: =IF(M55=N55,0.5,(J55-N55)/(M55-N55)) | BE55: 13.972 | BF55: 9.218 | BG55: =100*(0.4*MIN(1,MAX(0,((U55*100)-(0.0))/((2.5)-(0.0))))+0.3*MIN(1,MAX(0,((V55)-(0.6))/((1.0)-(0.6))))+0.3*MIN(1,MAX(0,((BE55)-(0.0))/((15.0)-(0.0))))) | BH55: =100*(0.4*MIN(1,MAX(0,((MIN(ABS(AA55),ABS(AB55)))-(0.75))/((0.0)-(0.75))))+0.3*MIN(1,MAX(0,((BC55)-(1.2))/((0.6)-(1.2))))+0.3*BD55) | BI55: =100*(0.5*MIN(1,MAX(0,((AK55)-(1.0))/((4.0)-(1.0))))+0.3*MIN(1,MAX(0,((IF(ISNUMBER(AO55),AO55,0)*100)-(0.0))/((8.0)-(0.0))))+0.2*MIN(1,MAX(0,((IF(ISNUMBER(AP55),AP55,0))-(25.0))/((5.0)-(25.0))))) | BJ55: =100*(0.35*MIN(1,MAX(0,((ABS(AU55))-(0.3))/((0.05)-(0.3))))+0.3*MIN(1,MAX(0,((AV55)-(0.0))/((0.3)-(0.0))))+0.25*MIN(1,MAX(0,((AW55)-(0.4))/((0.7)-(0.4))))+0.1*IF(AY55>=2,1,0.5)) | BK55: =0.25*BG55+0.25*BH55+0.2*BI55+0.3*BJ55 | BL55: 全部通過
A56: 1 | B56: 55 | C56: SWBI | D56: Smith & Wesson Brands Inc. | E56: NASDAQ | F56: 工業 | G56: Ordnance And Accessories | H56: 0.63 | I56: 小型 | J56: 14.41 | K56: 14.06 | L56: =J56/K56-1 | M56: 14.43 | N56: 14.03 | O56: 439000 | P56: 678300 | Q56: =O56/P56 | R56: 14.0244 | S56: 13.7931 | T56: 13.5623 | U56: =S56/T56-1 | V56: 1 | W56: =J56/R56-1 | X56: =J56/S56-1 | Y56: 0.3878 | Z56: =Y56/J56 | AA56: =(J56-R56)/Y56 | AB56: =(J56-S56)/Y56 | AC56: =IF(ABS(AA56)<=ABS(AB56),"9EMA","21EMA") | AD56: 9EMA | AE56: 持續在上方 | AH56: ✓ | AI56: 2026-09-22 | AJ56: 7 | AK56: 2 | AL56: 2026-09-17 | AM56: 12.9 | AN56: 12.09 | AO56: =IF(ISNUMBER(AN56),AM56/AN56-1,"") | AP56: 10 | AQ56: =IF(ISNUMBER(AM56),J56/AM56-1,"") | AR56: 14.41 | AS56: =J56/AR56-1 | AT56: 上傾收窄（楔形） | AU56: 0.4053 | AV56: 0.6246 | AW56: 0.5124 | AX56: 0.4762 | AY56: 3 | AZ56: 14.43 | BA56: 12.09 | BB56: 13.289 | BC56: 0.7484 | BD56: =IF(M56=N56,0.5,(J56-N56)/(M56-N56)) | BE56: 17.597 | BF56: 12.843 | BG56: =100*(0.4*MIN(1,MAX(0,((U56*100)-(0.0))/((2.5)-(0.0))))+0.3*MIN(1,MAX(0,((V56)-(0.6))/((1.0)-(0.6))))+0.3*MIN(1,MAX(0,((BE56)-(0.0))/((15.0)-(0.0))))) | BH56: =100*(0.4*MIN(1,MAX(0,((MIN(ABS(AA56),ABS(AB56)))-(0.75))/((0.0)-(0.75))))+0.3*MIN(1,MAX(0,((BC56)-(1.2))/((0.6)-(1.2))))+0.3*BD56) | BI56: =100*(0.5*MIN(1,MAX(0,((AK56)-(1.0))/((4.0)-(1.0))))+0.3*MIN(1,MAX(0,((IF(ISNUMBER(AO56),AO56,0)*100)-(0.0))/((8.0)-(0.0))))+0.2*MIN(1,MAX(0,((IF(ISNUMBER(AP56),AP56,0))-(25.0))/((5.0)-(25.0))))) | BJ56: =100*(0.35*MIN(1,MAX(0,((ABS(AU56))-(0.3))/((0.05)-(0.3))))+0.3*MIN(1,MAX(0,((AV56)-(0.0))/((0.3)-(0.0))))+0.25*MIN(1,MAX(0,((AW56)-(0.4))/((0.7)-(0.4))))+0.1*IF(AY56>=2,1,0.5)) | BK56: =0.25*BG56+0.25*BH56+0.2*BI56+0.3*BJ56 | BL56: 全部通過
A57: 1 | B57: 56 | C57: CSTL | D57: Castle Biosciences Inc. | E57: NASDAQ | F57: 醫療保健 | G57: Medical Specialities | H57: 1.085 | I57: 小型 | J57: 35.255 | K57: 35.53 | L57: =J57/K57-1 | M57: 36.99 | N57: 35.17 | O57: 522300 | P57: 361270 | Q57: =O57/P57 | R57: 35.2251 | S57: 34.4861 | T57: 33.8957 | U57: =S57/T57-1 | V57: 1 | W57: =J57/R57-1 | X57: =J57/S57-1 | Y57: 1.5727 | Z57: =Y57/J57 | AA57: =(J57-R57)/Y57 | AB57: =(J57-S57)/Y57 | AC57: =IF(ABS(AA57)<=ABS(AB57),"9EMA","21EMA") | AD57: 9+21EMA | AE57: 持續在上方 | AH57: ✓ | AI57: 2026-06-23 | AJ57: 70 | AK57: 2 | AL57: 2026-09-24 | AM57: 33.9 | AN57: 31.44 | AO57: =IF(ISNUMBER(AN57),AM57/AN57-1,"") | AP57: 5 | AQ57: =IF(ISNUMBER(AM57),J57/AM57-1,"") | AR57: 36.78 | AS57: =J57/AR57-1 | AT57: 上傾擴張 | AU57: 0.6013 | AV57: 0.2871 | AW57: 0.5714 | AX57: 0.5149 | AY57: 4 | AZ57: 36.99 | BA57: 31.44 | BB57: 34.6115 | BC57: 1.0481 | BD57: =IF(M57=N57,0.5,(J57-N57)/(M57-N57)) | BE57: 10.182 | BF57: 5.428 | BG57: =100*(0.4*MIN(1,MAX(0,((U57*100)-(0.0))/((2.5)-(0.0))))+0.3*MIN(1,MAX(0,((V57)-(0.6))/((1.0)-(0.6))))+0.3*MIN(1,MAX(0,((BE57)-(0.0))/((15.0)-(0.0))))) | BH57: =100*(0.4*MIN(1,MAX(0,((MIN(ABS(AA57),ABS(AB57)))-(0.75))/((0.0)-(0.75))))+0.3*MIN(1,MAX(0,((BC57)-(1.2))/((0.6)-(1.2))))+0.3*BD57) | BI57: =100*(0.5*MIN(1,MAX(0,((AK57)-(1.0))/((4.0)-(1.0))))+0.3*MIN(1,MAX(0,((IF(ISNUMBER(AO57),AO57,0)*100)-(0.0))/((8.0)-(0.0))))+0.2*MIN(1,MAX(0,((IF(ISNUMBER(AP57),AP57,0))-(25.0))/((5.0)-(25.0))))) | BJ57: =100*(0.35*MIN(1,MAX(0,((ABS(AU57))-(0.3))/((0.05)-(0.3))))+0.3*MIN(1,MAX(0,((AV57)-(0.0))/((0.3)-(0.0))))+0.25*MIN(1,MAX(0,((AW57)-(0.4))/((0.7)-(0.4))))+0.1*IF(AY57>=2,1,0.5)) | BK57: =0.25*BG57+0.25*BH57+0.2*BI57+0.3*BJ57 | BL57: 全部通過
A58: 1 | B58: 57 | C58: PBYI | D58: Puma Biotechnology Inc | E58: NASDAQ | F58: 醫療保健 | G58: Biotechnology: Pharmaceutical Preparations | H58: 0.513 | I58: 小型 | J58: 9.84 | K58: 9.93 | L58: =J58/K58-1 | M58: 10.08 | N58: 9.77 | O58: 518400 | P58: 309220 | Q58: =O58/P58 | R58: 9.7358 | S58: 9.5327 | T58: 9.3495 | U58: =S58/T58-1 | V58: 0.9 | W58: =J58/R58-1 | X58: =J58/S58-1 | Y58: 0.3794 | Z58: =Y58/J58 | AA58: =(J58-R58)/Y58 | AB58: =(J58-S58)/Y58 | AC58: =IF(ABS(AA58)<=ABS(AB58),"9EMA","21EMA") | AD58: 9EMA | AE58: 持續在上方 | AH58: ✓ | AI58: 2026-08-07 | AJ58: 38 | AK58: 4 | AL58: 2026-09-24 | AM58: 9.02 | AN58: 8.85 | AO58: =IF(ISNUMBER(AN58),AM58/AN58-1,"") | AP58: 5 | AQ58: =IF(ISNUMBER(AM58),J58/AM58-1,"") | AR58: 9.93 | AS58: =J58/AR58-1 | AT58: 上傾擴張 | AU58: 0.1876 | AV58: 0.1436 | AW58: 0.537 | AX58: 0.4986 | AY58: 3 | AZ58: 10.1 | BA58: 8.78 | BB58: 9.4888 | BC58: 0.9413 | BD58: =IF(M58=N58,0.5,(J58-N58)/(M58-N58)) | BE58: 9.995 | BF58: 5.241 | BG58: =100*(0.4*MIN(1,MAX(0,((U58*100)-(0.0))/((2.5)-(0.0))))+0.3*MIN(1,MAX(0,((V58)-(0.6))/((1.0)-(0.6))))+0.3*MIN(1,MAX(0,((BE58)-(0.0))/((15.0)-(0.0))))) | BH58: =100*(0.4*MIN(1,MAX(0,((MIN(ABS(AA58),ABS(AB58)))-(0.75))/((0.0)-(0.75))))+0.3*MIN(1,MAX(0,((BC58)-(1.2))/((0.6)-(1.2))))+0.3*BD58) | BI58: =100*(0.5*MIN(1,MAX(0,((AK58)-(1.0))/((4.0)-(1.0))))+0.3*MIN(1,MAX(0,((IF(ISNUMBER(AO58),AO58,0)*100)-(0.0))/((8.0)-(0.0))))+0.2*MIN(1,MAX(0,((IF(ISNUMBER(AP58),AP58,0))-(25.0))/((5.0)-(25.0))))) | BJ58: =100*(0.35*MIN(1,MAX(0,((ABS(AU58))-(0.3))/((0.05)-(0.3))))+0.3*MIN(1,MAX(0,((AV58)-(0.0))/((0.3)-(0.0))))+0.25*MIN(1,MAX(0,((AW58)-(0.4))/((0.7)-(0.4))))+0.1*IF(AY58>=2,1,0.5)) | BK58: =0.25*BG58+0.25*BH58+0.2*BI58+0.3*BJ58 | BL58: 全部通過
A59: 1 | B59: 58 | C59: HWKN | D59: Hawkins Inc. | E59: NASDAQ | F59: 非必需消費 | G59: Specialty Chemicals | H59: 2.63 | I59: 中型 | J59: 127.19 | K59: 126 | L59: =J59/K59-1 | M59: 127.32 | N59: 123.23 | O59: 165500 | P59: 186630 | Q59: =O59/P59 | R59: 126.1157 | S59: 125.4812 | T59: 124.4678 | U59: =S59/T59-1 | V59: 0.8 | W59: =J59/R59-1 | X59: =J59/S59-1 | Y59: 3.9301 | Z59: =Y59/J59 | AA59: =(J59-R59)/Y59 | AB59: =(J59-S59)/Y59 | AC59: =IF(ABS(AA59)<=ABS(AB59),"9EMA","21EMA") | AD59: 9+21EMA | AE59: 剛黃金交叉 | AF59: ✓ | AH59: ✓ | AI59: 2026-09-25 | AJ59: 4 | AK59: 2 | AL59: 2026-09-15 | AM59: 118.71 | AN59: 116.05 | AO59: =IF(ISNUMBER(AN59),AM59/AN59-1,"") | AP59: 12 | AQ59: =IF(ISNUMBER(AM59),J59/AM59-1,"") | AR59: 129.03 | AS59: =J59/AR59-1 | AT59: 上升三角（平頂） | AU59: -0.0298 | AV59: 0.1743 | AW59: 0.5789 | AX59: 0.5794 | AY59: 6 | AZ59: 130.52 | BA59: 116.05 | BB59: 124.4264 | BC59: 0.7497 | BD59: =IF(M59=N59,0.5,(J59-N59)/(M59-N59)) | BE59: 6.849 | BF59: 2.095 | BG59: =100*(0.4*MIN(1,MAX(0,((U59*100)-(0.0))/((2.5)-(0.0))))+0.3*MIN(1,MAX(0,((V59)-(0.6))/((1.0)-(0.6))))+0.3*MIN(1,MAX(0,((BE59)-(0.0))/((15.0)-(0.0))))) | BH59: =100*(0.4*MIN(1,MAX(0,((MIN(ABS(AA59),ABS(AB59)))-(0.75))/((0.0)-(0.75))))+0.3*MIN(1,MAX(0,((BC59)-(1.2))/((0.6)-(1.2))))+0.3*BD59) | BI59: =100*(0.5*MIN(1,MAX(0,((AK59)-(1.0))/((4.0)-(1.0))))+0.3*MIN(1,MAX(0,((IF(ISNUMBER(AO59),AO59,0)*100)-(0.0))/((8.0)-(0.0))))+0.2*MIN(1,MAX(0,((IF(ISNUMBER(AP59),AP59,0))-(25.0))/((5.0)-(25.0))))) | BJ59: =100*(0.35*MIN(1,MAX(0,((ABS(AU59))-(0.3))/((0.05)-(0.3))))+0.3*MIN(1,MAX(0,((AV59)-(0.0))/((0.3)-(0.0))))+0.25*MIN(1,MAX(0,((AW59)-(0.4))/((0.7)-(0.4))))+0.1*IF(AY59>=2,1,0.5)) | BK59: =0.25*BG59+0.25*BH59+0.2*BI59+0.3*BJ59 | BL59: 全部通過
A60: 1 | B60: 59 | C60: S | D60: SentinelOne Inc. | E60: NYSE | F60: 科技 | G60: Computer Software: Prepackaged Software | H60: 8.27 | I60: 中型 | J60: 24.67 | K60: 23.76 | L60: =J60/K60-1 | M60: 24.69 | N60: 23.41 | O60: 8961500 | P60: 8949675 | Q60: =O60/P60 | R60: 23.4682 | S60: 22.6827 | T60: 22.1964 | U60: =S60/T60-1 | V60: 1 | W60: =J60/R60-1 | X60: =J60/S60-1 | Y60: 1.1296 | Z60: =Y60/J60 | AA60: =(J60-R60)/Y60 | AB60: =(J60-S60)/Y60 | AC60: =IF(ABS(AA60)<=ABS(AB60),"9EMA","21EMA") | AD60: 9EMA | AE60: 持續在上方 | AI60: 2026-09-15 | AJ60: 12 | AK60: 2 | AL60: 2026-09-28 | AM60: 21.79 | AN60: 19.07 | AO60: =IF(ISNUMBER(AN60),AM60/AN60-1,"") | AP60: 3 | AQ60: =IF(ISNUMBER(AM60),J60/AM60-1,"") | AR60: 24.67 | AS60: =J60/AR60-1 | AT60: 上傾收窄（楔形） | AU60: 0.325 | AV60: 0.7875 | AW60: 0.5522 | AX60: 0.5236 | AY60: 2 | AZ60: 24.69 | BA60: 19.07 | BB60: 22.1735 | BC60: 1.2657 | BD60: =IF(M60=N60,0.5,(J60-N60)/(M60-N60)) | BE60: 24.337 | BF60: 19.583 | BG60: =100*(0.4*MIN(1,MAX(0,((U60*100)-(0.0))/((2.5)-(0.0))))+0.3*MIN(1,MAX(0,((V60)-(0.6))/((1.0)-(0.6))))+0.3*MIN(1,MAX(0,((BE60)-(0.0))/((15.0)-(0.0))))) | BH60: =100*(0.4*MIN(1,MAX(0,((MIN(ABS(AA60),ABS(AB60)))-(0.75))/((0.0)-(0.75))))+0.3*MIN(1,MAX(0,((BC60)-(1.2))/((0.6)-(1.2))))+0.3*BD60) | BI60: =100*(0.5*MIN(1,MAX(0,((AK60)-(1.0))/((4.0)-(1.0))))+0.3*MIN(1,MAX(0,((IF(ISNUMBER(AO60),AO60,0)*100)-(0.0))/((8.0)-(0.0))))+0.2*MIN(1,MAX(0,((IF(ISNUMBER(AP60),AP60,0))-(25.0))/((5.0)-(25.0))))) | BJ60: =100*(0.35*MIN(1,MAX(0,((ABS(AU60))-(0.3))/((0.05)-(0.3))))+0.3*MIN(1,MAX(0,((AV60)-(0.0))/((0.3)-(0.0))))+0.25*MIN(1,MAX(0,((AW60)-(0.4))/((0.7)-(0.4))))+0.1*IF(AY60>=2,1,0.5)) | BK60: =0.25*BG60+0.25*BH60+0.2*BI60+0.3*BJ60 | BL60: 全部通過
A61: 1 | B61: 60 | C61: BRKR | D61: Bruker Corporation | E61: NASDAQ | F61: 工業 | G61: Biotechnology: Laboratory Analytical Instruments | H61: 9.865 | I61: 中型 | J61: 61.94 | K61: 64.75 | L61: =J61/K61-1 | M61: 64.82 | N61: 61.7 | O61: 2378100 | P61: 2302435 | Q61: =O61/P61 | R61: 62.553 | S61: 60.8002 | T61: 59.0479 | U61: =S61/T61-1 | V61: 1 | W61: =J61/R61-1 | X61: =J61/S61-1 | Y61: 2.9845 | Z61: =Y61/J61 | AA61: =(J61-R61)/Y61 | AB61: =(J61-S61)/Y61 | AC61: =IF(ABS(AA61)<=ABS(AB61),"9EMA","21EMA") | AD61: 9EMA | AE61: 持續在上方 | AH61: ✓ | AI61: 2026-09-17 | AJ61: 10 | AK61: 2 | AL61: 2026-09-24 | AM61: 59.17 | AN61: 51.54 | AO61: =IF(ISNUMBER(AN61),AM61/AN61-1,"") | AP61: 5 | AQ61: =IF(ISNUMBER(AM61),J61/AM61-1,"") | AR61: 64.75 | AS61: =J61/AR61-1 | AT61: 上傾擴張 | AU61: 0.586 | AV61: 0.3542 | AW61: 0.5132 | AX61: 0.5628 | AY61: 1 | AZ61: 66.98 | BA61: 51.54 | BB61: 59.464 | BC61: 1.1975 | BD61: =IF(M61=N61,0.5,(J61-N61)/(M61-N61)) | BE61: 15.302 | BF61: 10.548 | BG61: =100*(0.4*MIN(1,MAX(0,((U61*100)-(0.0))/((2.5)-(0.0))))+0.3*MIN(1,MAX(0,((V61)-(0.6))/((1.0)-(0.6))))+0.3*MIN(1,MAX(0,((BE61)-(0.0))/((15.0)-(0.0))))) | BH61: =100*(0.4*MIN(1,MAX(0,((MIN(ABS(AA61),ABS(AB61)))-(0.75))/((0.0)-(0.75))))+0.3*MIN(1,MAX(0,((BC61)-(1.2))/((0.6)-(1.2))))+0.3*BD61) | BI61: =100*(0.5*MIN(1,MAX(0,((AK61)-(1.0))/((4.0)-(1.0))))+0.3*MIN(1,MAX(0,((IF(ISNUMBER(AO61),AO61,0)*100)-(0.0))/((8.0)-(0.0))))+0.2*MIN(1,MAX(0,((IF(ISNUMBER(AP61),AP61,0))-(25.0))/((5.0)-(25.0))))) | BJ61: =100*(0.35*MIN(1,MAX(0,((ABS(AU61))-(0.3))/((0.05)-(0.3))))+0.3*MIN(1,MAX(0,((AV61)-(0.0))/((0.3)-(0.0))))+0.25*MIN(1,MAX(0,((AW61)-(0.4))/((0.7)-(0.4))))+0.1*IF(AY61>=2,1,0.5)) | BK61: =0.25*BG61+0.25*BH61+0.2*BI61+0.3*BJ61 | BL61: 全部通過
A62: 1 | B62: 61 | C62: BTGO | D62: BitGo Holdings Inc. | E62: NYSE | F62: 金融 | G62: Finance: Consumer Services | H62: 0.87 | I62: 小型 | J62: 7.36 | K62: 7.4 | L62: =J62/K62-1 | M62: 7.57 | N62: 7.21 | O62: 766600 | P62: 2226155 | Q62: =O62/P62 | R62: 7.4687 | S62: 7.3272 | T62: 7.3118 | U62: =S62/T62-1 | V62: 0.8 | W62: =J62/R62-1 | X62: =J62/S62-1 | Y62: 0.5537 | Z62: =Y62/J62 | AA62: =(J62-R62)/Y62 | AB62: =(J62-S62)/Y62 | AC62: =IF(ABS(AA62)<=ABS(AB62),"9EMA","21EMA") | AD62: 9+21EMA | AE62: 持續在上方 | AG62: ✓ | AI62: 2026-08-13 | AJ62: 34 | AK62: 2 | AL62: 2026-09-28 | AM62: 7.1 | AN62: 6.19 | AO62: =IF(ISNUMBER(AN62),AM62/AN62-1,"") | AP62: 3 | AQ62: =IF(ISNUMBER(AM62),J62/AM62-1,"") | AR62: 8.28 | AS62: =J62/AR62-1 | AT62: 上傾擴張 | AU62: 0.7018 | AV62: 0.3053 | AW62: 0.5658 | AX62: 0.536 | AY62: 3 | AZ62: 8.35 | BA62: 6.19 | BB62: 7.4122 | BC62: 0.2927 | BD62: =IF(M62=N62,0.5,(J62-N62)/(M62-N62)) | BE62: 10.959 | BF62: 6.205 | BG62: =100*(0.4*MIN(1,MAX(0,((U62*100)-(0.0))/((2.5)-(0.0))))+0.3*MIN(1,MAX(0,((V62)-(0.6))/((1.0)-(0.6))))+0.3*MIN(1,MAX(0,((BE62)-(0.0))/((15.0)-(0.0))))) | BH62: =100*(0.4*MIN(1,MAX(0,((MIN(ABS(AA62),ABS(AB62)))-(0.75))/((0.0)-(0.75))))+0.3*MIN(1,MAX(0,((BC62)-(1.2))/((0.6)-(1.2))))+0.3*BD62) | BI62: =100*(0.5*MIN(1,MAX(0,((AK62)-(1.0))/((4.0)-(1.0))))+0.3*MIN(1,MAX(0,((IF(ISNUMBER(AO62),AO62,0)*100)-(0.0))/((8.0)-(0.0))))+0.2*MIN(1,MAX(0,((IF(ISNUMBER(AP62),AP62,0))-(25.0))/((5.0)-(25.0))))) | BJ62: =100*(0.35*MIN(1,MAX(0,((ABS(AU62))-(0.3))/((0.05)-(0.3))))+0.3*MIN(1,MAX(0,((AV62)-(0.0))/((0.3)-(0.0))))+0.25*MIN(1,MAX(0,((AW62)-(0.4))/((0.7)-(0.4))))+0.1*IF(AY62>=2,1,0.5)) | BK62: =0.25*BG62+0.25*BH62+0.2*BI62+0.3*BJ62 | BL62: 全部通過
A63: 1 | B63: 62 | C63: GFS | D63: GlobalFoundries Inc. | E63: NASDAQ | F63: 科技 | G63: Semiconductors | H63: 26.711 | I63: 大型 | J63: 48.68 | K63: 47.92 | L63: =J63/K63-1 | M63: 48.99 | N63: 47.61 | O63: 2334000 | P63: 3876080 | Q63: =O63/P63 | R63: 47.6834 | S63: 47.2927 | T63: 46.713 | U63: =S63/T63-1 | V63: 0.9 | W63: =J63/R63-1 | X63: =J63/S63-1 | Y63: 1.9848 | Z63: =Y63/J63 | AA63: =(J63-R63)/Y63 | AB63: =(J63-S63)/Y63 | AC63: =IF(ABS(AA63)<=ABS(AB63),"9EMA","21EMA") | AD63: 9EMA | AE63: 剛黃金交叉 | AF63: ✓ | AH63: ✓ | AI63: 2026-09-25 | AJ63: 4 | AK63: 2 | AL63: 2026-09-24 | AM63: 45.39 | AN63: 42.15 | AO63: =IF(ISNUMBER(AN63),AM63/AN63-1,"") | AP63: 5 | AQ63: =IF(ISNUMBER(AM63),J63/AM63-1,"") | AR63: 49 | AS63: =J63/AR63-1 | AT63: 上升通道 | AU63: 0.4304 | AV63: 0.3947 | AW63: 0.5414 | AX63: 0.5342 | AY63: 6 | AZ63: 49.425 | BA63: 42.15 | BB63: 46.0885 | BC63: 0.9438 | BD63: =IF(M63=N63,0.5,(J63-N63)/(M63-N63)) | BE63: 15.567 | BF63: 10.813 | BG63: =100*(0.4*MIN(1,MAX(0,((U63*100)-(0.0))/((2.5)-(0.0))))+0.3*MIN(1,MAX(0,((V63)-(0.6))/((1.0)-(0.6))))+0.3*MIN(1,MAX(0,((BE63)-(0.0))/((15.0)-(0.0))))) | BH63: =100*(0.4*MIN(1,MAX(0,((MIN(ABS(AA63),ABS(AB63)))-(0.75))/((0.0)-(0.75))))+0.3*MIN(1,MAX(0,((BC63)-(1.2))/((0.6)-(1.2))))+0.3*BD63) | BI63: =100*(0.5*MIN(1,MAX(0,((AK63)-(1.0))/((4.0)-(1.0))))+0.3*MIN(1,MAX(0,((IF(ISNUMBER(AO63),AO63,0)*100)-(0.0))/((8.0)-(0.0))))+0.2*MIN(1,MAX(0,((IF(ISNUMBER(AP63),AP63,0))-(25.0))/((5.0)-(25.0))))) | BJ63: =100*(0.35*MIN(1,MAX(0,((ABS(AU63))-(0.3))/((0.05)-(0.3))))+0.3*MIN(1,MAX(0,((AV63)-(0.0))/((0.3)-(0.0))))+0.25*MIN(1,MAX(0,((AW63)-(0.4))/((0.7)-(0.4))))+0.1*IF(AY63>=2,1,0.5)) | BK63: =0.25*BG63+0.25*BH63+0.2*BI63+0.3*BJ63 | BL63: 全部通過
A64: 1 | B64: 63 | C64: EGBN | D64: Eagle Bancorp Inc. | E64: NASDAQ | F64: 金融 | G64: Major Banks | H64: 0.847 | I64: 小型 | J64: 28.21 | K64: 27.79 | L64: =J64/K64-1 | M64: 28.23 | N64: 27.01 | O64: 337900 | P64: 334955 | Q64: =O64/P64 | R64: 28.1232 | S64: 28.0508 | T64: 27.9803 | U64: =S64/T64-1 | V64: 0.8 | W64: =J64/R64-1 | X64: =J64/S64-1 | Y64: 0.6604 | Z64: =Y64/J64 | AA64: =(J64-R64)/Y64 | AB64: =(J64-S64)/Y64 | AC64: =IF(ABS(AA64)<=ABS(AB64),"9EMA","21EMA") | AD64: 9+21EMA | AE64: 持續在上方 | AH64: ✓ | AI64: 2026-09-15 | AJ64: 12 | AK64: 2 | AL64: 2026-09-10 | AM64: 27.12 | AN64: 26.52 | AO64: =IF(ISNUMBER(AN64),AM64/AN64-1,"") | AP64: 15 | AQ64: =IF(ISNUMBER(AM64),J64/AM64-1,"") | AR64: 28.54 | AS64: =J64/AR64-1 | AT64: 上傾收窄（楔形） | AU64: 0.1868 | AV64: 0.3545 | AW64: 0.597 | AX64: 0.6848 | AY64: 4 | AZ64: 28.99 | BA64: 26.52 | BB64: 27.9946 | BC64: 0.8073 | BD64: =IF(M64=N64,0.5,(J64-N64)/(M64-N64)) | BE64: 9.976 | BF64: 5.222 | BG64: =100*(0.4*MIN(1,MAX(0,((U64*100)-(0.0))/((2.5)-(0.0))))+0.3*MIN(1,MAX(0,((V64)-(0.6))/((1.0)-(0.6))))+0.3*MIN(1,MAX(0,((BE64)-(0.0))/((15.0)-(0.0))))) | BH64: =100*(0.4*MIN(1,MAX(0,((MIN(ABS(AA64),ABS(AB64)))-(0.75))/((0.0)-(0.75))))+0.3*MIN(1,MAX(0,((BC64)-(1.2))/((0.6)-(1.2))))+0.3*BD64) | BI64: =100*(0.5*MIN(1,MAX(0,((AK64)-(1.0))/((4.0)-(1.0))))+0.3*MIN(1,MAX(0,((IF(ISNUMBER(AO64),AO64,0)*100)-(0.0))/((8.0)-(0.0))))+0.2*MIN(1,MAX(0,((IF(ISNUMBER(AP64),AP64,0))-(25.0))/((5.0)-(25.0))))) | BJ64: =100*(0.35*MIN(1,MAX(0,((ABS(AU64))-(0.3))/((0.05)-(0.3))))+0.3*MIN(1,MAX(0,((AV64)-(0.0))/((0.3)-(0.0))))+0.25*MIN(1,MAX(0,((AW64)-(0.4))/((0.7)-(0.4))))+0.1*IF(AY64>=2,1,0.5)) | BK64: =0.25*BG64+0.25*BH64+0.2*BI64+0.3*BJ64 | BL64: 全部通過
A65: 1 | B65: 64 | C65: DJCO | D65: Daily Journal Corp. (S.C.) | E65: NASDAQ | F65: 非必需消費 | G65: Newspapers/Magazines | H65: 0.89 | I65: 小型 | J65: 653.04 | K65: 646.22 | L65: =J65/K65-1 | M65: 661.45 | N65: 631.97 | O65: 68300 | P65: 64935 | Q65: =O65/P65 | R65: 655.2064 | S65: 649.0879 | T65: 646.0161 | U65: =S65/T65-1 | V65: 0.9 | W65: =J65/R65-1 | X65: =J65/S65-1 | Y65: 24.1067 | Z65: =Y65/J65 | AA65: =(J65-R65)/Y65 | AB65: =(J65-S65)/Y65 | AC65: =IF(ABS(AA65)<=ABS(AB65),"9EMA","21EMA") | AD65: 9+21EMA | AE65: 持續在上方 | AH65: ✓ | AI65: 2026-08-14 | AJ65: 33 | AK65: 3 | AL65: 2026-09-22 | AM65: 640.05 | AN65: 594.83 | AO65: =IF(ISNUMBER(AN65),AM65/AN65-1,"") | AP65: 7 | AQ65: =IF(ISNUMBER(AM65),J65/AM65-1,"") | AR65: 687.66 | AS65: =J65/AR65-1 | AT65: 上升通道 | AU65: 0.4811 | AV65: 0.5327 | AW65: 0.5533 | AX65: 0.4644 | AY65: 2 | AZ65: 692.5 | BA65: 594.83 | BB65: 648.871 | BC65: 1.3745 | BD65: =IF(M65=N65,0.5,(J65-N65)/(M65-N65)) | BE65: 10.898 | BF65: 6.144 | BG65: =100*(0.4*MIN(1,MAX(0,((U65*100)-(0.0))/((2.5)-(0.0))))+0.3*MIN(1,MAX(0,((V65)-(0.6))/((1.0)-(0.6))))+0.3*MIN(1,MAX(0,((BE65)-(0.0))/((15.0)-(0.0))))) | BH65: =100*(0.4*MIN(1,MAX(0,((MIN(ABS(AA65),ABS(AB65)))-(0.75))/((0.0)-(0.75))))+0.3*MIN(1,MAX(0,((BC65)-(1.2))/((0.6)-(1.2))))+0.3*BD65) | BI65: =100*(0.5*MIN(1,MAX(0,((AK65)-(1.0))/((4.0)-(1.0))))+0.3*MIN(1,MAX(0,((IF(ISNUMBER(AO65),AO65,0)*100)-(0.0))/((8.0)-(0.0))))+0.2*MIN(1,MAX(0,((IF(ISNUMBER(AP65),AP65,0))-(25.0))/((5.0)-(25.0))))) | BJ65: =100*(0.35*MIN(1,MAX(0,((ABS(AU65))-(0.3))/((0.05)-(0.3))))+0.3*MIN(1,MAX(0,((AV65)-(0.0))/((0.3)-(0.0))))+0.25*MIN(1,MAX(0,((AW65)-(0.4))/((0.7)-(0.4))))+0.1*IF(AY65>=2,1,0.5)) | BK65: =0.25*BG65+0.25*BH65+0.2*BI65+0.3*BJ65 | BL65: 全部通過
A66: 1 | B66: 65 | C66: XMTR | D66: Xometry Inc. | E66: NASDAQ | F66: 非必需消費 | G66: Business Services | H66: 5.896 | I66: 中型 | J66: 104.23 | K66: 102.85 | L66: =J66/K66-1 | M66: 106.24 | N66: 101.515 | O66: 533500 | P66: 848670 | Q66: =O66/P66 | R66: 101.3768 | S66: 97.5125 | T66: 94.0809 | U66: =S66/T66-1 | V66: 1 | W66: =J66/R66-1 | X66: =J66/S66-1 | Y66: 5.0895 | Z66: =Y66/J66 | AA66: =(J66-R66)/Y66 | AB66: =(J66-S66)/Y66 | AC66: =IF(ABS(AA66)<=ABS(AB66),"9EMA","21EMA") | AD66: 9EMA | AE66: 持續在上方 | AH66: ✓ | AI66: 2026-09-17 | AJ66: 10 | AK66: 2 | AL66: 2026-09-24 | AM66: 96.16 | AN66: 83 | AO66: =IF(ISNUMBER(AN66),AM66/AN66-1,"") | AP66: 5 | AQ66: =IF(ISNUMBER(AM66),J66/AM66-1,"") | AR66: 105.13 | AS66: =J66/AR66-1 | AT66: 上升通道 | AU66: 0.5238 | AV66: 0.5343 | AW66: 0.5299 | AX66: 0.5602 | AY66: 1 | AZ66: 107.93 | BA66: 83 | BB66: 96.21 | BC66: 1.2762 | BD66: =IF(M66=N66,0.5,(J66-N66)/(M66-N66)) | BE66: 19.104 | BF66: 14.35 | BG66: =100*(0.4*MIN(1,MAX(0,((U66*100)-(0.0))/((2.5)-(0.0))))+0.3*MIN(1,MAX(0,((V66)-(0.6))/((1.0)-(0.6))))+0.3*MIN(1,MAX(0,((BE66)-(0.0))/((15.0)-(0.0))))) | BH66: =100*(0.4*MIN(1,MAX(0,((MIN(ABS(AA66),ABS(AB66)))-(0.75))/((0.0)-(0.75))))+0.3*MIN(1,MAX(0,((BC66)-(1.2))/((0.6)-(1.2))))+0.3*BD66) | BI66: =100*(0.5*MIN(1,MAX(0,((AK66)-(1.0))/((4.0)-(1.0))))+0.3*MIN(1,MAX(0,((IF(ISNUMBER(AO66),AO66,0)*100)-(0.0))/((8.0)-(0.0))))+0.2*MIN(1,MAX(0,((IF(ISNUMBER(AP66),AP66,0))-(25.0))/((5.0)-(25.0))))) | BJ66: =100*(0.35*MIN(1,MAX(0,((ABS(AU66))-(0.3))/((0.05)-(0.3))))+0.3*MIN(1,MAX(0,((AV66)-(0.0))/((0.3)-(0.0))))+0.25*MIN(1,MAX(0,((AW66)-(0.4))/((0.7)-(0.4))))+0.1*IF(AY66>=2,1,0.5)) | BK66: =0.25*BG66+0.25*BH66+0.2*BI66+0.3*BJ66 | BL66: 全部通過
A67: 1 | B67: 66 | C67: QLYS | D67: Qualys Inc. | E67: NASDAQ | F67: 科技 | G67: Computer Software: Prepackaged Software | H67: 6.476 | I67: 中型 | J67: 187.43 | K67: 187.2 | L67: =J67/K67-1 | M67: 190.92 | N67: 184.38 | O67: 654000 | P67: 730315 | Q67: =O67/P67 | R67: 181.1269 | S67: 178.5106 | T67: 177.1905 | U67: =S67/T67-1 | V67: 0.8 | W67: =J67/R67-1 | X67: =J67/S67-1 | Y67: 9.1773 | Z67: =Y67/J67 | AA67: =(J67-R67)/Y67 | AB67: =(J67-S67)/Y67 | AC67: =IF(ABS(AA67)<=ABS(AB67),"9EMA","21EMA") | AD67: 9+21EMA | AE67: 持續在上方 | AI67: 2026-09-16 | AJ67: 11 | AK67: 2 | AL67: 2026-09-28 | AM67: 168.06 | AN67: 149.13 | AO67: =IF(ISNUMBER(AN67),AM67/AN67-1,"") | AP67: 3 | AQ67: =IF(ISNUMBER(AM67),J67/AM67-1,"") | AR67: 187.43 | AS67: =J67/AR67-1 | AT67: 上升三角（平頂） | AU67: -0.044 | AV67: 0.9182 | AW67: 0.653 | AX67: 0.6835 | AY67: 6 | AZ67: 190.99 | BA67: 149.13 | BB67: 176.4647 | BC67: 1.4438 | BD67: =IF(M67=N67,0.5,(J67-N67)/(M67-N67)) | BE67: 10.641 | BF67: 5.887 | BG67: =100*(0.4*MIN(1,MAX(0,((U67*100)-(0.0))/((2.5)-(0.0))))+0.3*MIN(1,MAX(0,((V67)-(0.6))/((1.0)-(0.6))))+0.3*MIN(1,MAX(0,((BE67)-(0.0))/((15.0)-(0.0))))) | BH67: =100*(0.4*MIN(1,MAX(0,((MIN(ABS(AA67),ABS(AB67)))-(0.75))/((0.0)-(0.75))))+0.3*MIN(1,MAX(0,((BC67)-(1.2))/((0.6)-(1.2))))+0.3*BD67) | BI67: =100*(0.5*MIN(1,MAX(0,((AK67)-(1.0))/((4.0)-(1.0))))+0.3*MIN(1,MAX(0,((IF(ISNUMBER(AO67),AO67,0)*100)-(0.0))/((8.0)-(0.0))))+0.2*MIN(1,MAX(0,((IF(ISNUMBER(AP67),AP67,0))-(25.0))/((5.0)-(25.0))))) | BJ67: =100*(0.35*MIN(1,MAX(0,((ABS(AU67))-(0.3))/((0.05)-(0.3))))+0.3*MIN(1,MAX(0,((AV67)-(0.0))/((0.3)-(0.0))))+0.25*MIN(1,MAX(0,((AW67)-(0.4))/((0.7)-(0.4))))+0.1*IF(AY67>=2,1,0.5)) | BK67: =0.25*BG67+0.25*BH67+0.2*BI67+0.3*BJ67 | BL67: 全部通過
A68: 1 | B68: 67 | C68: BWIN | D68: The Baldwin Insurance Group Inc. | E68: NASDAQ | F68: 金融 | G68: Specialty Insurers | H68: 4.435 | I68: 中型 | J68: 31.77 | K68: 31.79 | L68: =J68/K68-1 | M68: 31.93 | N68: 31.77 | O68: 5514700 | P68: 5347480 | Q68: =O68/P68 | R68: 31.75 | S68: 31.3795 | T68: 31.1237 | U68: =S68/T68-1 | V68: 1 | W68: =J68/R68-1 | X68: =J68/S68-1 | Y68: 0.6275 | Z68: =Y68/J68 | AA68: =(J68-R68)/Y68 | AB68: =(J68-S68)/Y68 | AC68: =IF(ABS(AA68)<=ABS(AB68),"9EMA","21EMA") | AD68: 9EMA | AE68: 持續在上方 | AH68: ✓ | AI68: 2026-09-14 | AJ68: 13 | AK68: 2 | AL68: 2026-09-24 | AM68: 31.7 | AN68: 27.74 | AO68: =IF(ISNUMBER(AN68),AM68/AN68-1,"") | AP68: 5 | AQ68: =IF(ISNUMBER(AM68),J68/AM68-1,"") | AR68: 32.49 | AS68: =J68/AR68-1 | AT68: 上升通道 | AU68: 0.362 | AV68: 0.3549 | AW68: 0.8217 | AX68: 0.8426 | AY68: 2 | AZ68: 32.705 | BA68: 27.74 | BB68: 31.8196 | BC68: 1.287 | BD68: =IF(M68=N68,0.5,(J68-N68)/(M68-N68)) | BE68: 9.744 | BF68: 4.99 | BG68: =100*(0.4*MIN(1,MAX(0,((U68*100)-(0.0))/((2.5)-(0.0))))+0.3*MIN(1,MAX(0,((V68)-(0.6))/((1.0)-(0.6))))+0.3*MIN(1,MAX(0,((BE68)-(0.0))/((15.0)-(0.0))))) | BH68: =100*(0.4*MIN(1,MAX(0,((MIN(ABS(AA68),ABS(AB68)))-(0.75))/((0.0)-(0.75))))+0.3*MIN(1,MAX(0,((BC68)-(1.2))/((0.6)-(1.2))))+0.3*BD68) | BI68: =100*(0.5*MIN(1,MAX(0,((AK68)-(1.0))/((4.0)-(1.0))))+0.3*MIN(1,MAX(0,((IF(ISNUMBER(AO68),AO68,0)*100)-(0.0))/((8.0)-(0.0))))+0.2*MIN(1,MAX(0,((IF(ISNUMBER(AP68),AP68,0))-(25.0))/((5.0)-(25.0))))) | BJ68: =100*(0.35*MIN(1,MAX(0,((ABS(AU68))-(0.3))/((0.05)-(0.3))))+0.3*MIN(1,MAX(0,((AV68)-(0.0))/((0.3)-(0.0))))+0.25*MIN(1,MAX(0,((AW68)-(0.4))/((0.7)-(0.4))))+0.1*IF(AY68>=2,1,0.5)) | BK68: =0.25*BG68+0.25*BH68+0.2*BI68+0.3*BJ68 | BL68: 全部通過
A69: 1 | B69: 68 | C69: CAT | D69: Caterpillar Inc. | E69: NYSE | F69: 工業 | G69: Construction/Ag Equipment/Trucks | H69: 372.7 | I69: 大型 | J69: 826.35 | K69: 810.79 | L69: =J69/K69-1 | M69: 833.62 | N69: 802.44 | O69: 2153800 | P69: 2326385 | Q69: =O69/P69 | R69: 816.0889 | S69: 814.0842 | T69: 809.8128 | U69: =S69/T69-1 | V69: 0.6 | W69: =J69/R69-1 | X69: =J69/S69-1 | Y69: 22.598 | Z69: =Y69/J69 | AA69: =(J69-R69)/Y69 | AB69: =(J69-S69)/Y69 | AC69: =IF(ABS(AA69)<=ABS(AB69),"9EMA","21EMA") | AD69: 9+21EMA | AE69: 剛黃金交叉 | AF69: ✓ | AH69: ✓ | AI69: 2026-09-29 | AJ69: 2 | AK69: 3 | AL69: 2026-09-24 | AM69: 794.2 | AN69: 772.86 | AO69: =IF(ISNUMBER(AN69),AM69/AN69-1,"") | AP69: 5 | AQ69: =IF(ISNUMBER(AM69),J69/AM69-1,"") | AR69: 826.64 | AS69: =J69/AR69-1 | AT69: 上升三角（平頂） | AU69: -0.0362 | AV69: 0.1873 | AW69: 0.552 | AX69: 0.5599 | AY69: 11 | AZ69: 833.62 | BA69: 771.39 | BB69: 805.7417 | BC69: 0.7926 | BD69: =IF(M69=N69,0.5,(J69-N69)/(M69-N69)) | BE69: 10.811 | BF69: 6.057 | BG69: =100*(0.4*MIN(1,MAX(0,((U69*100)-(0.0))/((2.5)-(0.0))))+0.3*MIN(1,MAX(0,((V69)-(0.6))/((1.0)-(0.6))))+0.3*MIN(1,MAX(0,((BE69)-(0.0))/((15.0)-(0.0))))) | BH69: =100*(0.4*MIN(1,MAX(0,((MIN(ABS(AA69),ABS(AB69)))-(0.75))/((0.0)-(0.75))))+0.3*MIN(1,MAX(0,((BC69)-(1.2))/((0.6)-(1.2))))+0.3*BD69) | BI69: =100*(0.5*MIN(1,MAX(0,((AK69)-(1.0))/((4.0)-(1.0))))+0.3*MIN(1,MAX(0,((IF(ISNUMBER(AO69),AO69,0)*100)-(0.0))/((8.0)-(0.0))))+0.2*MIN(1,MAX(0,((IF(ISNUMBER(AP69),AP69,0))-(25.0))/((5.0)-(25.0))))) | BJ69: =100*(0.35*MIN(1,MAX(0,((ABS(AU69))-(0.3))/((0.05)-(0.3))))+0.3*MIN(1,MAX(0,((AV69)-(0.0))/((0.3)-(0.0))))+0.25*MIN(1,MAX(0,((AW69)-(0.4))/((0.7)-(0.4))))+0.1*IF(AY69>=2,1,0.5)) | BK69: =0.25*BG69+0.25*BH69+0.2*BI69+0.3*BJ69 | BL69: 全部通過
A70: 1 | B70: 69 | C70: CRVL | D70: CorVel Corp. | E70: NASDAQ | F70: 金融 | G70: Specialty Insurers | H70: 3.766 | I70: 中型 | J70: 74.72 | K70: 74.55 | L70: =J70/K70-1 | M70: 75.86 | N70: 74.51 | O70: 216700 | P70: 230715 | Q70: =O70/P70 | R70: 73.6479 | S70: 71.8831 | T70: 70.3399 | U70: =S70/T70-1 | V70: 1 | W70: =J70/R70-1 | X70: =J70/S70-1 | Y70: 1.7759 | Z70: =Y70/J70 | AA70: =(J70-R70)/Y70 | AB70: =(J70-S70)/Y70 | AC70: =IF(ABS(AA70)<=ABS(AB70),"9EMA","21EMA") | AD70: 9EMA | AE70: 持續在上方 | AH70: ✓ | AI70: 2026-08-06 | AJ70: 39 | AK70: 2 | AL70: 2026-09-18 | AM70: 69.15 | AN70: 65.18 | AO70: =IF(ISNUMBER(AN70),AM70/AN70-1,"") | AP70: 9 | AQ70: =IF(ISNUMBER(AM70),J70/AM70-1,"") | AR70: 74.72 | AS70: =J70/AR70-1 | AT70: 上傾收窄（楔形） | AU70: 0.2794 | AV70: 0.759 | AW70: 0.5567 | AX70: 0.5659 | AY70: 4 | AZ70: 75.86 | BA70: 65.18 | BB70: 71.1257 | BC70: 0.8283 | BD70: =IF(M70=N70,0.5,(J70-N70)/(M70-N70)) | BE70: 11.895 | BF70: 7.141 | BG70: =100*(0.4*MIN(1,MAX(0,((U70*100)-(0.0))/((2.5)-(0.0))))+0.3*MIN(1,MAX(0,((V70)-(0.6))/((1.0)-(0.6))))+0.3*MIN(1,MAX(0,((BE70)-(0.0))/((15.0)-(0.0))))) | BH70: =100*(0.4*MIN(1,MAX(0,((MIN(ABS(AA70),ABS(AB70)))-(0.75))/((0.0)-(0.75))))+0.3*MIN(1,MAX(0,((BC70)-(1.2))/((0.6)-(1.2))))+0.3*BD70) | BI70: =100*(0.5*MIN(1,MAX(0,((AK70)-(1.0))/((4.0)-(1.0))))+0.3*MIN(1,MAX(0,((IF(ISNUMBER(AO70),AO70,0)*100)-(0.0))/((8.0)-(0.0))))+0.2*MIN(1,MAX(0,((IF(ISNUMBER(AP70),AP70,0))-(25.0))/((5.0)-(25.0))))) | BJ70: =100*(0.35*MIN(1,MAX(0,((ABS(AU70))-(0.3))/((0.05)-(0.3))))+0.3*MIN(1,MAX(0,((AV70)-(0.0))/((0.3)-(0.0))))+0.25*MIN(1,MAX(0,((AW70)-(0.4))/((0.7)-(0.4))))+0.1*IF(AY70>=2,1,0.5)) | BK70: =0.25*BG70+0.25*BH70+0.2*BI70+0.3*BJ70 | BL70: 全部通過
A71: 1 | B71: 70 | C71: UTMD | D71: Utah Medical Products Inc. | E71: NASDAQ | F71: 醫療保健 | G71: Medical/Dental Instruments | H71: 0.236 | I71: 小型 | J71: 74.35 | K71: 74.05 | L71: =J71/K71-1 | M71: 74.51 | N71: 74.07 | O71: 18900 | P71: 35115 | Q71: =O71/P71 | R71: 74.3086 | S71: 73.4627 | T71: 72.8899 | U71: =S71/T71-1 | V71: 1 | W71: =J71/R71-1 | X71: =J71/S71-1 | Y71: 1.3854 | Z71: =Y71/J71 | AA71: =(J71-R71)/Y71 | AB71: =(J71-S71)/Y71 | AC71: =IF(ABS(AA71)<=ABS(AB71),"9EMA","21EMA") | AD71: 9EMA | AE71: 持續在上方 | AH71: ✓ | AI71: 2026-09-15 | AJ71: 12 | AK71: 3 | AL71: 2026-09-28 | AM71: 73.75 | AN71: 73.7 | AO71: =IF(ISNUMBER(AN71),AM71/AN71-1,"") | AP71: 3 | AQ71: =IF(ISNUMBER(AM71),J71/AM71-1,"") | AR71: 76.66 | AS71: =J71/AR71-1 | AT71: 上傾收窄（楔形） | AU71: 0.2984 | AV71: 0.541 | AW71: 0.5188 | AX71: 0.4898 | AY71: 2 | AZ71: 76.89 | BA71: 68.46 | BB71: 72.8333 | BC71: 0.9739 | BD71: =IF(M71=N71,0.5,(J71-N71)/(M71-N71)) | BE71: 8.363 | BF71: 3.609 | BG71: =100*(0.4*MIN(1,MAX(0,((U71*100)-(0.0))/((2.5)-(0.0))))+0.3*MIN(1,MAX(0,((V71)-(0.6))/((1.0)-(0.6))))+0.3*MIN(1,MAX(0,((BE71)-(0.0))/((15.0)-(0.0))))) | BH71: =100*(0.4*MIN(1,MAX(0,((MIN(ABS(AA71),ABS(AB71)))-(0.75))/((0.0)-(0.75))))+0.3*MIN(1,MAX(0,((BC71)-(1.2))/((0.6)-(1.2))))+0.3*BD71) | BI71: =100*(0.5*MIN(1,MAX(0,((AK71)-(1.0))/((4.0)-(1.0))))+0.3*MIN(1,MAX(0,((IF(ISNUMBER(AO71),AO71,0)*100)-(0.0))/((8.0)-(0.0))))+0.2*MIN(1,MAX(0,((IF(ISNUMBER(AP71),AP71,0))-(25.0))/((5.0)-(25.0))))) | BJ71: =100*(0.35*MIN(1,MAX(0,((ABS(AU71))-(0.3))/((0.05)-(0.3))))+0.3*MIN(1,MAX(0,((AV71)-(0.0))/((0.3)-(0.0))))+0.25*MIN(1,MAX(0,((AW71)-(0.4))/((0.7)-(0.4))))+0.1*IF(AY71>=2,1,0.5)) | BK71: =0.25*BG71+0.25*BH71+0.2*BI71+0.3*BJ71 | BL71: 全部通過
A72: 1 | B72: 71 | C72: WAT | D72: Waters Corporation | E72: NYSE | F72: 工業 | G72: Biotechnology: Laboratory Analytical Instruments | H72: 43.169 | I72: 大型 | J72: 425.53 | K72: 439.39 | L72: =J72/K72-1 | M72: 438.03 | N72: 424.7 | O72: 810700 | P72: 698275 | Q72: =O72/P72 | R72: 431.2563 | S72: 423.8139 | T72: 416.06 | U72: =S72/T72-1 | V72: 1 | W72: =J72/R72-1 | X72: =J72/S72-1 | Y72: 11.7786 | Z72: =Y72/J72 | AA72: =(J72-R72)/Y72 | AB72: =(J72-S72)/Y72 | AC72: =IF(ABS(AA72)<=ABS(AB72),"9EMA","21EMA") | AD72: 9+21EMA | AE72: 持續在上方 | AG72: ✓ | AI72: 2026-05-05 | AJ72: 103 | AK72: 2 | AL72: 2026-09-24 | AM72: 418 | AN72: 392.95 | AO72: =IF(ISNUMBER(AN72),AM72/AN72-1,"") | AP72: 5 | AQ72: =IF(ISNUMBER(AM72),J72/AM72-1,"") | AR72: 443.26 | AS72: =J72/AR72-1 | AT72: 上傾收窄（楔形） | AU72: 0.2921 | AV72: 0.5887 | AW72: 0.5113 | AX72: 0.47 | AY72: 3 | AZ72: 448.21 | BA72: 392.95 | BB72: 421.2033 | BC72: 1.0319 | BD72: =IF(M72=N72,0.5,(J72-N72)/(M72-N72)) | BE72: 9.606 | BF72: 4.852 | BG72: =100*(0.4*MIN(1,MAX(0,((U72*100)-(0.0))/((2.5)-(0.0))))+0.3*MIN(1,MAX(0,((V72)-(0.6))/((1.0)-(0.6))))+0.3*MIN(1,MAX(0,((BE72)-(0.0))/((15.0)-(0.0))))) | BH72: =100*(0.4*MIN(1,MAX(0,((MIN(ABS(AA72),ABS(AB72)))-(0.75))/((0.0)-(0.75))))+0.3*MIN(1,MAX(0,((BC72)-(1.2))/((0.6)-(1.2))))+0.3*BD72) | BI72: =100*(0.5*MIN(1,MAX(0,((AK72)-(1.0))/((4.0)-(1.0))))+0.3*MIN(1,MAX(0,((IF(ISNUMBER(AO72),AO72,0)*100)-(0.0))/((8.0)-(0.0))))+0.2*MIN(1,MAX(0,((IF(ISNUMBER(AP72),AP72,0))-(25.0))/((5.0)-(25.0))))) | BJ72: =100*(0.35*MIN(1,MAX(0,((ABS(AU72))-(0.3))/((0.05)-(0.3))))+0.3*MIN(1,MAX(0,((AV72)-(0.0))/((0.3)-(0.0))))+0.25*MIN(1,MAX(0,((AW72)-(0.4))/((0.7)-(0.4))))+0.1*IF(AY72>=2,1,0.5)) | BK72: =0.25*BG72+0.25*BH72+0.2*BI72+0.3*BJ72 | BL72: 全部通過
A73: 1 | B73: 72 | C73: PWR | D73: Quanta Services Inc. | E73: NYSE | F73: 工業 | G73: Engineering & Construction | H73: 94.661 | I73: 大型 | J73: 662.6 | K73: 642.51 | L73: =J73/K73-1 | M73: 664.36 | N73: 638.71 | O73: 904300 | P73: 824975 | Q73: =O73/P73 | R73: 645.8046 | S73: 639.9754 | T73: 633.4983 | U73: =S73/T73-1 | V73: 1 | W73: =J73/R73-1 | X73: =J73/S73-1 | Y73: 21.5665 | Z73: =Y73/J73 | AA73: =(J73-R73)/Y73 | AB73: =(J73-S73)/Y73 | AC73: =IF(ABS(AA73)<=ABS(AB73),"9EMA","21EMA") | AD73: 9+21EMA | AE73: 剛黃金交叉 | AF73: ✓ | AH73: ✓ | AI73: 2026-09-24 | AJ73: 5 | AK73: 3 | AL73: 2026-09-24 | AM73: 626.41 | AN73: 607.45 | AO73: =IF(ISNUMBER(AN73),AM73/AN73-1,"") | AP73: 5 | AQ73: =IF(ISNUMBER(AM73),J73/AM73-1,"") | AR73: 662.6 | AS73: =J73/AR73-1 | AT73: 上升通道 | AU73: 0.2561 | AV73: 0.2889 | AW73: 0.512 | AX73: 0.4537 | AY73: 5 | AZ73: 664.36 | BA73: 593.7 | BB73: 629.8784 | BC73: 0.9657 | BD73: =IF(M73=N73,0.5,(J73-N73)/(M73-N73)) | BE73: 13.13 | BF73: 8.376 | BG73: =100*(0.4*MIN(1,MAX(0,((U73*100)-(0.0))/((2.5)-(0.0))))+0.3*MIN(1,MAX(0,((V73)-(0.6))/((1.0)-(0.6))))+0.3*MIN(1,MAX(0,((BE73)-(0.0))/((15.0)-(0.0))))) | BH73: =100*(0.4*MIN(1,MAX(0,((MIN(ABS(AA73),ABS(AB73)))-(0.75))/((0.0)-(0.75))))+0.3*MIN(1,MAX(0,((BC73)-(1.2))/((0.6)-(1.2))))+0.3*BD73) | BI73: =100*(0.5*MIN(1,MAX(0,((AK73)-(1.0))/((4.0)-(1.0))))+0.3*MIN(1,MAX(0,((IF(ISNUMBER(AO73),AO73,0)*100)-(0.0))/((8.0)-(0.0))))+0.2*MIN(1,MAX(0,((IF(ISNUMBER(AP73),AP73,0))-(25.0))/((5.0)-(25.0))))) | BJ73: =100*(0.35*MIN(1,MAX(0,((ABS(AU73))-(0.3))/((0.05)-(0.3))))+0.3*MIN(1,MAX(0,((AV73)-(0.0))/((0.3)-(0.0))))+0.25*MIN(1,MAX(0,((AW73)-(0.4))/((0.7)-(0.4))))+0.1*IF(AY73>=2,1,0.5)) | BK73: =0.25*BG73+0.25*BH73+0.2*BI73+0.3*BJ73 | BL73: 全部通過
A74: 1 | B74: 73 | C74: M | D74: Macy's Inc | E74: NYSE | F74: 非必需消費 | G74: Department/Specialty Retail Stores | H74: 5.947 | I74: 中型 | J74: 22.76 | K74: 22.77 | L74: =J74/K74-1 | M74: 23.23 | N74: 22.61 | O74: 7484600 | P74: 7020895 | Q74: =O74/P74 | R74: 22.6606 | S74: 22.5586 | T74: 22.3571 | U74: =S74/T74-1 | V74: 0.6 | W74: =J74/R74-1 | X74: =J74/S74-1 | Y74: 0.8223 | Z74: =Y74/J74 | AA74: =(J74-R74)/Y74 | AB74: =(J74-S74)/Y74 | AC74: =IF(ABS(AA74)<=ABS(AB74),"9EMA","21EMA") | AD74: 9+21EMA | AE74: 剛黃金交叉 | AF74: ✓ | AH74: ✓ | AI74: 2026-09-29 | AJ74: 2 | AK74: 3 | AL74: 2026-09-28 | AM74: 22.13 | AN74: 21.54 | AO74: =IF(ISNUMBER(AN74),AM74/AN74-1,"") | AP74: 3 | AQ74: =IF(ISNUMBER(AM74),J74/AM74-1,"") | AR74: 23.27 | AS74: =J74/AR74-1 | AT74: 上升三角（平頂） | AU74: -0.0539 | AV74: 0.2024 | AW74: 0.6182 | AX74: 0.598 | AY74: 3 | AZ74: 23.63 | BA74: 19.77 | BB74: 22.1564 | BC74: 1.1073 | BD74: =IF(M74=N74,0.5,(J74-N74)/(M74-N74)) | BE74: 8.539 | BF74: 3.785 | BG74: =100*(0.4*MIN(1,MAX(0,((U74*100)-(0.0))/((2.5)-(0.0))))+0.3*MIN(1,MAX(0,((V74)-(0.6))/((1.0)-(0.6))))+0.3*MIN(1,MAX(0,((BE74)-(0.0))/((15.0)-(0.0))))) | BH74: =100*(0.4*MIN(1,MAX(0,((MIN(ABS(AA74),ABS(AB74)))-(0.75))/((0.0)-(0.75))))+0.3*MIN(1,MAX(0,((BC74)-(1.2))/((0.6)-(1.2))))+0.3*BD74) | BI74: =100*(0.5*MIN(1,MAX(0,((AK74)-(1.0))/((4.0)-(1.0))))+0.3*MIN(1,MAX(0,((IF(ISNUMBER(AO74),AO74,0)*100)-(0.0))/((8.0)-(0.0))))+0.2*MIN(1,MAX(0,((IF(ISNUMBER(AP74),AP74,0))-(25.0))/((5.0)-(25.0))))) | BJ74: =100*(0.35*MIN(1,MAX(0,((ABS(AU74))-(0.3))/((0.05)-(0.3))))+0.3*MIN(1,MAX(0,((AV74)-(0.0))/((0.3)-(0.0))))+0.25*MIN(1,MAX(0,((AW74)-(0.4))/((0.7)-(0.4))))+0.1*IF(AY74>=2,1,0.5)) | BK74: =0.25*BG74+0.25*BH74+0.2*BI74+0.3*BJ74 | BL74: 全部通過
A75: 1 | B75: 74 | C75: ITGR | D75: Integer Holdings Corporation | E75: NYSE | F75: 醫療保健 | G75: Biotechnology: Electromedical & Electrotherapeutic Apparatus | H75: 4.295 | I75: 中型 | J75: 126.42 | K75: 126.35 | L75: =J75/K75-1 | M75: 126.47 | N75: 126.37 | O75: 415000 | P75: 817795 | Q75: =O75/P75 | R75: 126.3154 | S75: 125.6835 | T75: 125.2664 | U75: =S75/T75-1 | V75: 1 | W75: =J75/R75-1 | X75: =J75/S75-1 | Y75: 0.4371 | Z75: =Y75/J75 | AA75: =(J75-R75)/Y75 | AB75: =(J75-S75)/Y75 | AC75: =IF(ABS(AA75)<=ABS(AB75),"9EMA","21EMA") | AD75: 9EMA | AE75: 持續在上方 | AH75: ✓ | AI75: 2026-05-13 | AJ75: 97 | AK75: 4 | AL75: 2026-09-24 | AM75: 126.16 | AN75: 124.84 | AO75: =IF(ISNUMBER(AN75),AM75/AN75-1,"") | AP75: 5 | AQ75: =IF(ISNUMBER(AM75),J75/AM75-1,"") | AR75: 126.42 | AS75: =J75/AR75-1 | AT75: 上升三角（平頂） | AU75: -0.0257 | AV75: 0.0386 | AW75: 0.5352 | AX75: 0.6563 | AY75: 25 | AZ75: 126.8 | BA75: 125.23 | BB75: 126.0703 | BC75: 1.0661 | BD75: =IF(M75=N75,0.5,(J75-N75)/(M75-N75)) | BE75: 5.576 | BF75: 0.821 | BG75: =100*(0.4*MIN(1,MAX(0,((U75*100)-(0.0))/((2.5)-(0.0))))+0.3*MIN(1,MAX(0,((V75)-(0.6))/((1.0)-(0.6))))+0.3*MIN(1,MAX(0,((BE75)-(0.0))/((15.0)-(0.0))))) | BH75: =100*(0.4*MIN(1,MAX(0,((MIN(ABS(AA75),ABS(AB75)))-(0.75))/((0.0)-(0.75))))+0.3*MIN(1,MAX(0,((BC75)-(1.2))/((0.6)-(1.2))))+0.3*BD75) | BI75: =100*(0.5*MIN(1,MAX(0,((AK75)-(1.0))/((4.0)-(1.0))))+0.3*MIN(1,MAX(0,((IF(ISNUMBER(AO75),AO75,0)*100)-(0.0))/((8.0)-(0.0))))+0.2*MIN(1,MAX(0,((IF(ISNUMBER(AP75),AP75,0))-(25.0))/((5.0)-(25.0))))) | BJ75: =100*(0.35*MIN(1,MAX(0,((ABS(AU75))-(0.3))/((0.05)-(0.3))))+0.3*MIN(1,MAX(0,((AV75)-(0.0))/((0.3)-(0.0))))+0.25*MIN(1,MAX(0,((AW75)-(0.4))/((0.7)-(0.4))))+0.1*IF(AY75>=2,1,0.5)) | BK75: =0.25*BG75+0.25*BH75+0.2*BI75+0.3*BJ75 | BL75: 全部通過
A76: 1 | B76: 75 | C76: GSAT | D76: Globalstar Inc. | E76: NASDAQ | F76: 非必需消費 | G76: Telecommunications Equipment | H76: 10.74 | I76: 大型 | J76: 82.88 | K76: 82.89 | L76: =J76/K76-1 | M76: 83.16 | N76: 82.64 | O76: 602600 | P76: 556795 | Q76: =O76/P76 | R76: 82.6455 | S76: 82.4429 | T76: 82.2692 | U76: =S76/T76-1 | V76: 1 | W76: =J76/R76-1 | X76: =J76/S76-1 | Y76: 0.6581 | Z76: =Y76/J76 | AA76: =(J76-R76)/Y76 | AB76: =(J76-S76)/Y76 | AC76: =IF(ABS(AA76)<=ABS(AB76),"9EMA","21EMA") | AD76: 9+21EMA | AE76: 持續在上方 | AH76: ✓ | AI76: 2026-09-17 | AJ76: 10 | AK76: 4 | AL76: 2026-09-23 | AM76: 81.95 | AN76: 81.55 | AO76: =IF(ISNUMBER(AN76),AM76/AN76-1,"") | AP76: 6 | AQ76: =IF(ISNUMBER(AM76),J76/AM76-1,"") | AR76: 83.04 | AS76: =J76/AR76-1 | AT76: 上升三角（平頂） | AU76: 0.091 | AV76: 0.076 | AW76: 0.568 | AX76: 0.525 | AY76: 22 | AZ76: 83.18 | BA76: 81.02 | BB76: 82.2468 | BC76: 0.8914 | BD76: =IF(M76=N76,0.5,(J76-N76)/(M76-N76)) | BE76: 6.61 | BF76: 1.856 | BG76: =100*(0.4*MIN(1,MAX(0,((U76*100)-(0.0))/((2.5)-(0.0))))+0.3*MIN(1,MAX(0,((V76)-(0.6))/((1.0)-(0.6))))+0.3*MIN(1,MAX(0,((BE76)-(0.0))/((15.0)-(0.0))))) | BH76: =100*(0.4*MIN(1,MAX(0,((MIN(ABS(AA76),ABS(AB76)))-(0.75))/((0.0)-(0.75))))+0.3*MIN(1,MAX(0,((BC76)-(1.2))/((0.6)-(1.2))))+0.3*BD76) | BI76: =100*(0.5*MIN(1,MAX(0,((AK76)-(1.0))/((4.0)-(1.0))))+0.3*MIN(1,MAX(0,((IF(ISNUMBER(AO76),AO76,0)*100)-(0.0))/((8.0)-(0.0))))+0.2*MIN(1,MAX(0,((IF(ISNUMBER(AP76),AP76,0))-(25.0))/((5.0)-(25.0))))) | BJ76: =100*(0.35*MIN(1,MAX(0,((ABS(AU76))-(0.3))/((0.05)-(0.3))))+0.3*MIN(1,MAX(0,((AV76)-(0.0))/((0.3)-(0.0))))+0.25*MIN(1,MAX(0,((AW76)-(0.4))/((0.7)-(0.4))))+0.1*IF(AY76>=2,1,0.5)) | BK76: =0.25*BG76+0.25*BH76+0.2*BI76+0.3*BJ76 | BL76: 全部通過
A77: 1 | B77: 76 | C77: TH | D77: Target Hospitality Corp. | E77: NASDAQ | F77: 非必需消費 | G77: Hotels/Resorts | H77: 1.965 | I77: 小型 | J77: 20.48 | K77: 19.72 | L77: =J77/K77-1 | M77: 20.925 | N77: 19.64 | O77: 1825400 | P77: 2423865 | Q77: =O77/P77 | R77: 20.1348 | S77: 19.7224 | T77: 19.6261 | U77: =S77/T77-1 | V77: 0.8 | W77: =J77/R77-1 | X77: =J77/S77-1 | Y77: 0.9849 | Z77: =Y77/J77 | AA77: =(J77-R77)/Y77 | AB77: =(J77-S77)/Y77 | AC77: =IF(ABS(AA77)<=ABS(AB77),"9EMA","21EMA") | AD77: 9+21EMA | AE77: 持續在上方 | AH77: ✓ | AI77: 2026-08-17 | AJ77: 32 | AK77: 3 | AL77: 2026-09-28 | AM77: 18.94 | AN77: 18.43 | AO77: =IF(ISNUMBER(AN77),AM77/AN77-1,"") | AP77: 3 | AQ77: =IF(ISNUMBER(AM77),J77/AM77-1,"") | AR77: 21.45 | AS77: =J77/AR77-1 | AT77: 上傾擴張 | AU77: 0.5656 | AV77: 0.249 | AW77: 0.5496 | AX77: 0.4974 | AY77: 5 | AZ77: 21.76 | BA77: 17.3 | BB77: 19.7512 | BC77: 0.7609 | BD77: =IF(M77=N77,0.5,(J77-N77)/(M77-N77)) | BE77: 18.091 | BF77: 13.337 | BG77: =100*(0.4*MIN(1,MAX(0,((U77*100)-(0.0))/((2.5)-(0.0))))+0.3*MIN(1,MAX(0,((V77)-(0.6))/((1.0)-(0.6))))+0.3*MIN(1,MAX(0,((BE77)-(0.0))/((15.0)-(0.0))))) | BH77: =100*(0.4*MIN(1,MAX(0,((MIN(ABS(AA77),ABS(AB77)))-(0.75))/((0.0)-(0.75))))+0.3*MIN(1,MAX(0,((BC77)-(1.2))/((0.6)-(1.2))))+0.3*BD77) | BI77: =100*(0.5*MIN(1,MAX(0,((AK77)-(1.0))/((4.0)-(1.0))))+0.3*MIN(1,MAX(0,((IF(ISNUMBER(AO77),AO77,0)*100)-(0.0))/((8.0)-(0.0))))+0.2*MIN(1,MAX(0,((IF(ISNUMBER(AP77),AP77,0))-(25.0))/((5.0)-(25.0))))) | BJ77: =100*(0.35*MIN(1,MAX(0,((ABS(AU77))-(0.3))/((0.05)-(0.3))))+0.3*MIN(1,MAX(0,((AV77)-(0.0))/((0.3)-(0.0))))+0.25*MIN(1,MAX(0,((AW77)-(0.4))/((0.7)-(0.4))))+0.1*IF(AY77>=2,1,0.5)) | BK77: =0.25*BG77+0.25*BH77+0.2*BI77+0.3*BJ77 | BL77: 全部通過
A78: 1 | B78: 77 | C78: CLDT | D78: Chatham Lodging Trust (REIT) | E78: NYSE | F78: 房地產 | G78: Real Estate Investment Trusts | H78: 0.623 | I78: 小型 | J78: 13.56 | K78: 13.38 | L78: =J78/K78-1 | M78: 13.63 | N78: 13.18 | O78: 257600 | P78: 286870 | Q78: =O78/P78 | R78: 13.3354 | S78: 13.2217 | T78: 13.0952 | U78: =S78/T78-1 | V78: 0.9 | W78: =J78/R78-1 | X78: =J78/S78-1 | Y78: 0.3356 | Z78: =Y78/J78 | AA78: =(J78-R78)/Y78 | AB78: =(J78-S78)/Y78 | AC78: =IF(ABS(AA78)<=ABS(AB78),"9EMA","21EMA") | AD78: 9+21EMA | AE78: 剛黃金交叉 | AF78: ✓ | AH78: ✓ | AI78: 2026-09-24 | AJ78: 5 | AK78: 3 | AL78: 2026-09-16 | AM78: 12.64 | AN78: 12.53 | AO78: =IF(ISNUMBER(AN78),AM78/AN78-1,"") | AP78: 11 | AQ78: =IF(ISNUMBER(AM78),J78/AM78-1,"") | AR78: 13.56 | AS78: =J78/AR78-1 | AT78: 上升三角（平頂） | AU78: 0.0405 | AV78: 0.1622 | AW78: 0.5179 | AX78: 0.427 | AY78: 7 | AZ78: 13.68 | BA78: 12.53 | BB78: 13.1256 | BC78: 0.9427 | BD78: =IF(M78=N78,0.5,(J78-N78)/(M78-N78)) | BE78: 8.424 | BF78: 3.67 | BG78: =100*(0.4*MIN(1,MAX(0,((U78*100)-(0.0))/((2.5)-(0.0))))+0.3*MIN(1,MAX(0,((V78)-(0.6))/((1.0)-(0.6))))+0.3*MIN(1,MAX(0,((BE78)-(0.0))/((15.0)-(0.0))))) | BH78: =100*(0.4*MIN(1,MAX(0,((MIN(ABS(AA78),ABS(AB78)))-(0.75))/((0.0)-(0.75))))+0.3*MIN(1,MAX(0,((BC78)-(1.2))/((0.6)-(1.2))))+0.3*BD78) | BI78: =100*(0.5*MIN(1,MAX(0,((AK78)-(1.0))/((4.0)-(1.0))))+0.3*MIN(1,MAX(0,((IF(ISNUMBER(AO78),AO78,0)*100)-(0.0))/((8.0)-(0.0))))+0.2*MIN(1,MAX(0,((IF(ISNUMBER(AP78),AP78,0))-(25.0))/((5.0)-(25.0))))) | BJ78: =100*(0.35*MIN(1,MAX(0,((ABS(AU78))-(0.3))/((0.05)-(0.3))))+0.3*MIN(1,MAX(0,((AV78)-(0.0))/((0.3)-(0.0))))+0.25*MIN(1,MAX(0,((AW78)-(0.4))/((0.7)-(0.4))))+0.1*IF(AY78>=2,1,0.5)) | BK78: =0.25*BG78+0.25*BH78+0.2*BI78+0.3*BJ78 | BL78: 全部通過
A79: 1 | B79: 78 | C79: AMBA | D79: Ambarella Inc. | E79: NASDAQ | F79: 科技 | G79: Semiconductors | H79: 3.068 | I79: 中型 | J79: 70.3 | K79: 69.51 | L79: =J79/K79-1 | M79: 70.95 | N79: 68.47 | O79: 580700 | P79: 2019600 | Q79: =O79/P79 | R79: 69.0585 | S79: 68.83 | T79: 68.1678 | U79: =S79/T79-1 | V79: 0.7 | W79: =J79/R79-1 | X79: =J79/S79-1 | Y79: 4.0239 | Z79: =Y79/J79 | AA79: =(J79-R79)/Y79 | AB79: =(J79-S79)/Y79 | AC79: =IF(ABS(AA79)<=ABS(AB79),"9EMA","21EMA") | AD79: 9+21EMA | AE79: 剛黃金交叉 | AF79: ✓ | AH79: ✓ | AI79: 2026-09-30 | AJ79: 1 | AK79: 3 | AL79: 2026-09-23 | AM79: 63.65 | AN79: 61.91 | AO79: =IF(ISNUMBER(AN79),AM79/AN79-1,"") | AP79: 6 | AQ79: =IF(ISNUMBER(AM79),J79/AM79-1,"") | AR79: 72.68 | AS79: =J79/AR79-1 | AT79: 上傾收窄（楔形） | AU79: 0.2389 | AV79: 0.6629 | AW79: 0.5177 | AX79: 0.4121 | AY79: 1 | AZ79: 74.99 | BA79: 58.12 | BB79: 66.8535 | BC79: 0.7744 | BD79: =IF(M79=N79,0.5,(J79-N79)/(M79-N79)) | BE79: 8.396 | BF79: 3.641 | BG79: =100*(0.4*MIN(1,MAX(0,((U79*100)-(0.0))/((2.5)-(0.0))))+0.3*MIN(1,MAX(0,((V79)-(0.6))/((1.0)-(0.6))))+0.3*MIN(1,MAX(0,((BE79)-(0.0))/((15.0)-(0.0))))) | BH79: =100*(0.4*MIN(1,MAX(0,((MIN(ABS(AA79),ABS(AB79)))-(0.75))/((0.0)-(0.75))))+0.3*MIN(1,MAX(0,((BC79)-(1.2))/((0.6)-(1.2))))+0.3*BD79) | BI79: =100*(0.5*MIN(1,MAX(0,((AK79)-(1.0))/((4.0)-(1.0))))+0.3*MIN(1,MAX(0,((IF(ISNUMBER(AO79),AO79,0)*100)-(0.0))/((8.0)-(0.0))))+0.2*MIN(1,MAX(0,((IF(ISNUMBER(AP79),AP79,0))-(25.0))/((5.0)-(25.0))))) | BJ79: =100*(0.35*MIN(1,MAX(0,((ABS(AU79))-(0.3))/((0.05)-(0.3))))+0.3*MIN(1,MAX(0,((AV79)-(0.0))/((0.3)-(0.0))))+0.25*MIN(1,MAX(0,((AW79)-(0.4))/((0.7)-(0.4))))+0.1*IF(AY79>=2,1,0.5)) | BK79: =0.25*BG79+0.25*BH79+0.2*BI79+0.3*BJ79 | BL79: 全部通過
A80: 1 | B80: 79 | C80: SMTI | D80: Sanara MedTech Inc. | E80: NASDAQ | F80: 醫療保健 | G80: Industrial Specialties | H80: 0.323 | I80: 小型 | J80: 34.88 | K80: 35.14 | L80: =J80/K80-1 | M80: 35.12 | N80: 34.79 | O80: 541800 | P80: 218980 | Q80: =O80/P80 | R80: 35.055 | S80: 34.8487 | T80: 34.7273 | U80: =S80/T80-1 | V80: 1 | W80: =J80/R80-1 | X80: =J80/S80-1 | Y80: 0.2778 | Z80: =Y80/J80 | AA80: =(J80-R80)/Y80 | AB80: =(J80-S80)/Y80 | AC80: =IF(ABS(AA80)<=ABS(AB80),"9EMA","21EMA") | AD80: 9+21EMA | AE80: 持續在上方 | AG80: ✓ | AI80: 2026-05-12 | AJ80: 98 | AK80: 6 | AL80: 2026-09-25 | AM80: 34.97 | AN80: 34.71 | AO80: =IF(ISNUMBER(AN80),AM80/AN80-1,"") | AP80: 4 | AQ80: =IF(ISNUMBER(AM80),J80/AM80-1,"") | AR80: 35.28 | AS80: =J80/AR80-1 | AT80: 上升三角（平頂） | AU80: 0.041 | AV80: 0.0728 | AW80: 0.5146 | AX80: 0.4828 | AY80: 22 | AZ80: 35.34 | BA80: 34.46 | BB80: 34.9128 | BC80: 1.421 | BD80: =IF(M80=N80,0.5,(J80-N80)/(M80-N80)) | BE80: 5.013 | BF80: 0.259 | BG80: =100*(0.4*MIN(1,MAX(0,((U80*100)-(0.0))/((2.5)-(0.0))))+0.3*MIN(1,MAX(0,((V80)-(0.6))/((1.0)-(0.6))))+0.3*MIN(1,MAX(0,((BE80)-(0.0))/((15.0)-(0.0))))) | BH80: =100*(0.4*MIN(1,MAX(0,((MIN(ABS(AA80),ABS(AB80)))-(0.75))/((0.0)-(0.75))))+0.3*MIN(1,MAX(0,((BC80)-(1.2))/((0.6)-(1.2))))+0.3*BD80) | BI80: =100*(0.5*MIN(1,MAX(0,((AK80)-(1.0))/((4.0)-(1.0))))+0.3*MIN(1,MAX(0,((IF(ISNUMBER(AO80),AO80,0)*100)-(0.0))/((8.0)-(0.0))))+0.2*MIN(1,MAX(0,((IF(ISNUMBER(AP80),AP80,0))-(25.0))/((5.0)-(25.0))))) | BJ80: =100*(0.35*MIN(1,MAX(0,((ABS(AU80))-(0.3))/((0.05)-(0.3))))+0.3*MIN(1,MAX(0,((AV80)-(0.0))/((0.3)-(0.0))))+0.25*MIN(1,MAX(0,((AW80)-(0.4))/((0.7)-(0.4))))+0.1*IF(AY80>=2,1,0.5)) | BK80: =0.25*BG80+0.25*BH80+0.2*BI80+0.3*BJ80 | BL80: 全部通過
A81: 1 | B81: 80 | C81: FAST | D81: Fastenal Company | E81: NASDAQ | F81: 非必需消費 | G81: RETAIL: Building Materials | H81: 56.836 | I81: 大型 | J81: 50.23 | K81: 49.53 | L81: =J81/K81-1 | M81: 50.27 | N81: 49.11 | O81: 6198900 | P81: 6994730 | Q81: =O81/P81 | R81: 50.0376 | S81: 49.8847 | T81: 49.7511 | U81: =S81/T81-1 | V81: 0.8 | W81: =J81/R81-1 | X81: =J81/S81-1 | Y81: 0.9813 | Z81: =Y81/J81 | AA81: =(J81-R81)/Y81 | AB81: =(J81-S81)/Y81 | AC81: =IF(ABS(AA81)<=ABS(AB81),"9EMA","21EMA") | AD81: 9+21EMA | AE81: 持續在上方 | AH81: ✓ | AI81: 2026-09-23 | AJ81: 6 | AK81: 3 | AL81: 2026-09-21 | AM81: 48.53 | AN81: 48.06 | AO81: =IF(ISNUMBER(AN81),AM81/AN81-1,"") | AP81: 8 | AQ81: =IF(ISNUMBER(AM81),J81/AM81-1,"") | AR81: 50.99 | AS81: =J81/AR81-1 | AT81: 上升三角（平頂） | AU81: 0.0068 | AV81: 0.1452 | AW81: 0.5121 | AX81: 0.5302 | AY81: 6 | AZ81: 51.52 | BA81: 47.65 | BB81: 49.6318 | BC81: 1.4559 | BD81: =IF(M81=N81,0.5,(J81-N81)/(M81-N81)) | BE81: 7.79 | BF81: 3.036 | BG81: =100*(0.4*MIN(1,MAX(0,((U81*100)-(0.0))/((2.5)-(0.0))))+0.3*MIN(1,MAX(0,((V81)-(0.6))/((1.0)-(0.6))))+0.3*MIN(1,MAX(0,((BE81)-(0.0))/((15.0)-(0.0))))) | BH81: =100*(0.4*MIN(1,MAX(0,((MIN(ABS(AA81),ABS(AB81)))-(0.75))/((0.0)-(0.75))))+0.3*MIN(1,MAX(0,((BC81)-(1.2))/((0.6)-(1.2))))+0.3*BD81) | BI81: =100*(0.5*MIN(1,MAX(0,((AK81)-(1.0))/((4.0)-(1.0))))+0.3*MIN(1,MAX(0,((IF(ISNUMBER(AO81),AO81,0)*100)-(0.0))/((8.0)-(0.0))))+0.2*MIN(1,MAX(0,((IF(ISNUMBER(AP81),AP81,0))-(25.0))/((5.0)-(25.0))))) | BJ81: =100*(0.35*MIN(1,MAX(0,((ABS(AU81))-(0.3))/((0.05)-(0.3))))+0.3*MIN(1,MAX(0,((AV81)-(0.0))/((0.3)-(0.0))))+0.25*MIN(1,MAX(0,((AW81)-(0.4))/((0.7)-(0.4))))+0.1*IF(AY81>=2,1,0.5)) | BK81: =0.25*BG81+0.25*BH81+0.2*BI81+0.3*BJ81 | BL81: 全部通過
A82: 1 | B82: 81 | C82: BPRN | D82: Princeton Bancorp Inc. | E82: NASDAQ | F82: 金融 | G82: Major Banks | H82: 0.292 | I82: 小型 | J82: 43.16 | K82: 42.92 | L82: =J82/K82-1 | M82: 44 | N82: 42.26 | O82: 57400 | P82: 30950 | Q82: =O82/P82 | R82: 43.2365 | S82: 43.1207 | T82: 43.0248 | U82: =S82/T82-1 | V82: 0.8 | W82: =J82/R82-1 | X82: =J82/S82-1 | Y82: 0.9989 | Z82: =Y82/J82 | AA82: =(J82-R82)/Y82 | AB82: =(J82-S82)/Y82 | AC82: =IF(ABS(AA82)<=ABS(AB82),"9EMA","21EMA") | AD82: 9+21EMA | AE82: 持續在上方 | AG82: ✓ | AI82: 2026-06-09 | AJ82: 79 | AK82: 2 | AL82: 2026-09-23 | AM82: 42.53 | AN82: 42.26 | AO82: =IF(ISNUMBER(AN82),AM82/AN82-1,"") | AP82: 6 | AQ82: =IF(ISNUMBER(AM82),J82/AM82-1,"") | AR82: 43.88 | AS82: =J82/AR82-1 | AT82: 上升三角（平頂） | AU82: 0.0512 | AV82: 0.0569 | AW82: 0.5874 | AX82: 0.5907 | AY82: 21 | AZ82: 44.1 | BA82: 41.92 | BB82: 43.2005 | BC82: 0.7301 | BD82: =IF(M82=N82,0.5,(J82-N82)/(M82-N82)) | BE82: 6.884 | BF82: 2.13 | BG82: =100*(0.4*MIN(1,MAX(0,((U82*100)-(0.0))/((2.5)-(0.0))))+0.3*MIN(1,MAX(0,((V82)-(0.6))/((1.0)-(0.6))))+0.3*MIN(1,MAX(0,((BE82)-(0.0))/((15.0)-(0.0))))) | BH82: =100*(0.4*MIN(1,MAX(0,((MIN(ABS(AA82),ABS(AB82)))-(0.75))/((0.0)-(0.75))))+0.3*MIN(1,MAX(0,((BC82)-(1.2))/((0.6)-(1.2))))+0.3*BD82) | BI82: =100*(0.5*MIN(1,MAX(0,((AK82)-(1.0))/((4.0)-(1.0))))+0.3*MIN(1,MAX(0,((IF(ISNUMBER(AO82),AO82,0)*100)-(0.0))/((8.0)-(0.0))))+0.2*MIN(1,MAX(0,((IF(ISNUMBER(AP82),AP82,0))-(25.0))/((5.0)-(25.0))))) | BJ82: =100*(0.35*MIN(1,MAX(0,((ABS(AU82))-(0.3))/((0.05)-(0.3))))+0.3*MIN(1,MAX(0,((AV82)-(0.0))/((0.3)-(0.0))))+0.25*MIN(1,MAX(0,((AW82)-(0.4))/((0.7)-(0.4))))+0.1*IF(AY82>=2,1,0.5)) | BK82: =0.25*BG82+0.25*BH82+0.2*BI82+0.3*BJ82 | BL82: 全部通過
A83: 1 | B83: 82 | C83: PKOH | D83: Park-Ohio Holdings Corp. | E83: NASDAQ | F83: 工業 | G83: Industrial Specialties | H83: 0.669 | I83: 小型 | J83: 46.54 | K83: 46.2 | L83: =J83/K83-1 | M83: 46.88 | N83: 44.38 | O83: 113600 | P83: 69405 | Q83: =O83/P83 | R83: 46.751 | S83: 46.358 | T83: 45.9681 | U83: =S83/T83-1 | V83: 0.9 | W83: =J83/R83-1 | X83: =J83/S83-1 | Y83: 1.692 | Z83: =Y83/J83 | AA83: =(J83-R83)/Y83 | AB83: =(J83-S83)/Y83 | AC83: =IF(ABS(AA83)<=ABS(AB83),"9EMA","21EMA") | AD83: 9+21EMA | AE83: 持續在上方 | AG83: ✓ | AI83: 2026-04-09 | AJ83: 121 | AK83: 2 | AL83: 2026-09-15 | AM83: 44 | AN83: 43.62 | AO83: =IF(ISNUMBER(AN83),AM83/AN83-1,"") | AP83: 12 | AQ83: =IF(ISNUMBER(AM83),J83/AM83-1,"") | AR83: 48.04 | AS83: =J83/AR83-1 | AT83: 上升通道 | AU83: 0.1101 | AV83: 0.1166 | AW83: 0.5157 | AX83: 0.5083 | AY83: 4 | AZ83: 48.52 | BA83: 43.62 | BB83: 46.1468 | BC83: 1.1494 | BD83: =IF(M83=N83,0.5,(J83-N83)/(M83-N83)) | BE83: 10.072 | BF83: 5.318 | BG83: =100*(0.4*MIN(1,MAX(0,((U83*100)-(0.0))/((2.5)-(0.0))))+0.3*MIN(1,MAX(0,((V83)-(0.6))/((1.0)-(0.6))))+0.3*MIN(1,MAX(0,((BE83)-(0.0))/((15.0)-(0.0))))) | BH83: =100*(0.4*MIN(1,MAX(0,((MIN(ABS(AA83),ABS(AB83)))-(0.75))/((0.0)-(0.75))))+0.3*MIN(1,MAX(0,((BC83)-(1.2))/((0.6)-(1.2))))+0.3*BD83) | BI83: =100*(0.5*MIN(1,MAX(0,((AK83)-(1.0))/((4.0)-(1.0))))+0.3*MIN(1,MAX(0,((IF(ISNUMBER(AO83),AO83,0)*100)-(0.0))/((8.0)-(0.0))))+0.2*MIN(1,MAX(0,((IF(ISNUMBER(AP83),AP83,0))-(25.0))/((5.0)-(25.0))))) | BJ83: =100*(0.35*MIN(1,MAX(0,((ABS(AU83))-(0.3))/((0.05)-(0.3))))+0.3*MIN(1,MAX(0,((AV83)-(0.0))/((0.3)-(0.0))))+0.25*MIN(1,MAX(0,((AW83)-(0.4))/((0.7)-(0.4))))+0.1*IF(AY83>=2,1,0.5)) | BK83: =0.25*BG83+0.25*BH83+0.2*BI83+0.3*BJ83 | BL83: 全部通過
A84: 1 | B84: 83 | C84: SLAB | D84: Silicon Laboratories Inc. | E84: NASDAQ | F84: 科技 | G84: Semiconductors | H84: 7.393 | I84: 中型 | J84: 222.51 | K84: 221.58 | L84: =J84/K84-1 | M84: 222.92 | N84: 221.49 | O84: 382100 | P84: 284125 | Q84: =O84/P84 | R84: 221.3622 | S84: 220.656 | T84: 220.0998 | U84: =S84/T84-1 | V84: 1 | W84: =J84/R84-1 | X84: =J84/S84-1 | Y84: 1.0733 | Z84: =Y84/J84 | AA84: =(J84-R84)/Y84 | AB84: =(J84-S84)/Y84 | AC84: =IF(ABS(AA84)<=ABS(AB84),"9EMA","21EMA") | AD84: 9+21EMA | AE84: 持續在上方 | AH84: ✓ | AI84: 2026-08-06 | AJ84: 39 | AK84: 2 | AL84: 2026-09-28 | AM84: 220.78 | AN84: 216.88 | AO84: =IF(ISNUMBER(AN84),AM84/AN84-1,"") | AP84: 3 | AQ84: =IF(ISNUMBER(AM84),J84/AM84-1,"") | AR84: 222.51 | AS84: =J84/AR84-1 | AT84: 上升三角（平頂） | AU84: -0.0049 | AV84: 0.0704 | AW84: 0.5744 | AX84: 0.4557 | AY84: 21 | AZ84: 222.92 | BA84: 216.88 | BB84: 220.3492 | BC84: 0.4571 | BD84: =IF(M84=N84,0.5,(J84-N84)/(M84-N84)) | BE84: 6.301 | BF84: 1.547 | BG84: =100*(0.4*MIN(1,MAX(0,((U84*100)-(0.0))/((2.5)-(0.0))))+0.3*MIN(1,MAX(0,((V84)-(0.6))/((1.0)-(0.6))))+0.3*MIN(1,MAX(0,((BE84)-(0.0))/((15.0)-(0.0))))) | BH84: =100*(0.4*MIN(1,MAX(0,((MIN(ABS(AA84),ABS(AB84)))-(0.75))/((0.0)-(0.75))))+0.3*MIN(1,MAX(0,((BC84)-(1.2))/((0.6)-(1.2))))+0.3*BD84) | BI84: =100*(0.5*MIN(1,MAX(0,((AK84)-(1.0))/((4.0)-(1.0))))+0.3*MIN(1,MAX(0,((IF(ISNUMBER(AO84),AO84,0)*100)-(0.0))/((8.0)-(0.0))))+0.2*MIN(1,MAX(0,((IF(ISNUMBER(AP84),AP84,0))-(25.0))/((5.0)-(25.0))))) | BJ84: =100*(0.35*MIN(1,MAX(0,((ABS(AU84))-(0.3))/((0.05)-(0.3))))+0.3*MIN(1,MAX(0,((AV84)-(0.0))/((0.3)-(0.0))))+0.25*MIN(1,MAX(0,((AW84)-(0.4))/((0.7)-(0.4))))+0.1*IF(AY84>=2,1,0.5)) | BK84: =0.25*BG84+0.25*BH84+0.2*BI84+0.3*BJ84 | BL84: 全部通過
A85: 1 | B85: 84 | C85: ETN | D85: Eaton Corporation PLC | E85: NYSE | F85: 科技 | G85: Industrial Machinery/Components | H85: 166.899 | I85: 大型 | J85: 437.28 | K85: 429.71 | L85: =J85/K85-1 | M85: 439.64 | N85: 423 | O85: 1606300 | P85: 2083440 | Q85: =O85/P85 | R85: 431.8085 | S85: 425.486 | T85: 420.1541 | U85: =S85/T85-1 | V85: 1 | W85: =J85/R85-1 | X85: =J85/S85-1 | Y85: 13.6387 | Z85: =Y85/J85 | AA85: =(J85-R85)/Y85 | AB85: =(J85-S85)/Y85 | AC85: =IF(ABS(AA85)<=ABS(AB85),"9EMA","21EMA") | AD85: 9+21EMA | AE85: 持續在上方 | AH85: ✓ | AI85: 2026-09-21 | AJ85: 8 | AK85: 2 | AL85: 2026-09-14 | AM85: 387 | AN85: 384.77 | AO85: =IF(ISNUMBER(AN85),AM85/AN85-1,"") | AP85: 13 | AQ85: =IF(ISNUMBER(AM85),J85/AM85-1,"") | AR85: 442.49 | AS85: =J85/AR85-1 | AT85: 上傾擴張 | AU85: 0.2315 | AV85: 0.085 | AW85: 0.504 | AX85: 0.4942 | AY85: 5 | AZ85: 447.33 | BA85: 384.77 | BB85: 416.3011 | BC85: 0.8194 | BD85: =IF(M85=N85,0.5,(J85-N85)/(M85-N85)) | BE85: 16.673 | BF85: 11.919 | BG85: =100*(0.4*MIN(1,MAX(0,((U85*100)-(0.0))/((2.5)-(0.0))))+0.3*MIN(1,MAX(0,((V85)-(0.6))/((1.0)-(0.6))))+0.3*MIN(1,MAX(0,((BE85)-(0.0))/((15.0)-(0.0))))) | BH85: =100*(0.4*MIN(1,MAX(0,((MIN(ABS(AA85),ABS(AB85)))-(0.75))/((0.0)-(0.75))))+0.3*MIN(1,MAX(0,((BC85)-(1.2))/((0.6)-(1.2))))+0.3*BD85) | BI85: =100*(0.5*MIN(1,MAX(0,((AK85)-(1.0))/((4.0)-(1.0))))+0.3*MIN(1,MAX(0,((IF(ISNUMBER(AO85),AO85,0)*100)-(0.0))/((8.0)-(0.0))))+0.2*MIN(1,MAX(0,((IF(ISNUMBER(AP85),AP85,0))-(25.0))/((5.0)-(25.0))))) | BJ85: =100*(0.35*MIN(1,MAX(0,((ABS(AU85))-(0.3))/((0.05)-(0.3))))+0.3*MIN(1,MAX(0,((AV85)-(0.0))/((0.3)-(0.0))))+0.25*MIN(1,MAX(0,((AW85)-(0.4))/((0.7)-(0.4))))+0.1*IF(AY85>=2,1,0.5)) | BK85: =0.25*BG85+0.25*BH85+0.2*BI85+0.3*BJ85 | BL85: 全部通過
A86: 1 | B86: 85 | C86: AIP | D86: Arteris Inc. | E86: NASDAQ | F86: 科技 | G86: Semiconductors | H86: 1.162 | I86: 小型 | J86: 24.01 | K86: 23.64 | L86: =J86/K86-1 | M86: 24.27 | N86: 23.41 | O86: 694000 | P86: 688470 | Q86: =O86/P86 | R86: 23.518 | S86: 23.4342 | T86: 23.3326 | U86: =S86/T86-1 | V86: 0.7 | W86: =J86/R86-1 | X86: =J86/S86-1 | Y86: 1.2946 | Z86: =Y86/J86 | AA86: =(J86-R86)/Y86 | AB86: =(J86-S86)/Y86 | AC86: =IF(ABS(AA86)<=ABS(AB86),"9EMA","21EMA") | AD86: 9+21EMA | AE86: 剛黃金交叉 | AF86: ✓ | AH86: ✓ | AI86: 2026-09-30 | AJ86: 1 | AK86: 2 | AL86: 2026-09-28 | AM86: 22.54 | AN86: 20.02 | AO86: =IF(ISNUMBER(AN86),AM86/AN86-1,"") | AP86: 3 | AQ86: =IF(ISNUMBER(AM86),J86/AM86-1,"") | AR86: 24.78 | AS86: =J86/AR86-1 | AT86: 上傾收窄（楔形） | AU86: 0.2328 | AV86: 0.6189 | AW86: 0.5002 | AX86: 0.4785 | AY86: 3 | AZ86: 24.98 | BA86: 20.02 | BB86: 22.501 | BC86: 1.1279 | BD86: =IF(M86=N86,0.5,(J86-N86)/(M86-N86)) | BE86: 20.521 | BF86: 15.767 | BG86: =100*(0.4*MIN(1,MAX(0,((U86*100)-(0.0))/((2.5)-(0.0))))+0.3*MIN(1,MAX(0,((V86)-(0.6))/((1.0)-(0.6))))+0.3*MIN(1,MAX(0,((BE86)-(0.0))/((15.0)-(0.0))))) | BH86: =100*(0.4*MIN(1,MAX(0,((MIN(ABS(AA86),ABS(AB86)))-(0.75))/((0.0)-(0.75))))+0.3*MIN(1,MAX(0,((BC86)-(1.2))/((0.6)-(1.2))))+0.3*BD86) | BI86: =100*(0.5*MIN(1,MAX(0,((AK86)-(1.0))/((4.0)-(1.0))))+0.3*MIN(1,MAX(0,((IF(ISNUMBER(AO86),AO86,0)*100)-(0.0))/((8.0)-(0.0))))+0.2*MIN(1,MAX(0,((IF(ISNUMBER(AP86),AP86,0))-(25.0))/((5.0)-(25.0))))) | BJ86: =100*(0.35*MIN(1,MAX(0,((ABS(AU86))-(0.3))/((0.05)-(0.3))))+0.3*MIN(1,MAX(0,((AV86)-(0.0))/((0.3)-(0.0))))+0.25*MIN(1,MAX(0,((AW86)-(0.4))/((0.7)-(0.4))))+0.1*IF(AY86>=2,1,0.5)) | BK86: =0.25*BG86+0.25*BH86+0.2*BI86+0.3*BJ86 | BL86: 全部通過
A87: 1 | B87: 86 | C87: FSBW | D87: FS Bancorp Inc. | E87: NASDAQ | F87: 金融 | G87: Banks | H87: 0.34 | I87: 小型 | J87: 44.01 | K87: 43.29 | L87: =J87/K87-1 | M87: 44.28 | N87: 43.08 | O87: 49400 | P87: 30190 | Q87: =O87/P87 | R87: 43.8838 | S87: 43.7352 | T87: 43.6174 | U87: =S87/T87-1 | V87: 0.7 | W87: =J87/R87-1 | X87: =J87/S87-1 | Y87: 0.9037 | Z87: =Y87/J87 | AA87: =(J87-R87)/Y87 | AB87: =(J87-S87)/Y87 | AC87: =IF(ABS(AA87)<=ABS(AB87),"9EMA","21EMA") | AD87: 9+21EMA | AE87: 持續在上方 | AH87: ✓ | AI87: 2026-09-04 | AJ87: 18 | AK87: 3 | AL87: 2026-09-21 | AM87: 43.23 | AN87: 42.06 | AO87: =IF(ISNUMBER(AN87),AM87/AN87-1,"") | AP87: 8 | AQ87: =IF(ISNUMBER(AM87),J87/AM87-1,"") | AR87: 44.48 | AS87: =J87/AR87-1 | AT87: 上傾收窄（楔形） | AU87: 0.1192 | AV87: 0.1662 | AW87: 0.5413 | AX87: 0.6274 | AY87: 10 | AZ87: 45.03 | BA87: 42.06 | BB87: 43.6676 | BC87: 1.3344 | BD87: =IF(M87=N87,0.5,(J87-N87)/(M87-N87)) | BE87: 8.478 | BF87: 3.724 | BG87: =100*(0.4*MIN(1,MAX(0,((U87*100)-(0.0))/((2.5)-(0.0))))+0.3*MIN(1,MAX(0,((V87)-(0.6))/((1.0)-(0.6))))+0.3*MIN(1,MAX(0,((BE87)-(0.0))/((15.0)-(0.0))))) | BH87: =100*(0.4*MIN(1,MAX(0,((MIN(ABS(AA87),ABS(AB87)))-(0.75))/((0.0)-(0.75))))+0.3*MIN(1,MAX(0,((BC87)-(1.2))/((0.6)-(1.2))))+0.3*BD87) | BI87: =100*(0.5*MIN(1,MAX(0,((AK87)-(1.0))/((4.0)-(1.0))))+0.3*MIN(1,MAX(0,((IF(ISNUMBER(AO87),AO87,0)*100)-(0.0))/((8.0)-(0.0))))+0.2*MIN(1,MAX(0,((IF(ISNUMBER(AP87),AP87,0))-(25.0))/((5.0)-(25.0))))) | BJ87: =100*(0.35*MIN(1,MAX(0,((ABS(AU87))-(0.3))/((0.05)-(0.3))))+0.3*MIN(1,MAX(0,((AV87)-(0.0))/((0.3)-(0.0))))+0.25*MIN(1,MAX(0,((AW87)-(0.4))/((0.7)-(0.4))))+0.1*IF(AY87>=2,1,0.5)) | BK87: =0.25*BG87+0.25*BH87+0.2*BI87+0.3*BJ87 | BL87: 全部通過
A88: 1 | B88: 87 | C88: AMG | D88: Affiliated Managers Group Inc. | E88: NYSE | F88: 金融 | G88: Investment Managers | H88: 9.455 | I88: 中型 | J88: 371.95 | K88: 365.61 | L88: =J88/K88-1 | M88: 375 | N88: 364.02 | O88: 176200 | P88: 296825 | Q88: =O88/P88 | R88: 366.938 | S88: 363.8325 | T88: 360.1289 | U88: =S88/T88-1 | V88: 0.9 | W88: =J88/R88-1 | X88: =J88/S88-1 | Y88: 10.9784 | Z88: =Y88/J88 | AA88: =(J88-R88)/Y88 | AB88: =(J88-S88)/Y88 | AC88: =IF(ABS(AA88)<=ABS(AB88),"9EMA","21EMA") | AD88: 9+21EMA | AE88: 剛黃金交叉 | AF88: ✓ | AH88: ✓ | AI88: 2026-09-24 | AJ88: 5 | AK88: 2 | AL88: 2026-09-28 | AM88: 356.18 | AN88: 339.87 | AO88: =IF(ISNUMBER(AN88),AM88/AN88-1,"") | AP88: 3 | AQ88: =IF(ISNUMBER(AM88),J88/AM88-1,"") | AR88: 373.69 | AS88: =J88/AR88-1 | AT88: 上升三角（平頂） | AU88: 0.0327 | AV88: 0.0133 | AW88: 0.5623 | AX88: 0.6183 | AY88: 7 | AZ88: 379.06 | BA88: 339.87 | BB88: 361.9073 | BC88: 1.3018 | BD88: =IF(M88=N88,0.5,(J88-N88)/(M88-N88)) | BE88: 7.859 | BF88: 3.105 | BG88: =100*(0.4*MIN(1,MAX(0,((U88*100)-(0.0))/((2.5)-(0.0))))+0.3*MIN(1,MAX(0,((V88)-(0.6))/((1.0)-(0.6))))+0.3*MIN(1,MAX(0,((BE88)-(0.0))/((15.0)-(0.0))))) | BH88: =100*(0.4*MIN(1,MAX(0,((MIN(ABS(AA88),ABS(AB88)))-(0.75))/((0.0)-(0.75))))+0.3*MIN(1,MAX(0,((BC88)-(1.2))/((0.6)-(1.2))))+0.3*BD88) | BI88: =100*(0.5*MIN(1,MAX(0,((AK88)-(1.0))/((4.0)-(1.0))))+0.3*MIN(1,MAX(0,((IF(ISNUMBER(AO88),AO88,0)*100)-(0.0))/((8.0)-(0.0))))+0.2*MIN(1,MAX(0,((IF(ISNUMBER(AP88),AP88,0))-(25.0))/((5.0)-(25.0))))) | BJ88: =100*(0.35*MIN(1,MAX(0,((ABS(AU88))-(0.3))/((0.05)-(0.3))))+0.3*MIN(1,MAX(0,((AV88)-(0.0))/((0.3)-(0.0))))+0.25*MIN(1,MAX(0,((AW88)-(0.4))/((0.7)-(0.4))))+0.1*IF(AY88>=2,1,0.5)) | BK88: =0.25*BG88+0.25*BH88+0.2*BI88+0.3*BJ88 | BL88: 全部通過
A89: 1 | B89: 88 | C89: FNRN | D89: First Northern Community Bancorp Common stock | E89: NASDAQ | F89: 金融 | G89: Savings Institutions | H89: 0.283 | I89: 小型 | J89: 17.64 | K89: 17.28 | L89: =J89/K89-1 | M89: 17.77 | N89: 16.98 | O89: 204600 | P89: 105270 | Q89: =O89/P89 | R89: 17.3154 | S89: 17.2877 | T89: 17.2526 | U89: =S89/T89-1 | V89: 0.4 | W89: =J89/R89-1 | X89: =J89/S89-1 | Y89: 0.3759 | Z89: =Y89/J89 | AA89: =(J89-R89)/Y89 | AB89: =(J89-S89)/Y89 | AC89: =IF(ABS(AA89)<=ABS(AB89),"9EMA","21EMA") | AD89: 9+21EMA | AE89: 剛黃金交叉 | AF89: ✓ | AH89: ✓ | AI89: 2026-10-01 | AJ89: 0 | AK89: 4 | AL89: 2026-09-24 | AM89: 16.95 | AN89: 16.86 | AO89: =IF(ISNUMBER(AN89),AM89/AN89-1,"") | AP89: 5 | AQ89: =IF(ISNUMBER(AM89),J89/AM89-1,"") | AR89: 17.64 | AS89: =J89/AR89-1 | AT89: 上升三角（平頂） | AU89: -0.0978 | AV89: 0.1523 | AW89: 0.5517 | AX89: 0.5783 | AY89: 4 | AZ89: 17.77 | BA89: 16.53 | BB89: 17.2141 | BC89: 0.8053 | BD89: =IF(M89=N89,0.5,(J89-N89)/(M89-N89)) | BE89: 10.827 | BF89: 6.073 | BG89: =100*(0.4*MIN(1,MAX(0,((U89*100)-(0.0))/((2.5)-(0.0))))+0.3*MIN(1,MAX(0,((V89)-(0.6))/((1.0)-(0.6))))+0.3*MIN(1,MAX(0,((BE89)-(0.0))/((15.0)-(0.0))))) | BH89: =100*(0.4*MIN(1,MAX(0,((MIN(ABS(AA89),ABS(AB89)))-(0.75))/((0.0)-(0.75))))+0.3*MIN(1,MAX(0,((BC89)-(1.2))/((0.6)-(1.2))))+0.3*BD89) | BI89: =100*(0.5*MIN(1,MAX(0,((AK89)-(1.0))/((4.0)-(1.0))))+0.3*MIN(1,MAX(0,((IF(ISNUMBER(AO89),AO89,0)*100)-(0.0))/((8.0)-(0.0))))+0.2*MIN(1,MAX(0,((IF(ISNUMBER(AP89),AP89,0))-(25.0))/((5.0)-(25.0))))) | BJ89: =100*(0.35*MIN(1,MAX(0,((ABS(AU89))-(0.3))/((0.05)-(0.3))))+0.3*MIN(1,MAX(0,((AV89)-(0.0))/((0.3)-(0.0))))+0.25*MIN(1,MAX(0,((AW89)-(0.4))/((0.7)-(0.4))))+0.1*IF(AY89>=2,1,0.5)) | BK89: =0.25*BG89+0.25*BH89+0.2*BI89+0.3*BJ89 | BL89: 全部通過
A90: 1 | B90: 89 | C90: WAY | D90: Waystar Holding Corp. | E90: NASDAQ | F90: 科技 | G90: EDP Services | H90: 4.859 | I90: 中型 | J90: 25.35 | K90: 25.34 | L90: =J90/K90-1 | M90: 26.55 | N90: 24.98 | O90: 1930200 | P90: 2026585 | Q90: =O90/P90 | R90: 25.2692 | S90: 25.162 | T90: 25.1045 | U90: =S90/T90-1 | V90: 0.6 | W90: =J90/R90-1 | X90: =J90/S90-1 | Y90: 1.1148 | Z90: =Y90/J90 | AA90: =(J90-R90)/Y90 | AB90: =(J90-S90)/Y90 | AC90: =IF(ABS(AA90)<=ABS(AB90),"9EMA","21EMA") | AD90: 9+21EMA | AE90: 持續在上方 | AH90: ✓ | AI90: 2026-09-15 | AJ90: 12 | AK90: 2 | AL90: 2026-09-25 | AM90: 24.325 | AN90: 22.955 | AO90: =IF(ISNUMBER(AN90),AM90/AN90-1,"") | AP90: 4 | AQ90: =IF(ISNUMBER(AM90),J90/AM90-1,"") | AR90: 26.67 | AS90: =J90/AR90-1 | AT90: 上傾收窄（楔形） | AU90: 0.147 | AV90: 0.4913 | AW90: 0.5954 | AX90: 0.6842 | AY90: 4 | AZ90: 27.28 | BA90: 22.955 | BB90: 25.5299 | BC90: 0.9794 | BD90: =IF(M90=N90,0.5,(J90-N90)/(M90-N90)) | BE90: 3.163 | BF90: -1.592 | BG90: =100*(0.4*MIN(1,MAX(0,((U90*100)-(0.0))/((2.5)-(0.0))))+0.3*MIN(1,MAX(0,((V90)-(0.6))/((1.0)-(0.6))))+0.3*MIN(1,MAX(0,((BE90)-(0.0))/((15.0)-(0.0))))) | BH90: =100*(0.4*MIN(1,MAX(0,((MIN(ABS(AA90),ABS(AB90)))-(0.75))/((0.0)-(0.75))))+0.3*MIN(1,MAX(0,((BC90)-(1.2))/((0.6)-(1.2))))+0.3*BD90) | BI90: =100*(0.5*MIN(1,MAX(0,((AK90)-(1.0))/((4.0)-(1.0))))+0.3*MIN(1,MAX(0,((IF(ISNUMBER(AO90),AO90,0)*100)-(0.0))/((8.0)-(0.0))))+0.2*MIN(1,MAX(0,((IF(ISNUMBER(AP90),AP90,0))-(25.0))/((5.0)-(25.0))))) | BJ90: =100*(0.35*MIN(1,MAX(0,((ABS(AU90))-(0.3))/((0.05)-(0.3))))+0.3*MIN(1,MAX(0,((AV90)-(0.0))/((0.3)-(0.0))))+0.25*MIN(1,MAX(0,((AW90)-(0.4))/((0.7)-(0.4))))+0.1*IF(AY90>=2,1,0.5)) | BK90: =0.25*BG90+0.25*BH90+0.2*BI90+0.3*BJ90 | BL90: 全部通過
A91: 1 | B91: 90 | C91: TXNM | D91: TXNM Energy Inc. | E91: NYSE | F91: 公用事業 | G91: Electric Utilities: Central | H91: 6.423 | I91: 中型 | J91: 58.53 | K91: 58.32 | L91: =J91/K91-1 | M91: 58.6 | N91: 58.1 | O91: 1765200 | P91: 1810575 | Q91: =O91/P91 | R91: 58.3904 | S91: 58.2223 | T91: 58.0957 | U91: =S91/T91-1 | V91: 1 | W91: =J91/R91-1 | X91: =J91/S91-1 | Y91: 0.3776 | Z91: =Y91/J91 | AA91: =(J91-R91)/Y91 | AB91: =(J91-S91)/Y91 | AC91: =IF(ABS(AA91)<=ABS(AB91),"9EMA","21EMA") | AD91: 9+21EMA | AE91: 持續在上方 | AH91: ✓ | AI91: 2026-09-01 | AJ91: 21 | AK91: 3 | AL91: 2026-09-25 | AM91: 58.09 | AN91: 57.61 | AO91: =IF(ISNUMBER(AN91),AM91/AN91-1,"") | AP91: 4 | AQ91: =IF(ISNUMBER(AM91),J91/AM91-1,"") | AR91: 58.63 | AS91: =J91/AR91-1 | AT91: 上升通道 | AU91: 0.1082 | AV91: 0.0911 | AW91: 0.5274 | AX91: 0.6264 | AY91: 18 | AZ91: 58.93 | BA91: 57.41 | BB91: 58.2116 | BC91: 1.4682 | BD91: =IF(M91=N91,0.5,(J91-N91)/(M91-N91)) | BE91: 5.93 | BF91: 1.175 | BG91: =100*(0.4*MIN(1,MAX(0,((U91*100)-(0.0))/((2.5)-(0.0))))+0.3*MIN(1,MAX(0,((V91)-(0.6))/((1.0)-(0.6))))+0.3*MIN(1,MAX(0,((BE91)-(0.0))/((15.0)-(0.0))))) | BH91: =100*(0.4*MIN(1,MAX(0,((MIN(ABS(AA91),ABS(AB91)))-(0.75))/((0.0)-(0.75))))+0.3*MIN(1,MAX(0,((BC91)-(1.2))/((0.6)-(1.2))))+0.3*BD91) | BI91: =100*(0.5*MIN(1,MAX(0,((AK91)-(1.0))/((4.0)-(1.0))))+0.3*MIN(1,MAX(0,((IF(ISNUMBER(AO91),AO91,0)*100)-(0.0))/((8.0)-(0.0))))+0.2*MIN(1,MAX(0,((IF(ISNUMBER(AP91),AP91,0))-(25.0))/((5.0)-(25.0))))) | BJ91: =100*(0.35*MIN(1,MAX(0,((ABS(AU91))-(0.3))/((0.05)-(0.3))))+0.3*MIN(1,MAX(0,((AV91)-(0.0))/((0.3)-(0.0))))+0.25*MIN(1,MAX(0,((AW91)-(0.4))/((0.7)-(0.4))))+0.1*IF(AY91>=2,1,0.5)) | BK91: =0.25*BG91+0.25*BH91+0.2*BI91+0.3*BJ91 | BL91: 全部通過
A92: 1 | B92: 91 | C92: VSTS | D92: Vestis Corporation | E92: NYSE | F92: 非必需消費 | G92: Consumer Specialties | H92: 1.766 | I92: 小型 | J92: 13.78 | K92: 13.36 | L92: =J92/K92-1 | M92: 13.91 | N92: 13.091 | O92: 1521900 | P92: 1632025 | Q92: =O92/P92 | R92: 13.6284 | S92: 13.5373 | T92: 13.5331 | U92: =S92/T92-1 | V92: 0.7 | W92: =J92/R92-1 | X92: =J92/S92-1 | Y92: 0.5463 | Z92: =Y92/J92 | AA92: =(J92-R92)/Y92 | AB92: =(J92-S92)/Y92 | AC92: =IF(ABS(AA92)<=ABS(AB92),"9EMA","21EMA") | AD92: 9+21EMA | AE92: 持續在上方 | AH92: ✓ | AI92: 2026-09-16 | AJ92: 11 | AK92: 3 | AL92: 2026-09-28 | AM92: 13.01 | AN92: 12.765 | AO92: =IF(ISNUMBER(AN92),AM92/AN92-1,"") | AP92: 3 | AQ92: =IF(ISNUMBER(AM92),J92/AM92-1,"") | AR92: 14.43 | AS92: =J92/AR92-1 | AT92: 上傾擴張 | AU92: 0.6234 | AV92: 0.379 | AW92: 0.51 | AX92: 0.5482 | AY92: 3 | AZ92: 14.66 | BA92: 12.07 | BB92: 13.3909 | BC92: 1.2097 | BD92: =IF(M92=N92,0.5,(J92-N92)/(M92-N92)) | BE92: 18.357 | BF92: 13.603 | BG92: =100*(0.4*MIN(1,MAX(0,((U92*100)-(0.0))/((2.5)-(0.0))))+0.3*MIN(1,MAX(0,((V92)-(0.6))/((1.0)-(0.6))))+0.3*MIN(1,MAX(0,((BE92)-(0.0))/((15.0)-(0.0))))) | BH92: =100*(0.4*MIN(1,MAX(0,((MIN(ABS(AA92),ABS(AB92)))-(0.75))/((0.0)-(0.75))))+0.3*MIN(1,MAX(0,((BC92)-(1.2))/((0.6)-(1.2))))+0.3*BD92) | BI92: =100*(0.5*MIN(1,MAX(0,((AK92)-(1.0))/((4.0)-(1.0))))+0.3*MIN(1,MAX(0,((IF(ISNUMBER(AO92),AO92,0)*100)-(0.0))/((8.0)-(0.0))))+0.2*MIN(1,MAX(0,((IF(ISNUMBER(AP92),AP92,0))-(25.0))/((5.0)-(25.0))))) | BJ92: =100*(0.35*MIN(1,MAX(0,((ABS(AU92))-(0.3))/((0.05)-(0.3))))+0.3*MIN(1,MAX(0,((AV92)-(0.0))/((0.3)-(0.0))))+0.25*MIN(1,MAX(0,((AW92)-(0.4))/((0.7)-(0.4))))+0.1*IF(AY92>=2,1,0.5)) | BK92: =0.25*BG92+0.25*BH92+0.2*BI92+0.3*BJ92 | BL92: 全部通過
A93: 1 | B93: 92 | C93: MKTX | D93: MarketAxess Holdings Inc. | E93: NASDAQ | F93: 金融 | G93: Investment Bankers/Brokers/Service | H93: 5.769 | I93: 中型 | J93: 164.22 | K93: 163.92 | L93: =J93/K93-1 | M93: 164.23 | N93: 164 | O93: 548800 | P93: 912965 | Q93: =O93/P93 | R93: 163.858 | S93: 162.8997 | T93: 162.1989 | U93: =S93/T93-1 | V93: 1 | W93: =J93/R93-1 | X93: =J93/S93-1 | Y93: 0.5906 | Z93: =Y93/J93 | AA93: =(J93-R93)/Y93 | AB93: =(J93-S93)/Y93 | AC93: =IF(ABS(AA93)<=ABS(AB93),"9EMA","21EMA") | AD93: 9EMA | AE93: 持續在上方 | AH93: ✓ | AI93: 2026-07-28 | AJ93: 46 | AK93: 3 | AL93: 2026-09-11 | AM93: 162.97 | AN93: 161.74 | AO93: =IF(ISNUMBER(AN93),AM93/AN93-1,"") | AP93: 14 | AQ93: =IF(ISNUMBER(AM93),J93/AM93-1,"") | AR93: 164.22 | AS93: =J93/AR93-1 | AT93: 上升三角（平頂） | AU93: 0.0261 | AV93: 0.0347 | AW93: 0.5056 | AX93: 0.5085 | AY93: 25 | AZ93: 164.23 | BA93: 162.46 | BB93: 163.355 | BC93: 1.1009 | BD93: =IF(M93=N93,0.5,(J93-N93)/(M93-N93)) | BE93: 5.719 | BF93: 0.965 | BG93: =100*(0.4*MIN(1,MAX(0,((U93*100)-(0.0))/((2.5)-(0.0))))+0.3*MIN(1,MAX(0,((V93)-(0.6))/((1.0)-(0.6))))+0.3*MIN(1,MAX(0,((BE93)-(0.0))/((15.0)-(0.0))))) | BH93: =100*(0.4*MIN(1,MAX(0,((MIN(ABS(AA93),ABS(AB93)))-(0.75))/((0.0)-(0.75))))+0.3*MIN(1,MAX(0,((BC93)-(1.2))/((0.6)-(1.2))))+0.3*BD93) | BI93: =100*(0.5*MIN(1,MAX(0,((AK93)-(1.0))/((4.0)-(1.0))))+0.3*MIN(1,MAX(0,((IF(ISNUMBER(AO93),AO93,0)*100)-(0.0))/((8.0)-(0.0))))+0.2*MIN(1,MAX(0,((IF(ISNUMBER(AP93),AP93,0))-(25.0))/((5.0)-(25.0))))) | BJ93: =100*(0.35*MIN(1,MAX(0,((ABS(AU93))-(0.3))/((0.05)-(0.3))))+0.3*MIN(1,MAX(0,((AV93)-(0.0))/((0.3)-(0.0))))+0.25*MIN(1,MAX(0,((AW93)-(0.4))/((0.7)-(0.4))))+0.1*IF(AY93>=2,1,0.5)) | BK93: =0.25*BG93+0.25*BH93+0.2*BI93+0.3*BJ93 | BL93: 全部通過
A94: 1 | B94: 93 | C94: PSX | D94: Phillips 66 | E94: NYSE | F94: 能源 | G94: Integrated oil Companies | H94: 101.874 | I94: 大型 | J94: 264.23 | K94: 255.31 | L94: =J94/K94-1 | M94: 264.43 | N94: 252.54 | O94: 2529500 | P94: 3343170 | Q94: =O94/P94 | R94: 258.1223 | S94: 255.5702 | T94: 254.9429 | U94: =S94/T94-1 | V94: 0.8 | W94: =J94/R94-1 | X94: =J94/S94-1 | Y94: 8.5352 | Z94: =Y94/J94 | AA94: =(J94-R94)/Y94 | AB94: =(J94-S94)/Y94 | AC94: =IF(ABS(AA94)<=ABS(AB94),"9EMA","21EMA") | AD94: 9+21EMA | AE94: 持續在上方 | AH94: ✓ | AI94: 2026-07-07 | AJ94: 61 | AK94: 3 | AL94: 2026-09-14 | AM94: 253.41 | AN94: 233.55 | AO94: =IF(ISNUMBER(AN94),AM94/AN94-1,"") | AP94: 13 | AQ94: =IF(ISNUMBER(AM94),J94/AM94-1,"") | AR94: 274.21 | AS94: =J94/AR94-1 | AT94: 上傾擴張 | AU94: 0.1964 | AV94: 0.1489 | AW94: 0.5433 | AX94: 0.5537 | AY94: 3 | AZ94: 277.12 | BA94: 237.13 | BB94: 258.8568 | BC94: 1.6799 | BD94: =IF(M94=N94,0.5,(J94-N94)/(M94-N94)) | BE94: 9.599 | BF94: 4.845 | BG94: =100*(0.4*MIN(1,MAX(0,((U94*100)-(0.0))/((2.5)-(0.0))))+0.3*MIN(1,MAX(0,((V94)-(0.6))/((1.0)-(0.6))))+0.3*MIN(1,MAX(0,((BE94)-(0.0))/((15.0)-(0.0))))) | BH94: =100*(0.4*MIN(1,MAX(0,((MIN(ABS(AA94),ABS(AB94)))-(0.75))/((0.0)-(0.75))))+0.3*MIN(1,MAX(0,((BC94)-(1.2))/((0.6)-(1.2))))+0.3*BD94) | BI94: =100*(0.5*MIN(1,MAX(0,((AK94)-(1.0))/((4.0)-(1.0))))+0.3*MIN(1,MAX(0,((IF(ISNUMBER(AO94),AO94,0)*100)-(0.0))/((8.0)-(0.0))))+0.2*MIN(1,MAX(0,((IF(ISNUMBER(AP94),AP94,0))-(25.0))/((5.0)-(25.0))))) | BJ94: =100*(0.35*MIN(1,MAX(0,((ABS(AU94))-(0.3))/((0.05)-(0.3))))+0.3*MIN(1,MAX(0,((AV94)-(0.0))/((0.3)-(0.0))))+0.25*MIN(1,MAX(0,((AW94)-(0.4))/((0.7)-(0.4))))+0.1*IF(AY94>=2,1,0.5)) | BK94: =0.25*BG94+0.25*BH94+0.2*BI94+0.3*BJ94 | BL94: 全部通過
A95: 1 | B95: 94 | C95: ATKR | D95: Atkore Inc. | E95: NYSE | F95: 其他 | G95: Industrial Machinery/Components | H95: 3.2 | I95: 中型 | J95: 94.77 | K95: 94.75 | L95: =J95/K95-1 | M95: 94.84 | N95: 94.75 | O95: 596600 | P95: 782225 | Q95: =O95/P95 | R95: 94.6057 | S95: 94.0418 | T95: 93.6434 | U95: =S95/T95-1 | V95: 1 | W95: =J95/R95-1 | X95: =J95/S95-1 | Y95: 0.3888 | Z95: =Y95/J95 | AA95: =(J95-R95)/Y95 | AB95: =(J95-S95)/Y95 | AC95: =IF(ABS(AA95)<=ABS(AB95),"9EMA","21EMA") | AD95: 9EMA | AE95: 持續在上方 | AH95: ✓ | AI95: 2026-08-03 | AJ95: 42 | AK95: 4 | AL95: 2026-08-28 | AM95: 93.5 | AN95: 93.315 | AO95: =IF(ISNUMBER(AN95),AM95/AN95-1,"") | AP95: 23 | AQ95: =IF(ISNUMBER(AM95),J95/AM95-1,"") | AR95: 94.77 | AS95: =J95/AR95-1 | AT95: 上升三角（平頂） | AU95: 0.0521 | AV95: 0.0589 | AW95: 0.5371 | AX95: 0.549 | AY95: 25 | AZ95: 94.84 | BA95: 93.5 | BB95: 94.2197 | BC95: 1.9764 | BD95: =IF(M95=N95,0.5,(J95-N95)/(M95-N95)) | BE95: 5.972 | BF95: 1.218 | BG95: =100*(0.4*MIN(1,MAX(0,((U95*100)-(0.0))/((2.5)-(0.0))))+0.3*MIN(1,MAX(0,((V95)-(0.6))/((1.0)-(0.6))))+0.3*MIN(1,MAX(0,((BE95)-(0.0))/((15.0)-(0.0))))) | BH95: =100*(0.4*MIN(1,MAX(0,((MIN(ABS(AA95),ABS(AB95)))-(0.75))/((0.0)-(0.75))))+0.3*MIN(1,MAX(0,((BC95)-(1.2))/((0.6)-(1.2))))+0.3*BD95) | BI95: =100*(0.5*MIN(1,MAX(0,((AK95)-(1.0))/((4.0)-(1.0))))+0.3*MIN(1,MAX(0,((IF(ISNUMBER(AO95),AO95,0)*100)-(0.0))/((8.0)-(0.0))))+0.2*MIN(1,MAX(0,((IF(ISNUMBER(AP95),AP95,0))-(25.0))/((5.0)-(25.0))))) | BJ95: =100*(0.35*MIN(1,MAX(0,((ABS(AU95))-(0.3))/((0.05)-(0.3))))+0.3*MIN(1,MAX(0,((AV95)-(0.0))/((0.3)-(0.0))))+0.25*MIN(1,MAX(0,((AW95)-(0.4))/((0.7)-(0.4))))+0.1*IF(AY95>=2,1,0.5)) | BK95: =0.25*BG95+0.25*BH95+0.2*BI95+0.3*BJ95 | BL95: 全部通過
A96: 1 | B96: 95 | C96: COLM | D96: Columbia Sportswear Company | E96: NASDAQ | F96: 非必需消費 | G96: Apparel | H96: 2.939 | I96: 中型 | J96: 57.69 | K96: 57.41 | L96: =J96/K96-1 | M96: 58.07 | N96: 57.03 | O96: 1006100 | P96: 691920 | Q96: =O96/P96 | R96: 57.6394 | S96: 57.613 | T96: 57.4237 | U96: =S96/T96-1 | V96: 0.5 | W96: =J96/R96-1 | X96: =J96/S96-1 | Y96: 1.5485 | Z96: =Y96/J96 | AA96: =(J96-R96)/Y96 | AB96: =(J96-S96)/Y96 | AC96: =IF(ABS(AA96)<=ABS(AB96),"9EMA","21EMA") | AD96: 9+21EMA | AE96: 剛黃金交叉 | AF96: ✓ | AH96: ✓ | AI96: 2026-09-29 | AJ96: 2 | AK96: 2 | AL96: 2026-09-21 | AM96: 55.67 | AN96: 55.01 | AO96: =IF(ISNUMBER(AN96),AM96/AN96-1,"") | AP96: 8 | AQ96: =IF(ISNUMBER(AM96),J96/AM96-1,"") | AR96: 58.69 | AS96: =J96/AR96-1 | AT96: 上升三角（平頂） | AU96: 0.0939 | AV96: 0.1634 | AW96: 0.5576 | AX96: 0.453 | AY96: 7 | AZ96: 59.03 | BA96: 55.01 | BB96: 57.2514 | BC96: 1.2066 | BD96: =IF(M96=N96,0.5,(J96-N96)/(M96-N96)) | BE96: 6.303 | BF96: 1.549 | BG96: =100*(0.4*MIN(1,MAX(0,((U96*100)-(0.0))/((2.5)-(0.0))))+0.3*MIN(1,MAX(0,((V96)-(0.6))/((1.0)-(0.6))))+0.3*MIN(1,MAX(0,((BE96)-(0.0))/((15.0)-(0.0))))) | BH96: =100*(0.4*MIN(1,MAX(0,((MIN(ABS(AA96),ABS(AB96)))-(0.75))/((0.0)-(0.75))))+0.3*MIN(1,MAX(0,((BC96)-(1.2))/((0.6)-(1.2))))+0.3*BD96) | BI96: =100*(0.5*MIN(1,MAX(0,((AK96)-(1.0))/((4.0)-(1.0))))+0.3*MIN(1,MAX(0,((IF(ISNUMBER(AO96),AO96,0)*100)-(0.0))/((8.0)-(0.0))))+0.2*MIN(1,MAX(0,((IF(ISNUMBER(AP96),AP96,0))-(25.0))/((5.0)-(25.0))))) | BJ96: =100*(0.35*MIN(1,MAX(0,((ABS(AU96))-(0.3))/((0.05)-(0.3))))+0.3*MIN(1,MAX(0,((AV96)-(0.0))/((0.3)-(0.0))))+0.25*MIN(1,MAX(0,((AW96)-(0.4))/((0.7)-(0.4))))+0.1*IF(AY96>=2,1,0.5)) | BK96: =0.25*BG96+0.25*BH96+0.2*BI96+0.3*BJ96 | BL96: 全部通過
A97: 1 | B97: 96 | C97: BIIB | D97: Biogen Inc. | E97: NASDAQ | F97: 醫療保健 | G97: Biotechnology: Biological Products (No Diagnostic Substances) | H97: 33.375 | I97: 大型 | J97: 222.82 | K97: 225.88 | L97: =J97/K97-1 | M97: 228.31 | N97: 222.5 | O97: 1755300 | P97: 1056660 | Q97: =O97/P97 | R97: 224.4891 | S97: 221.5939 | T97: 218.8001 | U97: =S97/T97-1 | V97: 0.9 | W97: =J97/R97-1 | X97: =J97/S97-1 | Y97: 5.5593 | Z97: =Y97/J97 | AA97: =(J97-R97)/Y97 | AB97: =(J97-S97)/Y97 | AC97: =IF(ABS(AA97)<=ABS(AB97),"9EMA","21EMA") | AD97: 9+21EMA | AE97: 持續在上方 | AG97: ✓ | AI97: 2026-07-29 | AJ97: 45 | AK97: 2 | AL97: 2026-09-21 | AM97: 214.59 | AN97: 208.93 | AO97: =IF(ISNUMBER(AN97),AM97/AN97-1,"") | AP97: 8 | AQ97: =IF(ISNUMBER(AM97),J97/AM97-1,"") | AR97: 228.69 | AS97: =J97/AR97-1 | AT97: 上傾擴張 | AU97: 0.1559 | AV97: 0.0324 | AW97: 0.5623 | AX97: 0.5748 | AY97: 7 | AZ97: 230.49 | BA97: 208.93 | BB97: 221.0532 | BC97: 1.3973 | BD97: =IF(M97=N97,0.5,(J97-N97)/(M97-N97)) | BE97: 7.892 | BF97: 3.138 | BG97: =100*(0.4*MIN(1,MAX(0,((U97*100)-(0.0))/((2.5)-(0.0))))+0.3*MIN(1,MAX(0,((V97)-(0.6))/((1.0)-(0.6))))+0.3*MIN(1,MAX(0,((BE97)-(0.0))/((15.0)-(0.0))))) | BH97: =100*(0.4*MIN(1,MAX(0,((MIN(ABS(AA97),ABS(AB97)))-(0.75))/((0.0)-(0.75))))+0.3*MIN(1,MAX(0,((BC97)-(1.2))/((0.6)-(1.2))))+0.3*BD97) | BI97: =100*(0.5*MIN(1,MAX(0,((AK97)-(1.0))/((4.0)-(1.0))))+0.3*MIN(1,MAX(0,((IF(ISNUMBER(AO97),AO97,0)*100)-(0.0))/((8.0)-(0.0))))+0.2*MIN(1,MAX(0,((IF(ISNUMBER(AP97),AP97,0))-(25.0))/((5.0)-(25.0))))) | BJ97: =100*(0.35*MIN(1,MAX(0,((ABS(AU97))-(0.3))/((0.05)-(0.3))))+0.3*MIN(1,MAX(0,((AV97)-(0.0))/((0.3)-(0.0))))+0.25*MIN(1,MAX(0,((AW97)-(0.4))/((0.7)-(0.4))))+0.1*IF(AY97>=2,1,0.5)) | BK97: =0.25*BG97+0.25*BH97+0.2*BI97+0.3*BJ97 | BL97: 全部通過
A98: 1 | B98: 97 | C98: SAFT | D98: Safety Insurance Group Inc. | E98: NASDAQ | F98: 金融 | G98: Property-Casualty Insurers | H98: 1.521 | I98: 小型 | J98: 103.81 | K98: 103.58 | L98: =J98/K98-1 | M98: 103.9 | N98: 103.52 | O98: 162800 | P98: 127330 | Q98: =O98/P98 | R98: 103.6029 | S98: 103.2596 | T98: 103.0323 | U98: =S98/T98-1 | V98: 1 | W98: =J98/R98-1 | X98: =J98/S98-1 | Y98: 0.3281 | Z98: =Y98/J98 | AA98: =(J98-R98)/Y98 | AB98: =(J98-S98)/Y98 | AC98: =IF(ABS(AA98)<=ABS(AB98),"9EMA","21EMA") | AD98: 9+21EMA | AE98: 持續在上方 | AH98: ✓ | AI98: 2026-07-24 | AJ98: 48 | AK98: 2 | AL98: 2026-09-24 | AM98: 103.43 | AN98: 103.05 | AO98: =IF(ISNUMBER(AN98),AM98/AN98-1,"") | AP98: 5 | AQ98: =IF(ISNUMBER(AM98),J98/AM98-1,"") | AR98: 103.81 | AS98: =J98/AR98-1 | AT98: 上升三角（平頂） | AU98: 0.0048 | AV98: 0.0229 | AW98: 0.5098 | AX98: 0.5399 | AY98: 25 | AZ98: 103.9 | BA98: 103.05 | BB98: 103.4833 | BC98: 1.376 | BD98: =IF(M98=N98,0.5,(J98-N98)/(M98-N98)) | BE98: 5.384 | BF98: 0.63 | BG98: =100*(0.4*MIN(1,MAX(0,((U98*100)-(0.0))/((2.5)-(0.0))))+0.3*MIN(1,MAX(0,((V98)-(0.6))/((1.0)-(0.6))))+0.3*MIN(1,MAX(0,((BE98)-(0.0))/((15.0)-(0.0))))) | BH98: =100*(0.4*MIN(1,MAX(0,((MIN(ABS(AA98),ABS(AB98)))-(0.75))/((0.0)-(0.75))))+0.3*MIN(1,MAX(0,((BC98)-(1.2))/((0.6)-(1.2))))+0.3*BD98) | BI98: =100*(0.5*MIN(1,MAX(0,((AK98)-(1.0))/((4.0)-(1.0))))+0.3*MIN(1,MAX(0,((IF(ISNUMBER(AO98),AO98,0)*100)-(0.0))/((8.0)-(0.0))))+0.2*MIN(1,MAX(0,((IF(ISNUMBER(AP98),AP98,0))-(25.0))/((5.0)-(25.0))))) | BJ98: =100*(0.35*MIN(1,MAX(0,((ABS(AU98))-(0.3))/((0.05)-(0.3))))+0.3*MIN(1,MAX(0,((AV98)-(0.0))/((0.3)-(0.0))))+0.25*MIN(1,MAX(0,((AW98)-(0.4))/((0.7)-(0.4))))+0.1*IF(AY98>=2,1,0.5)) | BK98: =0.25*BG98+0.25*BH98+0.2*BI98+0.3*BJ98 | BL98: 全部通過
A99: 1 | B99: 98 | C99: TRNS | D99: Transcat Inc. | E99: NASDAQ | F99: 工業 | G99: Electrical Products | H99: 0.83 | I99: 小型 | J99: 90.18 | K99: 88.42 | L99: =J99/K99-1 | M99: 92.38 | N99: 87.69 | O99: 210600 | P99: 120960 | Q99: =O99/P99 | R99: 87.8298 | S99: 87.2175 | T99: 86.6692 | U99: =S99/T99-1 | V99: 0.8 | W99: =J99/R99-1 | X99: =J99/S99-1 | Y99: 3.532 | Z99: =Y99/J99 | AA99: =(J99-R99)/Y99 | AB99: =(J99-S99)/Y99 | AC99: =IF(ABS(AA99)<=ABS(AB99),"9EMA","21EMA") | AD99: 9+21EMA | AE99: 持續在上方 | AH99: ✓ | AI99: 2026-09-23 | AJ99: 6 | AK99: 2 | AL99: 2026-09-28 | AM99: 83.5 | AN99: 79.68 | AO99: =IF(ISNUMBER(AN99),AM99/AN99-1,"") | AP99: 3 | AQ99: =IF(ISNUMBER(AM99),J99/AM99-1,"") | AR99: 91.83 | AS99: =J99/AR99-1 | AT99: 上傾擴張 | AU99: 0.5412 | AV99: 0.1627 | AW99: 0.5367 | AX99: 0.5074 | AY99: 5 | AZ99: 92.38 | BA99: 79.68 | BB99: 86.4957 | BC99: 1.1409 | BD99: =IF(M99=N99,0.5,(J99-N99)/(M99-N99)) | BE99: 10.998 | BF99: 6.244 | BG99: =100*(0.4*MIN(1,MAX(0,((U99*100)-(0.0))/((2.5)-(0.0))))+0.3*MIN(1,MAX(0,((V99)-(0.6))/((1.0)-(0.6))))+0.3*MIN(1,MAX(0,((BE99)-(0.0))/((15.0)-(0.0))))) | BH99: =100*(0.4*MIN(1,MAX(0,((MIN(ABS(AA99),ABS(AB99)))-(0.75))/((0.0)-(0.75))))+0.3*MIN(1,MAX(0,((BC99)-(1.2))/((0.6)-(1.2))))+0.3*BD99) | BI99: =100*(0.5*MIN(1,MAX(0,((AK99)-(1.0))/((4.0)-(1.0))))+0.3*MIN(1,MAX(0,((IF(ISNUMBER(AO99),AO99,0)*100)-(0.0))/((8.0)-(0.0))))+0.2*MIN(1,MAX(0,((IF(ISNUMBER(AP99),AP99,0))-(25.0))/((5.0)-(25.0))))) | BJ99: =100*(0.35*MIN(1,MAX(0,((ABS(AU99))-(0.3))/((0.05)-(0.3))))+0.3*MIN(1,MAX(0,((AV99)-(0.0))/((0.3)-(0.0))))+0.25*MIN(1,MAX(0,((AW99)-(0.4))/((0.7)-(0.4))))+0.1*IF(AY99>=2,1,0.5)) | BK99: =0.25*BG99+0.25*BH99+0.2*BI99+0.3*BJ99 | BL99: 全部通過
A100: 1 | B100: 99 | C100: APXT | D100: Apex Treasury Corporation | E100: NASDAQ | F100: 金融 | G100: Blank Checks | I100: 未分類 | J100: 10.15 | K100: 10.13 | L100: =J100/K100-1 | M100: 10.15 | N100: 10.14 | O100: 132300 | P100: 154065 | Q100: =O100/P100 | R100: 10.1384 | S100: 10.1339 | T100: 10.1301 | U100: =S100/T100-1 | V100: 0.8 | W100: =J100/R100-1 | X100: =J100/S100-1 | Y100: 0.0128 | Z100: =Y100/J100 | AA100: =(J100-R100)/Y100 | AB100: =(J100-S100)/Y100 | AC100: =IF(ABS(AA100)<=ABS(AB100),"9EMA","21EMA") | AD100: 9+21EMA | AE100: 持續在上方 | AH100: ✓ | AI100: 2026-04-06 | AJ100: 124 | AK100: 2 | AL100: 2026-09-21 | AM100: 10.12 | AN100: 10.1 | AO100: =IF(ISNUMBER(AN100),AM100/AN100-1,"") | AP100: 8 | AQ100: =IF(ISNUMBER(AM100),J100/AM100-1,"") | AR100: 10.15 | AS100: =J100/AR100-1 | AT100: 上升三角（平頂） | AU100: 0 | AV100: 0.0058 | AW100: 0.5266 | AX100: 0.5266 | AY100: 25 | AZ100: 10.15 | BA100: 10.12 | BB100: 10.1358 | BC100: 1.0407 | BD100: =IF(M100=N100,0.5,(J100-N100)/(M100-N100)) | BE100: 5.051 | BF100: 0.296 | BG100: =100*(0.4*MIN(1,MAX(0,((U100*100)-(0.0))/((2.5)-(0.0))))+0.3*MIN(1,MAX(0,((V100)-(0.6))/((1.0)-(0.6))))+0.3*MIN(1,MAX(0,((BE100)-(0.0))/((15.0)-(0.0))))) | BH100: =100*(0.4*MIN(1,MAX(0,((MIN(ABS(AA100),ABS(AB100)))-(0.75))/((0.0)-(0.75))))+0.3*MIN(1,MAX(0,((BC100)-(1.2))/((0.6)-(1.2))))+0.3*BD100) | BI100: =100*(0.5*MIN(1,MAX(0,((AK100)-(1.0))/((4.0)-(1.0))))+0.3*MIN(1,MAX(0,((IF(ISNUMBER(AO100),AO100,0)*100)-(0.0))/((8.0)-(0.0))))+0.2*MIN(1,MAX(0,((IF(ISNUMBER(AP100),AP100,0))-(25.0))/((5.0)-(25.0))))) | BJ100: =100*(0.35*MIN(1,MAX(0,((ABS(AU100))-(0.3))/((0.05)-(0.3))))+0.3*MIN(1,MAX(0,((AV100)-(0.0))/((0.3)-(0.0))))+0.25*MIN(1,MAX(0,((AW100)-(0.4))/((0.7)-(0.4))))+0.1*IF(AY100>=2,1,0.5)) | BK100: =0.25*BG100+0.25*BH100+0.2*BI100+0.3*BJ100 | BL100: 全部通過
...

Sheet a 剛黃金交叉
A1: 頁內排名 | B1: 代號 | C1: 公司 | D1: 板塊 | E1: 行業 | F1: 市值組 | G1: 市值(十億美元) | H1: 收市價 | I1: 當日% | J1: EMA9 | K1: EMA21 | L1: 距EMA9% | M1: 距EMA21% | N1: 距EMA9（ATR倍） | O1: 距EMA21（ATR倍） | P1: 近3日低位觸及 | Q1: EMA21 5日斜率% | R1: 9/21狀態 | S1: 金叉日期 | T1: 金叉後日數 | U1: 連續上升底數目 | V1: 最後一底日期 | W1: 距最後一底% | X1: 距15日高% | Y1: 形態（25日） | Z1: 重心 | AA1: RS21% | AB1: 趨勢分數 | AC1: 回調質素 | AD1: 底部結構 | AE1: 三角形分數 | AF1: 綜合分數 | AG1: 總表排名
A2: 1 | B2: UCTT | C2: ='總表'!D33 | D2: ='總表'!F33 | E2: ='總表'!G33 | F2: ='總表'!I33 | G2: ='總表'!H33 | H2: ='總表'!J33 | I2: ='總表'!L33 | J2: ='總表'!R33 | K2: ='總表'!S33 | L2: ='總表'!W33 | M2: ='總表'!X33 | N2: ='總表'!AA33 | O2: ='總表'!AB33 | P2: ='總表'!AD33 | Q2: ='總表'!U33 | R2: ='總表'!AE33 | S2: ='總表'!AI33 | T2: ='總表'!AJ33 | U2: ='總表'!AK33 | V2: ='總表'!AL33 | W2: ='總表'!AQ33 | X2: ='總表'!AS33 | Y2: ='總表'!AT33 | Z2: ='總表'!AW33 | AA2: ='總表'!BE33 | AB2: ='總表'!BG33 | AC2: ='總表'!BH33 | AD2: ='總表'!BI33 | AE2: ='總表'!BJ33 | AF2: ='總表'!BK33 | AG2: ='總表'!B33
A3: 2 | B3: MAZE | C3: ='總表'!D51 | D3: ='總表'!F51 | E3: ='總表'!G51 | F3: ='總表'!I51 | G3: ='總表'!H51 | H3: ='總表'!J51 | I3: ='總表'!L51 | J3: ='總表'!R51 | K3: ='總表'!S51 | L3: ='總表'!W51 | M3: ='總表'!X51 | N3: ='總表'!AA51 | O3: ='總表'!AB51 | P3: ='總表'!AD51 | Q3: ='總表'!U51 | R3: ='總表'!AE51 | S3: ='總表'!AI51 | T3: ='總表'!AJ51 | U3: ='總表'!AK51 | V3: ='總表'!AL51 | W3: ='總表'!AQ51 | X3: ='總表'!AS51 | Y3: ='總表'!AT51 | Z3: ='總表'!AW51 | AA3: ='總表'!BE51 | AB3: ='總表'!BG51 | AC3: ='總表'!BH51 | AD3: ='總表'!BI51 | AE3: ='總表'!BJ51 | AF3: ='總表'!BK51 | AG3: ='總表'!B51
A4: 3 | B4: NEU | C4: ='總表'!D53 | D4: ='總表'!F53 | E4: ='總表'!G53 | F4: ='總表'!I53 | G4: ='總表'!H53 | H4: ='總表'!J53 | I4: ='總表'!L53 | J4: ='總表'!R53 | K4: ='總表'!S53 | L4: ='總表'!W53 | M4: ='總表'!X53 | N4: ='總表'!AA53 | O4: ='總表'!AB53 | P4: ='總表'!AD53 | Q4: ='總表'!U53 | R4: ='總表'!AE53 | S4: ='總表'!AI53 | T4: ='總表'!AJ53 | U4: ='總表'!AK53 | V4: ='總表'!AL53 | W4: ='總表'!AQ53 | X4: ='總表'!AS53 | Y4: ='總表'!AT53 | Z4: ='總表'!AW53 | AA4: ='總表'!BE53 | AB4: ='總表'!BG53 | AC4: ='總表'!BH53 | AD4: ='總表'!BI53 | AE4: ='總表'!BJ53 | AF4: ='總表'!BK53 | AG4: ='總表'!B53
A5: 4 | B5: HWKN | C5: ='總表'!D59 | D5: ='總表'!F59 | E5: ='總表'!G59 | F5: ='總表'!I59 | G5: ='總表'!H59 | H5: ='總表'!J59 | I5: ='總表'!L59 | J5: ='總表'!R59 | K5: ='總表'!S59 | L5: ='總表'!W59 | M5: ='總表'!X59 | N5: ='總表'!AA59 | O5: ='總表'!AB59 | P5: ='總表'!AD59 | Q5: ='總表'!U59 | R5: ='總表'!AE59 | S5: ='總表'!AI59 | T5: ='總表'!AJ59 | U5: ='總表'!AK59 | V5: ='總表'!AL59 | W5: ='總表'!AQ59 | X5: ='總表'!AS59 | Y5: ='總表'!AT59 | Z5: ='總表'!AW59 | AA5: ='總表'!BE59 | AB5: ='總表'!BG59 | AC5: ='總表'!BH59 | AD5: ='總表'!BI59 | AE5: ='總表'!BJ59 | AF5: ='總表'!BK59 | AG5: ='總表'!B59
A6: 5 | B6: GFS | C6: ='總表'!D63 | D6: ='總表'!F63 | E6: ='總表'!G63 | F6: ='總表'!I63 | G6: ='總表'!H63 | H6: ='總表'!J63 | I6: ='總表'!L63 | J6: ='總表'!R63 | K6: ='總表'!S63 | L6: ='總表'!W63 | M6: ='總表'!X63 | N6: ='總表'!AA63 | O6: ='總表'!AB63 | P6: ='總表'!AD63 | Q6: ='總表'!U63 | R6: ='總表'!AE63 | S6: ='總表'!AI63 | T6: ='總表'!AJ63 | U6: ='總表'!AK63 | V6: ='總表'!AL63 | W6: ='總表'!AQ63 | X6: ='總表'!AS63 | Y6: ='總表'!AT63 | Z6: ='總表'!AW63 | AA6: ='總表'!BE63 | AB6: ='總表'!BG63 | AC6: ='總表'!BH63 | AD6: ='總表'!BI63 | AE6: ='總表'!BJ63 | AF6: ='總表'!BK63 | AG6: ='總表'!B63
A7: 6 | B7: CAT | C7: ='總表'!D69 | D7: ='總表'!F69 | E7: ='總表'!G69 | F7: ='總表'!I69 | G7: ='總表'!H69 | H7: ='總表'!J69 | I7: ='總表'!L69 | J7: ='總表'!R69 | K7: ='總表'!S69 | L7: ='總表'!W69 | M7: ='總表'!X69 | N7: ='總表'!AA69 | O7: ='總表'!AB69 | P7: ='總表'!AD69 | Q7: ='總表'!U69 | R7: ='總表'!AE69 | S7: ='總表'!AI69 | T7: ='總表'!AJ69 | U7: ='總表'!AK69 | V7: ='總表'!AL69 | W7: ='總表'!AQ69 | X7: ='總表'!AS69 | Y7: ='總表'!AT69 | Z7: ='總表'!AW69 | AA7: ='總表'!BE69 | AB7: ='總表'!BG69 | AC7: ='總表'!BH69 | AD7: ='總表'!BI69 | AE7: ='總表'!BJ69 | AF7: ='總表'!BK69 | AG7: ='總表'!B69
A8: 7 | B8: PWR | C8: ='總表'!D73 | D8: ='總表'!F73 | E8: ='總表'!G73 | F8: ='總表'!I73 | G8: ='總表'!H73 | H8: ='總表'!J73 | I8: ='總表'!L73 | J8: ='總表'!R73 | K8: ='總表'!S73 | L8: ='總表'!W73 | M8: ='總表'!X73 | N8: ='總表'!AA73 | O8: ='總表'!AB73 | P8: ='總表'!AD73 | Q8: ='總表'!U73 | R8: ='總表'!AE73 | S8: ='總表'!AI73 | T8: ='總表'!AJ73 | U8: ='總表'!AK73 | V8: ='總表'!AL73 | W8: ='總表'!AQ73 | X8: ='總表'!AS73 | Y8: ='總表'!AT73 | Z8: ='總表'!AW73 | AA8: ='總表'!BE73 | AB8: ='總表'!BG73 | AC8: ='總表'!BH73 | AD8: ='總表'!BI73 | AE8: ='總表'!BJ73 | AF8: ='總表'!BK73 | AG8: ='總表'!B73
A9: 8 | B9: M | C9: ='總表'!D74 | D9: ='總表'!F74 | E9: ='總表'!G74 | F9: ='總表'!I74 | G9: ='總表'!H74 | H9: ='總表'!J74 | I9: ='總表'!L74 | J9: ='總表'!R74 | K9: ='總表'!S74 | L9: ='總表'!W74 | M9: ='總表'!X74 | N9: ='總表'!AA74 | O9: ='總表'!AB74 | P9: ='總表'!AD74 | Q9: ='總表'!U74 | R9: ='總表'!AE74 | S9: ='總表'!AI74 | T9: ='總表'!AJ74 | U9: ='總表'!AK74 | V9: ='總表'!AL74 | W9: ='總表'!AQ74 | X9: ='總表'!AS74 | Y9: ='總表'!AT74 | Z9: ='總表'!AW74 | AA9: ='總表'!BE74 | AB9: ='總表'!BG74 | AC9: ='總表'!BH74 | AD9: ='總表'!BI74 | AE9: ='總表'!BJ74 | AF9: ='總表'!BK74 | AG9: ='總表'!B74
A10: 9 | B10: CLDT | C10: ='總表'!D78 | D10: ='總表'!F78 | E10: ='總表'!G78 | F10: ='總表'!I78 | G10: ='總表'!H78 | H10: ='總表'!J78 | I10: ='總表'!L78 | J10: ='總表'!R78 | K10: ='總表'!S78 | L10: ='總表'!W78 | M10: ='總表'!X78 | N10: ='總表'!AA78 | O10: ='總表'!AB78 | P10: ='總表'!AD78 | Q10: ='總表'!U78 | R10: ='總表'!AE78 | S10: ='總表'!AI78 | T10: ='總表'!AJ78 | U10: ='總表'!AK78 | V10: ='總表'!AL78 | W10: ='總表'!AQ78 | X10: ='總表'!AS78 | Y10: ='總表'!AT78 | Z10: ='總表'!AW78 | AA10: ='總表'!BE78 | AB10: ='總表'!BG78 | AC10: ='總表'!BH78 | AD10: ='總表'!BI78 | AE10: ='總表'!BJ78 | AF10: ='總表'!BK78 | AG10: ='總表'!B78
A11: 10 | B11: AMBA | C11: ='總表'!D79 | D11: ='總表'!F79 | E11: ='總表'!G79 | F11: ='總表'!I79 | G11: ='總表'!H79 | H11: ='總表'!J79 | I11: ='總表'!L79 | J11: ='總表'!R79 | K11: ='總表'!S79 | L11: ='總表'!W79 | M11: ='總表'!X79 | N11: ='總表'!AA79 | O11: ='總表'!AB79 | P11: ='總表'!AD79 | Q11: ='總表'!U79 | R11: ='總表'!AE79 | S11: ='總表'!AI79 | T11: ='總表'!AJ79 | U11: ='總表'!AK79 | V11: ='總表'!AL79 | W11: ='總表'!AQ79 | X11: ='總表'!AS79 | Y11: ='總表'!AT79 | Z11: ='總表'!AW79 | AA11: ='總表'!BE79 | AB11: ='總表'!BG79 | AC11: ='總表'!BH79 | AD11: ='總表'!BI79 | AE11: ='總表'!BJ79 | AF11: ='總表'!BK79 | AG11: ='總表'!B79
A12: 11 | B12: AIP | C12: ='總表'!D86 | D12: ='總表'!F86 | E12: ='總表'!G86 | F12: ='總表'!I86 | G12: ='總表'!H86 | H12: ='總表'!J86 | I12: ='總表'!L86 | J12: ='總表'!R86 | K12: ='總表'!S86 | L12: ='總表'!W86 | M12: ='總表'!X86 | N12: ='總表'!AA86 | O12: ='總表'!AB86 | P12: ='總表'!AD86 | Q12: ='總表'!U86 | R12: ='總表'!AE86 | S12: ='總表'!AI86 | T12: ='總表'!AJ86 | U12: ='總表'!AK86 | V12: ='總表'!AL86 | W12: ='總表'!AQ86 | X12: ='總表'!AS86 | Y12: ='總表'!AT86 | Z12: ='總表'!AW86 | AA12: ='總表'!BE86 | AB12: ='總表'!BG86 | AC12: ='總表'!BH86 | AD12: ='總表'!BI86 | AE12: ='總表'!BJ86 | AF12: ='總表'!BK86 | AG12: ='總表'!B86
A13: 12 | B13: AMG | C13: ='總表'!D88 | D13: ='總表'!F88 | E13: ='總表'!G88 | F13: ='總表'!I88 | G13: ='總表'!H88 | H13: ='總表'!J88 | I13: ='總表'!L88 | J13: ='總表'!R88 | K13: ='總表'!S88 | L13: ='總表'!W88 | M13: ='總表'!X88 | N13: ='總表'!AA88 | O13: ='總表'!AB88 | P13: ='總表'!AD88 | Q13: ='總表'!U88 | R13: ='總表'!AE88 | S13: ='總表'!AI88 | T13: ='總表'!AJ88 | U13: ='總表'!AK88 | V13: ='總表'!AL88 | W13: ='總表'!AQ88 | X13: ='總表'!AS88 | Y13: ='總表'!AT88 | Z13: ='總表'!AW88 | AA13: ='總表'!BE88 | AB13: ='總表'!BG88 | AC13: ='總表'!BH88 | AD13: ='總表'!BI88 | AE13: ='總表'!BJ88 | AF13: ='總表'!BK88 | AG13: ='總表'!B88
A14: 13 | B14: FNRN | C14: ='總表'!D89 | D14: ='總表'!F89 | E14: ='總表'!G89 | F14: ='總表'!I89 | G14: ='總表'!H89 | H14: ='總表'!J89 | I14: ='總表'!L89 | J14: ='總表'!R89 | K14: ='總表'!S89 | L14: ='總表'!W89 | M14: ='總表'!X89 | N14: ='總表'!AA89 | O14: ='總表'!AB89 | P14: ='總表'!AD89 | Q14: ='總表'!U89 | R14: ='總表'!AE89 | S14: ='總表'!AI89 | T14: ='總表'!AJ89 | U14: ='總表'!AK89 | V14: ='總表'!AL89 | W14: ='總表'!AQ89 | X14: ='總表'!AS89 | Y14: ='總表'!AT89 | Z14: ='總表'!AW89 | AA14: ='總表'!BE89 | AB14: ='總表'!BG89 | AC14: ='總表'!BH89 | AD14: ='總表'!BI89 | AE14: ='總表'!BJ89 | AF14: ='總表'!BK89 | AG14: ='總表'!B89
A15: 14 | B15: COLM | C15: ='總表'!D96 | D15: ='總表'!F96 | E15: ='總表'!G96 | F15: ='總表'!I96 | G15: ='總表'!H96 | H15: ='總表'!J96 | I15: ='總表'!L96 | J15: ='總表'!R96 | K15: ='總表'!S96 | L15: ='總表'!W96 | M15: ='總表'!X96 | N15: ='總表'!AA96 | O15: ='總表'!AB96 | P15: ='總表'!AD96 | Q15: ='總表'!U96 | R15: ='總表'!AE96 | S15: ='總表'!AI96 | T15: ='總表'!AJ96 | U15: ='總表'!AK96 | V15: ='總表'!AL96 | W15: ='總表'!AQ96 | X15: ='總表'!AS96 | Y15: ='總表'!AT96 | Z15: ='總表'!AW96 | AA15: ='總表'!BE96 | AB15: ='總表'!BG96 | AC15: ='總表'!BH96 | AD15: ='總表'!BI96 | AE15: ='總表'!BJ96 | AF15: ='總表'!BK96 | AG15: ='總表'!B96
A16: 15 | B16: OPY | C16: ='總表'!D101 | D16: ='總表'!F101 | E16: ='總表'!G101 | F16: ='總表'!I101 | G16: ='總表'!H101 | H16: ='總表'!J101 | I16: ='總表'!L101 | J16: ='總表'!R101 | K16: ='總表'!S101 | L16: ='總表'!W101 | M16: ='總表'!X101 | N16: ='總表'!AA101 | O16: ='總表'!AB101 | P16: ='總表'!AD101 | Q16: ='總表'!U101 | R16: ='總表'!AE101 | S16: ='總表'!AI101 | T16: ='總表'!AJ101 | U16: ='總表'!AK101 | V16: ='總表'!AL101 | W16: ='總表'!AQ101 | X16: ='總表'!AS101 | Y16: ='總表'!AT101 | Z16: ='總表'!AW101 | AA16: ='總表'!BE101 | AB16: ='總表'!BG101 | AC16: ='總表'!BH101 | AD16: ='總表'!BI101 | AE16: ='總表'!BJ101 | AF16: ='總表'!BK101 | AG16: ='總表'!B101
A18: 核心四條件全過，而且 9EMA 喺最近 5 個交易日內剛升穿 21EMA（金叉日期欄）。 每格引用總表同一行，改總表會跟住變。

Sheet b 回到21EMA
A1: 頁內排名 | B1: 代號 | C1: 公司 | D1: 板塊 | E1: 行業 | F1: 市值組 | G1: 市值(十億美元) | H1: 收市價 | I1: 當日% | J1: EMA9 | K1: EMA21 | L1: 距EMA9% | M1: 距EMA21% | N1: 距EMA9（ATR倍） | O1: 距EMA21（ATR倍） | P1: 近3日低位觸及 | Q1: EMA21 5日斜率% | R1: 9/21狀態 | S1: 金叉日期 | T1: 金叉後日數 | U1: 連續上升底數目 | V1: 最後一底日期 | W1: 距最後一底% | X1: 距15日高% | Y1: 形態（25日） | Z1: 重心 | AA1: RS21% | AB1: 趨勢分數 | AC1: 回調質素 | AD1: 底部結構 | AE1: 三角形分數 | AF1: 綜合分數 | AG1: 總表排名
A2: 1 | B2: FRNM | C2: ='總表'!D8 | D2: ='總表'!F8 | E2: ='總表'!G8 | F2: ='總表'!I8 | G2: ='總表'!H8 | H2: ='總表'!J8 | I2: ='總表'!L8 | J2: ='總表'!R8 | K2: ='總表'!S8 | L2: ='總表'!W8 | M2: ='總表'!X8 | N2: ='總表'!AA8 | O2: ='總表'!AB8 | P2: ='總表'!AD8 | Q2: ='總表'!U8 | R2: ='總表'!AE8 | S2: ='總表'!AI8 | T2: ='總表'!AJ8 | U2: ='總表'!AK8 | V2: ='總表'!AL8 | W2: ='總表'!AQ8 | X2: ='總表'!AS8 | Y2: ='總表'!AT8 | Z2: ='總表'!AW8 | AA2: ='總表'!BE8 | AB2: ='總表'!BG8 | AC2: ='總表'!BH8 | AD2: ='總表'!BI8 | AE2: ='總表'!BJ8 | AF2: ='總表'!BK8 | AG2: ='總表'!B8
A3: 2 | B3: ADPT | C3: ='總表'!D25 | D3: ='總表'!F25 | E3: ='總表'!G25 | F3: ='總表'!I25 | G3: ='總表'!H25 | H3: ='總表'!J25 | I3: ='總表'!L25 | J3: ='總表'!R25 | K3: ='總表'!S25 | L3: ='總表'!W25 | M3: ='總表'!X25 | N3: ='總表'!AA25 | O3: ='總表'!AB25 | P3: ='總表'!AD25 | Q3: ='總表'!U25 | R3: ='總表'!AE25 | S3: ='總表'!AI25 | T3: ='總表'!AJ25 | U3: ='總表'!AK25 | V3: ='總表'!AL25 | W3: ='總表'!AQ25 | X3: ='總表'!AS25 | Y3: ='總表'!AT25 | Z3: ='總表'!AW25 | AA3: ='總表'!BE25 | AB3: ='總表'!BG25 | AC3: ='總表'!BH25 | AD3: ='總表'!BI25 | AE3: ='總表'!BJ25 | AF3: ='總表'!BK25 | AG3: ='總表'!B25
A4: 3 | B4: FLGT | C4: ='總表'!D31 | D4: ='總表'!F31 | E4: ='總表'!G31 | F4: ='總表'!I31 | G4: ='總表'!H31 | H4: ='總表'!J31 | I4: ='總表'!L31 | J4: ='總表'!R31 | K4: ='總表'!S31 | L4: ='總表'!W31 | M4: ='總表'!X31 | N4: ='總表'!AA31 | O4: ='總表'!AB31 | P4: ='總表'!AD31 | Q4: ='總表'!U31 | R4: ='總表'!AE31 | S4: ='總表'!AI31 | T4: ='總表'!AJ31 | U4: ='總表'!AK31 | V4: ='總表'!AL31 | W4: ='總表'!AQ31 | X4: ='總表'!AS31 | Y4: ='總表'!AT31 | Z4: ='總表'!AW31 | AA4: ='總表'!BE31 | AB4: ='總表'!BG31 | AC4: ='總表'!BH31 | AD4: ='總表'!BI31 | AE4: ='總表'!BJ31 | AF4: ='總表'!BK31 | AG4: ='總表'!B31
A5: 4 | B5: FTRE | C5: ='總表'!D45 | D5: ='總表'!F45 | E5: ='總表'!G45 | F5: ='總表'!I45 | G5: ='總表'!H45 | H5: ='總表'!J45 | I5: ='總表'!L45 | J5: ='總表'!R45 | K5: ='總表'!S45 | L5: ='總表'!W45 | M5: ='總表'!X45 | N5: ='總表'!AA45 | O5: ='總表'!AB45 | P5: ='總表'!AD45 | Q5: ='總表'!U45 | R5: ='總表'!AE45 | S5: ='總表'!AI45 | T5: ='總表'!AJ45 | U5: ='總表'!AK45 | V5: ='總表'!AL45 | W5: ='總表'!AQ45 | X5: ='總表'!AS45 | Y5: ='總表'!AT45 | Z5: ='總表'!AW45 | AA5: ='總表'!BE45 | AB5: ='總表'!BG45 | AC5: ='總表'!BH45 | AD5: ='總表'!BI45 | AE5: ='總表'!BJ45 | AF5: ='總表'!BK45 | AG5: ='總表'!B45
A6: 5 | B6: BTGO | C6: ='總表'!D62 | D6: ='總表'!F62 | E6: ='總表'!G62 | F6: ='總表'!I62 | G6: ='總表'!H62 | H6: ='總表'!J62 | I6: ='總表'!L62 | J6: ='總表'!R62 | K6: ='總表'!S62 | L6: ='總表'!W62 | M6: ='總表'!X62 | N6: ='總表'!AA62 | O6: ='總表'!AB62 | P6: ='總表'!AD62 | Q6: ='總表'!U62 | R6: ='總表'!AE62 | S6: ='總表'!AI62 | T6: ='總表'!AJ62 | U6: ='總表'!AK62 | V6: ='總表'!AL62 | W6: ='總表'!AQ62 | X6: ='總表'!AS62 | Y6: ='總表'!AT62 | Z6: ='總表'!AW62 | AA6: ='總表'!BE62 | AB6: ='總表'!BG62 | AC6: ='總表'!BH62 | AD6: ='總表'!BI62 | AE6: ='總表'!BJ62 | AF6: ='總表'!BK62 | AG6: ='總表'!B62
A7: 6 | B7: WAT | C7: ='總表'!D72 | D7: ='總表'!F72 | E7: ='總表'!G72 | F7: ='總表'!I72 | G7: ='總表'!H72 | H7: ='總表'!J72 | I7: ='總表'!L72 | J7: ='總表'!R72 | K7: ='總表'!S72 | L7: ='總表'!W72 | M7: ='總表'!X72 | N7: ='總表'!AA72 | O7: ='總表'!AB72 | P7: ='總表'!AD72 | Q7: ='總表'!U72 | R7: ='總表'!AE72 | S7: ='總表'!AI72 | T7: ='總表'!AJ72 | U7: ='總表'!AK72 | V7: ='總表'!AL72 | W7: ='總表'!AQ72 | X7: ='總表'!AS72 | Y7: ='總表'!AT72 | Z7: ='總表'!AW72 | AA7: ='總表'!BE72 | AB7: ='總表'!BG72 | AC7: ='總表'!BH72 | AD7: ='總表'!BI72 | AE7: ='總表'!BJ72 | AF7: ='總表'!BK72 | AG7: ='總表'!B72
A8: 7 | B8: SMTI | C8: ='總表'!D80 | D8: ='總表'!F80 | E8: ='總表'!G80 | F8: ='總表'!I80 | G8: ='總表'!H80 | H8: ='總表'!J80 | I8: ='總表'!L80 | J8: ='總表'!R80 | K8: ='總表'!S80 | L8: ='總表'!W80 | M8: ='總表'!X80 | N8: ='總表'!AA80 | O8: ='總表'!AB80 | P8: ='總表'!AD80 | Q8: ='總表'!U80 | R8: ='總表'!AE80 | S8: ='總表'!AI80 | T8: ='總表'!AJ80 | U8: ='總表'!AK80 | V8: ='總表'!AL80 | W8: ='總表'!AQ80 | X8: ='總表'!AS80 | Y8: ='總表'!AT80 | Z8: ='總表'!AW80 | AA8: ='總表'!BE80 | AB8: ='總表'!BG80 | AC8: ='總表'!BH80 | AD8: ='總表'!BI80 | AE8: ='總表'!BJ80 | AF8: ='總表'!BK80 | AG8: ='總表'!B80
A9: 8 | B9: BPRN | C9: ='總表'!D82 | D9: ='總表'!F82 | E9: ='總表'!G82 | F9: ='總表'!I82 | G9: ='總表'!H82 | H9: ='總表'!J82 | I9: ='總表'!L82 | J9: ='總表'!R82 | K9: ='總表'!S82 | L9: ='總表'!W82 | M9: ='總表'!X82 | N9: ='總表'!AA82 | O9: ='總表'!AB82 | P9: ='總表'!AD82 | Q9: ='總表'!U82 | R9: ='總表'!AE82 | S9: ='總表'!AI82 | T9: ='總表'!AJ82 | U9: ='總表'!AK82 | V9: ='總表'!AL82 | W9: ='總表'!AQ82 | X9: ='總表'!AS82 | Y9: ='總表'!AT82 | Z9: ='總表'!AW82 | AA9: ='總表'!BE82 | AB9: ='總表'!BG82 | AC9: ='總表'!BH82 | AD9: ='總表'!BI82 | AE9: ='總表'!BJ82 | AF9: ='總表'!BK82 | AG9: ='總表'!B82
A10: 9 | B10: PKOH | C10: ='總表'!D83 | D10: ='總表'!F83 | E10: ='總表'!G83 | F10: ='總表'!I83 | G10: ='總表'!H83 | H10: ='總表'!J83 | I10: ='總表'!L83 | J10: ='總表'!R83 | K10: ='總表'!S83 | L10: ='總表'!W83 | M10: ='總表'!X83 | N10: ='總表'!AA83 | O10: ='總表'!AB83 | P10: ='總表'!AD83 | Q10: ='總表'!U83 | R10: ='總表'!AE83 | S10: ='總表'!AI83 | T10: ='總表'!AJ83 | U10: ='總表'!AK83 | V10: ='總表'!AL83 | W10: ='總表'!AQ83 | X10: ='總表'!AS83 | Y10: ='總表'!AT83 | Z10: ='總表'!AW83 | AA10: ='總表'!BE83 | AB10: ='總表'!BG83 | AC10: ='總表'!BH83 | AD10: ='總表'!BI83 | AE10: ='總表'!BJ83 | AF10: ='總表'!BK83 | AG10: ='總表'!B83
A11: 10 | B11: BIIB | C11: ='總表'!D97 | D11: ='總表'!F97 | E11: ='總表'!G97 | F11: ='總表'!I97 | G11: ='總表'!H97 | H11: ='總表'!J97 | I11: ='總表'!L97 | J11: ='總表'!R97 | K11: ='總表'!S97 | L11: ='總表'!W97 | M11: ='總表'!X97 | N11: ='總表'!AA97 | O11: ='總表'!AB97 | P11: ='總表'!AD97 | Q11: ='總表'!U97 | R11: ='總表'!AE97 | S11: ='總表'!AI97 | T11: ='總表'!AJ97 | U11: ='總表'!AK97 | V11: ='總表'!AL97 | W11: ='總表'!AQ97 | X11: ='總表'!AS97 | Y11: ='總表'!AT97 | Z11: ='總表'!AW97 | AA11: ='總表'!BE97 | AB11: ='總表'!BG97 | AC11: ='總表'!BH97 | AD11: ='總表'!BI97 | AE11: ='總表'!BJ97 | AF11: ='總表'!BK97 | AG11: ='總表'!B97
A13: 核心四條件全過，而且收市離 EMA21 ≤3% 兼（≤0.75 ATR14 或近 3 日最低價觸及 EMA21）、收市唔低過 EMA21 3%；離兩條 EMA 都近嘅股票歸較近嗰條（呢頁係較深嘅回調）。 每格引用總表同一行，改總表會跟住變。

Sheet c 回到9EMA
A1: 頁內排名 | B1: 代號 | C1: 公司 | D1: 板塊 | E1: 行業 | F1: 市值組 | G1: 市值(十億美元) | H1: 收市價 | I1: 當日% | J1: EMA9 | K1: EMA21 | L1: 距EMA9% | M1: 距EMA21% | N1: 距EMA9（ATR倍） | O1: 距EMA21（ATR倍） | P1: 近3日低位觸及 | Q1: EMA21 5日斜率% | R1: 9/21狀態 | S1: 金叉日期 | T1: 金叉後日數 | U1: 連續上升底數目 | V1: 最後一底日期 | W1: 距最後一底% | X1: 距15日高% | Y1: 形態（25日） | Z1: 重心 | AA1: RS21% | AB1: 趨勢分數 | AC1: 回調質素 | AD1: 底部結構 | AE1: 三角形分數 | AF1: 綜合分數 | AG1: 總表排名
A2: 1 | B2: JILL | C2: ='總表'!D2 | D2: ='總表'!F2 | E2: ='總表'!G2 | F2: ='總表'!I2 | G2: ='總表'!H2 | H2: ='總表'!J2 | I2: ='總表'!L2 | J2: ='總表'!R2 | K2: ='總表'!S2 | L2: ='總表'!W2 | M2: ='總表'!X2 | N2: ='總表'!AA2 | O2: ='總表'!AB2 | P2: ='總表'!AD2 | Q2: ='總表'!U2 | R2: ='總表'!AE2 | S2: ='總表'!AI2 | T2: ='總表'!AJ2 | U2: ='總表'!AK2 | V2: ='總表'!AL2 | W2: ='總表'!AQ2 | X2: ='總表'!AS2 | Y2: ='總表'!AT2 | Z2: ='總表'!AW2 | AA2: ='總表'!BE2 | AB2: ='總表'!BG2 | AC2: ='總表'!BH2 | AD2: ='總表'!BI2 | AE2: ='總表'!BJ2 | AF2: ='總表'!BK2 | AG2: ='總表'!B2
A3: 2 | B3: PPIH | C3: ='總表'!D3 | D3: ='總表'!F3 | E3: ='總表'!G3 | F3: ='總表'!I3 | G3: ='總表'!H3 | H3: ='總表'!J3 | I3: ='總表'!L3 | J3: ='總表'!R3 | K3: ='總表'!S3 | L3: ='總表'!W3 | M3: ='總表'!X3 | N3: ='總表'!AA3 | O3: ='總表'!AB3 | P3: ='總表'!AD3 | Q3: ='總表'!U3 | R3: ='總表'!AE3 | S3: ='總表'!AI3 | T3: ='總表'!AJ3 | U3: ='總表'!AK3 | V3: ='總表'!AL3 | W3: ='總表'!AQ3 | X3: ='總表'!AS3 | Y3: ='總表'!AT3 | Z3: ='總表'!AW3 | AA3: ='總表'!BE3 | AB3: ='總表'!BG3 | AC3: ='總表'!BH3 | AD3: ='總表'!BI3 | AE3: ='總表'!BJ3 | AF3: ='總表'!BK3 | AG3: ='總表'!B3
A4: 3 | B4: MG | C4: ='總表'!D4 | D4: ='總表'!F4 | E4: ='總表'!G4 | F4: ='總表'!I4 | G4: ='總表'!H4 | H4: ='總表'!J4 | I4: ='總表'!L4 | J4: ='總表'!R4 | K4: ='總表'!S4 | L4: ='總表'!W4 | M4: ='總表'!X4 | N4: ='總表'!AA4 | O4: ='總表'!AB4 | P4: ='總表'!AD4 | Q4: ='總表'!U4 | R4: ='總表'!AE4 | S4: ='總表'!AI4 | T4: ='總表'!AJ4 | U4: ='總表'!AK4 | V4: ='總表'!AL4 | W4: ='總表'!AQ4 | X4: ='總表'!AS4 | Y4: ='總表'!AT4 | Z4: ='總表'!AW4 | AA4: ='總表'!BE4 | AB4: ='總表'!BG4 | AC4: ='總表'!BH4 | AD4: ='總表'!BI4 | AE4: ='總表'!BJ4 | AF4: ='總表'!BK4 | AG4: ='總表'!B4
A5: 4 | B5: TTMI | C5: ='總表'!D6 | D5: ='總表'!F6 | E5: ='總表'!G6 | F5: ='總表'!I6 | G5: ='總表'!H6 | H5: ='總表'!J6 | I5: ='總表'!L6 | J5: ='總表'!R6 | K5: ='總表'!S6 | L5: ='總表'!W6 | M5: ='總表'!X6 | N5: ='總表'!AA6 | O5: ='總表'!AB6 | P5: ='總表'!AD6 | Q5: ='總表'!U6 | R5: ='總表'!AE6 | S5: ='總表'!AI6 | T5: ='總表'!AJ6 | U5: ='總表'!AK6 | V5: ='總表'!AL6 | W5: ='總表'!AQ6 | X5: ='總表'!AS6 | Y5: ='總表'!AT6 | Z5: ='總表'!AW6 | AA5: ='總表'!BE6 | AB5: ='總表'!BG6 | AC5: ='總表'!BH6 | AD5: ='總表'!BI6 | AE5: ='總表'!BJ6 | AF5: ='總表'!BK6 | AG5: ='總表'!B6
A6: 5 | B6: NVAX | C6: ='總表'!D7 | D6: ='總表'!F7 | E6: ='總表'!G7 | F6: ='總表'!I7 | G6: ='總表'!H7 | H6: ='總表'!J7 | I6: ='總表'!L7 | J6: ='總表'!R7 | K6: ='總表'!S7 | L6: ='總表'!W7 | M6: ='總表'!X7 | N6: ='總表'!AA7 | O6: ='總表'!AB7 | P6: ='總表'!AD7 | Q6: ='總表'!U7 | R6: ='總表'!AE7 | S6: ='總表'!AI7 | T6: ='總表'!AJ7 | U6: ='總表'!AK7 | V6: ='總表'!AL7 | W6: ='總表'!AQ7 | X6: ='總表'!AS7 | Y6: ='總表'!AT7 | Z6: ='總表'!AW7 | AA6: ='總表'!BE7 | AB6: ='總表'!BG7 | AC6: ='總表'!BH7 | AD6: ='總表'!BI7 | AE6: ='總表'!BJ7 | AF6: ='總表'!BK7 | AG6: ='總表'!B7
A7: 6 | B7: NET | C7: ='總表'!D9 | D7: ='總表'!F9 | E7: ='總表'!G9 | F7: ='總表'!I9 | G7: ='總表'!H9 | H7: ='總表'!J9 | I7: ='總表'!L9 | J7: ='總表'!R9 | K7: ='總表'!S9 | L7: ='總表'!W9 | M7: ='總表'!X9 | N7: ='總表'!AA9 | O7: ='總表'!AB9 | P7: ='總表'!AD9 | Q7: ='總表'!U9 | R7: ='總表'!AE9 | S7: ='總表'!AI9 | T7: ='總表'!AJ9 | U7: ='總表'!AK9 | V7: ='總表'!AL9 | W7: ='總表'!AQ9 | X7: ='總表'!AS9 | Y7: ='總表'!AT9 | Z7: ='總表'!AW9 | AA7: ='總表'!BE9 | AB7: ='總表'!BG9 | AC7: ='總表'!BH9 | AD7: ='總表'!BI9 | AE7: ='總表'!BJ9 | AF7: ='總表'!BK9 | AG7: ='總表'!B9
A8: 7 | B8: ACVA | C8: ='總表'!D11 | D8: ='總表'!F11 | E8: ='總表'!G11 | F8: ='總表'!I11 | G8: ='總表'!H11 | H8: ='總表'!J11 | I8: ='總表'!L11 | J8: ='總表'!R11 | K8: ='總表'!S11 | L8: ='總表'!W11 | M8: ='總表'!X11 | N8: ='總表'!AA11 | O8: ='總表'!AB11 | P8: ='總表'!AD11 | Q8: ='總表'!U11 | R8: ='總表'!AE11 | S8: ='總表'!AI11 | T8: ='總表'!AJ11 | U8: ='總表'!AK11 | V8: ='總表'!AL11 | W8: ='總表'!AQ11 | X8: ='總表'!AS11 | Y8: ='總表'!AT11 | Z8: ='總表'!AW11 | AA8: ='總表'!BE11 | AB8: ='總表'!BG11 | AC8: ='總表'!BH11 | AD8: ='總表'!BI11 | AE8: ='總表'!BJ11 | AF8: ='總表'!BK11 | AG8: ='總表'!B11
A9: 8 | B9: LTC | C9: ='總表'!D12 | D9: ='總表'!F12 | E9: ='總表'!G12 | F9: ='總表'!I12 | G9: ='總表'!H12 | H9: ='總表'!J12 | I9: ='總表'!L12 | J9: ='總表'!R12 | K9: ='總表'!S12 | L9: ='總表'!W12 | M9: ='總表'!X12 | N9: ='總表'!AA12 | O9: ='總表'!AB12 | P9: ='總表'!AD12 | Q9: ='總表'!U12 | R9: ='總表'!AE12 | S9: ='總表'!AI12 | T9: ='總表'!AJ12 | U9: ='總表'!AK12 | V9: ='總表'!AL12 | W9: ='總表'!AQ12 | X9: ='總表'!AS12 | Y9: ='總表'!AT12 | Z9: ='總表'!AW12 | AA9: ='總表'!BE12 | AB9: ='總表'!BG12 | AC9: ='總表'!BH12 | AD9: ='總表'!BI12 | AE9: ='總表'!BJ12 | AF9: ='總表'!BK12 | AG9: ='總表'!B12
A10: 9 | B10: PANW | C10: ='總表'!D13 | D10: ='總表'!F13 | E10: ='總表'!G13 | F10: ='總表'!I13 | G10: ='總表'!H13 | H10: ='總表'!J13 | I10: ='總表'!L13 | J10: ='總表'!R13 | K10: ='總表'!S13 | L10: ='總表'!W13 | M10: ='總表'!X13 | N10: ='總表'!AA13 | O10: ='總表'!AB13 | P10: ='總表'!AD13 | Q10: ='總表'!U13 | R10: ='總表'!AE13 | S10: ='總表'!AI13 | T10: ='總表'!AJ13 | U10: ='總表'!AK13 | V10: ='總表'!AL13 | W10: ='總表'!AQ13 | X10: ='總表'!AS13 | Y10: ='總表'!AT13 | Z10: ='總表'!AW13 | AA10: ='總表'!BE13 | AB10: ='總表'!BG13 | AC10: ='總表'!BH13 | AD10: ='總表'!BI13 | AE10: ='總表'!BJ13 | AF10: ='總表'!BK13 | AG10: ='總表'!B13
A11: 10 | B11: PENG | C11: ='總表'!D14 | D11: ='總表'!F14 | E11: ='總表'!G14 | F11: ='總表'!I14 | G11: ='總表'!H14 | H11: ='總表'!J14 | I11: ='總表'!L14 | J11: ='總表'!R14 | K11: ='總表'!S14 | L11: ='總表'!W14 | M11: ='總表'!X14 | N11: ='總表'!AA14 | O11: ='總表'!AB14 | P11: ='總表'!AD14 | Q11: ='總表'!U14 | R11: ='總表'!AE14 | S11: ='總表'!AI14 | T11: ='總表'!AJ14 | U11: ='總表'!AK14 | V11: ='總表'!AL14 | W11: ='總表'!AQ14 | X11: ='總表'!AS14 | Y11: ='總表'!AT14 | Z11: ='總表'!AW14 | AA11: ='總表'!BE14 | AB11: ='總表'!BG14 | AC11: ='總表'!BH14 | AD11: ='總表'!BI14 | AE11: ='總表'!BJ14 | AF11: ='總表'!BK14 | AG11: ='總表'!B14
A12: 11 | B12: DT | C12: ='總表'!D15 | D12: ='總表'!F15 | E12: ='總表'!G15 | F12: ='總表'!I15 | G12: ='總表'!H15 | H12: ='總表'!J15 | I12: ='總表'!L15 | J12: ='總表'!R15 | K12: ='總表'!S15 | L12: ='總表'!W15 | M12: ='總表'!X15 | N12: ='總表'!AA15 | O12: ='總表'!AB15 | P12: ='總表'!AD15 | Q12: ='總表'!U15 | R12: ='總表'!AE15 | S12: ='總表'!AI15 | T12: ='總表'!AJ15 | U12: ='總表'!AK15 | V12: ='總表'!AL15 | W12: ='總表'!AQ15 | X12: ='總表'!AS15 | Y12: ='總表'!AT15 | Z12: ='總表'!AW15 | AA12: ='總表'!BE15 | AB12: ='總表'!BG15 | AC12: ='總表'!BH15 | AD12: ='總表'!BI15 | AE12: ='總表'!BJ15 | AF12: ='總表'!BK15 | AG12: ='總表'!B15
A13: 12 | B13: NUTX | C13: ='總表'!D16 | D13: ='總表'!F16 | E13: ='總表'!G16 | F13: ='總表'!I16 | G13: ='總表'!H16 | H13: ='總表'!J16 | I13: ='總表'!L16 | J13: ='總表'!R16 | K13: ='總表'!S16 | L13: ='總表'!W16 | M13: ='總表'!X16 | N13: ='總表'!AA16 | O13: ='總表'!AB16 | P13: ='總表'!AD16 | Q13: ='總表'!U16 | R13: ='總表'!AE16 | S13: ='總表'!AI16 | T13: ='總表'!AJ16 | U13: ='總表'!AK16 | V13: ='總表'!AL16 | W13: ='總表'!AQ16 | X13: ='總表'!AS16 | Y13: ='總表'!AT16 | Z13: ='總表'!AW16 | AA13: ='總表'!BE16 | AB13: ='總表'!BG16 | AC13: ='總表'!BH16 | AD13: ='總表'!BI16 | AE13: ='總表'!BJ16 | AF13: ='總表'!BK16 | AG13: ='總表'!B16
A14: 13 | B14: DDD | C14: ='總表'!D17 | D14: ='總表'!F17 | E14: ='總表'!G17 | F14: ='總表'!I17 | G14: ='總表'!H17 | H14: ='總表'!J17 | I14: ='總表'!L17 | J14: ='總表'!R17 | K14: ='總表'!S17 | L14: ='總表'!W17 | M14: ='總表'!X17 | N14: ='總表'!AA17 | O14: ='總表'!AB17 | P14: ='總表'!AD17 | Q14: ='總表'!U17 | R14: ='總表'!AE17 | S14: ='總表'!AI17 | T14: ='總表'!AJ17 | U14: ='總表'!AK17 | V14: ='總表'!AL17 | W14: ='總表'!AQ17 | X14: ='總表'!AS17 | Y14: ='總表'!AT17 | Z14: ='總表'!AW17 | AA14: ='總表'!BE17 | AB14: ='總表'!BG17 | AC14: ='總表'!BH17 | AD14: ='總表'!BI17 | AE14: ='總表'!BJ17 | AF14: ='總表'!BK17 | AG14: ='總表'!B17
A15: 14 | B15: MTW | C15: ='總表'!D18 | D15: ='總表'!F18 | E15: ='總表'!G18 | F15: ='總表'!I18 | G15: ='總表'!H18 | H15: ='總表'!J18 | I15: ='總表'!L18 | J15: ='總表'!R18 | K15: ='總表'!S18 | L15: ='總表'!W18 | M15: ='總表'!X18 | N15: ='總表'!AA18 | O15: ='總表'!AB18 | P15: ='總表'!AD18 | Q15: ='總表'!U18 | R15: ='總表'!AE18 | S15: ='總表'!AI18 | T15: ='總表'!AJ18 | U15: ='總表'!AK18 | V15: ='總表'!AL18 | W15: ='總表'!AQ18 | X15: ='總表'!AS18 | Y15: ='總表'!AT18 | Z15: ='總表'!AW18 | AA15: ='總表'!BE18 | AB15: ='總表'!BG18 | AC15: ='總表'!BH18 | AD15: ='總表'!BI18 | AE15: ='總表'!BJ18 | AF15: ='總表'!BK18 | AG15: ='總表'!B18
A16: 15 | B16: ISRG | C16: ='總表'!D19 | D16: ='總表'!F19 | E16: ='總表'!G19 | F16: ='總表'!I19 | G16: ='總表'!H19 | H16: ='總表'!J19 | I16: ='總表'!L19 | J16: ='總表'!R19 | K16: ='總表'!S19 | L16: ='總表'!W19 | M16: ='總表'!X19 | N16: ='總表'!AA19 | O16: ='總表'!AB19 | P16: ='總表'!AD19 | Q16: ='總表'!U19 | R16: ='總表'!AE19 | S16: ='總表'!AI19 | T16: ='總表'!AJ19 | U16: ='總表'!AK19 | V16: ='總表'!AL19 | W16: ='總表'!AQ19 | X16: ='總表'!AS19 | Y16: ='總表'!AT19 | Z16: ='總表'!AW19 | AA16: ='總表'!BE19 | AB16: ='總表'!BG19 | AC16: ='總表'!BH19 | AD16: ='總表'!BI19 | AE16: ='總表'!BJ19 | AF16: ='總表'!BK19 | AG16: ='總表'!B19
A17: 16 | B17: FTNT | C17: ='總表'!D21 | D17: ='總表'!F21 | E17: ='總表'!G21 | F17: ='總表'!I21 | G17: ='總表'!H21 | H17: ='總表'!J21 | I17: ='總表'!L21 | J17: ='總表'!R21 | K17: ='總表'!S21 | L17: ='總表'!W21 | M17: ='總表'!X21 | N17: ='總表'!AA21 | O17: ='總表'!AB21 | P17: ='總表'!AD21 | Q17: ='總表'!U21 | R17: ='總表'!AE21 | S17: ='總表'!AI21 | T17: ='總表'!AJ21 | U17: ='總表'!AK21 | V17: ='總表'!AL21 | W17: ='總表'!AQ21 | X17: ='總表'!AS21 | Y17: ='總表'!AT21 | Z17: ='總表'!AW21 | AA17: ='總表'!BE21 | AB17: ='總表'!BG21 | AC17: ='總表'!BH21 | AD17: ='總表'!BI21 | AE17: ='總表'!BJ21 | AF17: ='總表'!BK21 | AG17: ='總表'!B21
A18: 17 | B18: AVT | C18: ='總表'!D22 | D18: ='總表'!F22 | E18: ='總表'!G22 | F18: ='總表'!I22 | G18: ='總表'!H22 | H18: ='總表'!J22 | I18: ='總表'!L22 | J18: ='總表'!R22 | K18: ='總表'!S22 | L18: ='總表'!W22 | M18: ='總表'!X22 | N18: ='總表'!AA22 | O18: ='總表'!AB22 | P18: ='總表'!AD22 | Q18: ='總表'!U22 | R18: ='總表'!AE22 | S18: ='總表'!AI22 | T18: ='總表'!AJ22 | U18: ='總表'!AK22 | V18: ='總表'!AL22 | W18: ='總表'!AQ22 | X18: ='總表'!AS22 | Y18: ='總表'!AT22 | Z18: ='總表'!AW22 | AA18: ='總表'!BE22 | AB18: ='總表'!BG22 | AC18: ='總表'!BH22 | AD18: ='總表'!BI22 | AE18: ='總表'!BJ22 | AF18: ='總表'!BK22 | AG18: ='總表'!B22
A19: 18 | B19: CVLT | C19: ='總表'!D24 | D19: ='總表'!F24 | E19: ='總表'!G24 | F19: ='總表'!I24 | G19: ='總表'!H24 | H19: ='總表'!J24 | I19: ='總表'!L24 | J19: ='總表'!R24 | K19: ='總表'!S24 | L19: ='總表'!W24 | M19: ='總表'!X24 | N19: ='總表'!AA24 | O19: ='總表'!AB24 | P19: ='總表'!AD24 | Q19: ='總表'!U24 | R19: ='總表'!AE24 | S19: ='總表'!AI24 | T19: ='總表'!AJ24 | U19: ='總表'!AK24 | V19: ='總表'!AL24 | W19: ='總表'!AQ24 | X19: ='總表'!AS24 | Y19: ='總表'!AT24 | Z19: ='總表'!AW24 | AA19: ='總表'!BE24 | AB19: ='總表'!BG24 | AC19: ='總表'!BH24 | AD19: ='總表'!BI24 | AE19: ='總表'!BJ24 | AF19: ='總表'!BK24 | AG19: ='總表'!B24
A20: 19 | B20: DELL | C20: ='總表'!D26 | D20: ='總表'!F26 | E20: ='總表'!G26 | F20: ='總表'!I26 | G20: ='總表'!H26 | H20: ='總表'!J26 | I20: ='總表'!L26 | J20: ='總表'!R26 | K20: ='總表'!S26 | L20: ='總表'!W26 | M20: ='總表'!X26 | N20: ='總表'!AA26 | O20: ='總表'!AB26 | P20: ='總表'!AD26 | Q20: ='總表'!U26 | R20: ='總表'!AE26 | S20: ='總表'!AI26 | T20: ='總表'!AJ26 | U20: ='總表'!AK26 | V20: ='總表'!AL26 | W20: ='總表'!AQ26 | X20: ='總表'!AS26 | Y20: ='總表'!AT26 | Z20: ='總表'!AW26 | AA20: ='總表'!BE26 | AB20: ='總表'!BG26 | AC20: ='總表'!BH26 | AD20: ='總表'!BI26 | AE20: ='總表'!BJ26 | AF20: ='總表'!BK26 | AG20: ='總表'!B26
A21: 20 | B21: ANET | C21: ='總表'!D29 | D21: ='總表'!F29 | E21: ='總表'!G29 | F21: ='總表'!I29 | G21: ='總表'!H29 | H21: ='總表'!J29 | I21: ='總表'!L29 | J21: ='總表'!R29 | K21: ='總表'!S29 | L21: ='總表'!W29 | M21: ='總表'!X29 | N21: ='總表'!AA29 | O21: ='總表'!AB29 | P21: ='總表'!AD29 | Q21: ='總表'!U29 | R21: ='總表'!AE29 | S21: ='總表'!AI29 | T21: ='總表'!AJ29 | U21: ='總表'!AK29 | V21: ='總表'!AL29 | W21: ='總表'!AQ29 | X21: ='總表'!AS29 | Y21: ='總表'!AT29 | Z21: ='總表'!AW29 | AA21: ='總表'!BE29 | AB21: ='總表'!BG29 | AC21: ='總表'!BH29 | AD21: ='總表'!BI29 | AE21: ='總表'!BJ29 | AF21: ='總表'!BK29 | AG21: ='總表'!B29
A22: 21 | B22: ARW | C22: ='總表'!D30 | D22: ='總表'!F30 | E22: ='總表'!G30 | F22: ='總表'!I30 | G22: ='總表'!H30 | H22: ='總表'!J30 | I22: ='總表'!L30 | J22: ='總表'!R30 | K22: ='總表'!S30 | L22: ='總表'!W30 | M22: ='總表'!X30 | N22: ='總表'!AA30 | O22: ='總表'!AB30 | P22: ='總表'!AD30 | Q22: ='總表'!U30 | R22: ='總表'!AE30 | S22: ='總表'!AI30 | T22: ='總表'!AJ30 | U22: ='總表'!AK30 | V22: ='總表'!AL30 | W22: ='總表'!AQ30 | X22: ='總表'!AS30 | Y22: ='總表'!AT30 | Z22: ='總表'!AW30 | AA22: ='總表'!BE30 | AB22: ='總表'!BG30 | AC22: ='總表'!BH30 | AD22: ='總表'!BI30 | AE22: ='總表'!BJ30 | AF22: ='總表'!BK30 | AG22: ='總表'!B30
A23: 22 | B23: CRSR | C23: ='總表'!D32 | D23: ='總表'!F32 | E23: ='總表'!G32 | F23: ='總表'!I32 | G23: ='總表'!H32 | H23: ='總表'!J32 | I23: ='總表'!L32 | J23: ='總表'!R32 | K23: ='總表'!S32 | L23: ='總表'!W32 | M23: ='總表'!X32 | N23: ='總表'!AA32 | O23: ='總表'!AB32 | P23: ='總表'!AD32 | Q23: ='總表'!U32 | R23: ='總表'!AE32 | S23: ='總表'!AI32 | T23: ='總表'!AJ32 | U23: ='總表'!AK32 | V23: ='總表'!AL32 | W23: ='總表'!AQ32 | X23: ='總表'!AS32 | Y23: ='總表'!AT32 | Z23: ='總表'!AW32 | AA23: ='總表'!BE32 | AB23: ='總表'!BG32 | AC23: ='總表'!BH32 | AD23: ='總表'!BI32 | AE23: ='總表'!BJ32 | AF23: ='總表'!BK32 | AG23: ='總表'!B32
A24: 23 | B24: UCTT | C24: ='總表'!D33 | D24: ='總表'!F33 | E24: ='總表'!G33 | F24: ='總表'!I33 | G24: ='總表'!H33 | H24: ='總表'!J33 | I24: ='總表'!L33 | J24: ='總表'!R33 | K24: ='總表'!S33 | L24: ='總表'!W33 | M24: ='總表'!X33 | N24: ='總表'!AA33 | O24: ='總表'!AB33 | P24: ='總表'!AD33 | Q24: ='總表'!U33 | R24: ='總表'!AE33 | S24: ='總表'!AI33 | T24: ='總表'!AJ33 | U24: ='總表'!AK33 | V24: ='總表'!AL33 | W24: ='總表'!AQ33 | X24: ='總表'!AS33 | Y24: ='總表'!AT33 | Z24: ='總表'!AW33 | AA24: ='總表'!BE33 | AB24: ='總表'!BG33 | AC24: ='總表'!BH33 | AD24: ='總表'!BI33 | AE24: ='總表'!BJ33 | AF24: ='總表'!BK33 | AG24: ='總表'!B33
A25: 24 | B25: OSPN | C25: ='總表'!D35 | D25: ='總表'!F35 | E25: ='總表'!G35 | F25: ='總表'!I35 | G25: ='總表'!H35 | H25: ='總表'!J35 | I25: ='總表'!L35 | J25: ='總表'!R35 | K25: ='總表'!S35 | L25: ='總表'!W35 | M25: ='總表'!X35 | N25: ='總表'!AA35 | O25: ='總表'!AB35 | P25: ='總表'!AD35 | Q25: ='總表'!U35 | R25: ='總表'!AE35 | S25: ='總表'!AI35 | T25: ='總表'!AJ35 | U25: ='總表'!AK35 | V25: ='總表'!AL35 | W25: ='總表'!AQ35 | X25: ='總表'!AS35 | Y25: ='總表'!AT35 | Z25: ='總表'!AW35 | AA25: ='總表'!BE35 | AB25: ='總表'!BG35 | AC25: ='總表'!BH35 | AD25: ='總表'!BI35 | AE25: ='總表'!BJ35 | AF25: ='總表'!BK35 | AG25: ='總表'!B35
A26: 25 | B26: VRNS | C26: ='總表'!D38 | D26: ='總表'!F38 | E26: ='總表'!G38 | F26: ='總表'!I38 | G26: ='總表'!H38 | H26: ='總表'!J38 | I26: ='總表'!L38 | J26: ='總表'!R38 | K26: ='總表'!S38 | L26: ='總表'!W38 | M26: ='總表'!X38 | N26: ='總表'!AA38 | O26: ='總表'!AB38 | P26: ='總表'!AD38 | Q26: ='總表'!U38 | R26: ='總表'!AE38 | S26: ='總表'!AI38 | T26: ='總表'!AJ38 | U26: ='總表'!AK38 | V26: ='總表'!AL38 | W26: ='總表'!AQ38 | X26: ='總表'!AS38 | Y26: ='總表'!AT38 | Z26: ='總表'!AW38 | AA26: ='總表'!BE38 | AB26: ='總表'!BG38 | AC26: ='總表'!BH38 | AD26: ='總表'!BI38 | AE26: ='總表'!BJ38 | AF26: ='總表'!BK38 | AG26: ='總表'!B38
