Workbook

Sheet 本版更新
A1: R4.00 更新重點
A2: 1 | B2: R4.00：加入 MACD（12/26/9）兩個核心條件 —— ⑤ 慢線（訊號線）高過前一日 ⑥ 柱狀圖動能轉勢：近 3 日內出現第一根「深紅之後嘅淺紅」或「淺綠之後嘅深綠」，其後每根都升（顏色跟 TradingView 四色柱）。連同 ① 21EMA 向上 ② 9EMA 在 21EMA 上 ③ 一底高於一底 ④ 上升三角重心偏上，六項全過＝第一梯隊。總表加咗 MACD、慢線、慢線斜率、三日柱值、柱顏色、轉勢種類／幾日前、柱顏色序列。
A3: 2 | B3: 三個分頁（引用總表）：a 剛黃金交叉（5 日內金叉）6 隻；b 回到 21EMA（離 EMA21 ≤3% 兼 ≤0.75 ATR 或近 3 日觸及）0 隻；c 回到 9EMA（同樣口徑對 EMA9，離兩條都近就歸較近嗰條）18 隻 —— 都係第一梯隊數目；每頁下方另加灰底第二梯隊（只差一項）同橙底第三梯隊（價格四項過、只差 MACD，共 71 隻）畀你候補。b 頁第一梯隊得零隻：回到 21EMA 嘅股票柱狀圖多數仲喺減速中、未出現第一根淺紅／深綠，候補嗰啲就係要等嘅名。
A4: 3 | B4: 數據更新至 2026-10-02 收市（193 個交易日，2025-12-26 起；Yahoo 日線由 GitHub Actions 抓取）。
A5: 4 | B5: 合資格 2,792 隻 → C1 630 → C2 597 → C3 368 → C4 97 → C5 MACD 慢線 44 → C6 柱轉勢 第一梯隊 26 隻（大型 9／中型 9／小型 7；平頂上升三角 10 隻）。第二梯隊（差一項）35 隻。
A6: 5 | B6: 排名：綜合分數 = 0.25 趨勢 + 0.25 回調質素 + 0.2 底部結構 + 0.3 三角形（每項 0–100，總表全部係公式）。頭五位：AMN（67）、SEI（65）、DDD（63）、FFIV（62）、ANET（62）。
A7: 6 | B7: 市況：10-02 就業轉弱（9 月只加 2.9 萬、失業率 4.2%）→ 10 月加息機率大減、債息油價齊回落、指數反彈；但闊度仍弱、10 年息仍 5.2% 樓上 —— 由「偏防守」升級為「審慎偏多」，只做 9/21EMA 回調、倉位由一半加至七成（市況頁有指數／ETF／商品／債息嘅 EMA 狀態、合資格股票池闊度、四大力量周期對標同領先指標觀察表）。
A8: 7 | B8: 頁：總表（兩個梯隊）、a 剛黃金交叉、b 回到21EMA、c 回到9EMA、大型股／中型股／小型股（引用總表）、差一項、樞軸底頂、篩選規則、市況、數據核對。所有代號連 TradingView；藍字係量度值、黑字係公式。
A9: 8 | B9: 產出：9EMA-Uptrend_Watchlist_R4.00_claudefable51xhigh_10.03_1043.xlsx（claudefable51xhigh = Claude Fable 5.1，effort xhigh；2026-10-03 10:43 香港時間）。

Sheet 總表
A1: 梯隊 | B1: 排名 | C1: 代號 | D1: 公司 | E1: 交易所 | F1: 板塊 | G1: 行業 | H1: 市值(十億美元) | I1: 市值組 | J1: 收市價 | K1: 前收 | L1: 當日% | M1: 當日高 | N1: 當日低 | O1: 成交量 | P1: 20日均量 | Q1: 量比 | R1: EMA9 | S1: EMA21 | T1: EMA21（5日前） | U1: EMA21 5日斜率% | V1: EMA21 10步上升比例 | W1: 距EMA9% | X1: 距EMA21% | Y1: ATR14 | Z1: ATR14% | AA1: 距EMA9（ATR倍） | AB1: 距EMA21（ATR倍） | AC1: 最接近 | AD1: 近3日低位觸及 | AE1: 9/21狀態 | AF1: a 剛金叉 | AG1: b 回到21EMA | AH1: c 回到9EMA | AI1: 金叉日期 | AJ1: 金叉後日數 | AK1: 連續上升底數目 | AL1: 最後一底日期 | AM1: 最後一底價 | AN1: 上一底價 | AO1: 底較底升% | AP1: 最後一底距今（日） | AQ1: 距最後一底% | AR1: 15日最高收市 | AS1: 距15日高% | AT1: MACD | AU1: MACD慢線 | AV1: 慢線（前日） | AW1: 慢線斜率 | AX1: 柱（今日） | AY1: 柱（前日） | AZ1: 柱（前2日） | BA1: 柱顏色 | BB1: 柱轉勢 | BC1: 轉勢幾日前 | BD1: 柱顏色序列（舊→新） | BE1: 形態（25日） | BF1: 高位斜率（%/日） | BG1: 低位斜率（%/日） | BH1: 重心（VWAP在25日高低區間位置） | BI1: 重心（收市範圍） | BJ1: 頂部觸及次數 | BK1: 25日最高 | BL1: 25日最低 | BM1: 25日VWAP | BN1: 跌日／升日量比（10日） | BO1: 收市在當日區間位置 | BP1: RS21（對全池中位數）% | BQ1: 21日回報% | BR1: 趨勢分數 | BS1: 回調質素 | BT1: 底部結構 | BU1: 三角形分數 | BV1: 綜合分數 | BW1: 唔過嘅條件 | BX1: 備註
A2: 1 | B2: 1 | C2: AMN | D2: AMN Healthcare Services Inc | E2: NYSE | F2: 非必需消費 | G2: Professional Services | H2: 1.389 | I2: 小型 | J2: 36.63 | K2: 35.86 | L2: =J2/K2-1 | M2: 36.9 | N2: 36.21 | O2: 887200 | P2: 637170 | Q2: =O2/P2 | R2: 35.289 | S2: 34.7366 | T2: 34.1968 | U2: =S2/T2-1 | V2: 0.9 | W2: =J2/R2-1 | X2: =J2/S2-1 | Y2: 1.2015 | Z2: =Y2/J2 | AA2: =(J2-R2)/Y2 | AB2: =(J2-S2)/Y2 | AC2: =IF(ABS(AA2)<=ABS(AB2),"9EMA","21EMA") | AD2: — | AE2: 持續在上方 | AI2: 2026-09-16 | AJ2: 12 | AK2: 3 | AL2: 2026-09-24 | AM2: 33.41 | AN2: 32.66 | AO2: =IF(ISNUMBER(AN2),AM2/AN2-1,"") | AP2: 6 | AQ2: =IF(ISNUMBER(AM2),J2/AM2-1,"") | AR2: 36.63 | AS2: =J2/AR2-1 | AT2: 0.4756 | AU2: 0.2509 | AV2: 0.1947 | AW2: =AU2-AV2 | AX2: 0.2247 | AY2: 0.1616 | AZ2: 0.1229 | BA2: 深綠 | BB2: 淺綠→深綠 | BC2: 3 | BD2: 淺綠 深綠 深綠 淺綠 深綠 深綠 深綠 深綠 | BE2: 上升三角（平頂） | BF2: -0.021 | BG2: 0.2567 | BH2: 0.5016 | BI2: 0.3974 | BJ2: 2 | BK2: 36.9 | BL2: 32.03 | BM2: 34.4728 | BN2: 0.5669 | BO2: =IF(M2=N2,0.5,(J2-N2)/(M2-N2)) | BP2: 14.777 | BQ2: 9.736 | BR2: =100*(0.4*MIN(1,MAX(0,((U2*100)-(0.0))/((2.5)-(0.0))))+0.3*MIN(1,MAX(0,((V2)-(0.6))/((1.0)-(0.6))))+0.3*MIN(1,MAX(0,((BP2)-(0.0))/((15.0)-(0.0))))) | BS2: =100*(0.4*MIN(1,MAX(0,((MIN(ABS(AA2),ABS(AB2)))-(0.75))/((0.0)-(0.75))))+0.3*MIN(1,MAX(0,((BN2)-(1.2))/((0.6)-(1.2))))+0.3*BO2) | BT2: =100*(0.5*MIN(1,MAX(0,((AK2)-(1.0))/((4.0)-(1.0))))+0.3*MIN(1,MAX(0,((IF(ISNUMBER(AO2),AO2,0)*100)-(0.0))/((8.0)-(0.0))))+0.2*MIN(1,MAX(0,((IF(ISNUMBER(AP2),AP2,0))-(25.0))/((5.0)-(25.0))))) | BU2: =100*(0.35*MIN(1,MAX(0,((ABS(BF2))-(0.3))/((0.05)-(0.3))))+0.3*MIN(1,MAX(0,((BG2)-(0.0))/((0.3)-(0.0))))+0.25*MIN(1,MAX(0,((BH2)-(0.4))/((0.7)-(0.4))))+0.1*IF(BJ2>=2,1,0.5)) | BV2: =0.25*BR2+0.25*BS2+0.2*BT2+0.3*BU2 | BW2: 全部通過
A3: 1 | B3: 2 | C3: SEI | D3: Solaris Energy Infrastructure Inc. | E3: NYSE | F3: 非必需消費 | G3: Oil and Gas Field Machinery | H3: 5.45 | I3: 中型 | J3: 74.93 | K3: 71.38 | L3: =J3/K3-1 | M3: 75.46 | N3: 72.19 | O3: 2870200 | P3: 2853615 | Q3: =O3/P3 | R3: 70.3182 | S3: 66.7953 | T3: 64.0582 | U3: =S3/T3-1 | V3: 1 | W3: =J3/R3-1 | X3: =J3/S3-1 | Y3: 4.0979 | Z3: =Y3/J3 | AA3: =(J3-R3)/Y3 | AB3: =(J3-S3)/Y3 | AC3: =IF(ABS(AA3)<=ABS(AB3),"9EMA","21EMA") | AD3: 9EMA | AE3: 持續在上方 | AI3: 2026-09-09 | AJ3: 17 | AK3: 3 | AL3: 2026-09-23 | AM3: 64.23 | AN3: 60.59 | AO3: =IF(ISNUMBER(AN3),AM3/AN3-1,"") | AP3: 7 | AQ3: =IF(ISNUMBER(AM3),J3/AM3-1,"") | AR3: 74.93 | AS3: =J3/AR3-1 | AT3: 3.5038 | AU3: 2.956 | AV3: 2.8191 | AW3: =AU3-AV3 | AX3: 0.5477 | AY3: 0.3936 | AZ3: 0.4351 | BA3: 深綠 | BB3: 淺綠→深綠 | BC3: 0 | BD3: 淺綠 淺綠 淺綠 淺綠 淺綠 淺綠 淺綠 深綠 | BE3: 上傾收窄（楔形） | BF3: 0.238 | BG3: 1.5653 | BH3: 0.6124 | BI3: 0.5972 | BJ3: 1 | BK3: 75.46 | BL3: 47.81 | BM3: 64.7421 | BN3: 1.1418 | BO3: =IF(M3=N3,0.5,(J3-N3)/(M3-N3)) | BP3: 47.035 | BQ3: 41.994 | BR3: =100*(0.4*MIN(1,MAX(0,((U3*100)-(0.0))/((2.5)-(0.0))))+0.3*MIN(1,MAX(0,((V3)-(0.6))/((1.0)-(0.6))))+0.3*MIN(1,MAX(0,((BP3)-(0.0))/((15.0)-(0.0))))) | BS3: =100*(0.4*MIN(1,MAX(0,((MIN(ABS(AA3),ABS(AB3)))-(0.75))/((0.0)-(0.75))))+0.3*MIN(1,MAX(0,((BN3)-(1.2))/((0.6)-(1.2))))+0.3*BO3) | BT3: =100*(0.5*MIN(1,MAX(0,((AK3)-(1.0))/((4.0)-(1.0))))+0.3*MIN(1,MAX(0,((IF(ISNUMBER(AO3),AO3,0)*100)-(0.0))/((8.0)-(0.0))))+0.2*MIN(1,MAX(0,((IF(ISNUMBER(AP3),AP3,0))-(25.0))/((5.0)-(25.0))))) | BU3: =100*(0.35*MIN(1,MAX(0,((ABS(BF3))-(0.3))/((0.05)-(0.3))))+0.3*MIN(1,MAX(0,((BG3)-(0.0))/((0.3)-(0.0))))+0.25*MIN(1,MAX(0,((BH3)-(0.4))/((0.7)-(0.4))))+0.1*IF(BJ3>=2,1,0.5)) | BV3: =0.25*BR3+0.25*BS3+0.2*BT3+0.3*BU3 | BW3: 全部通過
A4: 1 | B4: 3 | C4: DDD | D4: 3D Systems Corporation | E4: NYSE | F4: 科技 | G4: Computer Software: Prepackaged Software | H4: 0.598 | I4: 小型 | J4: 3.78 | K4: 3.54 | L4: =J4/K4-1 | M4: 3.78 | N4: 3.57 | O4: 3224800 | P4: 2286085 | Q4: =O4/P4 | R4: 3.569 | S4: 3.4791 | T4: 3.4037 | U4: =S4/T4-1 | V4: 1 | W4: =J4/R4-1 | X4: =J4/S4-1 | Y4: 0.2031 | Z4: =Y4/J4 | AA4: =(J4-R4)/Y4 | AB4: =(J4-S4)/Y4 | AC4: =IF(ABS(AA4)<=ABS(AB4),"9EMA","21EMA") | AD4: 9+21EMA | AE4: 持續在上方 | AI4: 2026-09-17 | AJ4: 11 | AK4: 2 | AL4: 2026-09-25 | AM4: 3.35 | AN4: 3.1 | AO4: =IF(ISNUMBER(AN4),AM4/AN4-1,"") | AP4: 5 | AQ4: =IF(ISNUMBER(AM4),J4/AM4-1,"") | AR4: 3.78 | AS4: =J4/AR4-1 | AT4: 0.0883 | AU4: 0.0669 | AV4: 0.0616 | AW4: =AU4-AV4 | AX4: 0.0214 | AY4: 0.0094 | AZ4: 0.013 | BA4: 深綠 | BB4: 淺綠→深綠 | BC4: 0 | BD4: 淺綠 淺綠 深綠 淺綠 淺綠 深綠 淺綠 深綠 | BE4: 上傾收窄（楔形） | BF4: 0.3118 | BG4: 0.9448 | BH4: 0.5228 | BI4: 0.493 | BJ4: 2 | BK4: 3.78 | BL4: 3.1 | BM4: 3.4555 | BN4: 0.92 | BO4: =IF(M4=N4,0.5,(J4-N4)/(M4-N4)) | BP4: 16.875 | BQ4: 11.834 | BR4: =100*(0.4*MIN(1,MAX(0,((U4*100)-(0.0))/((2.5)-(0.0))))+0.3*MIN(1,MAX(0,((V4)-(0.6))/((1.0)-(0.6))))+0.3*MIN(1,MAX(0,((BP4)-(0.0))/((15.0)-(0.0))))) | BS4: =100*(0.4*MIN(1,MAX(0,((MIN(ABS(AA4),ABS(AB4)))-(0.75))/((0.0)-(0.75))))+0.3*MIN(1,MAX(0,((BN4)-(1.2))/((0.6)-(1.2))))+0.3*BO4) | BT4: =100*(0.5*MIN(1,MAX(0,((AK4)-(1.0))/((4.0)-(1.0))))+0.3*MIN(1,MAX(0,((IF(ISNUMBER(AO4),AO4,0)*100)-(0.0))/((8.0)-(0.0))))+0.2*MIN(1,MAX(0,((IF(ISNUMBER(AP4),AP4,0))-(25.0))/((5.0)-(25.0))))) | BU4: =100*(0.35*MIN(1,MAX(0,((ABS(BF4))-(0.3))/((0.05)-(0.3))))+0.3*MIN(1,MAX(0,((BG4)-(0.0))/((0.3)-(0.0))))+0.25*MIN(1,MAX(0,((BH4)-(0.4))/((0.7)-(0.4))))+0.1*IF(BJ4>=2,1,0.5)) | BV4: =0.25*BR4+0.25*BS4+0.2*BT4+0.3*BU4 | BW4: 全部通過
A5: 1 | B5: 4 | C5: FFIV | D5: F5 Inc. | E5: NASDAQ | F5: 電訊 | G5: Computer Communications Equipment | H5: 25.209 | I5: 大型 | J5: 454.04 | K5: 443.68 | L5: =J5/K5-1 | M5: 459.88 | N5: 446.13 | O5: 633200 | P5: 563155 | Q5: =O5/P5 | R5: 443.1567 | S5: 431.9116 | T5: 424.4576 | U5: =S5/T5-1 | V5: 1 | W5: =J5/R5-1 | X5: =J5/S5-1 | Y5: 13.6727 | Z5: =Y5/J5 | AA5: =(J5-R5)/Y5 | AB5: =(J5-S5)/Y5 | AC5: =IF(ABS(AA5)<=ABS(AB5),"9EMA","21EMA") | AD5: 9EMA | AE5: 持續在上方 | AH5: ✓ | AI5: 2026-09-11 | AJ5: 15 | AK5: 3 | AL5: 2026-09-29 | AM5: 428.93 | AN5: 384.95 | AO5: =IF(ISNUMBER(AN5),AM5/AN5-1,"") | AP5: 3 | AQ5: =IF(ISNUMBER(AM5),J5/AM5-1,"") | AR5: 455.99 | AS5: =J5/AR5-1 | AT5: 11.906 | AU5: 11.0672 | AV5: 10.8575 | AW5: =AU5-AV5 | AX5: 0.8388 | AY5: 0.5942 | AZ5: 1.0512 | BA5: 深綠 | BB5: 淺綠→深綠 | BC5: 0 | BD5: 深綠 淺綠 淺綠 淺綠 淺綠 淺綠 淺綠 深綠 | BE5: 上升通道 | BF5: 0.6261 | BG5: 0.5381 | BH5: 0.5245 | BI5: 0.5385 | BJ5: 3 | BK5: 462 | BL5: 384.95 | BM5: 425.36 | BN5: 0.9017 | BO5: =IF(M5=N5,0.5,(J5-N5)/(M5-N5)) | BP5: 21.14 | BQ5: 16.099 | BR5: =100*(0.4*MIN(1,MAX(0,((U5*100)-(0.0))/((2.5)-(0.0))))+0.3*MIN(1,MAX(0,((V5)-(0.6))/((1.0)-(0.6))))+0.3*MIN(1,MAX(0,((BP5)-(0.0))/((15.0)-(0.0))))) | BS5: =100*(0.4*MIN(1,MAX(0,((MIN(ABS(AA5),ABS(AB5)))-(0.75))/((0.0)-(0.75))))+0.3*MIN(1,MAX(0,((BN5)-(1.2))/((0.6)-(1.2))))+0.3*BO5) | BT5: =100*(0.5*MIN(1,MAX(0,((AK5)-(1.0))/((4.0)-(1.0))))+0.3*MIN(1,MAX(0,((IF(ISNUMBER(AO5),AO5,0)*100)-(0.0))/((8.0)-(0.0))))+0.2*MIN(1,MAX(0,((IF(ISNUMBER(AP5),AP5,0))-(25.0))/((5.0)-(25.0))))) | BU5: =100*(0.35*MIN(1,MAX(0,((ABS(BF5))-(0.3))/((0.05)-(0.3))))+0.3*MIN(1,MAX(0,((BG5)-(0.0))/((0.3)-(0.0))))+0.25*MIN(1,MAX(0,((BH5)-(0.4))/((0.7)-(0.4))))+0.1*IF(BJ5>=2,1,0.5)) | BV5: =0.25*BR5+0.25*BS5+0.2*BT5+0.3*BU5 | BW5: 全部通過
A6: 1 | B6: 5 | C6: ANET | D6: Arista Networks Inc. | E6: NYSE | F6: 電訊 | G6: Computer Communications Equipment | H6: 256.773 | I6: 大型 | J6: 207.35 | K6: 204.49 | L6: =J6/K6-1 | M6: 208.632 | N6: 204.66 | O6: 4145600 | P6: 4783005 | Q6: =O6/P6 | R6: 204.0727 | S6: 200.6033 | T6: 198.0568 | U6: =S6/T6-1 | V6: 1 | W6: =J6/R6-1 | X6: =J6/S6-1 | Y6: 6.86 | Z6: =Y6/J6 | AA6: =(J6-R6)/Y6 | AB6: =(J6-S6)/Y6 | AC6: =IF(ABS(AA6)<=ABS(AB6),"9EMA","21EMA") | AD6: 9+21EMA | AE6: 持續在上方 | AH6: ✓ | AI6: 2026-07-31 | AJ6: 44 | AK6: 3 | AL6: 2026-09-24 | AM6: 198.757 | AN6: 186.11 | AO6: =IF(ISNUMBER(AN6),AM6/AN6-1,"") | AP6: 6 | AQ6: =IF(ISNUMBER(AM6),J6/AM6-1,"") | AR6: 207.35 | AS6: =J6/AR6-1 | AT6: 3.8867 | AU6: 3.7117 | AV6: 3.668 | AW6: =AU6-AV6 | AX6: 0.175 | AY6: 0.1031 | AZ6: 0.2175 | BA6: 深綠 | BB6: 淺綠→深綠 | BC6: 0 | BD6: 淺綠 深綠 深綠 淺綠 淺綠 淺綠 淺綠 深綠 | BE6: 上傾收窄（楔形） | BF6: 0.4201 | BG6: 0.611 | BH6: 0.553 | BI6: 0.5724 | BJ6: 1 | BK6: 212 | BL6: 181.27 | BM6: 198.2633 | BN6: 0.9529 | BO6: =IF(M6=N6,0.5,(J6-N6)/(M6-N6)) | BP6: 16.46 | BQ6: 11.419 | BR6: =100*(0.4*MIN(1,MAX(0,((U6*100)-(0.0))/((2.5)-(0.0))))+0.3*MIN(1,MAX(0,((V6)-(0.6))/((1.0)-(0.6))))+0.3*MIN(1,MAX(0,((BP6)-(0.0))/((15.0)-(0.0))))) | BS6: =100*(0.4*MIN(1,MAX(0,((MIN(ABS(AA6),ABS(AB6)))-(0.75))/((0.0)-(0.75))))+0.3*MIN(1,MAX(0,((BN6)-(1.2))/((0.6)-(1.2))))+0.3*BO6) | BT6: =100*(0.5*MIN(1,MAX(0,((AK6)-(1.0))/((4.0)-(1.0))))+0.3*MIN(1,MAX(0,((IF(ISNUMBER(AO6),AO6,0)*100)-(0.0))/((8.0)-(0.0))))+0.2*MIN(1,MAX(0,((IF(ISNUMBER(AP6),AP6,0))-(25.0))/((5.0)-(25.0))))) | BU6: =100*(0.35*MIN(1,MAX(0,((ABS(BF6))-(0.3))/((0.05)-(0.3))))+0.3*MIN(1,MAX(0,((BG6)-(0.0))/((0.3)-(0.0))))+0.25*MIN(1,MAX(0,((BH6)-(0.4))/((0.7)-(0.4))))+0.1*IF(BJ6>=2,1,0.5)) | BV6: =0.25*BR6+0.25*BS6+0.2*BT6+0.3*BU6 | BW6: 全部通過
A7: 1 | B7: 6 | C7: FTNT | D7: Fortinet Inc. | E7: NASDAQ | F7: 科技 | G7: Computer peripheral equipment | H7: 131.159 | I7: 大型 | J7: 180.95 | K7: 178.72 | L7: =J7/K7-1 | M7: 183.09 | N7: 180.04 | O7: 3412200 | P7: 3976270 | Q7: =O7/P7 | R7: 176.8402 | S7: 172.0605 | T7: 168.2061 | U7: =S7/T7-1 | V7: 1 | W7: =J7/R7-1 | X7: =J7/S7-1 | Y7: 6.3068 | Z7: =Y7/J7 | AA7: =(J7-R7)/Y7 | AB7: =(J7-S7)/Y7 | AC7: =IF(ABS(AA7)<=ABS(AB7),"9EMA","21EMA") | AD7: 9EMA | AE7: 持續在上方 | AH7: ✓ | AI7: 2026-09-14 | AJ7: 14 | AK7: 4 | AL7: 2026-09-28 | AM7: 169.56 | AN7: 166.09 | AO7: =IF(ISNUMBER(AN7),AM7/AN7-1,"") | AP7: 4 | AQ7: =IF(ISNUMBER(AM7),J7/AM7-1,"") | AR7: 180.95 | AS7: =J7/AR7-1 | AT7: 4.9944 | AU7: 4.4384 | AV7: 4.2994 | AW7: =AU7-AV7 | AX7: 0.5559 | AY7: 0.5413 | AZ7: 0.6371 | BA7: 深綠 | BB7: 淺綠→深綠 | BC7: 0 | BD7: 深綠 淺綠 淺綠 淺綠 淺綠 淺綠 淺綠 深綠 | BE7: 上升通道 | BF7: 0.5825 | BG7: 0.5947 | BH7: 0.5457 | BI7: 0.5428 | BJ7: 3 | BK7: 183.09 | BL7: 151.8 | BM7: 168.8756 | BN7: 0.9929 | BO7: =IF(M7=N7,0.5,(J7-N7)/(M7-N7)) | BP7: 22.13 | BQ7: 17.089 | BR7: =100*(0.4*MIN(1,MAX(0,((U7*100)-(0.0))/((2.5)-(0.0))))+0.3*MIN(1,MAX(0,((V7)-(0.6))/((1.0)-(0.6))))+0.3*MIN(1,MAX(0,((BP7)-(0.0))/((15.0)-(0.0))))) | BS7: =100*(0.4*MIN(1,MAX(0,((MIN(ABS(AA7),ABS(AB7)))-(0.75))/((0.0)-(0.75))))+0.3*MIN(1,MAX(0,((BN7)-(1.2))/((0.6)-(1.2))))+0.3*BO7) | BT7: =100*(0.5*MIN(1,MAX(0,((AK7)-(1.0))/((4.0)-(1.0))))+0.3*MIN(1,MAX(0,((IF(ISNUMBER(AO7),AO7,0)*100)-(0.0))/((8.0)-(0.0))))+0.2*MIN(1,MAX(0,((IF(ISNUMBER(AP7),AP7,0))-(25.0))/((5.0)-(25.0))))) | BU7: =100*(0.35*MIN(1,MAX(0,((ABS(BF7))-(0.3))/((0.05)-(0.3))))+0.3*MIN(1,MAX(0,((BG7)-(0.0))/((0.3)-(0.0))))+0.25*MIN(1,MAX(0,((BH7)-(0.4))/((0.7)-(0.4))))+0.1*IF(BJ7>=2,1,0.5)) | BV7: =0.25*BR7+0.25*BS7+0.2*BT7+0.3*BU7 | BW7: 全部通過
A8: 1 | B8: 7 | C8: PANW | D8: Palo Alto Networks Inc. | E8: NASDAQ | F8: 科技 | G8: Computer peripheral equipment | H8: 325 | I8: 大型 | J8: 403.24 | K8: 396.25 | L8: =J8/K8-1 | M8: 409.5 | N8: 399.95 | O8: 4904700 | P8: 6269560 | Q8: =O8/P8 | R8: 389.6546 | S8: 377.5477 | T8: 366.2564 | U8: =S8/T8-1 | V8: 1 | W8: =J8/R8-1 | X8: =J8/S8-1 | Y8: 17.2522 | Z8: =Y8/J8 | AA8: =(J8-R8)/Y8 | AB8: =(J8-S8)/Y8 | AC8: =IF(ABS(AA8)<=ABS(AB8),"9EMA","21EMA") | AD8: 9EMA | AE8: 持續在上方 | AI8: 2026-09-15 | AJ8: 13 | AK8: 3 | AL8: 2026-09-28 | AM8: 367.27 | AN8: 356 | AO8: =IF(ISNUMBER(AN8),AM8/AN8-1,"") | AP8: 4 | AQ8: =IF(ISNUMBER(AM8),J8/AM8-1,"") | AR8: 403.24 | AS8: =J8/AR8-1 | AT8: 11.6713 | AU8: 8.7792 | AV8: 8.0561 | AW8: =AU8-AV8 | AX8: 2.8921 | AY8: 2.7769 | AZ8: 2.9553 | BA8: 深綠 | BB8: 淺綠→深綠 | BC8: 0 | BD8: 深綠 深綠 淺綠 深綠 淺綠 深綠 淺綠 深綠 | BE8: 上升通道 | BF8: 0.6537 | BG8: 0.683 | BH8: 0.5102 | BI8: 0.5065 | BJ8: 2 | BK8: 409.5 | BL8: 321.39 | BM8: 366.3431 | BN8: 0.7854 | BO8: =IF(M8=N8,0.5,(J8-N8)/(M8-N8)) | BP8: 27.8 | BQ8: 22.759 | BR8: =100*(0.4*MIN(1,MAX(0,((U8*100)-(0.0))/((2.5)-(0.0))))+0.3*MIN(1,MAX(0,((V8)-(0.6))/((1.0)-(0.6))))+0.3*MIN(1,MAX(0,((BP8)-(0.0))/((15.0)-(0.0))))) | BS8: =100*(0.4*MIN(1,MAX(0,((MIN(ABS(AA8),ABS(AB8)))-(0.75))/((0.0)-(0.75))))+0.3*MIN(1,MAX(0,((BN8)-(1.2))/((0.6)-(1.2))))+0.3*BO8) | BT8: =100*(0.5*MIN(1,MAX(0,((AK8)-(1.0))/((4.0)-(1.0))))+0.3*MIN(1,MAX(0,((IF(ISNUMBER(AO8),AO8,0)*100)-(0.0))/((8.0)-(0.0))))+0.2*MIN(1,MAX(0,((IF(ISNUMBER(AP8),AP8,0))-(25.0))/((5.0)-(25.0))))) | BU8: =100*(0.35*MIN(1,MAX(0,((ABS(BF8))-(0.3))/((0.05)-(0.3))))+0.3*MIN(1,MAX(0,((BG8)-(0.0))/((0.3)-(0.0))))+0.25*MIN(1,MAX(0,((BH8)-(0.4))/((0.7)-(0.4))))+0.1*IF(BJ8>=2,1,0.5)) | BV8: =0.25*BR8+0.25*BS8+0.2*BT8+0.3*BU8 | BW8: 全部通過
A9: 1 | B9: 8 | C9: NEU | D9: NewMarket Corp | E9: NYSE | F9: 工業 | G9: Major Chemicals | H9: 8.254 | I9: 中型 | J9: 924.06 | K9: 921.14 | L9: =J9/K9-1 | M9: 929.74 | N9: 913.15 | O9: 113500 | P9: 121270 | Q9: =O9/P9 | R9: 906.476 | S9: 899.7516 | T9: 891.8104 | U9: =S9/T9-1 | V9: 0.7 | W9: =J9/R9-1 | X9: =J9/S9-1 | Y9: 22.764 | Z9: =Y9/J9 | AA9: =(J9-R9)/Y9 | AB9: =(J9-S9)/Y9 | AC9: =IF(ABS(AA9)<=ABS(AB9),"9EMA","21EMA") | AD9: 9+21EMA | AE9: 剛黃金交叉 | AF9: ✓ | AH9: ✓ | AI9: 2026-09-28 | AJ9: 4 | AK9: 4 | AL9: 2026-09-22 | AM9: 874.71 | AN9: 833.43 | AO9: =IF(ISNUMBER(AN9),AM9/AN9-1,"") | AP9: 8 | AQ9: =IF(ISNUMBER(AM9),J9/AM9-1,"") | AR9: 924.06 | AS9: =J9/AR9-1 | AT9: 6.2616 | AU9: 3.3488 | AV9: 2.6206 | AW9: =AU9-AV9 | AX9: 2.9128 | AY9: 2.0799 | AZ9: 0.8363 | BA9: 深綠 | BB9: 淺綠→深綠 | BC9: 1 | BD9: 淺紅 淺紅 淺紅 深綠 深綠 淺綠 深綠 深綠 | BE9: 上升三角（平頂） | BF9: 0.0163 | BG9: 0.4964 | BH9: 0.5851 | BI9: 0.5102 | BJ9: 3 | BK9: 936.77 | BL9: 833.43 | BM9: 893.8933 | BN9: 0.9945 | BO9: =IF(M9=N9,0.5,(J9-N9)/(M9-N9)) | BP9: 6.681 | BQ9: 1.64 | BR9: =100*(0.4*MIN(1,MAX(0,((U9*100)-(0.0))/((2.5)-(0.0))))+0.3*MIN(1,MAX(0,((V9)-(0.6))/((1.0)-(0.6))))+0.3*MIN(1,MAX(0,((BP9)-(0.0))/((15.0)-(0.0))))) | BS9: =100*(0.4*MIN(1,MAX(0,((MIN(ABS(AA9),ABS(AB9)))-(0.75))/((0.0)-(0.75))))+0.3*MIN(1,MAX(0,((BN9)-(1.2))/((0.6)-(1.2))))+0.3*BO9) | BT9: =100*(0.5*MIN(1,MAX(0,((AK9)-(1.0))/((4.0)-(1.0))))+0.3*MIN(1,MAX(0,((IF(ISNUMBER(AO9),AO9,0)*100)-(0.0))/((8.0)-(0.0))))+0.2*MIN(1,MAX(0,((IF(ISNUMBER(AP9),AP9,0))-(25.0))/((5.0)-(25.0))))) | BU9: =100*(0.35*MIN(1,MAX(0,((ABS(BF9))-(0.3))/((0.05)-(0.3))))+0.3*MIN(1,MAX(0,((BG9)-(0.0))/((0.3)-(0.0))))+0.25*MIN(1,MAX(0,((BH9)-(0.4))/((0.7)-(0.4))))+0.1*IF(BJ9>=2,1,0.5)) | BV9: =0.25*BR9+0.25*BS9+0.2*BT9+0.3*BU9 | BW9: 全部通過
A10: 1 | B10: 9 | C10: HNGE | D10: Hinge Health Inc. | E10: NYSE | F10: 科技 | G10: EDP Services | H10: 7.847 | I10: 中型 | J10: 97.67 | K10: 97.94 | L10: =J10/K10-1 | M10: 99.73 | N10: 96.95 | O10: 975300 | P10: 1797980 | Q10: =O10/P10 | R10: 95.6008 | S10: 93.6582 | T10: 92.0176 | U10: =S10/T10-1 | V10: 1 | W10: =J10/R10-1 | X10: =J10/S10-1 | Y10: 4.0328 | Z10: =Y10/J10 | AA10: =(J10-R10)/Y10 | AB10: =(J10-S10)/Y10 | AC10: =IF(ABS(AA10)<=ABS(AB10),"9EMA","21EMA") | AD10: 9EMA | AE10: 持續在上方 | AH10: ✓ | AI10: 2026-08-07 | AJ10: 39 | AK10: 5 | AL10: 2026-09-23 | AM10: 89.75 | AN10: 86.29 | AO10: =IF(ISNUMBER(AN10),AM10/AN10-1,"") | AP10: 7 | AQ10: =IF(ISNUMBER(AM10),J10/AM10-1,"") | AR10: 97.94 | AS10: =J10/AR10-1 | AT10: 2.1522 | AU10: 1.9662 | AV10: 1.9197 | AW10: =AU10-AV10 | AX10: 0.186 | AY10: 0.1384 | AZ10: -0.0045 | BA10: 深綠 | BB10: 深紅→淺紅 | BC10: 3 | BD10: 深紅 深紅 淺紅 深紅 淺紅 淺紅 深綠 深綠 | BE10: 上升通道 | BF10: 0.2509 | BG10: 0.256 | BH10: 0.5031 | BI10: 0.5131 | BJ10: 3 | BK10: 99.73 | BL10: 85.75 | BM10: 92.7834 | BN10: 0.9903 | BO10: =IF(M10=N10,0.5,(J10-N10)/(M10-N10)) | BP10: 11.377 | BQ10: 6.336 | BR10: =100*(0.4*MIN(1,MAX(0,((U10*100)-(0.0))/((2.5)-(0.0))))+0.3*MIN(1,MAX(0,((V10)-(0.6))/((1.0)-(0.6))))+0.3*MIN(1,MAX(0,((BP10)-(0.0))/((15.0)-(0.0))))) | BS10: =100*(0.4*MIN(1,MAX(0,((MIN(ABS(AA10),ABS(AB10)))-(0.75))/((0.0)-(0.75))))+0.3*MIN(1,MAX(0,((BN10)-(1.2))/((0.6)-(1.2))))+0.3*BO10) | BT10: =100*(0.5*MIN(1,MAX(0,((AK10)-(1.0))/((4.0)-(1.0))))+0.3*MIN(1,MAX(0,((IF(ISNUMBER(AO10),AO10,0)*100)-(0.0))/((8.0)-(0.0))))+0.2*MIN(1,MAX(0,((IF(ISNUMBER(AP10),AP10,0))-(25.0))/((5.0)-(25.0))))) | BU10: =100*(0.35*MIN(1,MAX(0,((ABS(BF10))-(0.3))/((0.05)-(0.3))))+0.3*MIN(1,MAX(0,((BG10)-(0.0))/((0.3)-(0.0))))+0.25*MIN(1,MAX(0,((BH10)-(0.4))/((0.7)-(0.4))))+0.1*IF(BJ10>=2,1,0.5)) | BV10: =0.25*BR10+0.25*BS10+0.2*BT10+0.3*BU10 | BW10: 全部通過
A11: 1 | B11: 10 | C11: QLYS | D11: Qualys Inc. | E11: NASDAQ | F11: 科技 | G11: Computer Software: Prepackaged Software | H11: 6.476 | I11: 中型 | J11: 193 | K11: 187.43 | L11: =J11/K11-1 | M11: 195.4 | N11: 188.87 | O11: 477400 | P11: 728015 | Q11: =O11/P11 | R11: 183.5015 | S11: 179.8278 | T11: 176.7577 | U11: =S11/T11-1 | V11: 0.8 | W11: =J11/R11-1 | X11: =J11/S11-1 | Y11: 9.0911 | Z11: =Y11/J11 | AA11: =(J11-R11)/Y11 | AB11: =(J11-S11)/Y11 | AC11: =IF(ABS(AA11)<=ABS(AB11),"9EMA","21EMA") | AD11: 9+21EMA | AE11: 持續在上方 | AI11: 2026-09-16 | AJ11: 12 | AK11: 2 | AL11: 2026-09-28 | AM11: 168.06 | AN11: 149.13 | AO11: =IF(ISNUMBER(AN11),AM11/AN11-1,"") | AP11: 4 | AQ11: =IF(ISNUMBER(AM11),J11/AM11-1,"") | AR11: 193 | AS11: =J11/AR11-1 | AT11: 3.5893 | AU11: 2.4661 | AV11: 2.1853 | AW11: =AU11-AV11 | AX11: 1.1232 | AY11: 0.5936 | AZ11: 0.2344 | BA11: 深綠 | BB11: 深紅→淺紅 | BC11: 3 | BD11: 深綠 深綠 深紅 深紅 淺紅 深綠 深綠 深綠 | BE11: 上傾收窄（楔形） | BF11: 0.2221 | BG11: 0.8917 | BH11: 0.5866 | BI11: 0.6085 | BJ11: 1 | BK11: 195.4 | BL11: 149.13 | BM11: 176.2734 | BN11: 0.8695 | BO11: =IF(M11=N11,0.5,(J11-N11)/(M11-N11)) | BP11: 18.019 | BQ11: 12.978 | BR11: =100*(0.4*MIN(1,MAX(0,((U11*100)-(0.0))/((2.5)-(0.0))))+0.3*MIN(1,MAX(0,((V11)-(0.6))/((1.0)-(0.6))))+0.3*MIN(1,MAX(0,((BP11)-(0.0))/((15.0)-(0.0))))) | BS11: =100*(0.4*MIN(1,MAX(0,((MIN(ABS(AA11),ABS(AB11)))-(0.75))/((0.0)-(0.75))))+0.3*MIN(1,MAX(0,((BN11)-(1.2))/((0.6)-(1.2))))+0.3*BO11) | BT11: =100*(0.5*MIN(1,MAX(0,((AK11)-(1.0))/((4.0)-(1.0))))+0.3*MIN(1,MAX(0,((IF(ISNUMBER(AO11),AO11,0)*100)-(0.0))/((8.0)-(0.0))))+0.2*MIN(1,MAX(0,((IF(ISNUMBER(AP11),AP11,0))-(25.0))/((5.0)-(25.0))))) | BU11: =100*(0.35*MIN(1,MAX(0,((ABS(BF11))-(0.3))/((0.05)-(0.3))))+0.3*MIN(1,MAX(0,((BG11)-(0.0))/((0.3)-(0.0))))+0.25*MIN(1,MAX(0,((BH11)-(0.4))/((0.7)-(0.4))))+0.1*IF(BJ11>=2,1,0.5)) | BV11: =0.25*BR11+0.25*BS11+0.2*BT11+0.3*BU11 | BW11: 全部通過
A12: 1 | B12: 11 | C12: CNXN | D12: PC Connection Inc. | E12: NASDAQ | F12: 非必需消費 | G12: Catalog/Specialty Distribution | H12: 2.277 | I12: 中型 | J12: 92.38 | K12: 92.57 | L12: =J12/K12-1 | M12: 93.89 | N12: 92.27 | O12: 124200 | P12: 146260 | Q12: =O12/P12 | R12: 89.9544 | S12: 87.4047 | T12: 85.1881 | U12: =S12/T12-1 | V12: 1 | W12: =J12/R12-1 | X12: =J12/S12-1 | Y12: 2.296 | Z12: =Y12/J12 | AA12: =(J12-R12)/Y12 | AB12: =(J12-S12)/Y12 | AC12: =IF(ABS(AA12)<=ABS(AB12),"9EMA","21EMA") | AD12: 9EMA | AE12: 持續在上方 | AH12: ✓ | AI12: 2026-09-03 | AJ12: 20 | AK12: 3 | AL12: 2026-09-18 | AM12: 84.11 | AN12: 77.98 | AO12: =IF(ISNUMBER(AN12),AM12/AN12-1,"") | AP12: 10 | AQ12: =IF(ISNUMBER(AM12),J12/AM12-1,"") | AR12: 92.57 | AS12: =J12/AR12-1 | AT12: 2.5942 | AU12: 2.1766 | AV12: 2.0722 | AW12: =AU12-AV12 | AX12: 0.4176 | AY12: 0.4065 | AZ12: 0.3055 | BA12: 深綠 | BB12: 淺綠→深綠 | BC12: 1 | BD12: 深綠 深綠 深綠 淺綠 淺綠 淺綠 深綠 深綠 | BE12: 上升通道 | BF12: 0.5602 | BG12: 0.553 | BH12: 0.5245 | BI12: 0.5159 | BJ12: 2 | BK12: 93.89 | BL12: 77.98 | BM12: 86.3246 | BN12: 0.9912 | BO12: =IF(M12=N12,0.5,(J12-N12)/(M12-N12)) | BP12: 19.133 | BQ12: 14.092 | BR12: =100*(0.4*MIN(1,MAX(0,((U12*100)-(0.0))/((2.5)-(0.0))))+0.3*MIN(1,MAX(0,((V12)-(0.6))/((1.0)-(0.6))))+0.3*MIN(1,MAX(0,((BP12)-(0.0))/((15.0)-(0.0))))) | BS12: =100*(0.4*MIN(1,MAX(0,((MIN(ABS(AA12),ABS(AB12)))-(0.75))/((0.0)-(0.75))))+0.3*MIN(1,MAX(0,((BN12)-(1.2))/((0.6)-(1.2))))+0.3*BO12) | BT12: =100*(0.5*MIN(1,MAX(0,((AK12)-(1.0))/((4.0)-(1.0))))+0.3*MIN(1,MAX(0,((IF(ISNUMBER(AO12),AO12,0)*100)-(0.0))/((8.0)-(0.0))))+0.2*MIN(1,MAX(0,((IF(ISNUMBER(AP12),AP12,0))-(25.0))/((5.0)-(25.0))))) | BU12: =100*(0.35*MIN(1,MAX(0,((ABS(BF12))-(0.3))/((0.05)-(0.3))))+0.3*MIN(1,MAX(0,((BG12)-(0.0))/((0.3)-(0.0))))+0.25*MIN(1,MAX(0,((BH12)-(0.4))/((0.7)-(0.4))))+0.1*IF(BJ12>=2,1,0.5)) | BV12: =0.25*BR12+0.25*BS12+0.2*BT12+0.3*BU12 | BW12: 全部通過
A13: 1 | B13: 12 | C13: CRVL | D13: CorVel Corp. | E13: NASDAQ | F13: 金融 | G13: Specialty Insurers | H13: 3.766 | I13: 中型 | J13: 75.47 | K13: 74.72 | L13: =J13/K13-1 | M13: 76 | N13: 74.37 | O13: 168800 | P13: 224250 | Q13: =O13/P13 | R13: 74.0124 | S13: 72.2092 | T13: 70.7026 | U13: =S13/T13-1 | V13: 1 | W13: =J13/R13-1 | X13: =J13/S13-1 | Y13: 1.7655 | Z13: =Y13/J13 | AA13: =(J13-R13)/Y13 | AB13: =(J13-S13)/Y13 | AC13: =IF(ABS(AA13)<=ABS(AB13),"9EMA","21EMA") | AD13: 9EMA | AE13: 持續在上方 | AH13: ✓ | AI13: 2026-08-06 | AJ13: 40 | AK13: 2 | AL13: 2026-09-18 | AM13: 69.15 | AN13: 65.18 | AO13: =IF(ISNUMBER(AN13),AM13/AN13-1,"") | AP13: 10 | AQ13: =IF(ISNUMBER(AM13),J13/AM13-1,"") | AR13: 75.47 | AS13: =J13/AR13-1 | AT13: 1.9798 | AU13: 1.8442 | AV13: 1.8103 | AW13: =AU13-AV13 | AX13: 0.1356 | AY13: 0.13 | AZ13: 0.1602 | BA13: 深綠 | BB13: 淺綠→深綠 | BC13: 0 | BD13: 深綠 深綠 深綠 淺綠 淺綠 淺綠 淺綠 深綠 | BE13: 上傾收窄（楔形） | BF13: 0.2766 | BG13: 0.7515 | BH13: 0.5653 | BI13: 0.5378 | BJ13: 5 | BK13: 76 | BL13: 65.18 | BM13: 71.2961 | BN13: 1.0296 | BO13: =IF(M13=N13,0.5,(J13-N13)/(M13-N13)) | BP13: 12.258 | BQ13: 7.217 | BR13: =100*(0.4*MIN(1,MAX(0,((U13*100)-(0.0))/((2.5)-(0.0))))+0.3*MIN(1,MAX(0,((V13)-(0.6))/((1.0)-(0.6))))+0.3*MIN(1,MAX(0,((BP13)-(0.0))/((15.0)-(0.0))))) | BS13: =100*(0.4*MIN(1,MAX(0,((MIN(ABS(AA13),ABS(AB13)))-(0.75))/((0.0)-(0.75))))+0.3*MIN(1,MAX(0,((BN13)-(1.2))/((0.6)-(1.2))))+0.3*BO13) | BT13: =100*(0.5*MIN(1,MAX(0,((AK13)-(1.0))/((4.0)-(1.0))))+0.3*MIN(1,MAX(0,((IF(ISNUMBER(AO13),AO13,0)*100)-(0.0))/((8.0)-(0.0))))+0.2*MIN(1,MAX(0,((IF(ISNUMBER(AP13),AP13,0))-(25.0))/((5.0)-(25.0))))) | BU13: =100*(0.35*MIN(1,MAX(0,((ABS(BF13))-(0.3))/((0.05)-(0.3))))+0.3*MIN(1,MAX(0,((BG13)-(0.0))/((0.3)-(0.0))))+0.25*MIN(1,MAX(0,((BH13)-(0.4))/((0.7)-(0.4))))+0.1*IF(BJ13>=2,1,0.5)) | BV13: =0.25*BR13+0.25*BS13+0.2*BT13+0.3*BU13 | BW13: 全部通過
A14: 1 | B14: 13 | C14: NVDA | D14: NVIDIA Corporation | E14: NASDAQ | F14: 科技 | G14: Semiconductors | H14: 5503.958 | I14: 大型 | J14: 233.95 | K14: 230.86 | L14: =J14/K14-1 | M14: 237.88 | N14: 233.6 | O14: 134914600 | P14: 109953295 | Q14: =O14/P14 | R14: 228.2091 | S14: 224.6694 | T14: 221.3392 | U14: =S14/T14-1 | V14: 1 | W14: =J14/R14-1 | X14: =J14/S14-1 | Y14: 5.9101 | Z14: =Y14/J14 | AA14: =(J14-R14)/Y14 | AB14: =(J14-S14)/Y14 | AC14: =IF(ABS(AA14)<=ABS(AB14),"9EMA","21EMA") | AD14: — | AE14: 持續在上方 | AI14: 2026-09-18 | AJ14: 10 | AK14: 2 | AL14: 2026-09-24 | AM14: 221.09 | AN14: 208.93 | AO14: =IF(ISNUMBER(AN14),AM14/AN14-1,"") | AP14: 6 | AQ14: =IF(ISNUMBER(AM14),J14/AM14-1,"") | AR14: 233.95 | AS14: =J14/AR14-1 | AT14: 3.4886 | AU14: 2.6614 | AV14: 2.4546 | AW14: =AU14-AV14 | AX14: 0.8272 | AY14: 0.6141 | AZ14: 0.5017 | BA14: 深綠 | BB14: 淺綠→深綠 | BC14: 2 | BD14: 深綠 淺綠 淺綠 深綠 淺綠 深綠 深綠 深綠 | BE14: 上升三角（平頂） | BF14: -0.0743 | BG14: 0.16 | BH14: 0.5016 | BI14: 0.5433 | BJ14: 2 | BK14: 237.88 | BL14: 208.93 | BM14: 223.4515 | BN14: 0.79 | BO14: =IF(M14=N14,0.5,(J14-N14)/(M14-N14)) | BP14: 9.292 | BQ14: 4.251 | BR14: =100*(0.4*MIN(1,MAX(0,((U14*100)-(0.0))/((2.5)-(0.0))))+0.3*MIN(1,MAX(0,((V14)-(0.6))/((1.0)-(0.6))))+0.3*MIN(1,MAX(0,((BP14)-(0.0))/((15.0)-(0.0))))) | BS14: =100*(0.4*MIN(1,MAX(0,((MIN(ABS(AA14),ABS(AB14)))-(0.75))/((0.0)-(0.75))))+0.3*MIN(1,MAX(0,((BN14)-(1.2))/((0.6)-(1.2))))+0.3*BO14) | BT14: =100*(0.5*MIN(1,MAX(0,((AK14)-(1.0))/((4.0)-(1.0))))+0.3*MIN(1,MAX(0,((IF(ISNUMBER(AO14),AO14,0)*100)-(0.0))/((8.0)-(0.0))))+0.2*MIN(1,MAX(0,((IF(ISNUMBER(AP14),AP14,0))-(25.0))/((5.0)-(25.0))))) | BU14: =100*(0.35*MIN(1,MAX(0,((ABS(BF14))-(0.3))/((0.05)-(0.3))))+0.3*MIN(1,MAX(0,((BG14)-(0.0))/((0.3)-(0.0))))+0.25*MIN(1,MAX(0,((BH14)-(0.4))/((0.7)-(0.4))))+0.1*IF(BJ14>=2,1,0.5)) | BV14: =0.25*BR14+0.25*BS14+0.2*BT14+0.3*BU14 | BW14: 全部通過
A15: 1 | B15: 14 | C15: LEGH | D15: Legacy Housing Corporation | E15: NASDAQ | F15: 非必需消費 | G15: Homebuilding | H15: 0.682 | I15: 小型 | J15: 29.35 | K15: 29.19 | L15: =J15/K15-1 | M15: 29.87 | N15: 29.05 | O15: 53800 | P15: 77855 | Q15: =O15/P15 | R15: 28.9334 | S15: 28.5714 | T15: 28.2677 | U15: =S15/T15-1 | V15: 1 | W15: =J15/R15-1 | X15: =J15/S15-1 | Y15: 0.9189 | Z15: =Y15/J15 | AA15: =(J15-R15)/Y15 | AB15: =(J15-S15)/Y15 | AC15: =IF(ABS(AA15)<=ABS(AB15),"9EMA","21EMA") | AD15: 9+21EMA | AE15: 持續在上方 | AH15: ✓ | AI15: 2026-09-21 | AJ15: 9 | AK15: 2 | AL15: 2026-09-29 | AM15: 28.28 | AN15: 26.37 | AO15: =IF(ISNUMBER(AN15),AM15/AN15-1,"") | AP15: 3 | AQ15: =IF(ISNUMBER(AM15),J15/AM15-1,"") | AR15: 29.35 | AS15: =J15/AR15-1 | AT15: 0.3552 | AU15: 0.2682 | AV15: 0.2465 | AW15: =AU15-AV15 | AX15: 0.0869 | AY15: 0.0829 | AZ15: 0.0822 | BA15: 深綠 | BB15: 淺綠→深綠 | BC15: 1 | BD15: 深綠 深綠 深綠 淺綠 淺綠 淺綠 深綠 深綠 | BE15: 上傾擴張 | BF15: 0.3672 | BG15: 0.2189 | BH15: 0.5591 | BI15: 0.5433 | BJ15: 4 | BK15: 29.87 | BL15: 26.37 | BM15: 28.327 | BN15: 0.797 | BO15: =IF(M15=N15,0.5,(J15-N15)/(M15-N15)) | BP15: 10.731 | BQ15: 5.69 | BR15: =100*(0.4*MIN(1,MAX(0,((U15*100)-(0.0))/((2.5)-(0.0))))+0.3*MIN(1,MAX(0,((V15)-(0.6))/((1.0)-(0.6))))+0.3*MIN(1,MAX(0,((BP15)-(0.0))/((15.0)-(0.0))))) | BS15: =100*(0.4*MIN(1,MAX(0,((MIN(ABS(AA15),ABS(AB15)))-(0.75))/((0.0)-(0.75))))+0.3*MIN(1,MAX(0,((BN15)-(1.2))/((0.6)-(1.2))))+0.3*BO15) | BT15: =100*(0.5*MIN(1,MAX(0,((AK15)-(1.0))/((4.0)-(1.0))))+0.3*MIN(1,MAX(0,((IF(ISNUMBER(AO15),AO15,0)*100)-(0.0))/((8.0)-(0.0))))+0.2*MIN(1,MAX(0,((IF(ISNUMBER(AP15),AP15,0))-(25.0))/((5.0)-(25.0))))) | BU15: =100*(0.35*MIN(1,MAX(0,((ABS(BF15))-(0.3))/((0.05)-(0.3))))+0.3*MIN(1,MAX(0,((BG15)-(0.0))/((0.3)-(0.0))))+0.25*MIN(1,MAX(0,((BH15)-(0.4))/((0.7)-(0.4))))+0.1*IF(BJ15>=2,1,0.5)) | BV15: =0.25*BR15+0.25*BS15+0.2*BT15+0.3*BU15 | BW15: 全部通過
A16: 1 | B16: 15 | C16: TENB | D16: Tenable Holdings Inc. | E16: NASDAQ | F16: 科技 | G16: Computer Software: Prepackaged Software | H16: 4.008 | I16: 中型 | J16: 36.85 | K16: 36.11 | L16: =J16/K16-1 | M16: 37.24 | N16: 36.15 | O16: 2044500 | P16: 4744640 | Q16: =O16/P16 | R16: 35.7646 | S16: 35.4596 | T16: 35.2075 | U16: =S16/T16-1 | V16: 0.7 | W16: =J16/R16-1 | X16: =J16/S16-1 | Y16: 2.0802 | Z16: =Y16/J16 | AA16: =(J16-R16)/Y16 | AB16: =(J16-S16)/Y16 | AC16: =IF(ABS(AA16)<=ABS(AB16),"9EMA","21EMA") | AD16: 9+21EMA | AE16: 剛黃金交叉 | AF16: ✓ | AI16: 2026-09-30 | AJ16: 2 | AK16: 2 | AL16: 2026-09-28 | AM16: 32.49 | AN16: 29.97 | AO16: =IF(ISNUMBER(AN16),AM16/AN16-1,"") | AP16: 4 | AQ16: =IF(ISNUMBER(AM16),J16/AM16-1,"") | AR16: 38.09 | AS16: =J16/AR16-1 | AT16: 0.2487 | AU16: 0.1031 | AV16: 0.0667 | AW16: =AU16-AV16 | AX16: 0.1456 | AY16: 0.0792 | AZ16: 0.041 | BA16: 深綠 | BB16: 深紅→淺紅 | BC16: 3 | BD16: 深綠 淺綠 深紅 深紅 淺紅 深綠 深綠 深綠 | BE16: 上升三角（平頂） | BF16: 0.0516 | BG16: 0.0319 | BH16: 0.5809 | BI16: 0.6271 | BJ16: 2 | BK16: 38.89 | BL16: 29.97 | BM16: 35.1516 | BN16: 0.8987 | BO16: =IF(M16=N16,0.5,(J16-N16)/(M16-N16)) | BP16: 12.664 | BQ16: 7.623 | BR16: =100*(0.4*MIN(1,MAX(0,((U16*100)-(0.0))/((2.5)-(0.0))))+0.3*MIN(1,MAX(0,((V16)-(0.6))/((1.0)-(0.6))))+0.3*MIN(1,MAX(0,((BP16)-(0.0))/((15.0)-(0.0))))) | BS16: =100*(0.4*MIN(1,MAX(0,((MIN(ABS(AA16),ABS(AB16)))-(0.75))/((0.0)-(0.75))))+0.3*MIN(1,MAX(0,((BN16)-(1.2))/((0.6)-(1.2))))+0.3*BO16) | BT16: =100*(0.5*MIN(1,MAX(0,((AK16)-(1.0))/((4.0)-(1.0))))+0.3*MIN(1,MAX(0,((IF(ISNUMBER(AO16),AO16,0)*100)-(0.0))/((8.0)-(0.0))))+0.2*MIN(1,MAX(0,((IF(ISNUMBER(AP16),AP16,0))-(25.0))/((5.0)-(25.0))))) | BU16: =100*(0.35*MIN(1,MAX(0,((ABS(BF16))-(0.3))/((0.05)-(0.3))))+0.3*MIN(1,MAX(0,((BG16)-(0.0))/((0.3)-(0.0))))+0.25*MIN(1,MAX(0,((BH16)-(0.4))/((0.7)-(0.4))))+0.1*IF(BJ16>=2,1,0.5)) | BV16: =0.25*BR16+0.25*BS16+0.2*BT16+0.3*BU16 | BW16: 全部通過
A17: 1 | B17: 16 | C17: NHC | D17: National HealthCare Corporation | E17: AMEX | F17: 醫療保健 | G17: Hospital/Nursing Management | H17: 3.438 | I17: 中型 | J17: 227.66 | K17: 223.35 | L17: =J17/K17-1 | M17: 229.53 | N17: 223.8 | O17: 88300 | P17: 106730 | Q17: =O17/P17 | R17: 224.3309 | S17: 224.0502 | T17: 223.9601 | U17: =S17/T17-1 | V17: 0.5 | W17: =J17/R17-1 | X17: =J17/S17-1 | Y17: 6.2622 | Z17: =Y17/J17 | AA17: =(J17-R17)/Y17 | AB17: =(J17-S17)/Y17 | AC17: =IF(ABS(AA17)<=ABS(AB17),"9EMA","21EMA") | AD17: 9+21EMA | AE17: 剛黃金交叉 | AF17: ✓ | AH17: ✓ | AI17: 2026-10-02 | AJ17: 0 | AK17: 4 | AL17: 2026-09-24 | AM17: 219.72 | AN17: 214.15 | AO17: =IF(ISNUMBER(AN17),AM17/AN17-1,"") | AP17: 6 | AQ17: =IF(ISNUMBER(AM17),J17/AM17-1,"") | AR17: 227.76 | AS17: =J17/AR17-1 | AT17: 0.3934 | AU17: 0.3868 | AV17: 0.3851 | AW17: =AU17-AV17 | AX17: 0.0067 | AY17: -0.3081 | AZ17: -0.3512 | BA17: 深綠 | BB17: 深紅→淺紅 | BC17: 1 | BD17: 淺紅 深紅 淺紅 深綠 深紅 深紅 淺紅 深綠 | BE17: 上升三角（平頂） | BF17: -0.0226 | BG17: 0.1439 | BH17: 0.5531 | BI17: 0.5731 | BJ17: 12 | BK17: 230.09 | BL17: 214.15 | BM17: 222.9659 | BN17: 0.8442 | BO17: =IF(M17=N17,0.5,(J17-N17)/(M17-N17)) | BP17: 9.789 | BQ17: 4.748 | BR17: =100*(0.4*MIN(1,MAX(0,((U17*100)-(0.0))/((2.5)-(0.0))))+0.3*MIN(1,MAX(0,((V17)-(0.6))/((1.0)-(0.6))))+0.3*MIN(1,MAX(0,((BP17)-(0.0))/((15.0)-(0.0))))) | BS17: =100*(0.4*MIN(1,MAX(0,((MIN(ABS(AA17),ABS(AB17)))-(0.75))/((0.0)-(0.75))))+0.3*MIN(1,MAX(0,((BN17)-(1.2))/((0.6)-(1.2))))+0.3*BO17) | BT17: =100*(0.5*MIN(1,MAX(0,((AK17)-(1.0))/((4.0)-(1.0))))+0.3*MIN(1,MAX(0,((IF(ISNUMBER(AO17),AO17,0)*100)-(0.0))/((8.0)-(0.0))))+0.2*MIN(1,MAX(0,((IF(ISNUMBER(AP17),AP17,0))-(25.0))/((5.0)-(25.0))))) | BU17: =100*(0.35*MIN(1,MAX(0,((ABS(BF17))-(0.3))/((0.05)-(0.3))))+0.3*MIN(1,MAX(0,((BG17)-(0.0))/((0.3)-(0.0))))+0.25*MIN(1,MAX(0,((BH17)-(0.4))/((0.7)-(0.4))))+0.1*IF(BJ17>=2,1,0.5)) | BV17: =0.25*BR17+0.25*BS17+0.2*BT17+0.3*BU17 | BW17: 全部通過
A18: 1 | B18: 17 | C18: SLAB | D18: Silicon Laboratories Inc. | E18: NASDAQ | F18: 科技 | G18: Semiconductors | H18: 7.393 | I18: 中型 | J18: 222.76 | K18: 222.51 | L18: =J18/K18-1 | M18: 223.5 | N18: 222.24 | O18: 304300 | P18: 281205 | Q18: =O18/P18 | R18: 221.6417 | S18: 220.8472 | T18: 220.2034 | U18: =S18/T18-1 | V18: 1 | W18: =J18/R18-1 | X18: =J18/S18-1 | Y18: 1.0866 | Z18: =Y18/J18 | AA18: =(J18-R18)/Y18 | AB18: =(J18-S18)/Y18 | AC18: =IF(ABS(AA18)<=ABS(AB18),"9EMA","21EMA") | AD18: 9+21EMA | AE18: 持續在上方 | AH18: ✓ | AI18: 2026-08-06 | AJ18: 40 | AK18: 2 | AL18: 2026-09-28 | AM18: 220.78 | AN18: 216.88 | AO18: =IF(ISNUMBER(AN18),AM18/AN18-1,"") | AP18: 4 | AQ18: =IF(ISNUMBER(AM18),J18/AM18-1,"") | AR18: 222.76 | AS18: =J18/AR18-1 | AT18: 0.8013 | AU18: 0.6571 | AV18: 0.6211 | AW18: =AU18-AV18 | AX18: 0.1442 | AY18: 0.1064 | AZ18: 0.0535 | BA18: 深綠 | BB18: 淺綠→深綠 | BC18: 2 | BD18: 淺綠 淺綠 淺綠 淺綠 淺綠 深綠 深綠 深綠 | BE18: 上升三角（平頂） | BF18: -0.0049 | BG18: 0.0704 | BH18: 0.5444 | BI18: 0.4606 | BJ18: 19 | BK18: 223.5 | BL18: 216.88 | BM18: 220.4838 | BN18: 0.4699 | BO18: =IF(M18=N18,0.5,(J18-N18)/(M18-N18)) | BP18: 6.19 | BQ18: 1.149 | BR18: =100*(0.4*MIN(1,MAX(0,((U18*100)-(0.0))/((2.5)-(0.0))))+0.3*MIN(1,MAX(0,((V18)-(0.6))/((1.0)-(0.6))))+0.3*MIN(1,MAX(0,((BP18)-(0.0))/((15.0)-(0.0))))) | BS18: =100*(0.4*MIN(1,MAX(0,((MIN(ABS(AA18),ABS(AB18)))-(0.75))/((0.0)-(0.75))))+0.3*MIN(1,MAX(0,((BN18)-(1.2))/((0.6)-(1.2))))+0.3*BO18) | BT18: =100*(0.5*MIN(1,MAX(0,((AK18)-(1.0))/((4.0)-(1.0))))+0.3*MIN(1,MAX(0,((IF(ISNUMBER(AO18),AO18,0)*100)-(0.0))/((8.0)-(0.0))))+0.2*MIN(1,MAX(0,((IF(ISNUMBER(AP18),AP18,0))-(25.0))/((5.0)-(25.0))))) | BU18: =100*(0.35*MIN(1,MAX(0,((ABS(BF18))-(0.3))/((0.05)-(0.3))))+0.3*MIN(1,MAX(0,((BG18)-(0.0))/((0.3)-(0.0))))+0.25*MIN(1,MAX(0,((BH18)-(0.4))/((0.7)-(0.4))))+0.1*IF(BJ18>=2,1,0.5)) | BV18: =0.25*BR18+0.25*BS18+0.2*BT18+0.3*BU18 | BW18: 全部通過
A19: 1 | B19: 18 | C19: FAST | D19: Fastenal Company | E19: NASDAQ | F19: 非必需消費 | G19: RETAIL: Building Materials | H19: 56.836 | I19: 大型 | J19: 50.75 | K19: 50.23 | L19: =J19/K19-1 | M19: 51.04 | N19: 50.43 | O19: 7156900 | P19: 7019355 | Q19: =O19/P19 | R19: 50.1801 | S19: 49.9633 | T19: 49.8128 | U19: =S19/T19-1 | V19: 0.9 | W19: =J19/R19-1 | X19: =J19/S19-1 | Y19: 0.9691 | Z19: =Y19/J19 | AA19: =(J19-R19)/Y19 | AB19: =(J19-S19)/Y19 | AC19: =IF(ABS(AA19)<=ABS(AB19),"9EMA","21EMA") | AD19: 9+21EMA | AE19: 持續在上方 | AH19: ✓ | AI19: 2026-09-23 | AJ19: 7 | AK19: 3 | AL19: 2026-09-21 | AM19: 48.53 | AN19: 48.06 | AO19: =IF(ISNUMBER(AN19),AM19/AN19-1,"") | AP19: 9 | AQ19: =IF(ISNUMBER(AM19),J19/AM19-1,"") | AR19: 50.99 | AS19: =J19/AR19-1 | AT19: 0.2121 | AU19: 0.1468 | AV19: 0.1305 | AW19: =AU19-AV19 | AX19: 0.0653 | AY19: 0.033 | AZ19: 0.0296 | BA19: 深綠 | BB19: 淺綠→深綠 | BC19: 1 | BD19: 深綠 深綠 淺綠 淺綠 淺綠 淺綠 深綠 深綠 | BE19: 上升三角（平頂） | BF19: 0.0067 | BG19: 0.1437 | BH19: 0.5113 | BI19: 0.5552 | BJ19: 6 | BK19: 51.52 | BL19: 47.65 | BM19: 49.6288 | BN19: 1.3414 | BO19: =IF(M19=N19,0.5,(J19-N19)/(M19-N19)) | BP19: 10.925 | BQ19: 5.884 | BR19: =100*(0.4*MIN(1,MAX(0,((U19*100)-(0.0))/((2.5)-(0.0))))+0.3*MIN(1,MAX(0,((V19)-(0.6))/((1.0)-(0.6))))+0.3*MIN(1,MAX(0,((BP19)-(0.0))/((15.0)-(0.0))))) | BS19: =100*(0.4*MIN(1,MAX(0,((MIN(ABS(AA19),ABS(AB19)))-(0.75))/((0.0)-(0.75))))+0.3*MIN(1,MAX(0,((BN19)-(1.2))/((0.6)-(1.2))))+0.3*BO19) | BT19: =100*(0.5*MIN(1,MAX(0,((AK19)-(1.0))/((4.0)-(1.0))))+0.3*MIN(1,MAX(0,((IF(ISNUMBER(AO19),AO19,0)*100)-(0.0))/((8.0)-(0.0))))+0.2*MIN(1,MAX(0,((IF(ISNUMBER(AP19),AP19,0))-(25.0))/((5.0)-(25.0))))) | BU19: =100*(0.35*MIN(1,MAX(0,((ABS(BF19))-(0.3))/((0.05)-(0.3))))+0.3*MIN(1,MAX(0,((BG19)-(0.0))/((0.3)-(0.0))))+0.25*MIN(1,MAX(0,((BH19)-(0.4))/((0.7)-(0.4))))+0.1*IF(BJ19>=2,1,0.5)) | BV19: =0.25*BR19+0.25*BS19+0.2*BT19+0.3*BU19 | BW19: 全部通過
A20: 1 | B20: 19 | C20: STRL | D20: Sterling Infrastructure Inc. | E20: NASDAQ | F20: 工業 | G20: Military/Government/Technical | H20: 15.043 | I20: 大型 | J20: 533.42 | K20: 505.12 | L20: =J20/K20-1 | M20: 537.01 | N20: 513.87 | O20: 606100 | P20: 536050 | Q20: =O20/P20 | R20: 509.023 | S20: 506.9403 | T20: 506.2181 | U20: =S20/T20-1 | V20: 0.7 | W20: =J20/R20-1 | X20: =J20/S20-1 | Y20: 26.4427 | Z20: =Y20/J20 | AA20: =(J20-R20)/Y20 | AB20: =(J20-S20)/Y20 | AC20: =IF(ABS(AA20)<=ABS(AB20),"9EMA","21EMA") | AD20: 9+21EMA | AE20: 剛黃金交叉 | AF20: ✓ | AI20: 2026-10-02 | AJ20: 0 | AK20: 3 | AL20: 2026-09-24 | AM20: 485 | AN20: 458.51 | AO20: =IF(ISNUMBER(AN20),AM20/AN20-1,"") | AP20: 6 | AQ20: =IF(ISNUMBER(AM20),J20/AM20-1,"") | AR20: 533.42 | AS20: =J20/AR20-1 | AT20: -3.0345 | AU20: -8.5052 | AV20: -9.8729 | AW20: =AU20-AV20 | AX20: 5.4707 | AY20: 3.9241 | AZ20: 4.1535 | BA20: 深綠 | BB20: 淺綠→深綠 | BC20: 0 | BD20: 淺綠 淺綠 淺綠 淺綠 淺綠 淺綠 淺綠 深綠 | BE20: 上升通道 | BF20: 0.439 | BG20: 0.5017 | BH20: 0.5227 | BI20: 0.4754 | BJ20: 2 | BK20: 537.01 | BL20: 444.52 | BM20: 492.8614 | BN20: 0.9802 | BO20: =IF(M20=N20,0.5,(J20-N20)/(M20-N20)) | BP20: 21.61 | BQ20: 16.569 | BR20: =100*(0.4*MIN(1,MAX(0,((U20*100)-(0.0))/((2.5)-(0.0))))+0.3*MIN(1,MAX(0,((V20)-(0.6))/((1.0)-(0.6))))+0.3*MIN(1,MAX(0,((BP20)-(0.0))/((15.0)-(0.0))))) | BS20: =100*(0.4*MIN(1,MAX(0,((MIN(ABS(AA20),ABS(AB20)))-(0.75))/((0.0)-(0.75))))+0.3*MIN(1,MAX(0,((BN20)-(1.2))/((0.6)-(1.2))))+0.3*BO20) | BT20: =100*(0.5*MIN(1,MAX(0,((AK20)-(1.0))/((4.0)-(1.0))))+0.3*MIN(1,MAX(0,((IF(ISNUMBER(AO20),AO20,0)*100)-(0.0))/((8.0)-(0.0))))+0.2*MIN(1,MAX(0,((IF(ISNUMBER(AP20),AP20,0))-(25.0))/((5.0)-(25.0))))) | BU20: =100*(0.35*MIN(1,MAX(0,((ABS(BF20))-(0.3))/((0.05)-(0.3))))+0.3*MIN(1,MAX(0,((BG20)-(0.0))/((0.3)-(0.0))))+0.25*MIN(1,MAX(0,((BH20)-(0.4))/((0.7)-(0.4))))+0.1*IF(BJ20>=2,1,0.5)) | BV20: =0.25*BR20+0.25*BS20+0.2*BT20+0.3*BU20 | BW20: 全部通過
A21: 1 | B21: 20 | C21: VSTS | D21: Vestis Corporation | E21: NYSE | F21: 非必需消費 | G21: Consumer Specialties | H21: 1.766 | I21: 小型 | J21: 14.03 | K21: 13.78 | L21: =J21/K21-1 | M21: 14.51 | N21: 13.67 | O21: 1981200 | P21: 1693705 | Q21: =O21/P21 | R21: 13.7087 | S21: 13.5821 | T21: 13.5437 | U21: =S21/T21-1 | V21: 0.7 | W21: =J21/R21-1 | X21: =J21/S21-1 | Y21: 0.5673 | Z21: =Y21/J21 | AA21: =(J21-R21)/Y21 | AB21: =(J21-S21)/Y21 | AC21: =IF(ABS(AA21)<=ABS(AB21),"9EMA","21EMA") | AD21: 9+21EMA | AE21: 持續在上方 | AH21: ✓ | AI21: 2026-09-16 | AJ21: 12 | AK21: 3 | AL21: 2026-09-28 | AM21: 13.01 | AN21: 12.765 | AO21: =IF(ISNUMBER(AN21),AM21/AN21-1,"") | AP21: 4 | AQ21: =IF(ISNUMBER(AM21),J21/AM21-1,"") | AR21: 14.43 | AS21: =J21/AR21-1 | AT21: 0.1085 | AU21: 0.0778 | AV21: 0.0701 | AW21: =AU21-AV21 | AX21: 0.0307 | AY21: 0.0106 | AZ21: 0.002 | BA21: 深綠 | BB21: 淺綠→深綠 | BC21: 1 | BD21: 淺綠 淺綠 淺綠 淺綠 淺綠 淺綠 深綠 深綠 | BE21: 上傾擴張 | BF21: 0.6123 | BG21: 0.3722 | BH21: 0.5265 | BI21: 0.5668 | BJ21: 4 | BK21: 14.66 | BL21: 12.07 | BM21: 13.4336 | BN21: 0.7942 | BO21: =IF(M21=N21,0.5,(J21-N21)/(M21-N21)) | BP21: 20.324 | BQ21: 15.283 | BR21: =100*(0.4*MIN(1,MAX(0,((U21*100)-(0.0))/((2.5)-(0.0))))+0.3*MIN(1,MAX(0,((V21)-(0.6))/((1.0)-(0.6))))+0.3*MIN(1,MAX(0,((BP21)-(0.0))/((15.0)-(0.0))))) | BS21: =100*(0.4*MIN(1,MAX(0,((MIN(ABS(AA21),ABS(AB21)))-(0.75))/((0.0)-(0.75))))+0.3*MIN(1,MAX(0,((BN21)-(1.2))/((0.6)-(1.2))))+0.3*BO21) | BT21: =100*(0.5*MIN(1,MAX(0,((AK21)-(1.0))/((4.0)-(1.0))))+0.3*MIN(1,MAX(0,((IF(ISNUMBER(AO21),AO21,0)*100)-(0.0))/((8.0)-(0.0))))+0.2*MIN(1,MAX(0,((IF(ISNUMBER(AP21),AP21,0))-(25.0))/((5.0)-(25.0))))) | BU21: =100*(0.35*MIN(1,MAX(0,((ABS(BF21))-(0.3))/((0.05)-(0.3))))+0.3*MIN(1,MAX(0,((BG21)-(0.0))/((0.3)-(0.0))))+0.25*MIN(1,MAX(0,((BH21)-(0.4))/((0.7)-(0.4))))+0.1*IF(BJ21>=2,1,0.5)) | BV21: =0.25*BR21+0.25*BS21+0.2*BT21+0.3*BU21 | BW21: 全部通過
A22: 1 | B22: 21 | C22: GSAT | D22: Globalstar Inc. | E22: NASDAQ | F22: 非必需消費 | G22: Telecommunications Equipment | H22: 10.74 | I22: 大型 | J22: 83.22 | K22: 82.88 | L22: =J22/K22-1 | M22: 83.42 | N22: 83 | O22: 535000 | P22: 565670 | Q22: =O22/P22 | R22: 82.7604 | S22: 82.5135 | T22: 82.3247 | U22: =S22/T22-1 | V22: 1 | W22: =J22/R22-1 | X22: =J22/S22-1 | Y22: 0.6496 | Z22: =Y22/J22 | AA22: =(J22-R22)/Y22 | AB22: =(J22-S22)/Y22 | AC22: =IF(ABS(AA22)<=ABS(AB22),"9EMA","21EMA") | AD22: 9+21EMA | AE22: 持續在上方 | AH22: ✓ | AI22: 2026-09-17 | AJ22: 11 | AK22: 4 | AL22: 2026-09-23 | AM22: 81.95 | AN22: 81.55 | AO22: =IF(ISNUMBER(AN22),AM22/AN22-1,"") | AP22: 7 | AQ22: =IF(ISNUMBER(AM22),J22/AM22-1,"") | AR22: 83.22 | AS22: =J22/AR22-1 | AT22: 0.2467 | AU22: 0.1921 | AV22: 0.1784 | AW22: =AU22-AV22 | AX22: 0.0547 | AY22: 0.0334 | AZ22: 0.0286 | BA22: 深綠 | BB22: 淺綠→深綠 | BC22: 2 | BD22: 淺綠 淺綠 深綠 淺綠 淺綠 深綠 深綠 深綠 | BE22: 上升三角（平頂） | BF22: 0.0906 | BG22: 0.0757 | BH22: 0.5308 | BI22: 0.4994 | BJ22: 19 | BK22: 83.42 | BL22: 81.02 | BM22: 82.294 | BN22: 1.1639 | BO22: =IF(M22=N22,0.5,(J22-N22)/(M22-N22)) | BP22: 7.202 | BQ22: 2.161 | BR22: =100*(0.4*MIN(1,MAX(0,((U22*100)-(0.0))/((2.5)-(0.0))))+0.3*MIN(1,MAX(0,((V22)-(0.6))/((1.0)-(0.6))))+0.3*MIN(1,MAX(0,((BP22)-(0.0))/((15.0)-(0.0))))) | BS22: =100*(0.4*MIN(1,MAX(0,((MIN(ABS(AA22),ABS(AB22)))-(0.75))/((0.0)-(0.75))))+0.3*MIN(1,MAX(0,((BN22)-(1.2))/((0.6)-(1.2))))+0.3*BO22) | BT22: =100*(0.5*MIN(1,MAX(0,((AK22)-(1.0))/((4.0)-(1.0))))+0.3*MIN(1,MAX(0,((IF(ISNUMBER(AO22),AO22,0)*100)-(0.0))/((8.0)-(0.0))))+0.2*MIN(1,MAX(0,((IF(ISNUMBER(AP22),AP22,0))-(25.0))/((5.0)-(25.0))))) | BU22: =100*(0.35*MIN(1,MAX(0,((ABS(BF22))-(0.3))/((0.05)-(0.3))))+0.3*MIN(1,MAX(0,((BG22)-(0.0))/((0.3)-(0.0))))+0.25*MIN(1,MAX(0,((BH22)-(0.4))/((0.7)-(0.4))))+0.1*IF(BJ22>=2,1,0.5)) | BV22: =0.25*BR22+0.25*BS22+0.2*BT22+0.3*BU22 | BW22: 全部通過
A23: 1 | B23: 22 | C23: EGBN | D23: Eagle Bancorp Inc. | E23: NASDAQ | F23: 金融 | G23: Major Banks | H23: 0.847 | I23: 小型 | J23: 28.38 | K23: 28.21 | L23: =J23/K23-1 | M23: 28.96 | N23: 28.25 | O23: 208200 | P23: 336765 | Q23: =O23/P23 | R23: 28.1745 | S23: 28.0807 | T23: 28.0312 | U23: =S23/T23-1 | V23: 0.8 | W23: =J23/R23-1 | X23: =J23/S23-1 | Y23: 0.6668 | Z23: =Y23/J23 | AA23: =(J23-R23)/Y23 | AB23: =(J23-S23)/Y23 | AC23: =IF(ABS(AA23)<=ABS(AB23),"9EMA","21EMA") | AD23: 9+21EMA | AE23: 持續在上方 | AH23: ✓ | AI23: 2026-09-15 | AJ23: 13 | AK23: 2 | AL23: 2026-09-10 | AM23: 27.12 | AN23: 26.52 | AO23: =IF(ISNUMBER(AN23),AM23/AN23-1,"") | AP23: 16 | AQ23: =IF(ISNUMBER(AM23),J23/AM23-1,"") | AR23: 28.54 | AS23: =J23/AR23-1 | AT23: 0.0984 | AU23: 0.0887 | AV23: 0.0863 | AW23: =AU23-AV23 | AX23: 0.0097 | AY23: -0.0035 | AZ23: -0.0082 | BA23: 深綠 | BB23: 深紅→淺紅 | BC23: 1 | BD23: 淺綠 深綠 深綠 深綠 淺綠 深紅 淺紅 深綠 | BE23: 上傾收窄（楔形） | BF23: 0.1857 | BG23: 0.3524 | BH23: 0.6051 | BI23: 0.6964 | BJ23: 5 | BK23: 28.99 | BL23: 26.52 | BM23: 28.0147 | BN23: 0.9716 | BO23: =IF(M23=N23,0.5,(J23-N23)/(M23-N23)) | BP23: 7.496 | BQ23: 2.455 | BR23: =100*(0.4*MIN(1,MAX(0,((U23*100)-(0.0))/((2.5)-(0.0))))+0.3*MIN(1,MAX(0,((V23)-(0.6))/((1.0)-(0.6))))+0.3*MIN(1,MAX(0,((BP23)-(0.0))/((15.0)-(0.0))))) | BS23: =100*(0.4*MIN(1,MAX(0,((MIN(ABS(AA23),ABS(AB23)))-(0.75))/((0.0)-(0.75))))+0.3*MIN(1,MAX(0,((BN23)-(1.2))/((0.6)-(1.2))))+0.3*BO23) | BT23: =100*(0.5*MIN(1,MAX(0,((AK23)-(1.0))/((4.0)-(1.0))))+0.3*MIN(1,MAX(0,((IF(ISNUMBER(AO23),AO23,0)*100)-(0.0))/((8.0)-(0.0))))+0.2*MIN(1,MAX(0,((IF(ISNUMBER(AP23),AP23,0))-(25.0))/((5.0)-(25.0))))) | BU23: =100*(0.35*MIN(1,MAX(0,((ABS(BF23))-(0.3))/((0.05)-(0.3))))+0.3*MIN(1,MAX(0,((BG23)-(0.0))/((0.3)-(0.0))))+0.25*MIN(1,MAX(0,((BH23)-(0.4))/((0.7)-(0.4))))+0.1*IF(BJ23>=2,1,0.5)) | BV23: =0.25*BR23+0.25*BS23+0.2*BT23+0.3*BU23 | BW23: 全部通過
A24: 1 | B24: 23 | C24: APXT | D24: Apex Treasury Corporation | E24: NASDAQ | F24: 金融 | G24: Blank Checks | I24: 未分類 | J24: 10.15 | K24: 10.15 | L24: =J24/K24-1 | M24: 10.15 | N24: 10.14 | O24: 214300 | P24: 146760 | Q24: =O24/P24 | R24: 10.1407 | S24: 10.1354 | T24: 10.131 | U24: =S24/T24-1 | V24: 0.8 | W24: =J24/R24-1 | X24: =J24/S24-1 | Y24: 0.0126 | Z24: =Y24/J24 | AA24: =(J24-R24)/Y24 | AB24: =(J24-S24)/Y24 | AC24: =IF(ABS(AA24)<=ABS(AB24),"9EMA","21EMA") | AD24: 9+21EMA | AE24: 持續在上方 | AH24: ✓ | AI24: 2026-04-06 | AJ24: 125 | AK24: 3 | AL24: 2026-09-29 | AM24: 10.13 | AN24: 10.12 | AO24: =IF(ISNUMBER(AN24),AM24/AN24-1,"") | AP24: 3 | AQ24: =IF(ISNUMBER(AM24),J24/AM24-1,"") | AR24: 10.15 | AS24: =J24/AR24-1 | AT24: 0.0062 | AU24: 0.006 | AV24: 0.0059 | AW24: =AU24-AV24 | AX24: 0.0002 | AY24: -0.0003 | AZ24: -0.0012 | BA24: 深綠 | BB24: 深紅→淺紅 | BC24: 1 | BD24: 深紅 淺紅 淺紅 淺紅 淺紅 深紅 淺紅 深綠 | BE24: 上升三角（平頂） | BF24: 0 | BG24: 0.0164 | BH24: 0.5571 | BI24: 0.5571 | BJ24: 25 | BK24: 10.15 | BL24: 10.12 | BM24: 10.1367 | BN24: 1.0407 | BO24: =IF(M24=N24,0.5,(J24-N24)/(M24-N24)) | BP24: 5.288 | BQ24: 0.247 | BR24: =100*(0.4*MIN(1,MAX(0,((U24*100)-(0.0))/((2.5)-(0.0))))+0.3*MIN(1,MAX(0,((V24)-(0.6))/((1.0)-(0.6))))+0.3*MIN(1,MAX(0,((BP24)-(0.0))/((15.0)-(0.0))))) | BS24: =100*(0.4*MIN(1,MAX(0,((MIN(ABS(AA24),ABS(AB24)))-(0.75))/((0.0)-(0.75))))+0.3*MIN(1,MAX(0,((BN24)-(1.2))/((0.6)-(1.2))))+0.3*BO24) | BT24: =100*(0.5*MIN(1,MAX(0,((AK24)-(1.0))/((4.0)-(1.0))))+0.3*MIN(1,MAX(0,((IF(ISNUMBER(AO24),AO24,0)*100)-(0.0))/((8.0)-(0.0))))+0.2*MIN(1,MAX(0,((IF(ISNUMBER(AP24),AP24,0))-(25.0))/((5.0)-(25.0))))) | BU24: =100*(0.35*MIN(1,MAX(0,((ABS(BF24))-(0.3))/((0.05)-(0.3))))+0.3*MIN(1,MAX(0,((BG24)-(0.0))/((0.3)-(0.0))))+0.25*MIN(1,MAX(0,((BH24)-(0.4))/((0.7)-(0.4))))+0.1*IF(BJ24>=2,1,0.5)) | BV24: =0.25*BR24+0.25*BS24+0.2*BT24+0.3*BU24 | BW24: 全部通過
A25: 1 | B25: 24 | C25: OPY | D25: Oppenheimer Holdings Inc. | E25: NYSE | F25: 金融 | G25: Investment Bankers/Brokers/Service | H25: 1.263 | I25: 小型 | J25: 120.13 | K25: 119.47 | L25: =J25/K25-1 | M25: 124.02 | N25: 119.91 | O25: 185000 | P25: 122170 | Q25: =O25/P25 | R25: 118.7478 | S25: 118.3189 | T25: 117.7539 | U25: =S25/T25-1 | V25: 0.7 | W25: =J25/R25-1 | X25: =J25/S25-1 | Y25: 4.7074 | Z25: =Y25/J25 | AA25: =(J25-R25)/Y25 | AB25: =(J25-S25)/Y25 | AC25: =IF(ABS(AA25)<=ABS(AB25),"9EMA","21EMA") | AD25: 9+21EMA | AE25: 剛黃金交叉 | AF25: ✓ | AH25: ✓ | AI25: 2026-09-28 | AJ25: 4 | AK25: 2 | AL25: 2026-09-22 | AM25: 111.05 | AN25: 110.35 | AO25: =IF(ISNUMBER(AN25),AM25/AN25-1,"") | AP25: 8 | AQ25: =IF(ISNUMBER(AM25),J25/AM25-1,"") | AR25: 123.29 | AS25: =J25/AR25-1 | AT25: 0.5409 | AU25: 0.497 | AV25: 0.486 | AW25: =AU25-AV25 | AX25: 0.0439 | AY25: -0.0564 | AZ25: -0.1516 | BA25: 深綠 | BB25: 深紅→淺紅 | BC25: 1 | BD25: 淺紅 淺紅 淺紅 淺紅 淺紅 深紅 淺紅 深綠 | BE25: 上升三角（平頂） | BF25: 0.0419 | BG25: 0.1457 | BH25: 0.5496 | BI25: 0.5039 | BJ25: 8 | BK25: 125.88 | BL25: 110.35 | BM25: 118.886 | BN25: 1.0601 | BO25: =IF(M25=N25,0.5,(J25-N25)/(M25-N25)) | BP25: 7.401 | BQ25: 2.36 | BR25: =100*(0.4*MIN(1,MAX(0,((U25*100)-(0.0))/((2.5)-(0.0))))+0.3*MIN(1,MAX(0,((V25)-(0.6))/((1.0)-(0.6))))+0.3*MIN(1,MAX(0,((BP25)-(0.0))/((15.0)-(0.0))))) | BS25: =100*(0.4*MIN(1,MAX(0,((MIN(ABS(AA25),ABS(AB25)))-(0.75))/((0.0)-(0.75))))+0.3*MIN(1,MAX(0,((BN25)-(1.2))/((0.6)-(1.2))))+0.3*BO25) | BT25: =100*(0.5*MIN(1,MAX(0,((AK25)-(1.0))/((4.0)-(1.0))))+0.3*MIN(1,MAX(0,((IF(ISNUMBER(AO25),AO25,0)*100)-(0.0))/((8.0)-(0.0))))+0.2*MIN(1,MAX(0,((IF(ISNUMBER(AP25),AP25,0))-(25.0))/((5.0)-(25.0))))) | BU25: =100*(0.35*MIN(1,MAX(0,((ABS(BF25))-(0.3))/((0.05)-(0.3))))+0.3*MIN(1,MAX(0,((BG25)-(0.0))/((0.3)-(0.0))))+0.25*MIN(1,MAX(0,((BH25)-(0.4))/((0.7)-(0.4))))+0.1*IF(BJ25>=2,1,0.5)) | BV25: =0.25*BR25+0.25*BS25+0.2*BT25+0.3*BU25 | BW25: 全部通過
A26: 1 | B26: 25 | C26: TRNS | D26: Transcat Inc. | E26: NASDAQ | F26: 工業 | G26: Electrical Products | H26: 0.83 | I26: 小型 | J26: 90.39 | K26: 90.18 | L26: =J26/K26-1 | M26: 92.49 | N26: 89.8 | O26: 101200 | P26: 122430 | Q26: =O26/P26 | R26: 88.3418 | S26: 87.5059 | T26: 86.7656 | U26: =S26/T26-1 | V26: 0.8 | W26: =J26/R26-1 | X26: =J26/S26-1 | Y26: 3.4718 | Z26: =Y26/J26 | AA26: =(J26-R26)/Y26 | AB26: =(J26-S26)/Y26 | AC26: =IF(ABS(AA26)<=ABS(AB26),"9EMA","21EMA") | AD26: 9+21EMA | AE26: 持續在上方 | AH26: ✓ | AI26: 2026-09-23 | AJ26: 7 | AK26: 2 | AL26: 2026-09-28 | AM26: 83.5 | AN26: 79.68 | AO26: =IF(ISNUMBER(AN26),AM26/AN26-1,"") | AP26: 4 | AQ26: =IF(ISNUMBER(AM26),J26/AM26-1,"") | AR26: 91.83 | AS26: =J26/AR26-1 | AT26: 0.4725 | AU26: -0.1513 | AV26: -0.3072 | AW26: =AU26-AV26 | AX26: 0.6237 | AY26: 0.5697 | AZ26: 0.4617 | BA26: 深綠 | BB26: 淺綠→深綠 | BC26: 2 | BD26: 深綠 淺綠 淺綠 淺綠 淺綠 深綠 深綠 深綠 | BE26: 上傾擴張 | BF26: 0.54 | BG26: 0.1624 | BH26: 0.5333 | BI26: 0.5089 | BJ26: 5 | BK26: 92.49 | BL26: 79.68 | BM26: 86.5111 | BN26: 1.1669 | BO26: =IF(M26=N26,0.5,(J26-N26)/(M26-N26)) | BP26: 10.686 | BQ26: 5.645 | BR26: =100*(0.4*MIN(1,MAX(0,((U26*100)-(0.0))/((2.5)-(0.0))))+0.3*MIN(1,MAX(0,((V26)-(0.6))/((1.0)-(0.6))))+0.3*MIN(1,MAX(0,((BP26)-(0.0))/((15.0)-(0.0))))) | BS26: =100*(0.4*MIN(1,MAX(0,((MIN(ABS(AA26),ABS(AB26)))-(0.75))/((0.0)-(0.75))))+0.3*MIN(1,MAX(0,((BN26)-(1.2))/((0.6)-(1.2))))+0.3*BO26) | BT26: =100*(0.5*MIN(1,MAX(0,((AK26)-(1.0))/((4.0)-(1.0))))+0.3*MIN(1,MAX(0,((IF(ISNUMBER(AO26),AO26,0)*100)-(0.0))/((8.0)-(0.0))))+0.2*MIN(1,MAX(0,((IF(ISNUMBER(AP26),AP26,0))-(25.0))/((5.0)-(25.0))))) | BU26: =100*(0.35*MIN(1,MAX(0,((ABS(BF26))-(0.3))/((0.05)-(0.3))))+0.3*MIN(1,MAX(0,((BG26)-(0.0))/((0.3)-(0.0))))+0.25*MIN(1,MAX(0,((BH26)-(0.4))/((0.7)-(0.4))))+0.1*IF(BJ26>=2,1,0.5)) | BV26: =0.25*BR26+0.25*BS26+0.2*BT26+0.3*BU26 | BW26: 全部通過
A27: 1 | B27: 26 | C27: BJ | D27: BJ's Wholesale Club Holdings Inc. | E27: NYSE | F27: 非必需消費 | G27: Department/Specialty Retail Stores | H27: 11.621 | I27: 大型 | J27: 94.96 | K27: 94.36 | L27: =J27/K27-1 | M27: 95.55 | N27: 93.075 | O27: 2439100 | P27: 1831645 | Q27: =O27/P27 | R27: 93.7887 | S27: 93.2333 | T27: 92.3738 | U27: =S27/T27-1 | V27: 0.5 | W27: =J27/R27-1 | X27: =J27/S27-1 | Y27: 2.7701 | Z27: =Y27/J27 | AA27: =(J27-R27)/Y27 | AB27: =(J27-S27)/Y27 | AC27: =IF(ABS(AA27)<=ABS(AB27),"9EMA","21EMA") | AD27: 9+21EMA | AE27: 剛黃金交叉 | AF27: ✓ | AH27: ✓ | AI27: 2026-09-28 | AJ27: 4 | AK27: 2 | AL27: 2026-09-23 | AM27: 89.89 | AN27: 87.72 | AO27: =IF(ISNUMBER(AN27),AM27/AN27-1,"") | AP27: 7 | AQ27: =IF(ISNUMBER(AM27),J27/AM27-1,"") | AR27: 96.81 | AS27: =J27/AR27-1 | AT27: 0.4088 | AU27: 0.1061 | AV27: 0.0304 | AW27: =AU27-AV27 | AX27: 0.3027 | AY27: 0.2689 | AZ27: 0.2531 | BA27: 深綠 | BB27: 淺綠→深綠 | BC27: 1 | BD27: 深紅 淺紅 深綠 深綠 深綠 淺綠 深綠 深綠 | BE27: 上傾擴張 | BF27: 0.239 | BG27: 0.003 | BH27: 0.5126 | BI27: 0.4965 | BJ27: 3 | BK27: 97.3 | BL27: 87.72 | BM27: 92.6306 | BN27: 1.0862 | BO27: =IF(M27=N27,0.5,(J27-N27)/(M27-N27)) | BP27: 7.424 | BQ27: 2.383 | BR27: =100*(0.4*MIN(1,MAX(0,((U27*100)-(0.0))/((2.5)-(0.0))))+0.3*MIN(1,MAX(0,((V27)-(0.6))/((1.0)-(0.6))))+0.3*MIN(1,MAX(0,((BP27)-(0.0))/((15.0)-(0.0))))) | BS27: =100*(0.4*MIN(1,MAX(0,((MIN(ABS(AA27),ABS(AB27)))-(0.75))/((0.0)-(0.75))))+0.3*MIN(1,MAX(0,((BN27)-(1.2))/((0.6)-(1.2))))+0.3*BO27) | BT27: =100*(0.5*MIN(1,MAX(0,((AK27)-(1.0))/((4.0)-(1.0))))+0.3*MIN(1,MAX(0,((IF(ISNUMBER(AO27),AO27,0)*100)-(0.0))/((8.0)-(0.0))))+0.2*MIN(1,MAX(0,((IF(ISNUMBER(AP27),AP27,0))-(25.0))/((5.0)-(25.0))))) | BU27: =100*(0.35*MIN(1,MAX(0,((ABS(BF27))-(0.3))/((0.05)-(0.3))))+0.3*MIN(1,MAX(0,((BG27)-(0.0))/((0.3)-(0.0))))+0.25*MIN(1,MAX(0,((BH27)-(0.4))/((0.7)-(0.4))))+0.1*IF(BJ27>=2,1,0.5)) | BV27: =0.25*BR27+0.25*BS27+0.2*BT27+0.3*BU27 | BW27: 全部通過
A28: 2 | B28: 1 | C28: DOCS | D28: Doximity Inc. | E28: NYSE | F28: 科技 | G28: EDP Services | H28: 5.051 | I28: 中型 | J28: 27.93 | K28: 28.5 | L28: =J28/K28-1 | M28: 29.2 | N28: 27.795 | O28: 2672100 | P28: 2977815 | Q28: =O28/P28 | R28: 27.2352 | S28: 26.5334 | T28: 25.8834 | U28: =S28/T28-1 | V28: 1 | W28: =J28/R28-1 | X28: =J28/S28-1 | Y28: 1.2021 | Z28: =Y28/J28 | AA28: =(J28-R28)/Y28 | AB28: =(J28-S28)/Y28 | AC28: =IF(ABS(AA28)<=ABS(AB28),"9EMA","21EMA") | AD28: 9EMA | AE28: 持續在上方 | AH28: ✓ | AI28: 2026-08-07 | AJ28: 39 | AK28: 2 | AL28: 2026-09-28 | AM28: 25.33 | AN28: 23.955 | AO28: =IF(ISNUMBER(AN28),AM28/AN28-1,"") | AP28: 4 | AQ28: =IF(ISNUMBER(AM28),J28/AM28-1,"") | AR28: 28.5 | AS28: =J28/AR28-1 | AT28: 0.7219 | AU28: 0.583 | AV28: 0.5483 | AW28: =AU28-AV28 | AX28: 0.1388 | AY28: 0.1384 | AZ28: 0.0601 | BA28: 深綠 | BB28: 深紅→淺紅 | BC28: 3 | BD28: 淺紅 深紅 深紅 深紅 淺紅 深綠 深綠 深綠 | BE28: 上升三角（平頂） | BF28: 0.0477 | BG28: 0.3787 | BH28: 0.4676 | BI28: 0.5146 | BJ28: 2 | BK28: 29.2 | BL28: 23.955 | BM28: 26.4077 | BN28: 0.8506 | BO28: =IF(M28=N28,0.5,(J28-N28)/(M28-N28)) | BP28: 11.158 | BQ28: 6.117 | BR28: =100*(0.4*MIN(1,MAX(0,((U28*100)-(0.0))/((2.5)-(0.0))))+0.3*MIN(1,MAX(0,((V28)-(0.6))/((1.0)-(0.6))))+0.3*MIN(1,MAX(0,((BP28)-(0.0))/((15.0)-(0.0))))) | BS28: =100*(0.4*MIN(1,MAX(0,((MIN(ABS(AA28),ABS(AB28)))-(0.75))/((0.0)-(0.75))))+0.3*MIN(1,MAX(0,((BN28)-(1.2))/((0.6)-(1.2))))+0.3*BO28) | BT28: =100*(0.5*MIN(1,MAX(0,((AK28)-(1.0))/((4.0)-(1.0))))+0.3*MIN(1,MAX(0,((IF(ISNUMBER(AO28),AO28,0)*100)-(0.0))/((8.0)-(0.0))))+0.2*MIN(1,MAX(0,((IF(ISNUMBER(AP28),AP28,0))-(25.0))/((5.0)-(25.0))))) | BU28: =100*(0.35*MIN(1,MAX(0,((ABS(BF28))-(0.3))/((0.05)-(0.3))))+0.3*MIN(1,MAX(0,((BG28)-(0.0))/((0.3)-(0.0))))+0.25*MIN(1,MAX(0,((BH28)-(0.4))/((0.7)-(0.4))))+0.1*IF(BJ28>=2,1,0.5)) | BV28: =0.25*BR28+0.25*BS28+0.2*BT28+0.3*BU28 | BW28: C4 上升三角／重心偏上
A29: 2 | B29: 2 | C29: HYLN | D29: Hyliion Holdings Corp. | E29: AMEX | F29: 非必需消費 | G29: Construction/Ag Equipment/Trucks | H29: 0.745 | I29: 小型 | J29: 4.53 | K29: 4.21 | L29: =J29/K29-1 | M29: 4.54 | N29: 4.29 | O29: 1955600 | P29: 1928700 | Q29: =O29/P29 | R29: 4.2095 | S29: 4.0725 | T29: 3.9936 | U29: =S29/T29-1 | V29: 0.9 | W29: =J29/R29-1 | X29: =J29/S29-1 | Y29: 0.2938 | Z29: =Y29/J29 | AA29: =(J29-R29)/Y29 | AB29: =(J29-S29)/Y29 | AC29: =IF(ABS(AA29)<=ABS(AB29),"9EMA","21EMA") | AD29: 9+21EMA | AE29: 持續在上方 | AI29: 2026-09-09 | AJ29: 17 | AK29: 4 | AL29: 2026-09-28 | AM29: 3.92 | AN29: 3.62 | AO29: =IF(ISNUMBER(AN29),AM29/AN29-1,"") | AP29: 4 | AQ29: =IF(ISNUMBER(AM29),J29/AM29-1,"") | AR29: 4.53 | AS29: =J29/AR29-1 | AT29: 0.1288 | AU29: 0.1018 | AV29: 0.095 | AW29: =AU29-AV29 | AX29: 0.027 | AY29: 0.0074 | AZ29: 0.0066 | BA29: 深綠 | BB29: 淺綠→深綠 | BC29: 1 | BD29: 淺綠 淺綠 淺綠 淺綠 淺綠 淺綠 深綠 深綠 | BE29: 上傾擴張 | BF29: 1.2952 | BG29: 0.8151 | BH29: 0.5223 | BI29: 0.5198 | BJ29: 1 | BK29: 4.68 | BL29: 3.25 | BM29: 3.997 | BN29: 0.8423 | BO29: =IF(M29=N29,0.5,(J29-N29)/(M29-N29)) | BP29: 32.288 | BQ29: 27.247 | BR29: =100*(0.4*MIN(1,MAX(0,((U29*100)-(0.0))/((2.5)-(0.0))))+0.3*MIN(1,MAX(0,((V29)-(0.6))/((1.0)-(0.6))))+0.3*MIN(1,MAX(0,((BP29)-(0.0))/((15.0)-(0.0))))) | BS29: =100*(0.4*MIN(1,MAX(0,((MIN(ABS(AA29),ABS(AB29)))-(0.75))/((0.0)-(0.75))))+0.3*MIN(1,MAX(0,((BN29)-(1.2))/((0.6)-(1.2))))+0.3*BO29) | BT29: =100*(0.5*MIN(1,MAX(0,((AK29)-(1.0))/((4.0)-(1.0))))+0.3*MIN(1,MAX(0,((IF(ISNUMBER(AO29),AO29,0)*100)-(0.0))/((8.0)-(0.0))))+0.2*MIN(1,MAX(0,((IF(ISNUMBER(AP29),AP29,0))-(25.0))/((5.0)-(25.0))))) | BU29: =100*(0.35*MIN(1,MAX(0,((ABS(BF29))-(0.3))/((0.05)-(0.3))))+0.3*MIN(1,MAX(0,((BG29)-(0.0))/((0.3)-(0.0))))+0.25*MIN(1,MAX(0,((BH29)-(0.4))/((0.7)-(0.4))))+0.1*IF(BJ29>=2,1,0.5)) | BV29: =0.25*BR29+0.25*BS29+0.2*BT29+0.3*BU29 | BW29: C4 上升三角／重心偏上
A30: 2 | B30: 3 | C30: SANM | D30: Sanmina Corporation | E30: NASDAQ | F30: 科技 | G30: Electrical Products | H30: 11.519 | I30: 大型 | J30: 229.04 | K30: 221.96 | L30: =J30/K30-1 | M30: 229.4 | N30: 223.62 | O30: 654800 | P30: 587230 | Q30: =O30/P30 | R30: 219.5123 | S30: 212.4794 | T30: 206.6132 | U30: =S30/T30-1 | V30: 1 | W30: =J30/R30-1 | X30: =J30/S30-1 | Y30: 10.7847 | Z30: =Y30/J30 | AA30: =(J30-R30)/Y30 | AB30: =(J30-S30)/Y30 | AC30: =IF(ABS(AA30)<=ABS(AB30),"9EMA","21EMA") | AD30: 9+21EMA | AE30: 持續在上方 | AI30: 2026-09-21 | AJ30: 9 | AK30: 4 | AL30: 2026-09-15 | AM30: 189.58 | AN30: 182.47 | AO30: =IF(ISNUMBER(AN30),AM30/AN30-1,"") | AP30: 13 | AQ30: =IF(ISNUMBER(AM30),J30/AM30-1,"") | AR30: 229.04 | AS30: =J30/AR30-1 | AT30: 6.3917 | AU30: 4.518 | AV30: 4.0496 | AW30: =AU30-AV30 | AX30: 1.8737 | AY30: 1.657 | AZ30: 1.8347 | BA30: 深綠 | BB30: 淺綠→深綠 | BC30: 0 | BD30: 深綠 深綠 深綠 淺綠 淺綠 淺綠 淺綠 深綠 | BE30: 上傾擴張 | BF30: 0.5833 | BG30: 0.388 | BH30: 0.4956 | BI30: 0.4783 | BJ30: 2 | BK30: 232.5 | BL30: 182.47 | BM30: 207.2625 | BN30: 0.921 | BO30: =IF(M30=N30,0.5,(J30-N30)/(M30-N30)) | BP30: 27.085 | BQ30: 22.044 | BR30: =100*(0.4*MIN(1,MAX(0,((U30*100)-(0.0))/((2.5)-(0.0))))+0.3*MIN(1,MAX(0,((V30)-(0.6))/((1.0)-(0.6))))+0.3*MIN(1,MAX(0,((BP30)-(0.0))/((15.0)-(0.0))))) | BS30: =100*(0.4*MIN(1,MAX(0,((MIN(ABS(AA30),ABS(AB30)))-(0.75))/((0.0)-(0.75))))+0.3*MIN(1,MAX(0,((BN30)-(1.2))/((0.6)-(1.2))))+0.3*BO30) | BT30: =100*(0.5*MIN(1,MAX(0,((AK30)-(1.0))/((4.0)-(1.0))))+0.3*MIN(1,MAX(0,((IF(ISNUMBER(AO30),AO30,0)*100)-(0.0))/((8.0)-(0.0))))+0.2*MIN(1,MAX(0,((IF(ISNUMBER(AP30),AP30,0))-(25.0))/((5.0)-(25.0))))) | BU30: =100*(0.35*MIN(1,MAX(0,((ABS(BF30))-(0.3))/((0.05)-(0.3))))+0.3*MIN(1,MAX(0,((BG30)-(0.0))/((0.3)-(0.0))))+0.25*MIN(1,MAX(0,((BH30)-(0.4))/((0.7)-(0.4))))+0.1*IF(BJ30>=2,1,0.5)) | BV30: =0.25*BR30+0.25*BS30+0.2*BT30+0.3*BU30 | BW30: C4 上升三角／重心偏上
A31: 2 | B31: 4 | C31: TTMI | D31: TTM Technologies Inc. | E31: NASDAQ | F31: 科技 | G31: Electrical Products | H31: 12.941 | I31: 大型 | J31: 131.87 | K31: 126.5 | L31: =J31/K31-1 | M31: 134.57 | N31: 127.32 | O31: 1609600 | P31: 1893870 | Q31: =O31/P31 | R31: 125.7196 | S31: 123.9692 | T31: 122.7188 | U31: =S31/T31-1 | V31: 0.8 | W31: =J31/R31-1 | X31: =J31/S31-1 | Y31: 7.7543 | Z31: =Y31/J31 | AA31: =(J31-R31)/Y31 | AB31: =(J31-S31)/Y31 | AC31: =IF(ABS(AA31)<=ABS(AB31),"9EMA","21EMA") | AD31: 9+21EMA | AE31: 持續在上方 | AI31: 2026-09-23 | AJ31: 7 | AK31: 5 | AL31: 2026-09-28 | AM31: 119.02 | AN31: 109.94 | AO31: =IF(ISNUMBER(AN31),AM31/AN31-1,"") | AP31: 4 | AQ31: =IF(ISNUMBER(AM31),J31/AM31-1,"") | AR31: 131.87 | AS31: =J31/AR31-1 | AT31: 0.8416 | AU31: -0.4241 | AV31: -0.7405 | AW31: =AU31-AV31 | AX31: 1.2657 | AY31: 0.9462 | AZ31: 0.9148 | BA31: 深綠 | BB31: 淺綠→深綠 | BC31: 1 | BD31: 深綠 深綠 深綠 淺綠 淺綠 淺綠 深綠 深綠 | BE31: 對稱三角 | BF31: -0.1429 | BG31: 0.4645 | BH31: 0.499 | BI31: 0.4928 | BJ31: 2 | BK31: 134.57 | BL31: 109.53 | BM31: 122.0252 | BN31: 0.8762 | BO31: =IF(M31=N31,0.5,(J31-N31)/(M31-N31)) | BP31: 19.115 | BQ31: 14.074 | BR31: =100*(0.4*MIN(1,MAX(0,((U31*100)-(0.0))/((2.5)-(0.0))))+0.3*MIN(1,MAX(0,((V31)-(0.6))/((1.0)-(0.6))))+0.3*MIN(1,MAX(0,((BP31)-(0.0))/((15.0)-(0.0))))) | BS31: =100*(0.4*MIN(1,MAX(0,((MIN(ABS(AA31),ABS(AB31)))-(0.75))/((0.0)-(0.75))))+0.3*MIN(1,MAX(0,((BN31)-(1.2))/((0.6)-(1.2))))+0.3*BO31) | BT31: =100*(0.5*MIN(1,MAX(0,((AK31)-(1.0))/((4.0)-(1.0))))+0.3*MIN(1,MAX(0,((IF(ISNUMBER(AO31),AO31,0)*100)-(0.0))/((8.0)-(0.0))))+0.2*MIN(1,MAX(0,((IF(ISNUMBER(AP31),AP31,0))-(25.0))/((5.0)-(25.0))))) | BU31: =100*(0.35*MIN(1,MAX(0,((ABS(BF31))-(0.3))/((0.05)-(0.3))))+0.3*MIN(1,MAX(0,((BG31)-(0.0))/((0.3)-(0.0))))+0.25*MIN(1,MAX(0,((BH31)-(0.4))/((0.7)-(0.4))))+0.1*IF(BJ31>=2,1,0.5)) | BV31: =0.25*BR31+0.25*BS31+0.2*BT31+0.3*BU31 | BW31: C4 上升三角／重心偏上
A32: 2 | B32: 5 | C32: ALMR | D32: Alamar Biosciences Inc. | E32: NASDAQ | F32: 工業 | G32: Biotechnology: Laboratory Analytical Instruments | H32: 2.364 | I32: 中型 | J32: 34.36 | K32: 32.46 | L32: =J32/K32-1 | M32: 34.62 | N32: 32.8 | O32: 339900 | P32: 507400 | Q32: =O32/P32 | R32: 33.0398 | S32: 32.1974 | T32: 31.5282 | U32: =S32/T32-1 | V32: 1 | W32: =J32/R32-1 | X32: =J32/S32-1 | Y32: 2.1941 | Z32: =Y32/J32 | AA32: =(J32-R32)/Y32 | AB32: =(J32-S32)/Y32 | AC32: =IF(ABS(AA32)<=ABS(AB32),"9EMA","21EMA") | AD32: 9EMA | AE32: 持續在上方 | AI32: 2026-09-18 | AJ32: 10 | AK32: 2 | AL32: 2026-09-24 | AM32: 31.68 | AN32: 27.25 | AO32: =IF(ISNUMBER(AN32),AM32/AN32-1,"") | AP32: 6 | AQ32: =IF(ISNUMBER(AM32),J32/AM32-1,"") | AR32: 35.05 | AS32: =J32/AR32-1 | AT32: 0.869 | AU32: 0.7185 | AV32: 0.6808 | AW32: =AU32-AV32 | AX32: 0.1506 | AY32: 0.0974 | AZ32: 0.1879 | BA32: 深綠 | BB32: 淺綠→深綠 | BC32: 0 | BD32: 淺綠 淺綠 淺綠 淺綠 淺綠 深綠 淺綠 深綠 | BE32: 上升通道 | BF32: 0.5462 | BG32: 0.4602 | BH32: 0.4706 | BI32: 0.608 | BJ32: 1 | BK32: 37.76 | BL32: 27.25 | BM32: 32.1964 | BN32: 0.5157 | BO32: =IF(M32=N32,0.5,(J32-N32)/(M32-N32)) | BP32: 17.734 | BQ32: 12.693 | BR32: =100*(0.4*MIN(1,MAX(0,((U32*100)-(0.0))/((2.5)-(0.0))))+0.3*MIN(1,MAX(0,((V32)-(0.6))/((1.0)-(0.6))))+0.3*MIN(1,MAX(0,((BP32)-(0.0))/((15.0)-(0.0))))) | BS32: =100*(0.4*MIN(1,MAX(0,((MIN(ABS(AA32),ABS(AB32)))-(0.75))/((0.0)-(0.75))))+0.3*MIN(1,MAX(0,((BN32)-(1.2))/((0.6)-(1.2))))+0.3*BO32) | BT32: =100*(0.5*MIN(1,MAX(0,((AK32)-(1.0))/((4.0)-(1.0))))+0.3*MIN(1,MAX(0,((IF(ISNUMBER(AO32),AO32,0)*100)-(0.0))/((8.0)-(0.0))))+0.2*MIN(1,MAX(0,((IF(ISNUMBER(AP32),AP32,0))-(25.0))/((5.0)-(25.0))))) | BU32: =100*(0.35*MIN(1,MAX(0,((ABS(BF32))-(0.3))/((0.05)-(0.3))))+0.3*MIN(1,MAX(0,((BG32)-(0.0))/((0.3)-(0.0))))+0.25*MIN(1,MAX(0,((BH32)-(0.4))/((0.7)-(0.4))))+0.1*IF(BJ32>=2,1,0.5)) | BV32: =0.25*BR32+0.25*BS32+0.2*BT32+0.3*BU32 | BW32: C4 上升三角／重心偏上
A33: 2 | B33: 6 | C33: AXTI | D33: AXT Inc | E33: NASDAQ | F33: 科技 | G33: Semiconductors | H33: 5.076 | I33: 中型 | J33: 85.87 | K33: 81.81 | L33: =J33/K33-1 | M33: 87.55 | N33: 80.71 | O33: 7328100 | P33: 8954795 | Q33: =O33/P33 | R33: 78.1385 | S33: 73.4872 | T33: 69.5573 | U33: =S33/T33-1 | V33: 1 | W33: =J33/R33-1 | X33: =J33/S33-1 | Y33: 7.0944 | Z33: =Y33/J33 | AA33: =(J33-R33)/Y33 | AB33: =(J33-S33)/Y33 | AC33: =IF(ABS(AA33)<=ABS(AB33),"9EMA","21EMA") | AD33: — | AE33: 持續在上方 | AI33: 2026-09-21 | AJ33: 9 | AK33: 3 | AL33: 2026-09-24 | AM33: 69.6 | AN33: 56.9 | AO33: =IF(ISNUMBER(AN33),AM33/AN33-1,"") | AP33: 6 | AQ33: =IF(ISNUMBER(AM33),J33/AM33-1,"") | AR33: 85.87 | AS33: =J33/AR33-1 | AT33: 4.0885 | AU33: 2.5538 | AV33: 2.1701 | AW33: =AU33-AV33 | AX33: 1.5348 | AY33: 1.298 | AZ33: 1.1935 | BA33: 深綠 | BB33: 淺綠→深綠 | BC33: 1 | BD33: 淺綠 淺綠 深綠 淺綠 淺綠 淺綠 深綠 深綠 | BE33: 上傾收窄（楔形） | BF33: 1.1005 | BG33: 1.425 | BH33: 0.4678 | BI33: 0.4343 | BJ33: 1 | BK33: 87.55 | BL33: 52.76 | BM33: 69.0355 | BN33: 0.7656 | BO33: =IF(M33=N33,0.5,(J33-N33)/(M33-N33)) | BP33: 55.822 | BQ33: 50.781 | BR33: =100*(0.4*MIN(1,MAX(0,((U33*100)-(0.0))/((2.5)-(0.0))))+0.3*MIN(1,MAX(0,((V33)-(0.6))/((1.0)-(0.6))))+0.3*MIN(1,MAX(0,((BP33)-(0.0))/((15.0)-(0.0))))) | BS33: =100*(0.4*MIN(1,MAX(0,((MIN(ABS(AA33),ABS(AB33)))-(0.75))/((0.0)-(0.75))))+0.3*MIN(1,MAX(0,((BN33)-(1.2))/((0.6)-(1.2))))+0.3*BO33) | BT33: =100*(0.5*MIN(1,MAX(0,((AK33)-(1.0))/((4.0)-(1.0))))+0.3*MIN(1,MAX(0,((IF(ISNUMBER(AO33),AO33,0)*100)-(0.0))/((8.0)-(0.0))))+0.2*MIN(1,MAX(0,((IF(ISNUMBER(AP33),AP33,0))-(25.0))/((5.0)-(25.0))))) | BU33: =100*(0.35*MIN(1,MAX(0,((ABS(BF33))-(0.3))/((0.05)-(0.3))))+0.3*MIN(1,MAX(0,((BG33)-(0.0))/((0.3)-(0.0))))+0.25*MIN(1,MAX(0,((BH33)-(0.4))/((0.7)-(0.4))))+0.1*IF(BJ33>=2,1,0.5)) | BV33: =0.25*BR33+0.25*BS33+0.2*BT33+0.3*BU33 | BW33: C4 上升三角／重心偏上
A34: 2 | B34: 7 | C34: PGEN | D34: Precigen Inc. | E34: NASDAQ | F34: 醫療保健 | G34: Biotechnology: Pharmaceutical Preparations | H34: 3.065 | I34: 中型 | J34: 8.54 | K34: 8.21 | L34: =J34/K34-1 | M34: 8.55 | N34: 8.18 | O34: 6361900 | P34: 5067305 | Q34: =O34/P34 | R34: 8.0611 | S34: 7.671 | T34: 7.3089 | U34: =S34/T34-1 | V34: 1 | W34: =J34/R34-1 | X34: =J34/S34-1 | Y34: 0.4327 | Z34: =Y34/J34 | AA34: =(J34-R34)/Y34 | AB34: =(J34-S34)/Y34 | AC34: =IF(ABS(AA34)<=ABS(AB34),"9EMA","21EMA") | AD34: — | AE34: 持續在上方 | AI34: 2026-06-12 | AJ34: 77 | AK34: 2 | AL34: 2026-09-23 | AM34: 7.19 | AN34: 6.54 | AO34: =IF(ISNUMBER(AN34),AM34/AN34-1,"") | AP34: 7 | AQ34: =IF(ISNUMBER(AM34),J34/AM34-1,"") | AR34: 8.56 | AS34: =J34/AR34-1 | AT34: 0.3962 | AU34: 0.3219 | AV34: 0.3033 | AW34: =AU34-AV34 | AX34: 0.0743 | AY34: 0.0637 | AZ34: 0.0707 | BA34: 深綠 | BB34: 淺綠→深綠 | BC34: 0 | BD34: 淺綠 淺綠 淺綠 淺綠 深綠 深綠 淺綠 深綠 | BE34: 上傾擴張 | BF34: 1.0018 | BG34: 0.4511 | BH34: 0.453 | BI34: 0.5134 | BJ34: 1 | BK34: 8.98 | BL34: 6.54 | BM34: 7.6452 | BN34: 0.7422 | BO34: =IF(M34=N34,0.5,(J34-N34)/(M34-N34)) | BP34: 26.867 | BQ34: 21.826 | BR34: =100*(0.4*MIN(1,MAX(0,((U34*100)-(0.0))/((2.5)-(0.0))))+0.3*MIN(1,MAX(0,((V34)-(0.6))/((1.0)-(0.6))))+0.3*MIN(1,MAX(0,((BP34)-(0.0))/((15.0)-(0.0))))) | BS34: =100*(0.4*MIN(1,MAX(0,((MIN(ABS(AA34),ABS(AB34)))-(0.75))/((0.0)-(0.75))))+0.3*MIN(1,MAX(0,((BN34)-(1.2))/((0.6)-(1.2))))+0.3*BO34) | BT34: =100*(0.5*MIN(1,MAX(0,((AK34)-(1.0))/((4.0)-(1.0))))+0.3*MIN(1,MAX(0,((IF(ISNUMBER(AO34),AO34,0)*100)-(0.0))/((8.0)-(0.0))))+0.2*MIN(1,MAX(0,((IF(ISNUMBER(AP34),AP34,0))-(25.0))/((5.0)-(25.0))))) | BU34: =100*(0.35*MIN(1,MAX(0,((ABS(BF34))-(0.3))/((0.05)-(0.3))))+0.3*MIN(1,MAX(0,((BG34)-(0.0))/((0.3)-(0.0))))+0.25*MIN(1,MAX(0,((BH34)-(0.4))/((0.7)-(0.4))))+0.1*IF(BJ34>=2,1,0.5)) | BV34: =0.25*BR34+0.25*BS34+0.2*BT34+0.3*BU34 | BW34: C4 上升三角／重心偏上
A35: 2 | B35: 8 | C35: HPE | D35: Hewlett Packard Enterprise Company | E35: NYSE | F35: 科技 | G35: Retail: Computer Software & Peripheral Equipment | H35: 84.812 | I35: 大型 | J35: 69.33 | K35: 64.58 | L35: =J35/K35-1 | M35: 70.29 | N35: 66 | O35: 29049700 | P35: 23624740 | Q35: =O35/P35 | R35: 63.7902 | S35: 60.7941 | T35: 58.4056 | U35: =S35/T35-1 | V35: 1 | W35: =J35/R35-1 | X35: =J35/S35-1 | Y35: 3.7631 | Z35: =Y35/J35 | AA35: =(J35-R35)/Y35 | AB35: =(J35-S35)/Y35 | AC35: =IF(ABS(AA35)<=ABS(AB35),"9EMA","21EMA") | AD35: 9EMA | AE35: 持續在上方 | AI35: 2026-09-03 | AJ35: 20 | AK35: 2 | AL35: 2026-09-16 | AM35: 55.02 | AN35: 45.7 | AO35: =IF(ISNUMBER(AN35),AM35/AN35-1,"") | AP35: 12 | AQ35: =IF(ISNUMBER(AM35),J35/AM35-1,"") | AR35: 69.33 | AS35: =J35/AR35-1 | AT35: 3.0401 | AU35: 2.507 | AV35: 2.3738 | AW35: =AU35-AV35 | AX35: 0.533 | AY35: 0.2544 | AZ35: 0.2377 | BA35: 深綠 | BB35: 淺綠→深綠 | BC35: 2 | BD35: 深綠 深綠 淺綠 淺綠 淺綠 深綠 深綠 深綠 | BE35: 上傾收窄（楔形） | BF35: 0.9252 | BG35: 1.6804 | BH35: 0.4997 | BI35: 0.3856 | BJ35: 1 | BK35: 70.29 | BL35: 45.7 | BM35: 57.9888 | BN35: 0.6622 | BO35: =IF(M35=N35,0.5,(J35-N35)/(M35-N35)) | BP35: 38.805 | BQ35: 33.764 | BR35: =100*(0.4*MIN(1,MAX(0,((U35*100)-(0.0))/((2.5)-(0.0))))+0.3*MIN(1,MAX(0,((V35)-(0.6))/((1.0)-(0.6))))+0.3*MIN(1,MAX(0,((BP35)-(0.0))/((15.0)-(0.0))))) | BS35: =100*(0.4*MIN(1,MAX(0,((MIN(ABS(AA35),ABS(AB35)))-(0.75))/((0.0)-(0.75))))+0.3*MIN(1,MAX(0,((BN35)-(1.2))/((0.6)-(1.2))))+0.3*BO35) | BT35: =100*(0.5*MIN(1,MAX(0,((AK35)-(1.0))/((4.0)-(1.0))))+0.3*MIN(1,MAX(0,((IF(ISNUMBER(AO35),AO35,0)*100)-(0.0))/((8.0)-(0.0))))+0.2*MIN(1,MAX(0,((IF(ISNUMBER(AP35),AP35,0))-(25.0))/((5.0)-(25.0))))) | BU35: =100*(0.35*MIN(1,MAX(0,((ABS(BF35))-(0.3))/((0.05)-(0.3))))+0.3*MIN(1,MAX(0,((BG35)-(0.0))/((0.3)-(0.0))))+0.25*MIN(1,MAX(0,((BH35)-(0.4))/((0.7)-(0.4))))+0.1*IF(BJ35>=2,1,0.5)) | BV35: =0.25*BR35+0.25*BS35+0.2*BT35+0.3*BU35 | BW35: C4 上升三角／重心偏上
A36: 2 | B36: 9 | C36: S | D36: SentinelOne Inc. | E36: NYSE | F36: 科技 | G36: Computer Software: Prepackaged Software | H36: 8.27 | I36: 中型 | J36: 25.06 | K36: 24.67 | L36: =J36/K36-1 | M36: 25.75 | N36: 24.92 | O36: 11317600 | P36: 8668240 | Q36: =O36/P36 | R36: 23.7866 | S36: 22.8988 | T36: 22.213 | U36: =S36/T36-1 | V36: 1 | W36: =J36/R36-1 | X36: =J36/S36-1 | Y36: 1.1261 | Z36: =Y36/J36 | AA36: =(J36-R36)/Y36 | AB36: =(J36-S36)/Y36 | AC36: =IF(ABS(AA36)<=ABS(AB36),"9EMA","21EMA") | AD36: 9EMA | AE36: 持續在上方 | AI36: 2026-09-15 | AJ36: 13 | AK36: 2 | AL36: 2026-09-28 | AM36: 21.79 | AN36: 19.07 | AO36: =IF(ISNUMBER(AN36),AM36/AN36-1,"") | AP36: 4 | AQ36: =IF(ISNUMBER(AM36),J36/AM36-1,"") | AR36: 25.06 | AS36: =J36/AR36-1 | AT36: 0.9046 | AU36: 0.7522 | AV36: 0.7141 | AW36: =AU36-AV36 | AX36: 0.1525 | AY36: 0.1065 | AZ36: 0.0535 | BA36: 深綠 | BB36: 淺綠→深綠 | BC36: 2 | BD36: 深綠 淺綠 淺綠 淺綠 淺綠 深綠 深綠 深綠 | BE36: 上傾收窄（楔形） | BF36: 0.1141 | BG36: 0.7753 | BH36: 0.4791 | BI36: 0.5045 | BJ36: 1 | BK36: 25.75 | BL36: 19.07 | BM36: 22.2704 | BN36: 1.005 | BO36: =IF(M36=N36,0.5,(J36-N36)/(M36-N36)) | BP36: 32.378 | BQ36: 27.337 | BR36: =100*(0.4*MIN(1,MAX(0,((U36*100)-(0.0))/((2.5)-(0.0))))+0.3*MIN(1,MAX(0,((V36)-(0.6))/((1.0)-(0.6))))+0.3*MIN(1,MAX(0,((BP36)-(0.0))/((15.0)-(0.0))))) | BS36: =100*(0.4*MIN(1,MAX(0,((MIN(ABS(AA36),ABS(AB36)))-(0.75))/((0.0)-(0.75))))+0.3*MIN(1,MAX(0,((BN36)-(1.2))/((0.6)-(1.2))))+0.3*BO36) | BT36: =100*(0.5*MIN(1,MAX(0,((AK36)-(1.0))/((4.0)-(1.0))))+0.3*MIN(1,MAX(0,((IF(ISNUMBER(AO36),AO36,0)*100)-(0.0))/((8.0)-(0.0))))+0.2*MIN(1,MAX(0,((IF(ISNUMBER(AP36),AP36,0))-(25.0))/((5.0)-(25.0))))) | BU36: =100*(0.35*MIN(1,MAX(0,((ABS(BF36))-(0.3))/((0.05)-(0.3))))+0.3*MIN(1,MAX(0,((BG36)-(0.0))/((0.3)-(0.0))))+0.25*MIN(1,MAX(0,((BH36)-(0.4))/((0.7)-(0.4))))+0.1*IF(BJ36>=2,1,0.5)) | BV36: =0.25*BR36+0.25*BS36+0.2*BT36+0.3*BU36 | BW36: C4 上升三角／重心偏上
A37: 2 | B37: 10 | C37: FTK | D37: Flotek Industries Inc. | E37: NYSE | F37: 工業 | G37: Major Chemicals | H37: 1.062 | I37: 小型 | J37: 30.94 | K37: 29.79 | L37: =J37/K37-1 | M37: 31.76 | N37: 30.12 | O37: 406200 | P37: 487785 | Q37: =O37/P37 | R37: 29.5667 | S37: 28.734 | T37: 28.2557 | U37: =S37/T37-1 | V37: 1 | W37: =J37/R37-1 | X37: =J37/S37-1 | Y37: 1.8813 | Z37: =Y37/J37 | AA37: =(J37-R37)/Y37 | AB37: =(J37-S37)/Y37 | AC37: =IF(ABS(AA37)<=ABS(AB37),"9EMA","21EMA") | AD37: 9+21EMA | AE37: 持續在上方 | AI37: 2026-09-16 | AJ37: 12 | AK37: 2 | AL37: 2026-09-14 | AM37: 25.91 | AN37: 22.15 | AO37: =IF(ISNUMBER(AN37),AM37/AN37-1,"") | AP37: 14 | AQ37: =IF(ISNUMBER(AM37),J37/AM37-1,"") | AR37: 31.4 | AS37: =J37/AR37-1 | AT37: 0.8333 | AU37: 0.706 | AV37: 0.6742 | AW37: =AU37-AV37 | AX37: 0.1272 | AY37: 0.0618 | AZ37: 0.0595 | BA37: 深綠 | BB37: 淺綠→深綠 | BC37: 1 | BD37: 淺綠 淺綠 淺綠 淺綠 淺綠 淺綠 深綠 深綠 | BE37: 上傾收窄（楔形） | BF37: 1.1348 | BG37: 1.7361 | BH37: 0.6083 | BI37: 0.6138 | BJ37: 4 | BK37: 31.89 | BL37: 22.15 | BM37: 28.0745 | BN37: 0.5171 | BO37: =IF(M37=N37,0.5,(J37-N37)/(M37-N37)) | BP37: 37.433 | BQ37: 32.392 | BR37: =100*(0.4*MIN(1,MAX(0,((U37*100)-(0.0))/((2.5)-(0.0))))+0.3*MIN(1,MAX(0,((V37)-(0.6))/((1.0)-(0.6))))+0.3*MIN(1,MAX(0,((BP37)-(0.0))/((15.0)-(0.0))))) | BS37: =100*(0.4*MIN(1,MAX(0,((MIN(ABS(AA37),ABS(AB37)))-(0.75))/((0.0)-(0.75))))+0.3*MIN(1,MAX(0,((BN37)-(1.2))/((0.6)-(1.2))))+0.3*BO37) | BT37: =100*(0.5*MIN(1,MAX(0,((AK37)-(1.0))/((4.0)-(1.0))))+0.3*MIN(1,MAX(0,((IF(ISNUMBER(AO37),AO37,0)*100)-(0.0))/((8.0)-(0.0))))+0.2*MIN(1,MAX(0,((IF(ISNUMBER(AP37),AP37,0))-(25.0))/((5.0)-(25.0))))) | BU37: =100*(0.35*MIN(1,MAX(0,((ABS(BF37))-(0.3))/((0.05)-(0.3))))+0.3*MIN(1,MAX(0,((BG37)-(0.0))/((0.3)-(0.0))))+0.25*MIN(1,MAX(0,((BH37)-(0.4))/((0.7)-(0.4))))+0.1*IF(BJ37>=2,1,0.5)) | BV37: =0.25*BR37+0.25*BS37+0.2*BT37+0.3*BU37 | BW37: C4 上升三角／重心偏上
A38: 2 | B38: 11 | C38: AEHR | D38: Aehr Test Systems | E38: NASDAQ | F38: 工業 | G38: Electrical Products | H38: 3.254 | I38: 中型 | J38: 107.21 | K38: 101.6 | L38: =J38/K38-1 | M38: 109.48 | N38: 103.5 | O38: 2194100 | P38: 2601830 | Q38: =O38/P38 | R38: 100.3893 | S38: 97.0854 | T38: 94.1486 | U38: =S38/T38-1 | V38: 1 | W38: =J38/R38-1 | X38: =J38/S38-1 | Y38: 8.4959 | Z38: =Y38/J38 | AA38: =(J38-R38)/Y38 | AB38: =(J38-S38)/Y38 | AC38: =IF(ABS(AA38)<=ABS(AB38),"9EMA","21EMA") | AD38: 9EMA | AE38: 持續在上方 | AI38: 2026-09-22 | AJ38: 8 | AK38: 3 | AL38: 2026-09-15 | AM38: 80.95 | AN38: 74.23 | AO38: =IF(ISNUMBER(AN38),AM38/AN38-1,"") | AP38: 13 | AQ38: =IF(ISNUMBER(AM38),J38/AM38-1,"") | AR38: 107.21 | AS38: =J38/AR38-1 | AT38: 2.5776 | AU38: 1.0276 | AV38: 0.6401 | AW38: =AU38-AV38 | AX38: 1.55 | AY38: 1.3211 | AZ38: 1.4074 | BA38: 深綠 | BB38: 淺綠→深綠 | BC38: 0 | BD38: 深綠 淺綠 深綠 淺綠 淺綠 淺綠 淺綠 深綠 | BE38: 上傾擴張 | BF38: 0.9375 | BG38: 0.6965 | BH38: 0.4674 | BI38: 0.4666 | BJ38: 2 | BK38: 109.48 | BL38: 74.23 | BM38: 90.7052 | BN38: 0.9501 | BO38: =IF(M38=N38,0.5,(J38-N38)/(M38-N38)) | BP38: 38.653 | BQ38: 33.612 | BR38: =100*(0.4*MIN(1,MAX(0,((U38*100)-(0.0))/((2.5)-(0.0))))+0.3*MIN(1,MAX(0,((V38)-(0.6))/((1.0)-(0.6))))+0.3*MIN(1,MAX(0,((BP38)-(0.0))/((15.0)-(0.0))))) | BS38: =100*(0.4*MIN(1,MAX(0,((MIN(ABS(AA38),ABS(AB38)))-(0.75))/((0.0)-(0.75))))+0.3*MIN(1,MAX(0,((BN38)-(1.2))/((0.6)-(1.2))))+0.3*BO38) | BT38: =100*(0.5*MIN(1,MAX(0,((AK38)-(1.0))/((4.0)-(1.0))))+0.3*MIN(1,MAX(0,((IF(ISNUMBER(AO38),AO38,0)*100)-(0.0))/((8.0)-(0.0))))+0.2*MIN(1,MAX(0,((IF(ISNUMBER(AP38),AP38,0))-(25.0))/((5.0)-(25.0))))) | BU38: =100*(0.35*MIN(1,MAX(0,((ABS(BF38))-(0.3))/((0.05)-(0.3))))+0.3*MIN(1,MAX(0,((BG38)-(0.0))/((0.3)-(0.0))))+0.25*MIN(1,MAX(0,((BH38)-(0.4))/((0.7)-(0.4))))+0.1*IF(BJ38>=2,1,0.5)) | BV38: =0.25*BR38+0.25*BS38+0.2*BT38+0.3*BU38 | BW38: C4 上升三角／重心偏上
A39: 2 | B39: 12 | C39: QMCO | D39: Quantum Corporation | E39: NASDAQ | F39: 科技 | G39: Electronic Components | H39: 1.25 | I39: 小型 | J39: 34.5 | K39: 31.89 | L39: =J39/K39-1 | M39: 35.17 | N39: 29.85 | O39: 3576500 | P39: 1836965 | Q39: =O39/P39 | R39: 30.8552 | S39: 27.775 | T39: 24.8435 | U39: =S39/T39-1 | V39: 1 | W39: =J39/R39-1 | X39: =J39/S39-1 | Y39: 2.6866 | Z39: =Y39/J39 | AA39: =(J39-R39)/Y39 | AB39: =(J39-S39)/Y39 | AC39: =IF(ABS(AA39)<=ABS(AB39),"9EMA","21EMA") | AD39: 9EMA | AE39: 持續在上方 | AI39: 2026-08-05 | AJ39: 41 | AK39: 6 | AL39: 2026-09-14 | AM39: 21.8 | AN39: 21.41 | AO39: =IF(ISNUMBER(AN39),AM39/AN39-1,"") | AP39: 14 | AQ39: =IF(ISNUMBER(AM39),J39/AM39-1,"") | AR39: 34.5 | AS39: =J39/AR39-1 | AT39: 3.141 | AU39: 2.58 | AV39: 2.4397 | AW39: =AU39-AV39 | AX39: 0.561 | AY39: 0.4869 | AZ39: 0.5582 | BA39: 深綠 | BB39: 淺綠→深綠 | BC39: 0 | BD39: 淺紅 深綠 深綠 深綠 深綠 淺綠 淺綠 深綠 | BE39: 上傾擴張 | BF39: 1.3876 | BG39: 0.1256 | BH39: 0.4787 | BI39: 0.4687 | BJ39: 2 | BK39: 35.17 | BL39: 21.41 | BM39: 27.9969 | BN39: 0.4317 | BO39: =IF(M39=N39,0.5,(J39-N39)/(M39-N39)) | BP39: 56.49 | BQ39: 51.449 | BR39: =100*(0.4*MIN(1,MAX(0,((U39*100)-(0.0))/((2.5)-(0.0))))+0.3*MIN(1,MAX(0,((V39)-(0.6))/((1.0)-(0.6))))+0.3*MIN(1,MAX(0,((BP39)-(0.0))/((15.0)-(0.0))))) | BS39: =100*(0.4*MIN(1,MAX(0,((MIN(ABS(AA39),ABS(AB39)))-(0.75))/((0.0)-(0.75))))+0.3*MIN(1,MAX(0,((BN39)-(1.2))/((0.6)-(1.2))))+0.3*BO39) | BT39: =100*(0.5*MIN(1,MAX(0,((AK39)-(1.0))/((4.0)-(1.0))))+0.3*MIN(1,MAX(0,((IF(ISNUMBER(AO39),AO39,0)*100)-(0.0))/((8.0)-(0.0))))+0.2*MIN(1,MAX(0,((IF(ISNUMBER(AP39),AP39,0))-(25.0))/((5.0)-(25.0))))) | BU39: =100*(0.35*MIN(1,MAX(0,((ABS(BF39))-(0.3))/((0.05)-(0.3))))+0.3*MIN(1,MAX(0,((BG39)-(0.0))/((0.3)-(0.0))))+0.25*MIN(1,MAX(0,((BH39)-(0.4))/((0.7)-(0.4))))+0.1*IF(BJ39>=2,1,0.5)) | BV39: =0.25*BR39+0.25*BS39+0.2*BT39+0.3*BU39 | BW39: C4 上升三角／重心偏上
A40: 2 | B40: 13 | C40: AVT | D40: Avnet Inc. | E40: NASDAQ | F40: 科技 | G40: Electronic Components | H40: 8.203 | I40: 中型 | J40: 106.94 | K40: 102.24 | L40: =J40/K40-1 | M40: 108.63 | N40: 103.72 | O40: 2155900 | P40: 1435020 | Q40: =O40/P40 | R40: 101.5385 | S40: 98.2045 | T40: 95.3801 | U40: =S40/T40-1 | V40: 1 | W40: =J40/R40-1 | X40: =J40/S40-1 | Y40: 4.0145 | Z40: =Y40/J40 | AA40: =(J40-R40)/Y40 | AB40: =(J40-S40)/Y40 | AC40: =IF(ABS(AA40)<=ABS(AB40),"9EMA","21EMA") | AD40: 9EMA | AE40: 持續在上方 | AI40: 2026-09-08 | AJ40: 18 | AK40: 5 | AL40: 2026-09-16 | AM40: 90.9 | AN40: 86.71 | AO40: =IF(ISNUMBER(AN40),AM40/AN40-1,"") | AP40: 12 | AQ40: =IF(ISNUMBER(AM40),J40/AM40-1,"") | AR40: 106.94 | AS40: =J40/AR40-1 | AT40: 3.2157 | AU40: 2.4591 | AV40: 2.27 | AW40: =AU40-AV40 | AX40: 0.7566 | AY40: 0.5478 | AZ40: 0.6144 | BA40: 深綠 | BB40: 淺綠→深綠 | BC40: 0 | BD40: 深綠 深綠 深綠 淺綠 淺綠 淺綠 淺綠 深綠 | BE40: 上升通道 | BF40: 0.5819 | BG40: 0.4898 | BH40: 0.4507 | BI40: 0.4347 | BJ40: 1 | BK40: 108.63 | BL40: 86.71 | BM40: 96.5889 | BN40: 0.9245 | BO40: =IF(M40=N40,0.5,(J40-N40)/(M40-N40)) | BP40: 23.876 | BQ40: 18.835 | BR40: =100*(0.4*MIN(1,MAX(0,((U40*100)-(0.0))/((2.5)-(0.0))))+0.3*MIN(1,MAX(0,((V40)-(0.6))/((1.0)-(0.6))))+0.3*MIN(1,MAX(0,((BP40)-(0.0))/((15.0)-(0.0))))) | BS40: =100*(0.4*MIN(1,MAX(0,((MIN(ABS(AA40),ABS(AB40)))-(0.75))/((0.0)-(0.75))))+0.3*MIN(1,MAX(0,((BN40)-(1.2))/((0.6)-(1.2))))+0.3*BO40) | BT40: =100*(0.5*MIN(1,MAX(0,((AK40)-(1.0))/((4.0)-(1.0))))+0.3*MIN(1,MAX(0,((IF(ISNUMBER(AO40),AO40,0)*100)-(0.0))/((8.0)-(0.0))))+0.2*MIN(1,MAX(0,((IF(ISNUMBER(AP40),AP40,0))-(25.0))/((5.0)-(25.0))))) | BU40: =100*(0.35*MIN(1,MAX(0,((ABS(BF40))-(0.3))/((0.05)-(0.3))))+0.3*MIN(1,MAX(0,((BG40)-(0.0))/((0.3)-(0.0))))+0.25*MIN(1,MAX(0,((BH40)-(0.4))/((0.7)-(0.4))))+0.1*IF(BJ40>=2,1,0.5)) | BV40: =0.25*BR40+0.25*BS40+0.2*BT40+0.3*BU40 | BW40: C4 上升三角／重心偏上
... A42: 2 | B42: 15 | C42: PRLB | D42: Proto Labs Inc. Common stock | E42: NYSE | F42: 工業 | G42: Metal Fabrications | H42: 2.269 | I42: 中型 | J42: 98.21 | K42: 94.37 | L42: =J42/K42-1 | M42: 99.42 | N42: 95.49 | O42: 241100 | P42: 244785 | Q42: =O42/P42 | R42: 93.7785 | S42: 89.525 | T42: 85.5739 | U42: =S42/T42-1 | V42: 1 | W42: =J42/R42-1 | X42: =J42/S42-1 | Y42: 3.3165 | Z42: =Y42/J42 | AA42: =(J42-R42)/Y42 | AB42: =(J42-S42)/Y42 | AC42: =IF(ABS(AA42)<=ABS(AB42),"9EMA","21EMA") | AD42: — | AE42: 持續在上方 | AI42: 2026-09-17 | AJ42: 11 | AK42: 4 | AL42: 2026-09-15 | AM42: 77.88 | AN42: 77.05 | AO42: =IF(ISNUMBER(AN42),AM42/AN42-1,"") | AP42: 13 | AQ42: =IF(ISNUMBER(AM42),J42/AM42-1,"") | AR42: 98.21 | AS42: =J42/AR42-1 | AT42: 4.0124 | AU42: 2.9683 | AV42: 2.7073 | AW42: =AU42-AV42 | AX42: 1.0441 | AY42: 1.039 | AZ42: 1.2955 | BA42: 深綠 | BB42: 淺綠→深綠 | BC42: 0 | BD42: 深綠 深綠 深綠 深綠 淺綠 淺綠 淺綠 深綠 | BE42: 上傾擴張 | BF42: 0.2138 | BG42: 0.1207 | BH42: 0.4658 | BI42: 0.4627 | BJ42: 2 | BK42: 99.42 | BL42: 77.05 | BM42: 87.4691 | BN42: 0.8203 | BO42: =IF(M42=N42,0.5,(J42-N42)/(M42-N42)) | BP42: 30.006 | BQ42: 24.965 | BR42: =100*(0.4*MIN(1,MAX(0,((U42*100)-(0.0))/((2.5)-(0.0))))+0.3*MIN(1,MAX(0,((V42)-(0.6))/((1.0)-(0.6))))+0.3*MIN(1,MAX(0,((BP42)-(0.0))/((15.0)-(0.0))))) | BS42: =100*(0.4*MIN(1,MAX(0,((MIN(ABS(AA42),ABS(AB42)))-(0.75))/((0.0)-(0.75))))+0.3*MIN(1,MAX(0,((BN42)-(1.2))/((0.6)-(1.2))))+0.3*BO42) | BT42: =100*(0.5*MIN(1,MAX(0,((AK42)-(1.0))/((4.0)-(1.0))))+0.3*MIN(1,MAX(0,((IF(ISNUMBER(AO42),AO42,0)*100)-(0.0))/((8.0)-(0.0))))+0.2*MIN(1,MAX(0,((IF(ISNUMBER(AP42),AP42,0))-(25.0))/((5.0)-(25.0))))) | BU42: =100*(0.35*MIN(1,MAX(0,((ABS(BF42))-(0.3))/((0.05)-(0.3))))+0.3*MIN(1,MAX(0,((BG42)-(0.0))/((0.3)-(0.0))))+0.25*MIN(1,MAX(0,((BH42)-(0.4))/((0.7)-(0.4))))+0.1*IF(BJ42>=2,1,0.5)) | BV42: =0.25*BR42+0.25*BS42+0.2*BT42+0.3*BU42 | BW42: C4 上升三角／重心偏上
A43: 2 | B43: 16 | C43: KODK | D43: Eastman Kodak Company Common New | E43: NYSE | F43: 非必需消費 | G43: Industrial Machinery/Components | H43: 0.936 | I43: 小型 | J43: 9.81 | K43: 9.85 | L43: =J43/K43-1 | M43: 10.05 | N43: 9.69 | O43: 866400 | P43: 785255 | Q43: =O43/P43 | R43: 9.6494 | S43: 9.5319 | T43: 9.4333 | U43: =S43/T43-1 | V43: 1 | W43: =J43/R43-1 | X43: =J43/S43-1 | Y43: 0.3114 | Z43: =Y43/J43 | AA43: =(J43-R43)/Y43 | AB43: =(J43-S43)/Y43 | AC43: =IF(ABS(AA43)<=ABS(AB43),"9EMA","21EMA") | AD43: 9+21EMA | AE43: 持續在上方 | AH43: ✓ | AI43: 2026-09-17 | AJ43: 11 | AK43: 4 | AL43: 2026-09-28 | AM43: 9.36 | AN43: 8.85 | AO43: =IF(ISNUMBER(AN43),AM43/AN43-1,"") | AP43: 4 | AQ43: =IF(ISNUMBER(AM43),J43/AM43-1,"") | AR43: 9.85 | AS43: =J43/AR43-1 | AT43: 0.1143 | AU43: 0.0863 | AV43: 0.0793 | AW43: =AU43-AV43 | AX43: 0.028 | AY43: 0.024 | AZ43: 0.0104 | BA43: 深綠 | BB43: 淺綠→深綠 | BC43: 1 | BD43: 淺綠 淺綠 淺綠 淺綠 淺綠 淺綠 深綠 深綠 | BE43: 上升通道 | BF43: 0.3175 | BG43: 0.3774 | BH43: 0.4931 | BI43: 0.4791 | BJ43: 1 | BK43: 10.05 | BL43: 8.71 | BM43: 9.3708 | BN43: 0.8059 | BO43: =IF(M43=N43,0.5,(J43-N43)/(M43-N43)) | BP43: 11.787 | BQ43: 6.746 | BR43: =100*(0.4*MIN(1,MAX(0,((U43*100)-(0.0))/((2.5)-(0.0))))+0.3*MIN(1,MAX(0,((V43)-(0.6))/((1.0)-(0.6))))+0.3*MIN(1,MAX(0,((BP43)-(0.0))/((15.0)-(0.0))))) | BS43: =100*(0.4*MIN(1,MAX(0,((MIN(ABS(AA43),ABS(AB43)))-(0.75))/((0.0)-(0.75))))+0.3*MIN(1,MAX(0,((BN43)-(1.2))/((0.6)-(1.2))))+0.3*BO43) | BT43: =100*(0.5*MIN(1,MAX(0,((AK43)-(1.0))/((4.0)-(1.0))))+0.3*MIN(1,MAX(0,((IF(ISNUMBER(AO43),AO43,0)*100)-(0.0))/((8.0)-(0.0))))+0.2*MIN(1,MAX(0,((IF(ISNUMBER(AP43),AP43,0))-(25.0))/((5.0)-(25.0))))) | BU43: =100*(0.35*MIN(1,MAX(0,((ABS(BF43))-(0.3))/((0.05)-(0.3))))+0.3*MIN(1,MAX(0,((BG43)-(0.0))/((0.3)-(0.0))))+0.25*MIN(1,MAX(0,((BH43)-(0.4))/((0.7)-(0.4))))+0.1*IF(BJ43>=2,1,0.5)) | BV43: =0.25*BR43+0.25*BS43+0.2*BT43+0.3*BU43 | BW43: C4 上升三角／重心偏上
A44: 2 | B44: 17 | C44: PWRL | D44: Powerlaw Corp. | E44: NASDAQ | F44: — | G44: — | I44: 未分類 | J44: 11.4 | K44: 11.13 | L44: =J44/K44-1 | M44: 11.45 | N44: 10.93 | O44: 136500 | P44: 176740 | Q44: =O44/P44 | R44: 11.1139 | S44: 11.0372 | T44: 10.9926 | U44: =S44/T44-1 | V44: 0.9 | W44: =J44/R44-1 | X44: =J44/S44-1 | Y44: 0.5626 | Z44: =Y44/J44 | AA44: =(J44-R44)/Y44 | AB44: =(J44-S44)/Y44 | AC44: =IF(ABS(AA44)<=ABS(AB44),"9EMA","21EMA") | AD44: 9+21EMA | AE44: 持續在上方 | AH44: ✓ | AI44: 2026-09-22 | AJ44: 8 | AK44: 2 | AL44: 2026-09-29 | AM44: 10.5 | AN44: 9.41 | AO44: =IF(ISNUMBER(AN44),AM44/AN44-1,"") | AP44: 3 | AQ44: =IF(ISNUMBER(AM44),J44/AM44-1,"") | AR44: 11.41 | AS44: =J44/AR44-1 | AT44: -0.0114 | AU44: -0.1045 | AV44: -0.1278 | AW44: =AU44-AV44 | AX44: 0.0931 | AY44: 0.0823 | AZ44: 0.0874 | BA44: 深綠 | BB44: 淺綠→深綠 | BC44: 0 | BD44: 淺綠 淺綠 淺綠 淺綠 淺綠 淺綠 淺綠 深綠 | BE44: 上傾擴張 | BF44: 1.0234 | BG44: 0.5312 | BH44: 0.5644 | BI44: 0.5246 | BJ44: 4 | BK44: 11.69 | BL44: 9.41 | BM44: 10.6969 | BN44: 0.8109 | BO44: =IF(M44=N44,0.5,(J44-N44)/(M44-N44)) | BP44: 19.96 | BQ44: 14.919 | BR44: =100*(0.4*MIN(1,MAX(0,((U44*100)-(0.0))/((2.5)-(0.0))))+0.3*MIN(1,MAX(0,((V44)-(0.6))/((1.0)-(0.6))))+0.3*MIN(1,MAX(0,((BP44)-(0.0))/((15.0)-(0.0))))) | BS44: =100*(0.4*MIN(1,MAX(0,((MIN(ABS(AA44),ABS(AB44)))-(0.75))/((0.0)-(0.75))))+0.3*MIN(1,MAX(0,((BN44)-(1.2))/((0.6)-(1.2))))+0.3*BO44) | BT44: =100*(0.5*MIN(1,MAX(0,((AK44)-(1.0))/((4.0)-(1.0))))+0.3*MIN(1,MAX(0,((IF(ISNUMBER(AO44),AO44,0)*100)-(0.0))/((8.0)-(0.0))))+0.2*MIN(1,MAX(0,((IF(ISNUMBER(AP44),AP44,0))-(25.0))/((5.0)-(25.0))))) | BU44: =100*(0.35*MIN(1,MAX(0,((ABS(BF44))-(0.3))/((0.05)-(0.3))))+0.3*MIN(1,MAX(0,((BG44)-(0.0))/((0.3)-(0.0))))+0.25*MIN(1,MAX(0,((BH44)-(0.4))/((0.7)-(0.4))))+0.1*IF(BJ44>=2,1,0.5)) | BV44: =0.25*BR44+0.25*BS44+0.2*BT44+0.3*BU44 | BW44: C4 上升三角／重心偏上
A45: 2 | B45: 18 | C45: TSSI | D45: TSS Inc. | E45: NASDAQ | F45: 非必需消費 | G45: Professional Services | H45: 0.275 | I45: 小型 | J45: 10.24 | K45: 9.84 | L45: =J45/K45-1 | M45: 10.34 | N45: 9.96 | O45: 729900 | P45: 973285 | Q45: =O45/P45 | R45: 9.6976 | S45: 9.3503 | T45: 9.0202 | U45: =S45/T45-1 | V45: 1 | W45: =J45/R45-1 | X45: =J45/S45-1 | Y45: 0.5569 | Z45: =Y45/J45 | AA45: =(J45-R45)/Y45 | AB45: =(J45-S45)/Y45 | AC45: =IF(ABS(AA45)<=ABS(AB45),"9EMA","21EMA") | AD45: 9EMA | AE45: 持續在上方 | AI45: 2026-09-24 | AJ45: 6 | AK45: 2 | AL45: 2026-09-16 | AM45: 8.11 | AN45: 7.62 | AO45: =IF(ISNUMBER(AN45),AM45/AN45-1,"") | AP45: 12 | AQ45: =IF(ISNUMBER(AM45),J45/AM45-1,"") | AR45: 10.24 | AS45: =J45/AR45-1 | AT45: 0.2352 | AU45: 0.0506 | AV45: 0.0045 | AW45: =AU45-AV45 | AX45: 0.1846 | AY45: 0.1807 | AZ45: 0.1999 | BA45: 深綠 | BB45: 淺綠→深綠 | BC45: 0 | BD45: 深綠 深綠 深綠 淺綠 淺綠 淺綠 淺綠 深綠 | BE45: 上傾擴張 | BF45: 1.1426 | BG45: 0.4785 | BH45: 0.4941 | BI45: 0.5074 | BJ45: 1 | BK45: 10.51 | BL45: 7.62 | BM45: 9.0479 | BN45: 0.8691 | BO45: =IF(M45=N45,0.5,(J45-N45)/(M45-N45)) | BP45: 35.987 | BQ45: 30.946 | BR45: =100*(0.4*MIN(1,MAX(0,((U45*100)-(0.0))/((2.5)-(0.0))))+0.3*MIN(1,MAX(0,((V45)-(0.6))/((1.0)-(0.6))))+0.3*MIN(1,MAX(0,((BP45)-(0.0))/((15.0)-(0.0))))) | BS45: =100*(0.4*MIN(1,MAX(0,((MIN(ABS(AA45),ABS(AB45)))-(0.75))/((0.0)-(0.75))))+0.3*MIN(1,MAX(0,((BN45)-(1.2))/((0.6)-(1.2))))+0.3*BO45) | BT45: =100*(0.5*MIN(1,MAX(0,((AK45)-(1.0))/((4.0)-(1.0))))+0.3*MIN(1,MAX(0,((IF(ISNUMBER(AO45),AO45,0)*100)-(0.0))/((8.0)-(0.0))))+0.2*MIN(1,MAX(0,((IF(ISNUMBER(AP45),AP45,0))-(25.0))/((5.0)-(25.0))))) | BU45: =100*(0.35*MIN(1,MAX(0,((ABS(BF45))-(0.3))/((0.05)-(0.3))))+0.3*MIN(1,MAX(0,((BG45)-(0.0))/((0.3)-(0.0))))+0.25*MIN(1,MAX(0,((BH45)-(0.4))/((0.7)-(0.4))))+0.1*IF(BJ45>=2,1,0.5)) | BV45: =0.25*BR45+0.25*BS45+0.2*BT45+0.3*BU45 | BW45: C4 上升三角／重心偏上
A46: 2 | B46: 19 | C46: PI | D46: Impinj Inc. | E46: NASDAQ | F46: 科技 | G46: Industrial Machinery/Components | H46: 5.478 | I46: 中型 | J46: 189.61 | K46: 183.87 | L46: =J46/K46-1 | M46: 192.645 | N46: 187.99 | O46: 479100 | P46: 409085 | Q46: =O46/P46 | R46: 181.157 | S46: 177.4395 | T46: 174.7426 | U46: =S46/T46-1 | V46: 1 | W46: =J46/R46-1 | X46: =J46/S46-1 | Y46: 7.4958 | Z46: =Y46/J46 | AA46: =(J46-R46)/Y46 | AB46: =(J46-S46)/Y46 | AC46: =IF(ABS(AA46)<=ABS(AB46),"9EMA","21EMA") | AD46: 9+21EMA | AE46: 持續在上方 | AI46: 2026-07-30 | AJ46: 45 | AK46: 4 | AL46: 2026-09-24 | AM46: 172.4 | AN46: 161.17 | AO46: =IF(ISNUMBER(AN46),AM46/AN46-1,"") | AP46: 6 | AQ46: =IF(ISNUMBER(AM46),J46/AM46-1,"") | AR46: 189.61 | AS46: =J46/AR46-1 | AT46: 4.1898 | AU46: 3.9046 | AV46: 3.8333 | AW46: =AU46-AV46 | AX46: 0.2852 | AY46: -0.2736 | AZ46: -0.6136 | BA46: 深綠 | BB46: 深紅→淺紅 | BC46: 2 | BD46: 淺綠 深紅 深紅 深紅 深紅 淺紅 淺紅 深綠 | BE46: 上傾收窄（楔形） | BF46: 0.2344 | BG46: 0.5923 | BH46: 0.496 | BI46: 0.485 | BJ46: 1 | BK46: 192.645 | BL46: 161.17 | BM46: 176.781 | BN46: 1.3298 | BO46: =IF(M46=N46,0.5,(J46-N46)/(M46-N46)) | BP46: 13.359 | BQ46: 8.318 | BR46: =100*(0.4*MIN(1,MAX(0,((U46*100)-(0.0))/((2.5)-(0.0))))+0.3*MIN(1,MAX(0,((V46)-(0.6))/((1.0)-(0.6))))+0.3*MIN(1,MAX(0,((BP46)-(0.0))/((15.0)-(0.0))))) | BS46: =100*(0.4*MIN(1,MAX(0,((MIN(ABS(AA46),ABS(AB46)))-(0.75))/((0.0)-(0.75))))+0.3*MIN(1,MAX(0,((BN46)-(1.2))/((0.6)-(1.2))))+0.3*BO46) | BT46: =100*(0.5*MIN(1,MAX(0,((AK46)-(1.0))/((4.0)-(1.0))))+0.3*MIN(1,MAX(0,((IF(ISNUMBER(AO46),AO46,0)*100)-(0.0))/((8.0)-(0.0))))+0.2*MIN(1,MAX(0,((IF(ISNUMBER(AP46),AP46,0))-(25.0))/((5.0)-(25.0))))) | BU46: =100*(0.35*MIN(1,MAX(0,((ABS(BF46))-(0.3))/((0.05)-(0.3))))+0.3*MIN(1,MAX(0,((BG46)-(0.0))/((0.3)-(0.0))))+0.25*MIN(1,MAX(0,((BH46)-(0.4))/((0.7)-(0.4))))+0.1*IF(BJ46>=2,1,0.5)) | BV46: =0.25*BR46+0.25*BS46+0.2*BT46+0.3*BU46 | BW46: C4 上升三角／重心偏上
A47: 2 | B47: 20 | C47: SWBI | D47: Smith & Wesson Brands Inc. | E47: NASDAQ | F47: 工業 | G47: Ordnance And Accessories | H47: 0.63 | I47: 小型 | J47: 14.64 | K47: 14.41 | L47: =J47/K47-1 | M47: 14.75 | N47: 14.47 | O47: 445500 | P47: 632665 | Q47: =O47/P47 | R47: 14.1475 | S47: 13.8701 | T47: 13.6257 | U47: =S47/T47-1 | V47: 1 | W47: =J47/R47-1 | X47: =J47/S47-1 | Y47: 0.3844 | Z47: =Y47/J47 | AA47: =(J47-R47)/Y47 | AB47: =(J47-S47)/Y47 | AC47: =IF(ABS(AA47)<=ABS(AB47),"9EMA","21EMA") | AD47: 9EMA | AE47: 持續在上方 | AI47: 2026-09-22 | AJ47: 8 | AK47: 2 | AL47: 2026-09-17 | AM47: 12.9 | AN47: 12.09 | AO47: =IF(ISNUMBER(AN47),AM47/AN47-1,"") | AP47: 11 | AQ47: =IF(ISNUMBER(AM47),J47/AM47-1,"") | AR47: 14.64 | AS47: =J47/AR47-1 | AT47: 0.1981 | AU47: 0.0602 | AV47: 0.0257 | AW47: =AU47-AV47 | AX47: 0.1379 | AY47: 0.1274 | AZ47: 0.1229 | BA47: 深綠 | BB47: 淺綠→深綠 | BC47: 1 | BD47: 深綠 深綠 深綠 淺綠 淺綠 淺綠 深綠 深綠 | BE47: 上傾收窄（楔形） | BF47: 0.4519 | BG47: 0.6148 | BH47: 0.4676 | BI47: 0.4488 | BJ47: 1 | BK47: 14.75 | BL47: 12.09 | BM47: 13.3337 | BN47: 0.9219 | BO47: =IF(M47=N47,0.5,(J47-N47)/(M47-N47)) | BP47: 19.595 | BQ47: 14.554 | BR47: =100*(0.4*MIN(1,MAX(0,((U47*100)-(0.0))/((2.5)-(0.0))))+0.3*MIN(1,MAX(0,((V47)-(0.6))/((1.0)-(0.6))))+0.3*MIN(1,MAX(0,((BP47)-(0.0))/((15.0)-(0.0))))) | BS47: =100*(0.4*MIN(1,MAX(0,((MIN(ABS(AA47),ABS(AB47)))-(0.75))/((0.0)-(0.75))))+0.3*MIN(1,MAX(0,((BN47)-(1.2))/((0.6)-(1.2))))+0.3*BO47) | BT47: =100*(0.5*MIN(1,MAX(0,((AK47)-(1.0))/((4.0)-(1.0))))+0.3*MIN(1,MAX(0,((IF(ISNUMBER(AO47),AO47,0)*100)-(0.0))/((8.0)-(0.0))))+0.2*MIN(1,MAX(0,((IF(ISNUMBER(AP47),AP47,0))-(25.0))/((5.0)-(25.0))))) | BU47: =100*(0.35*MIN(1,MAX(0,((ABS(BF47))-(0.3))/((0.05)-(0.3))))+0.3*MIN(1,MAX(0,((BG47)-(0.0))/((0.3)-(0.0))))+0.25*MIN(1,MAX(0,((BH47)-(0.4))/((0.7)-(0.4))))+0.1*IF(BJ47>=2,1,0.5)) | BV47: =0.25*BR47+0.25*BS47+0.2*BT47+0.3*BU47 | BW47: C4 上升三角／重心偏上
A48: 2 | B48: 21 | C48: RLGT | D48: Radiant Logistics Inc. | E48: AMEX | F48: 工業 | G48: Integrated Freight & Logistics | H48: 0.408 | I48: 小型 | J48: 9.36 | K48: 9.01 | L48: =J48/K48-1 | M48: 9.36 | N48: 9.06 | O48: 159300 | P48: 406800 | Q48: =O48/P48 | R48: 8.8754 | S48: 8.7451 | T48: 8.6221 | U48: =S48/T48-1 | V48: 0.7 | W48: =J48/R48-1 | X48: =J48/S48-1 | Y48: 0.3239 | Z48: =Y48/J48 | AA48: =(J48-R48)/Y48 | AB48: =(J48-S48)/Y48 | AC48: =IF(ABS(AA48)<=ABS(AB48),"9EMA","21EMA") | AD48: 9+21EMA | AE48: 持續在上方 | AI48: 2026-09-15 | AJ48: 13 | AK48: 4 | AL48: 2026-09-28 | AM48: 8.49 | AN48: 8.44 | AO48: =IF(ISNUMBER(AN48),AM48/AN48-1,"") | AP48: 4 | AQ48: =IF(ISNUMBER(AM48),J48/AM48-1,"") | AR48: 9.81 | AS48: =J48/AR48-1 | AT48: 0.1038 | AU48: 0.0461 | AV48: 0.0317 | AW48: =AU48-AV48 | AX48: 0.0577 | AY48: 0.0262 | AZ48: 0.0088 | BA48: 深綠 | BB48: 淺綠→深綠 | BC48: 1 | BD48: 淺綠 淺綠 淺綠 深綠 深綠 淺綠 深綠 深綠 | BE48: 上傾收窄（楔形） | BF48: 0.2124 | BG48: 0.3385 | BH48: 0.4578 | BI48: 0.5383 | BJ48: 1 | BK48: 10.2 | BL48: 8.05 | BM48: 9.0343 | BN48: 1.3135 | BO48: =IF(M48=N48,0.5,(J48-N48)/(M48-N48)) | BP48: 19.466 | BQ48: 14.425 | BR48: =100*(0.4*MIN(1,MAX(0,((U48*100)-(0.0))/((2.5)-(0.0))))+0.3*MIN(1,MAX(0,((V48)-(0.6))/((1.0)-(0.6))))+0.3*MIN(1,MAX(0,((BP48)-(0.0))/((15.0)-(0.0))))) | BS48: =100*(0.4*MIN(1,MAX(0,((MIN(ABS(AA48),ABS(AB48)))-(0.75))/((0.0)-(0.75))))+0.3*MIN(1,MAX(0,((BN48)-(1.2))/((0.6)-(1.2))))+0.3*BO48) | BT48: =100*(0.5*MIN(1,MAX(0,((AK48)-(1.0))/((4.0)-(1.0))))+0.3*MIN(1,MAX(0,((IF(ISNUMBER(AO48),AO48,0)*100)-(0.0))/((8.0)-(0.0))))+0.2*MIN(1,MAX(0,((IF(ISNUMBER(AP48),AP48,0))-(25.0))/((5.0)-(25.0))))) | BU48: =100*(0.35*MIN(1,MAX(0,((ABS(BF48))-(0.3))/((0.05)-(0.3))))+0.3*MIN(1,MAX(0,((BG48)-(0.0))/((0.3)-(0.0))))+0.25*MIN(1,MAX(0,((BH48)-(0.4))/((0.7)-(0.4))))+0.1*IF(BJ48>=2,1,0.5)) | BV48: =0.25*BR48+0.25*BS48+0.2*BT48+0.3*BU48 | BW48: C4 上升三角／重心偏上
A49: 2 | B49: 22 | C49: CLDT | D49: Chatham Lodging Trust (REIT) | E49: NYSE | F49: 房地產 | G49: Real Estate Investment Trusts | H49: 0.623 | I49: 小型 | J49: 13.68 | K49: 13.56 | L49: =J49/K49-1 | M49: 13.78 | N49: 13.22 | O49: 267100 | P49: 289470 | Q49: =O49/P49 | R49: 13.4043 | S49: 13.2634 | T49: 13.1183 | U49: =S49/T49-1 | V49: 1 | W49: =J49/R49-1 | X49: =J49/S49-1 | Y49: 0.3516 | Z49: =Y49/J49 | AA49: =(J49-R49)/Y49 | AB49: =(J49-S49)/Y49 | AC49: =IF(ABS(AA49)<=ABS(AB49),"9EMA","21EMA") | AD49: 9+21EMA | AE49: 持續在上方 | AH49: ✓ | AI49: 2026-09-24 | AJ49: 6 | AK49: 3 | AL49: 2026-09-16 | AM49: 12.64 | AN49: 12.53 | AO49: =IF(ISNUMBER(AN49),AM49/AN49-1,"") | AP49: 12 | AQ49: =IF(ISNUMBER(AM49),J49/AM49-1,"") | AR49: 13.68 | AS49: =J49/AR49-1 | AT49: 0.1145 | AU49: 0.0499 | AV49: 0.0338 | AW49: =AU49-AV49 | AX49: 0.0646 | AY49: 0.0563 | AZ49: 0.0501 | BA49: 深綠 | BB49: 淺綠→深綠 | BC49: 1 | BD49: 深綠 深綠 深綠 深綠 深綠 淺綠 深綠 深綠 | BE49: 上升三角（平頂） | BF49: 0.0913 | BG49: 0.1608 | BH49: 0.4883 | BI49: 0.4379 | BJ49: 4 | BK49: 13.78 | BL49: 12.53 | BM49: 13.1403 | BN49: 1.1727 | BO49: =IF(M49=N49,0.5,(J49-N49)/(M49-N49)) | BP49: 9.151 | BQ49: 4.11 | BR49: =100*(0.4*MIN(1,MAX(0,((U49*100)-(0.0))/((2.5)-(0.0))))+0.3*MIN(1,MAX(0,((V49)-(0.6))/((1.0)-(0.6))))+0.3*MIN(1,MAX(0,((BP49)-(0.0))/((15.0)-(0.0))))) | BS49: =100*(0.4*MIN(1,MAX(0,((MIN(ABS(AA49),ABS(AB49)))-(0.75))/((0.0)-(0.75))))+0.3*MIN(1,MAX(0,((BN49)-(1.2))/((0.6)-(1.2))))+0.3*BO49) | BT49: =100*(0.5*MIN(1,MAX(0,((AK49)-(1.0))/((4.0)-(1.0))))+0.3*MIN(1,MAX(0,((IF(ISNUMBER(AO49),AO49,0)*100)-(0.0))/((8.0)-(0.0))))+0.2*MIN(1,MAX(0,((IF(ISNUMBER(AP49),AP49,0))-(25.0))/((5.0)-(25.0))))) | BU49: =100*(0.35*MIN(1,MAX(0,((ABS(BF49))-(0.3))/((0.05)-(0.3))))+0.3*MIN(1,MAX(0,((BG49)-(0.0))/((0.3)-(0.0))))+0.25*MIN(1,MAX(0,((BH49)-(0.4))/((0.7)-(0.4))))+0.1*IF(BJ49>=2,1,0.5)) | BV49: =0.25*BR49+0.25*BS49+0.2*BT49+0.3*BU49 | BW49: C4 上升三角／重心偏上
A50: 2 | B50: 23 | C50: WMK | D50: Weis Markets Inc. | E50: NYSE | F50: 必需消費 | G50: Food Chains | H50: 1.806 | I50: 小型 | J50: 74.04 | K50: 72.62 | L50: =J50/K50-1 | M50: 74.22 | N50: 72.78 | O50: 149600 | P50: 226195 | Q50: =O50/P50 | R50: 72.8905 | S50: 72.513 | T50: 72.1428 | U50: =S50/T50-1 | V50: 0.9 | W50: =J50/R50-1 | X50: =J50/S50-1 | Y50: 1.6037 | Z50: =Y50/J50 | AA50: =(J50-R50)/Y50 | AB50: =(J50-S50)/Y50 | AC50: =IF(ABS(AA50)<=ABS(AB50),"9EMA","21EMA") | AD50: 9+21EMA | AE50: 持續在上方 | AH50: ✓ | AI50: 2026-09-16 | AJ50: 12 | AK50: 4 | AL50: 2026-09-25 | AM50: 71.41 | AN50: 69.46 | AO50: =IF(ISNUMBER(AN50),AM50/AN50-1,"") | AP50: 5 | AQ50: =IF(ISNUMBER(AM50),J50/AM50-1,"") | AR50: 74.04 | AS50: =J50/AR50-1 | AT50: 0.2322 | AU50: 0.0237 | AV50: -0.0285 | AW50: =AU50-AV50 | AX50: 0.2085 | AY50: 0.1475 | AZ50: 0.1827 | BA50: 深綠 | BB50: 淺綠→深綠 | BC50: 0 | BD50: 淺綠 淺綠 淺綠 深綠 淺綠 淺綠 淺綠 深綠 | BE50: 上升通道 | BF50: 0.2992 | BG50: 0.2394 | BH50: 0.4578 | BI50: 0.5566 | BJ50: 2 | BK50: 75.32 | BL50: 69.46 | BM50: 72.1424 | BN50: 0.8928 | BO50: =IF(M50=N50,0.5,(J50-N50)/(M50-N50)) | BP50: 10.226 | BQ50: 5.185 | BR50: =100*(0.4*MIN(1,MAX(0,((U50*100)-(0.0))/((2.5)-(0.0))))+0.3*MIN(1,MAX(0,((V50)-(0.6))/((1.0)-(0.6))))+0.3*MIN(1,MAX(0,((BP50)-(0.0))/((15.0)-(0.0))))) | BS50: =100*(0.4*MIN(1,MAX(0,((MIN(ABS(AA50),ABS(AB50)))-(0.75))/((0.0)-(0.75))))+0.3*MIN(1,MAX(0,((BN50)-(1.2))/((0.6)-(1.2))))+0.3*BO50) | BT50: =100*(0.5*MIN(1,MAX(0,((AK50)-(1.0))/((4.0)-(1.0))))+0.3*MIN(1,MAX(0,((IF(ISNUMBER(AO50),AO50,0)*100)-(0.0))/((8.0)-(0.0))))+0.2*MIN(1,MAX(0,((IF(ISNUMBER(AP50),AP50,0))-(25.0))/((5.0)-(25.0))))) | BU50: =100*(0.35*MIN(1,MAX(0,((ABS(BF50))-(0.3))/((0.05)-(0.3))))+0.3*MIN(1,MAX(0,((BG50)-(0.0))/((0.3)-(0.0))))+0.25*MIN(1,MAX(0,((BH50)-(0.4))/((0.7)-(0.4))))+0.1*IF(BJ50>=2,1,0.5)) | BV50: =0.25*BR50+0.25*BS50+0.2*BT50+0.3*BU50 | BW50: C4 上升三角／重心偏上
A51: 2 | B51: 24 | C51: MRVI | D51: Maravai LifeSciences Holdings Inc. | E51: NASDAQ | F51: 醫療保健 | G51: Biotechnology: Pharmaceutical Preparations | H51: 1.989 | I51: 小型 | J51: 7.9 | K51: 7.5 | L51: =J51/K51-1 | M51: 7.92 | N51: 7.5 | O51: 1913600 | P51: 2495150 | Q51: =O51/P51 | R51: 7.5729 | S51: 7.4011 | T51: 7.2332 | U51: =S51/T51-1 | V51: 1 | W51: =J51/R51-1 | X51: =J51/S51-1 | Y51: 0.3915 | Z51: =Y51/J51 | AA51: =(J51-R51)/Y51 | AB51: =(J51-S51)/Y51 | AC51: =IF(ABS(AA51)<=ABS(AB51),"9EMA","21EMA") | AD51: 9+21EMA | AE51: 持續在上方 | AI51: 2026-09-23 | AJ51: 7 | AK51: 3 | AL51: 2026-09-11 | AM51: 6.485 | AN51: 5.53 | AO51: =IF(ISNUMBER(AN51),AM51/AN51-1,"") | AP51: 15 | AQ51: =IF(ISNUMBER(AM51),J51/AM51-1,"") | AR51: 7.9 | AS51: =J51/AR51-1 | AT51: 0.1688 | AU51: 0.1219 | AV51: 0.1102 | AW51: =AU51-AV51 | AX51: 0.0469 | AY51: 0.033 | AZ51: 0.0471 | BA51: 深綠 | BB51: 淺綠→深綠 | BC51: 0 | BD51: 淺紅 深綠 深綠 深綠 深綠 淺綠 淺綠 深綠 | BE51: 上傾擴張 | BF51: 0.6203 | BG51: 0.0775 | BH51: 0.4839 | BI51: 0.5641 | BJ51: 1 | BK51: 8.175 | BL51: 6.485 | BM51: 7.3029 | BN51: 1.1786 | BO51: =IF(M51=N51,0.5,(J51-N51)/(M51-N51)) | BP51: 12.087 | BQ51: 7.046 | BR51: =100*(0.4*MIN(1,MAX(0,((U51*100)-(0.0))/((2.5)-(0.0))))+0.3*MIN(1,MAX(0,((V51)-(0.6))/((1.0)-(0.6))))+0.3*MIN(1,MAX(0,((BP51)-(0.0))/((15.0)-(0.0))))) | BS51: =100*(0.4*MIN(1,MAX(0,((MIN(ABS(AA51),ABS(AB51)))-(0.75))/((0.0)-(0.75))))+0.3*MIN(1,MAX(0,((BN51)-(1.2))/((0.6)-(1.2))))+0.3*BO51) | BT51: =100*(0.5*MIN(1,MAX(0,((AK51)-(1.0))/((4.0)-(1.0))))+0.3*MIN(1,MAX(0,((IF(ISNUMBER(AO51),AO51,0)*100)-(0.0))/((8.0)-(0.0))))+0.2*MIN(1,MAX(0,((IF(ISNUMBER(AP51),AP51,0))-(25.0))/((5.0)-(25.0))))) | BU51: =100*(0.35*MIN(1,MAX(0,((ABS(BF51))-(0.3))/((0.05)-(0.3))))+0.3*MIN(1,MAX(0,((BG51)-(0.0))/((0.3)-(0.0))))+0.25*MIN(1,MAX(0,((BH51)-(0.4))/((0.7)-(0.4))))+0.1*IF(BJ51>=2,1,0.5)) | BV51: =0.25*BR51+0.25*BS51+0.2*BT51+0.3*BU51 | BW51: C4 上升三角／重心偏上
A52: 2 | B52: 25 | C52: AIP | D52: Arteris Inc. | E52: NASDAQ | F52: 科技 | G52: Semiconductors | H52: 1.162 | I52: 小型 | J52: 24.66 | K52: 24.01 | L52: =J52/K52-1 | M52: 25.15 | N52: 24.27 | O52: 614000 | P52: 687955 | Q52: =O52/P52 | R52: 23.7464 | S52: 23.5457 | T52: 23.3833 | U52: =S52/T52-1 | V52: 0.8 | W52: =J52/R52-1 | X52: =J52/S52-1 | Y52: 1.2836 | Z52: =Y52/J52 | AA52: =(J52-R52)/Y52 | AB52: =(J52-S52)/Y52 | AC52: =IF(ABS(AA52)<=ABS(AB52),"9EMA","21EMA") | AD52: 9+21EMA | AE52: 剛黃金交叉 | AF52: ✓ | AI52: 2026-09-30 | AJ52: 2 | AK52: 2 | AL52: 2026-09-28 | AM52: 22.54 | AN52: 20.02 | AO52: =IF(ISNUMBER(AN52),AM52/AN52-1,"") | AP52: 4 | AQ52: =IF(ISNUMBER(AM52),J52/AM52-1,"") | AR52: 24.78 | AS52: =J52/AR52-1 | AT52: -0.1597 | AU52: -0.573 | AV52: -0.6763 | AW52: =AU52-AV52 | AX52: 0.4133 | AY52: 0.3952 | AZ52: 0.4092 | BA52: 深綠 | BB52: 淺綠→深綠 | BC52: 0 | BD52: 深綠 淺綠 淺綠 淺綠 淺綠 淺綠 淺綠 深綠 | BE52: 上傾收窄（楔形） | BF52: 0.4579 | BG52: 0.6026 | BH52: 0.488 | BI52: 0.4836 | BJ52: 3 | BK52: 25.15 | BL52: 20.02 | BM52: 22.5232 | BN52: 0.7751 | BO52: =IF(M52=N52,0.5,(J52-N52)/(M52-N52)) | BP52: 23.371 | BQ52: 18.33 | BR52: =100*(0.4*MIN(1,MAX(0,((U52*100)-(0.0))/((2.5)-(0.0))))+0.3*MIN(1,MAX(0,((V52)-(0.6))/((1.0)-(0.6))))+0.3*MIN(1,MAX(0,((BP52)-(0.0))/((15.0)-(0.0))))) | BS52: =100*(0.4*MIN(1,MAX(0,((MIN(ABS(AA52),ABS(AB52)))-(0.75))/((0.0)-(0.75))))+0.3*MIN(1,MAX(0,((BN52)-(1.2))/((0.6)-(1.2))))+0.3*BO52) | BT52: =100*(0.5*MIN(1,MAX(0,((AK52)-(1.0))/((4.0)-(1.0))))+0.3*MIN(1,MAX(0,((IF(ISNUMBER(AO52),AO52,0)*100)-(0.0))/((8.0)-(0.0))))+0.2*MIN(1,MAX(0,((IF(ISNUMBER(AP52),AP52,0))-(25.0))/((5.0)-(25.0))))) | BU52: =100*(0.35*MIN(1,MAX(0,((ABS(BF52))-(0.3))/((0.05)-(0.3))))+0.3*MIN(1,MAX(0,((BG52)-(0.0))/((0.3)-(0.0))))+0.25*MIN(1,MAX(0,((BH52)-(0.4))/((0.7)-(0.4))))+0.1*IF(BJ52>=2,1,0.5)) | BV52: =0.25*BR52+0.25*BS52+0.2*BT52+0.3*BU52 | BW52: C4 上升三角／重心偏上
A53: 2 | B53: 26 | C53: WEST | D53: Westrock Coffee Company | E53: NASDAQ | F53: 必需消費 | G53: Beverages (Production/Distribution) | H53: 0.785 | I53: 小型 | J53: 8.14 | K53: 8 | L53: =J53/K53-1 | M53: 8.255 | N53: 8.02 | O53: 339000 | P53: 323040 | Q53: =O53/P53 | R53: 8.0502 | S53: 7.9964 | T53: 7.9307 | U53: =S53/T53-1 | V53: 0.9 | W53: =J53/R53-1 | X53: =J53/S53-1 | Y53: 0.2959 | Z53: =Y53/J53 | AA53: =(J53-R53)/Y53 | AB53: =(J53-S53)/Y53 | AC53: =IF(ABS(AA53)<=ABS(AB53),"9EMA","21EMA") | AD53: 9+21EMA | AE53: 持續在上方 | AH53: ✓ | AI53: 2026-09-24 | AJ53: 6 | AK53: 3 | AL53: 2026-09-21 | AM53: 7.66 | AN53: 7.58 | AO53: =IF(ISNUMBER(AN53),AM53/AN53-1,"") | AP53: 9 | AQ53: =IF(ISNUMBER(AM53),J53/AM53-1,"") | AR53: 8.25 | AS53: =J53/AR53-1 | AT53: 0.0371 | AU53: 0.0061 | AV53: -0.0016 | AW53: =AU53-AV53 | AX53: 0.031 | AY53: 0.0303 | AZ53: 0.0409 | BA53: 深綠 | BB53: 淺綠→深綠 | BC53: 0 | BD53: 深綠 淺綠 深綠 深綠 淺綠 淺綠 淺綠 深綠 | BE53: 上升通道 | BF53: 0.1185 | BG53: 0.1404 | BH53: 0.4616 | BI53: 0.3915 | BJ53: 9 | BK53: 8.28 | BL53: 7.58 | BM53: 7.9031 | BN53: 1.1721 | BO53: =IF(M53=N53,0.5,(J53-N53)/(M53-N53)) | BP53: 8.867 | BQ53: 3.827 | BR53: =100*(0.4*MIN(1,MAX(0,((U53*100)-(0.0))/((2.5)-(0.0))))+0.3*MIN(1,MAX(0,((V53)-(0.6))/((1.0)-(0.6))))+0.3*MIN(1,MAX(0,((BP53)-(0.0))/((15.0)-(0.0))))) | BS53: =100*(0.4*MIN(1,MAX(0,((MIN(ABS(AA53),ABS(AB53)))-(0.75))/((0.0)-(0.75))))+0.3*MIN(1,MAX(0,((BN53)-(1.2))/((0.6)-(1.2))))+0.3*BO53) | BT53: =100*(0.5*MIN(1,MAX(0,((AK53)-(1.0))/((4.0)-(1.0))))+0.3*MIN(1,MAX(0,((IF(ISNUMBER(AO53),AO53,0)*100)-(0.0))/((8.0)-(0.0))))+0.2*MIN(1,MAX(0,((IF(ISNUMBER(AP53),AP53,0))-(25.0))/((5.0)-(25.0))))) | BU53: =100*(0.35*MIN(1,MAX(0,((ABS(BF53))-(0.3))/((0.05)-(0.3))))+0.3*MIN(1,MAX(0,((BG53)-(0.0))/((0.3)-(0.0))))+0.25*MIN(1,MAX(0,((BH53)-(0.4))/((0.7)-(0.4))))+0.1*IF(BJ53>=2,1,0.5)) | BV53: =0.25*BR53+0.25*BS53+0.2*BT53+0.3*BU53 | BW53: C4 上升三角／重心偏上
A54: 2 | B54: 27 | C54: HWKN | D54: Hawkins Inc. | E54: NASDAQ | F54: 非必需消費 | G54: Specialty Chemicals | H54: 2.63 | I54: 中型 | J54: 131.41 | K54: 127.19 | L54: =J54/K54-1 | M54: 132.41 | N54: 129.45 | O54: 199700 | P54: 183740 | Q54: =O54/P54 | R54: 127.1746 | S54: 126.0202 | T54: 124.8825 | U54: =S54/T54-1 | V54: 0.9 | W54: =J54/R54-1 | X54: =J54/S54-1 | Y54: 4.0223 | Z54: =Y54/J54 | AA54: =(J54-R54)/Y54 | AB54: =(J54-S54)/Y54 | AC54: =IF(ABS(AA54)<=ABS(AB54),"9EMA","21EMA") | AD54: 9+21EMA | AE54: 剛黃金交叉 | AF54: ✓ | AI54: 2026-09-25 | AJ54: 5 | AK54: 2 | AL54: 2026-09-15 | AM54: 118.71 | AN54: 116.05 | AO54: =IF(ISNUMBER(AN54),AM54/AN54-1,"") | AP54: 13 | AQ54: =IF(ISNUMBER(AM54),J54/AM54-1,"") | AR54: 131.41 | AS54: =J54/AR54-1 | AT54: 0.5145 | AU54: -0.3886 | AV54: -0.6144 | AW54: =AU54-AV54 | AX54: 0.9031 | AY54: 0.6856 | AZ54: 0.72 | BA54: 深綠 | BB54: 淺綠→深綠 | BC54: 0 | BD54: 淺綠 深綠 深綠 深綠 淺綠 淺綠 淺綠 深綠 | BE54: 上升三角（平頂） | BF54: -0.0288 | BG54: 0.1712 | BH54: 0.4746 | BI54: 0.4196 | BJ54: 2 | BK54: 132.41 | BL54: 118.2 | BM54: 124.9444 | BN54: 0.8964 | BO54: =IF(M54=N54,0.5,(J54-N54)/(M54-N54)) | BP54: 9.029 | BQ54: 3.988 | BR54: =100*(0.4*MIN(1,MAX(0,((U54*100)-(0.0))/((2.5)-(0.0))))+0.3*MIN(1,MAX(0,((V54)-(0.6))/((1.0)-(0.6))))+0.3*MIN(1,MAX(0,((BP54)-(0.0))/((15.0)-(0.0))))) | BS54: =100*(0.4*MIN(1,MAX(0,((MIN(ABS(AA54),ABS(AB54)))-(0.75))/((0.0)-(0.75))))+0.3*MIN(1,MAX(0,((BN54)-(1.2))/((0.6)-(1.2))))+0.3*BO54) | BT54: =100*(0.5*MIN(1,MAX(0,((AK54)-(1.0))/((4.0)-(1.0))))+0.3*MIN(1,MAX(0,((IF(ISNUMBER(AO54),AO54,0)*100)-(0.0))/((8.0)-(0.0))))+0.2*MIN(1,MAX(0,((IF(ISNUMBER(AP54),AP54,0))-(25.0))/((5.0)-(25.0))))) | BU54: =100*(0.35*MIN(1,MAX(0,((ABS(BF54))-(0.3))/((0.05)-(0.3))))+0.3*MIN(1,MAX(0,((BG54)-(0.0))/((0.3)-(0.0))))+0.25*MIN(1,MAX(0,((BH54)-(0.4))/((0.7)-(0.4))))+0.1*IF(BJ54>=2,1,0.5)) | BV54: =0.25*BR54+0.25*BS54+0.2*BT54+0.3*BU54 | BW54: C4 上升三角／重心偏上
A55: 2 | B55: 28 | C55: FIX | D55: Comfort Systems USA Inc. | E55: NYSE | F55: 工業 | G55: Engineering & Construction | H55: 58.215 | I55: 大型 | J55: 1728.01 | K55: 1685.29 | L55: =J55/K55-1 | M55: 1750.39 | N55: 1706.4399 | O55: 276600 | P55: 312770 | Q55: =O55/P55 | R55: 1667.3393 | S55: 1647.9849 | T55: 1627.6557 | U55: =S55/T55-1 | V55: 1 | W55: =J55/R55-1 | X55: =J55/S55-1 | Y55: 68.6681 | Z55: =Y55/J55 | AA55: =(J55-R55)/Y55 | AB55: =(J55-S55)/Y55 | AC55: =IF(ABS(AA55)<=ABS(AB55),"9EMA","21EMA") | AD55: 9+21EMA | AE55: 剛黃金交叉 | AF55: ✓ | AI55: 2026-09-25 | AJ55: 5 | AK55: 3 | AL55: 2026-09-24 | AM55: 1570 | AN55: 1545.21 | AO55: =IF(ISNUMBER(AN55),AM55/AN55-1,"") | AP55: 6 | AQ55: =IF(ISNUMBER(AM55),J55/AM55-1,"") | AR55: 1728.01 | AS55: =J55/AR55-1 | AT55: 10.704 | AU55: -3.0698 | AV55: -6.5133 | AW55: =AU55-AV55 | AX55: 13.7738 | AY55: 11.0241 | AZ55: 10.1594 | BA55: 深綠 | BB55: 淺綠→深綠 | BC55: 1 | BD55: 淺綠 深綠 深綠 深綠 深綠 淺綠 深綠 深綠 | BE55: 對稱三角 | BF55: -0.1823 | BG55: 0.2195 | BH55: 0.4569 | BI55: 0.472 | BJ55: 1 | BK55: 1750.39 | BL55: 1505.73 | BM55: 1617.5067 | BN55: 1.2356 | BO55: =IF(M55=N55,0.5,(J55-N55)/(M55-N55)) | BP55: 15.802 | BQ55: 10.761 | BR55: =100*(0.4*MIN(1,MAX(0,((U55*100)-(0.0))/((2.5)-(0.0))))+0.3*MIN(1,MAX(0,((V55)-(0.6))/((1.0)-(0.6))))+0.3*MIN(1,MAX(0,((BP55)-(0.0))/((15.0)-(0.0))))) | BS55: =100*(0.4*MIN(1,MAX(0,((MIN(ABS(AA55),ABS(AB55)))-(0.75))/((0.0)-(0.75))))+0.3*MIN(1,MAX(0,((BN55)-(1.2))/((0.6)-(1.2))))+0.3*BO55) | BT55: =100*(0.5*MIN(1,MAX(0,((AK55)-(1.0))/((4.0)-(1.0))))+0.3*MIN(1,MAX(0,((IF(ISNUMBER(AO55),AO55,0)*100)-(0.0))/((8.0)-(0.0))))+0.2*MIN(1,MAX(0,((IF(ISNUMBER(AP55),AP55,0))-(25.0))/((5.0)-(25.0))))) | BU55: =100*(0.35*MIN(1,MAX(0,((ABS(BF55))-(0.3))/((0.05)-(0.3))))+0.3*MIN(1,MAX(0,((BG55)-(0.0))/((0.3)-(0.0))))+0.25*MIN(1,MAX(0,((BH55)-(0.4))/((0.7)-(0.4))))+0.1*IF(BJ55>=2,1,0.5)) | BV55: =0.25*BR55+0.25*BS55+0.2*BT55+0.3*BU55 | BW55: C4 上升三角／重心偏上
A56: 2 | B56: 29 | C56: NVTS | D56: Navitas Semiconductor Corporation | E56: NASDAQ | F56: 科技 | G56: Semiconductors | H56: 3.031 | I56: 中型 | J56: 12.4 | K56: 12.12 | L56: =J56/K56-1 | M56: 13.195 | N56: 12.23 | O56: 24676100 | P56: 14217395 | Q56: =O56/P56 | R56: 11.9337 | S56: 11.8666 | T56: 11.8145 | U56: =S56/T56-1 | V56: 0.7 | W56: =J56/R56-1 | X56: =J56/S56-1 | Y56: 0.8366 | Z56: =Y56/J56 | AA56: =(J56-R56)/Y56 | AB56: =(J56-S56)/Y56 | AC56: =IF(ABS(AA56)<=ABS(AB56),"9EMA","21EMA") | AD56: 9+21EMA | AE56: 剛黃金交叉 | AF56: ✓ | AI56: 2026-10-01 | AJ56: 1 | AK56: 2 | AL56: 2026-09-24 | AM56: 11.43 | AN56: 10.27 | AO56: =IF(ISNUMBER(AN56),AM56/AN56-1,"") | AP56: 6 | AQ56: =IF(ISNUMBER(AM56),J56/AM56-1,"") | AR56: 12.46 | AS56: =J56/AR56-1 | AT56: -0.0486 | AU56: -0.1873 | AV56: -0.2219 | AW56: =AU56-AV56 | AX56: 0.1387 | AY56: 0.1166 | AZ56: 0.1034 | BA56: 深綠 | BB56: 淺綠→深綠 | BC56: 1 | BD56: 淺綠 淺綠 深綠 淺綠 淺綠 淺綠 深綠 深綠 | BE56: 上升三角（平頂） | BF56: -0.0887 | BG56: 0.2415 | BH56: 0.4643 | BI56: 0.5799 | BJ56: 1 | BK56: 13.195 | BL56: 10.27 | BM56: 11.6281 | BN56: 1.1254 | BO56: =IF(M56=N56,0.5,(J56-N56)/(M56-N56)) | BP56: 15.656 | BQ56: 10.616 | BR56: =100*(0.4*MIN(1,MAX(0,((U56*100)-(0.0))/((2.5)-(0.0))))+0.3*MIN(1,MAX(0,((V56)-(0.6))/((1.0)-(0.6))))+0.3*MIN(1,MAX(0,((BP56)-(0.0))/((15.0)-(0.0))))) | BS56: =100*(0.4*MIN(1,MAX(0,((MIN(ABS(AA56),ABS(AB56)))-(0.75))/((0.0)-(0.75))))+0.3*MIN(1,MAX(0,((BN56)-(1.2))/((0.6)-(1.2))))+0.3*BO56) | BT56: =100*(0.5*MIN(1,MAX(0,((AK56)-(1.0))/((4.0)-(1.0))))+0.3*MIN(1,MAX(0,((IF(ISNUMBER(AO56),AO56,0)*100)-(0.0))/((8.0)-(0.0))))+0.2*MIN(1,MAX(0,((IF(ISNUMBER(AP56),AP56,0))-(25.0))/((5.0)-(25.0))))) | BU56: =100*(0.35*MIN(1,MAX(0,((ABS(BF56))-(0.3))/((0.05)-(0.3))))+0.3*MIN(1,MAX(0,((BG56)-(0.0))/((0.3)-(0.0))))+0.25*MIN(1,MAX(0,((BH56)-(0.4))/((0.7)-(0.4))))+0.1*IF(BJ56>=2,1,0.5)) | BV56: =0.25*BR56+0.25*BS56+0.2*BT56+0.3*BU56 | BW56: C4 上升三角／重心偏上
A57: 2 | B57: 30 | C57: PCRX | D57: Pacira BioSciences Inc. | E57: NASDAQ | F57: 醫療保健 | G57: Biotechnology: Pharmaceutical Preparations | H57: 0.999 | I57: 小型 | J57: 25.21 | K57: 25.01 | L57: =J57/K57-1 | M57: 25.66 | N57: 24.66 | O57: 469800 | P57: 544745 | Q57: =O57/P57 | R57: 25.1316 | S57: 25.1303 | T57: 25.0612 | U57: =S57/T57-1 | V57: 0.5 | W57: =J57/R57-1 | X57: =J57/S57-1 | Y57: 0.7984 | Z57: =Y57/J57 | AA57: =(J57-R57)/Y57 | AB57: =(J57-S57)/Y57 | AC57: =IF(ABS(AA57)<=ABS(AB57),"9EMA","21EMA") | AD57: 9+21EMA | AE57: 剛黃金交叉 | AF57: ✓ | AH57: ✓ | AI57: 2026-10-02 | AJ57: 0 | AK57: 3 | AL57: 2026-09-21 | AM57: 23.98 | AN57: 23.65 | AO57: =IF(ISNUMBER(AN57),AM57/AN57-1,"") | AP57: 9 | AQ57: =IF(ISNUMBER(AM57),J57/AM57-1,"") | AR57: 25.65 | AS57: =J57/AR57-1 | AT57: -0.0158 | AU57: -0.0469 | AV57: -0.0547 | AW57: =AU57-AV57 | AX57: 0.0311 | AY57: 0.0286 | AZ57: 0.0432 | BA57: 深綠 | BB57: 淺綠→深綠 | BC57: 0 | BD57: 淺紅 淺紅 淺紅 深綠 深綠 淺綠 淺綠 深綠 | BE57: 對稱三角 | BF57: -0.1912 | BG57: 0.3273 | BH57: 0.5197 | BI57: 0.5016 | BJ57: 3 | BK57: 26.91 | BL57: 23.65 | BM57: 25.3441 | BN57: 0.8931 | BO57: =IF(M57=N57,0.5,(J57-N57)/(M57-N57)) | BP57: -0.113 | BQ57: -5.154 | BR57: =100*(0.4*MIN(1,MAX(0,((U57*100)-(0.0))/((2.5)-(0.0))))+0.3*MIN(1,MAX(0,((V57)-(0.6))/((1.0)-(0.6))))+0.3*MIN(1,MAX(0,((BP57)-(0.0))/((15.0)-(0.0))))) | BS57: =100*(0.4*MIN(1,MAX(0,((MIN(ABS(AA57),ABS(AB57)))-(0.75))/((0.0)-(0.75))))+0.3*MIN(1,MAX(0,((BN57)-(1.2))/((0.6)-(1.2))))+0.3*BO57) | BT57: =100*(0.5*MIN(1,MAX(0,((AK57)-(1.0))/((4.0)-(1.0))))+0.3*MIN(1,MAX(0,((IF(ISNUMBER(AO57),AO57,0)*100)-(0.0))/((8.0)-(0.0))))+0.2*MIN(1,MAX(0,((IF(ISNUMBER(AP57),AP57,0))-(25.0))/((5.0)-(25.0))))) | BU57: =100*(0.35*MIN(1,MAX(0,((ABS(BF57))-(0.3))/((0.05)-(0.3))))+0.3*MIN(1,MAX(0,((BG57)-(0.0))/((0.3)-(0.0))))+0.25*MIN(1,MAX(0,((BH57)-(0.4))/((0.7)-(0.4))))+0.1*IF(BJ57>=2,1,0.5)) | BV57: =0.25*BR57+0.25*BS57+0.2*BT57+0.3*BU57 | BW57: C4 上升三角／重心偏上
A58: 2 | B58: 31 | C58: FBLA | D58: FB Bancorp Inc. | E58: NASDAQ | F58: 金融 | G58: Banks | H58: 0.263 | I58: 小型 | J58: 16.96 | K58: 16.78 | L58: =J58/K58-1 | M58: 17.02 | N58: 16.81 | O58: 72200 | P58: 110285 | Q58: =O58/P58 | R58: 16.5568 | S58: 16.2921 | T58: 16.0449 | U58: =S58/T58-1 | V58: 1 | W58: =J58/R58-1 | X58: =J58/S58-1 | Y58: 0.2726 | Z58: =Y58/J58 | AA58: =(J58-R58)/Y58 | AB58: =(J58-S58)/Y58 | AC58: =IF(ABS(AA58)<=ABS(AB58),"9EMA","21EMA") | AD58: 9EMA | AE58: 持續在上方 | AH58: ✓ | AI58: 2026-06-08 | AJ58: 81 | AK58: 3 | AL58: 2026-09-18 | AM58: 15.735 | AN58: 15.72 | AO58: =IF(ISNUMBER(AN58),AM58/AN58-1,"") | AP58: 10 | AQ58: =IF(ISNUMBER(AM58),J58/AM58-1,"") | AR58: 16.96 | AS58: =J58/AR58-1 | AT58: 0.2606 | AU58: 0.2014 | AV58: 0.1866 | AW58: =AU58-AV58 | AX58: 0.0592 | AY58: 0.0454 | AZ58: 0.0351 | BA58: 深綠 | BB58: 淺綠→深綠 | BC58: 1 | BD58: 淺綠 淺綠 深綠 深綠 深綠 淺綠 深綠 深綠 | BE58: 上傾擴張 | BF58: 0.2638 | BG58: 0.1645 | BH58: 0.4502 | BI58: 0.3856 | BJ58: 4 | BK58: 17.02 | BL58: 15.38 | BM58: 16.1183 | BN58: 1.0412 | BO58: =IF(M58=N58,0.5,(J58-N58)/(M58-N58)) | BP58: 12.998 | BQ58: 7.957 | BR58: =100*(0.4*MIN(1,MAX(0,((U58*100)-(0.0))/((2.5)-(0.0))))+0.3*MIN(1,MAX(0,((V58)-(0.6))/((1.0)-(0.6))))+0.3*MIN(1,MAX(0,((BP58)-(0.0))/((15.0)-(0.0))))) | BS58: =100*(0.4*MIN(1,MAX(0,((MIN(ABS(AA58),ABS(AB58)))-(0.75))/((0.0)-(0.75))))+0.3*MIN(1,MAX(0,((BN58)-(1.2))/((0.6)-(1.2))))+0.3*BO58) | BT58: =100*(0.5*MIN(1,MAX(0,((AK58)-(1.0))/((4.0)-(1.0))))+0.3*MIN(1,MAX(0,((IF(ISNUMBER(AO58),AO58,0)*100)-(0.0))/((8.0)-(0.0))))+0.2*MIN(1,MAX(0,((IF(ISNUMBER(AP58),AP58,0))-(25.0))/((5.0)-(25.0))))) | BU58: =100*(0.35*MIN(1,MAX(0,((ABS(BF58))-(0.3))/((0.05)-(0.3))))+0.3*MIN(1,MAX(0,((BG58)-(0.0))/((0.3)-(0.0))))+0.25*MIN(1,MAX(0,((BH58)-(0.4))/((0.7)-(0.4))))+0.1*IF(BJ58>=2,1,0.5)) | BV58: =0.25*BR58+0.25*BS58+0.2*BT58+0.3*BU58 | BW58: C4 上升三角／重心偏上
A59: 2 | B59: 32 | C59: GFS | D59: GlobalFoundries Inc. | E59: NASDAQ | F59: 科技 | G59: Semiconductors | H59: 26.711 | I59: 大型 | J59: 50.17 | K59: 48.68 | L59: =J59/K59-1 | M59: 50.99 | N59: 49.827 | O59: 3646700 | P59: 3842365 | Q59: =O59/P59 | R59: 48.1808 | S59: 47.5542 | T59: 46.9209 | U59: =S59/T59-1 | V59: 0.9 | W59: =J59/R59-1 | X59: =J59/S59-1 | Y59: 2.008 | Z59: =Y59/J59 | AA59: =(J59-R59)/Y59 | AB59: =(J59-S59)/Y59 | AC59: =IF(ABS(AA59)<=ABS(AB59),"9EMA","21EMA") | AD59: 9EMA | AE59: 剛黃金交叉 | AF59: ✓ | AI59: 2026-09-25 | AJ59: 5 | AK59: 2 | AL59: 2026-09-24 | AM59: 45.39 | AN59: 42.15 | AO59: =IF(ISNUMBER(AN59),AM59/AN59-1,"") | AP59: 6 | AQ59: =IF(ISNUMBER(AM59),J59/AM59-1,"") | AR59: 50.17 | AS59: =J59/AR59-1 | AT59: 0.0932 | AU59: -0.5724 | AV59: -0.7387 | AW59: =AU59-AV59 | AX59: 0.6655 | AY59: 0.6039 | AZ59: 0.6176 | BA59: 深綠 | BB59: 淺綠→深綠 | BC59: 0 | BD59: 淺綠 淺綠 深綠 淺綠 淺綠 淺綠 淺綠 深綠 | BE59: 上升通道 | BF59: 0.4176 | BG59: 0.383 | BH59: 0.4617 | BI59: 0.4692 | BJ59: 1 | BK59: 50.99 | BL59: 42.15 | BM59: 46.2312 | BN59: 1.0587 | BO59: =IF(M59=N59,0.5,(J59-N59)/(M59-N59)) | BP59: 19.141 | BQ59: 14.101 | BR59: =100*(0.4*MIN(1,MAX(0,((U59*100)-(0.0))/((2.5)-(0.0))))+0.3*MIN(1,MAX(0,((V59)-(0.6))/((1.0)-(0.6))))+0.3*MIN(1,MAX(0,((BP59)-(0.0))/((15.0)-(0.0))))) | BS59: =100*(0.4*MIN(1,MAX(0,((MIN(ABS(AA59),ABS(AB59)))-(0.75))/((0.0)-(0.75))))+0.3*MIN(1,MAX(0,((BN59)-(1.2))/((0.6)-(1.2))))+0.3*BO59) | BT59: =100*(0.5*MIN(1,MAX(0,((AK59)-(1.0))/((4.0)-(1.0))))+0.3*MIN(1,MAX(0,((IF(ISNUMBER(AO59),AO59,0)*100)-(0.0))/((8.0)-(0.0))))+0.2*MIN(1,MAX(0,((IF(ISNUMBER(AP59),AP59,0))-(25.0))/((5.0)-(25.0))))) | BU59: =100*(0.35*MIN(1,MAX(0,((ABS(BF59))-(0.3))/((0.05)-(0.3))))+0.3*MIN(1,MAX(0,((BG59)-(0.0))/((0.3)-(0.0))))+0.25*MIN(1,MAX(0,((BH59)-(0.4))/((0.7)-(0.4))))+0.1*IF(BJ59>=2,1,0.5)) | BV59: =0.25*BR59+0.25*BS59+0.2*BT59+0.3*BU59 | BW59: C4 上升三角／重心偏上
A60: 2 | B60: 33 | C60: NTNX | D60: Nutanix Inc. | E60: NASDAQ | F60: 科技 | G60: Computer Software: Prepackaged Software | H60: 19.051 | I60: 大型 | J60: 72.29 | K60: 71.52 | L60: =J60/K60-1 | M60: 72.75 | N60: 71.815 | O60: 1960300 | P60: 2348405 | Q60: =O60/P60 | R60: 70.2375 | S60: 68.9434 | T60: 67.8313 | U60: =S60/T60-1 | V60: 1 | W60: =J60/R60-1 | X60: =J60/S60-1 | Y60: 2.0031 | Z60: =Y60/J60 | AA60: =(J60-R60)/Y60 | AB60: =(J60-S60)/Y60 | AC60: =IF(ABS(AA60)<=ABS(AB60),"9EMA","21EMA") | AD60: 9EMA | AE60: 持續在上方 | AH60: ✓ | AI60: 2026-06-29 | AJ60: 67 | AK60: 2 | AL60: 2026-09-28 | AM60: 66.25 | AN60: 65.25 | AO60: =IF(ISNUMBER(AN60),AM60/AN60-1,"") | AP60: 4 | AQ60: =IF(ISNUMBER(AM60),J60/AM60-1,"") | AR60: 72.29 | AS60: =J60/AR60-1 | AT60: 1.4903 | AU60: 1.4032 | AV60: 1.3814 | AW60: =AU60-AV60 | AX60: 0.0871 | AY60: -0.0174 | AZ60: -0.1244 | BA60: 深綠 | BB60: 深紅→淺紅 | BC60: 3 | BD60: 深紅 深紅 深紅 深紅 淺紅 淺紅 淺紅 深綠 | BE60: 上傾擴張 | BF60: 0.1629 | BG60: 0.049 | BH60: 0.4749 | BI60: 0.4937 | BJ60: 3 | BK60: 72.75 | BL60: 65.25 | BM60: 68.8117 | BN60: 1.0803 | BO60: =IF(M60=N60,0.5,(J60-N60)/(M60-N60)) | BP60: 13.179 | BQ60: 8.138 | BR60: =100*(0.4*MIN(1,MAX(0,((U60*100)-(0.0))/((2.5)-(0.0))))+0.3*MIN(1,MAX(0,((V60)-(0.6))/((1.0)-(0.6))))+0.3*MIN(1,MAX(0,((BP60)-(0.0))/((15.0)-(0.0))))) | BS60: =100*(0.4*MIN(1,MAX(0,((MIN(ABS(AA60),ABS(AB60)))-(0.75))/((0.0)-(0.75))))+0.3*MIN(1,MAX(0,((BN60)-(1.2))/((0.6)-(1.2))))+0.3*BO60) | BT60: =100*(0.5*MIN(1,MAX(0,((AK60)-(1.0))/((4.0)-(1.0))))+0.3*MIN(1,MAX(0,((IF(ISNUMBER(AO60),AO60,0)*100)-(0.0))/((8.0)-(0.0))))+0.2*MIN(1,MAX(0,((IF(ISNUMBER(AP60),AP60,0))-(25.0))/((5.0)-(25.0))))) | BU60: =100*(0.35*MIN(1,MAX(0,((ABS(BF60))-(0.3))/((0.05)-(0.3))))+0.3*MIN(1,MAX(0,((BG60)-(0.0))/((0.3)-(0.0))))+0.25*MIN(1,MAX(0,((BH60)-(0.4))/((0.7)-(0.4))))+0.1*IF(BJ60>=2,1,0.5)) | BV60: =0.25*BR60+0.25*BS60+0.2*BT60+0.3*BU60 | BW60: C4 上升三角／重心偏上
A61: 2 | B61: 34 | C61: LYTS | D61: LSI Industries Inc. | E61: NASDAQ | F61: 非必需消費 | G61: Building Products | H61: 0.773 | I61: 小型 | J61: 21.25 | K61: 20.94 | L61: =J61/K61-1 | M61: 21.51 | N61: 21.14 | O61: 246100 | P61: 393920 | Q61: =O61/P61 | R61: 20.8453 | S61: 20.7789 | T61: 20.6683 | U61: =S61/T61-1 | V61: 0.8 | W61: =J61/R61-1 | X61: =J61/S61-1 | Y61: 0.6932 | Z61: =Y61/J61 | AA61: =(J61-R61)/Y61 | AB61: =(J61-S61)/Y61 | AC61: =IF(ABS(AA61)<=ABS(AB61),"9EMA","21EMA") | AD61: 9+21EMA | AE61: 剛黃金交叉 | AF61: ✓ | AH61: ✓ | AI61: 2026-10-01 | AJ61: 1 | AK61: 2 | AL61: 2026-09-24 | AM61: 19.94 | AN61: 19.11 | AO61: =IF(ISNUMBER(AN61),AM61/AN61-1,"") | AP61: 6 | AQ61: =IF(ISNUMBER(AM61),J61/AM61-1,"") | AR61: 21.25 | AS61: =J61/AR61-1 | AT61: -0.1059 | AU61: -0.3119 | AV61: -0.3634 | AW61: =AU61-AV61 | AX61: 0.206 | AY61: 0.2005 | AZ61: 0.2119 | BA61: 深綠 | BB61: 淺綠→深綠 | BC61: 0 | BD61: 淺綠 深綠 深綠 淺綠 淺綠 淺綠 淺綠 深綠 | BE61: 上升通道 | BF61: 0.2715 | BG61: 0.2328 | BH61: 0.4777 | BI61: 0.4086 | BJ61: 4 | BK61: 21.51 | BL61: 19.11 | BM61: 20.2564 | BN61: 0.8691 | BO61: =IF(M61=N61,0.5,(J61-N61)/(M61-N61)) | BP61: 11.771 | BQ61: 6.73 | BR61: =100*(0.4*MIN(1,MAX(0,((U61*100)-(0.0))/((2.5)-(0.0))))+0.3*MIN(1,MAX(0,((V61)-(0.6))/((1.0)-(0.6))))+0.3*MIN(1,MAX(0,((BP61)-(0.0))/((15.0)-(0.0))))) | BS61: =100*(0.4*MIN(1,MAX(0,((MIN(ABS(AA61),ABS(AB61)))-(0.75))/((0.0)-(0.75))))+0.3*MIN(1,MAX(0,((BN61)-(1.2))/((0.6)-(1.2))))+0.3*BO61) | BT61: =100*(0.5*MIN(1,MAX(0,((AK61)-(1.0))/((4.0)-(1.0))))+0.3*MIN(1,MAX(0,((IF(ISNUMBER(AO61),AO61,0)*100)-(0.0))/((8.0)-(0.0))))+0.2*MIN(1,MAX(0,((IF(ISNUMBER(AP61),AP61,0))-(25.0))/((5.0)-(25.0))))) | BU61: =100*(0.35*MIN(1,MAX(0,((ABS(BF61))-(0.3))/((0.05)-(0.3))))+0.3*MIN(1,MAX(0,((BG61)-(0.0))/((0.3)-(0.0))))+0.25*MIN(1,MAX(0,((BH61)-(0.4))/((0.7)-(0.4))))+0.1*IF(BJ61>=2,1,0.5)) | BV61: =0.25*BR61+0.25*BS61+0.2*BT61+0.3*BU61 | BW61: C4 上升三角／重心偏上
A62: 2 | B62: 35 | C62: FLEX | D62: Flex Ltd. | E62: NASDAQ | F62: 科技 | G62: Electrical Products | H62: 40.631 | I62: 大型 | J62: 116.61 | K62: 112.78 | L62: =J62/K62-1 | M62: 117.84 | N62: 113.99 | O62: 1953500 | P62: 3232120 | Q62: =O62/P62 | R62: 113.067 | S62: 112.573 | T62: 112.082 | U62: =S62/T62-1 | V62: 0.9 | W62: =J62/R62-1 | X62: =J62/S62-1 | Y62: 5.3301 | Z62: =Y62/J62 | AA62: =(J62-R62)/Y62 | AB62: =(J62-S62)/Y62 | AC62: =IF(ABS(AA62)<=ABS(AB62),"9EMA","21EMA") | AD62: 9+21EMA | AE62: 剛黃金交叉 | AF62: ✓ | AI62: 2026-10-01 | AJ62: 1 | AK62: 2 | AL62: 2026-09-16 | AM62: 105.85 | AN62: 102.25 | AO62: =IF(ISNUMBER(AN62),AM62/AN62-1,"") | AP62: 12 | AQ62: =IF(ISNUMBER(AM62),J62/AM62-1,"") | AR62: 116.61 | AS62: =J62/AR62-1 | AT62: -0.1692 | AU62: -0.9798 | AV62: -1.1824 | AW62: =AU62-AV62 | AX62: 0.8106 | AY62: 0.6051 | AZ62: 0.6337 | BA62: 深綠 | BB62: 淺綠→深綠 | BC62: 0 | BD62: 深綠 淺綠 深綠 淺綠 淺綠 淺綠 淺綠 深綠 | BE62: 上傾收窄（楔形） | BF62: 0.2641 | BG62: 0.3859 | BH62: 0.4514 | BI62: 0.4367 | BJ62: 1 | BK62: 120.76 | BL62: 102.25 | BM62: 110.6048 | BN62: 1.2348 | BO62: =IF(M62=N62,0.5,(J62-N62)/(M62-N62)) | BP62: 15.102 | BQ62: 10.061 | BR62: =100*(0.4*MIN(1,MAX(0,((U62*100)-(0.0))/((2.5)-(0.0))))+0.3*MIN(1,MAX(0,((V62)-(0.6))/((1.0)-(0.6))))+0.3*MIN(1,MAX(0,((BP62)-(0.0))/((15.0)-(0.0))))) | BS62: =100*(0.4*MIN(1,MAX(0,((MIN(ABS(AA62),ABS(AB62)))-(0.75))/((0.0)-(0.75))))+0.3*MIN(1,MAX(0,((BN62)-(1.2))/((0.6)-(1.2))))+0.3*BO62) | BT62: =100*(0.5*MIN(1,MAX(0,((AK62)-(1.0))/((4.0)-(1.0))))+0.3*MIN(1,MAX(0,((IF(ISNUMBER(AO62),AO62,0)*100)-(0.0))/((8.0)-(0.0))))+0.2*MIN(1,MAX(0,((IF(ISNUMBER(AP62),AP62,0))-(25.0))/((5.0)-(25.0))))) | BU62: =100*(0.35*MIN(1,MAX(0,((ABS(BF62))-(0.3))/((0.05)-(0.3))))+0.3*MIN(1,MAX(0,((BG62)-(0.0))/((0.3)-(0.0))))+0.25*MIN(1,MAX(0,((BH62)-(0.4))/((0.7)-(0.4))))+0.1*IF(BJ62>=2,1,0.5)) | BV62: =0.25*BR62+0.25*BS62+0.2*BT62+0.3*BU62 | BW62: C4 上升三角／重心偏上
A63: 3 | B63: 1 | C63: FEIM | D63: Frequency Electronics Inc. | E63: NASDAQ | F63: 工業 | G63: Electrical Products | H63: 0.953 | I63: 小型 | J63: 86.03 | K63: 85.97 | L63: =J63/K63-1 | M63: 88.19 | N63: 85.55 | O63: 184200 | P63: 400650 | Q63: =O63/P63 | R63: 84.6603 | S63: 80.6744 | T63: 78.1551 | U63: =S63/T63-1 | V63: 1 | W63: =J63/R63-1 | X63: =J63/S63-1 | Y63: 4.8344 | Z63: =Y63/J63 | AA63: =(J63-R63)/Y63 | AB63: =(J63-S63)/Y63 | AC63: =IF(ABS(AA63)<=ABS(AB63),"9EMA","21EMA") | AD63: 9EMA | AE63: 持續在上方 | AH63: ✓ | AI63: 2026-09-11 | AJ63: 15 | AK63: 2 | AL63: 2026-09-28 | AM63: 81.58 | AN63: 56.98 | AO63: =IF(ISNUMBER(AN63),AM63/AN63-1,"") | AP63: 4 | AQ63: =IF(ISNUMBER(AM63),J63/AM63-1,"") | AR63: 89 | AS63: =J63/AR63-1 | AT63: 4.5115 | AU63: 4.624 | AV63: 4.6521 | AW63: =AU63-AV63 | AX63: -0.1125 | AY63: -0.0124 | AZ63: 0.0868 | BA63: 深紅 | BB63: — | BC63: — | BD63: 淺綠 淺綠 淺綠 淺綠 淺綠 淺綠 深紅 深紅 | BE63: 上升三角（平頂） | BF63: -0.0206 | BG63: 1.5886 | BH63: 0.7217 | BI63: 0.7215 | BJ63: 5 | BK63: 89.76 | BL63: 56.98 | BM63: 80.6386 | BN63: 1.0567 | BO63: =IF(M63=N63,0.5,(J63-N63)/(M63-N63)) | BP63: 50.682 | BQ63: 45.641 | BR63: =100*(0.4*MIN(1,MAX(0,((U63*100)-(0.0))/((2.5)-(0.0))))+0.3*MIN(1,MAX(0,((V63)-(0.6))/((1.0)-(0.6))))+0.3*MIN(1,MAX(0,((BP63)-(0.0))/((15.0)-(0.0))))) | BS63: =100*(0.4*MIN(1,MAX(0,((MIN(ABS(AA63),ABS(AB63)))-(0.75))/((0.0)-(0.75))))+0.3*MIN(1,MAX(0,((BN63)-(1.2))/((0.6)-(1.2))))+0.3*BO63) | BT63: =100*(0.5*MIN(1,MAX(0,((AK63)-(1.0))/((4.0)-(1.0))))+0.3*MIN(1,MAX(0,((IF(ISNUMBER(AO63),AO63,0)*100)-(0.0))/((8.0)-(0.0))))+0.2*MIN(1,MAX(0,((IF(ISNUMBER(AP63),AP63,0))-(25.0))/((5.0)-(25.0))))) | BU63: =100*(0.35*MIN(1,MAX(0,((ABS(BF63))-(0.3))/((0.05)-(0.3))))+0.3*MIN(1,MAX(0,((BG63)-(0.0))/((0.3)-(0.0))))+0.25*MIN(1,MAX(0,((BH63)-(0.4))/((0.7)-(0.4))))+0.1*IF(BJ63>=2,1,0.5)) | BV63: =0.25*BR63+0.25*BS63+0.2*BT63+0.3*BU63 | BW63: C5 MACD慢線向上、C6 MACD柱轉勢
A64: 3 | B64: 2 | C64: JILL | D64: J. Jill Inc. | E64: NYSE | F64: 非必需消費 | G64: Apparel | H64: 0.362 | I64: 小型 | J64: 24.84 | K64: 24.4 | L64: =J64/K64-1 | M64: 25.135 | N64: 24.47 | O64: 267000 | P64: 258625 | Q64: =O64/P64 | R64: 24.3132 | S64: 23.338 | T64: 22.638 | U64: =S64/T64-1 | V64: 1 | W64: =J64/R64-1 | X64: =J64/S64-1 | Y64: 0.9502 | Z64: =Y64/J64 | AA64: =(J64-R64)/Y64 | AB64: =(J64-S64)/Y64 | AC64: =IF(ABS(AA64)<=ABS(AB64),"9EMA","21EMA") | AD64: 9EMA | AE64: 持續在上方 | AH64: ✓ | AI64: 2026-05-28 | AJ64: 88 | AK64: 6 | AL64: 2026-09-24 | AM64: 22.86 | AN64: 18.49 | AO64: =IF(ISNUMBER(AN64),AM64/AN64-1,"") | AP64: 6 | AQ64: =IF(ISNUMBER(AM64),J64/AM64-1,"") | AR64: 24.84 | AS64: =J64/AR64-1 | AT64: 1.1803 | AU64: 1.2636 | AV64: 1.2844 | AW64: =AU64-AV64 | AX64: -0.0833 | AY64: -0.0852 | AZ64: -0.055 | BA64: 淺紅 | BB64: 深紅→淺紅 | BC64: 0 | BD64: 淺綠 淺綠 淺綠 淺綠 深紅 深紅 深紅 淺紅 | BE64: 上傾收窄（楔形） | BF64: 0.9803 | BG64: 1.2566 | BH64: 0.7162 | BI64: 0.7194 | BJ64: 3 | BK64: 25.135 | BL64: 18.49 | BM64: 23.249 | BN64: 0.7178 | BO64: =IF(M64=N64,0.5,(J64-N64)/(M64-N64)) | BP64: 34.618 | BQ64: 29.577 | BR64: =100*(0.4*MIN(1,MAX(0,((U64*100)-(0.0))/((2.5)-(0.0))))+0.3*MIN(1,MAX(0,((V64)-(0.6))/((1.0)-(0.6))))+0.3*MIN(1,MAX(0,((BP64)-(0.0))/((15.0)-(0.0))))) | BS64: =100*(0.4*MIN(1,MAX(0,((MIN(ABS(AA64),ABS(AB64)))-(0.75))/((0.0)-(0.75))))+0.3*MIN(1,MAX(0,((BN64)-(1.2))/((0.6)-(1.2))))+0.3*BO64) | BT64: =100*(0.5*MIN(1,MAX(0,((AK64)-(1.0))/((4.0)-(1.0))))+0.3*MIN(1,MAX(0,((IF(ISNUMBER(AO64),AO64,0)*100)-(0.0))/((8.0)-(0.0))))+0.2*MIN(1,MAX(0,((IF(ISNUMBER(AP64),AP64,0))-(25.0))/((5.0)-(25.0))))) | BU64: =100*(0.35*MIN(1,MAX(0,((ABS(BF64))-(0.3))/((0.05)-(0.3))))+0.3*MIN(1,MAX(0,((BG64)-(0.0))/((0.3)-(0.0))))+0.25*MIN(1,MAX(0,((BH64)-(0.4))/((0.7)-(0.4))))+0.1*IF(BJ64>=2,1,0.5)) | BV64: =0.25*BR64+0.25*BS64+0.2*BT64+0.3*BU64 | BW64: C5 MACD慢線向上
A65: 3 | B65: 3 | C65: PPIH | D65: Perma-Pipe International Holdings Inc. | E65: NASDAQ | F65: 工業 | G65: Pollution Control Equipment | H65: 0.252 | I65: 小型 | J65: 31.86 | K65: 31.32 | L65: =J65/K65-1 | M65: 32.13 | N65: 31.41 | O65: 51600 | P65: 97185 | Q65: =O65/P65 | R65: 31.1648 | S65: 30.2585 | T65: 29.5552 | U65: =S65/T65-1 | V65: 1 | W65: =J65/R65-1 | X65: =J65/S65-1 | Y65: 1.0224 | Z65: =Y65/J65 | AA65: =(J65-R65)/Y65 | AB65: =(J65-S65)/Y65 | AC65: =IF(ABS(AA65)<=ABS(AB65),"9EMA","21EMA") | AD65: 9EMA | AE65: 持續在上方 | AH65: ✓ | AI65: 2026-08-10 | AJ65: 38 | AK65: 4 | AL65: 2026-09-23 | AM65: 29.77 | AN65: 26.24 | AO65: =IF(ISNUMBER(AN65),AM65/AN65-1,"") | AP65: 7 | AQ65: =IF(ISNUMBER(AM65),J65/AM65-1,"") | AR65: 31.88 | AS65: =J65/AR65-1 | AT65: 1.0338 | AU65: 1.0442 | AV65: 1.0468 | AW65: =AU65-AV65 | AX65: -0.0104 | AY65: -0.0232 | AZ65: -0.0018 | BA65: 淺紅 | BB65: 深紅→淺紅 | BC65: 0 | BD65: 淺綠 深綠 深綠 深綠 淺綠 深紅 深紅 淺紅 | BE65: 上傾收窄（楔形） | BF65: 0.1548 | BG65: 0.6517 | BH65: 0.5965 | BI65: 0.601 | BJ65: 5 | BK65: 32.19 | BL65: 26.24 | BM65: 29.7894 | BN65: 0.8518 | BO65: =IF(M65=N65,0.5,(J65-N65)/(M65-N65)) | BP65: 21.873 | BQ65: 16.832 | BR65: =100*(0.4*MIN(1,MAX(0,((U65*100)-(0.0))/((2.5)-(0.0))))+0.3*MIN(1,MAX(0,((V65)-(0.6))/((1.0)-(0.6))))+0.3*MIN(1,MAX(0,((BP65)-(0.0))/((15.0)-(0.0))))) | BS65: =100*(0.4*MIN(1,MAX(0,((MIN(ABS(AA65),ABS(AB65)))-(0.75))/((0.0)-(0.75))))+0.3*MIN(1,MAX(0,((BN65)-(1.2))/((0.6)-(1.2))))+0.3*BO65) | BT65: =100*(0.5*MIN(1,MAX(0,((AK65)-(1.0))/((4.0)-(1.0))))+0.3*MIN(1,MAX(0,((IF(ISNUMBER(AO65),AO65,0)*100)-(0.0))/((8.0)-(0.0))))+0.2*MIN(1,MAX(0,((IF(ISNUMBER(AP65),AP65,0))-(25.0))/((5.0)-(25.0))))) | BU65: =100*(0.35*MIN(1,MAX(0,((ABS(BF65))-(0.3))/((0.05)-(0.3))))+0.3*MIN(1,MAX(0,((BG65)-(0.0))/((0.3)-(0.0))))+0.25*MIN(1,MAX(0,((BH65)-(0.4))/((0.7)-(0.4))))+0.1*IF(BJ65>=2,1,0.5)) | BV65: =0.25*BR65+0.25*BS65+0.2*BT65+0.3*BU65 | BW65: C5 MACD慢線向上
A66: 3 | B66: 4 | C66: NET | D66: Cloudflare Inc. | E66: NYSE | F66: 科技 | G66: Computer Software: Prepackaged Software | H66: 123.659 | I66: 大型 | J66: 349.07 | K66: 351 | L66: =J66/K66-1 | M66: 354.58 | N66: 344.51 | O66: 2834400 | P66: 3112035 | Q66: =O66/P66 | R66: 347.38 | S66: 334.2457 | T66: 324.3122 | U66: =S66/T66-1 | V66: 1 | W66: =J66/R66-1 | X66: =J66/S66-1 | Y66: 16.017 | Z66: =Y66/J66 | AA66: =(J66-R66)/Y66 | AB66: =(J66-S66)/Y66 | AC66: =IF(ABS(AA66)<=ABS(AB66),"9EMA","21EMA") | AD66: 9EMA | AE66: 持續在上方 | AH66: ✓ | AI66: 2026-09-09 | AJ66: 17 | AK66: 3 | AL66: 2026-09-28 | AM66: 338.67 | AN66: 313.5 | AO66: =IF(ISNUMBER(AN66),AM66/AN66-1,"") | AP66: 4 | AQ66: =IF(ISNUMBER(AM66),J66/AM66-1,"") | AR66: 358.82 | AS66: =J66/AR66-1 | AT66: 14.8374 | AU66: 14.8413 | AV66: 14.8423 | AW66: =AU66-AV66 | AX66: -0.0039 | AY66: 0.6865 | AZ66: 1.3181 | BA66: 深紅 | BB66: — | BC66: — | BD66: 淺綠 深綠 淺綠 淺綠 淺綠 淺綠 淺綠 深紅 | BE66: 上升通道 | BF66: 0.948 | BG66: 1.1668 | BH66: 0.5661 | BI66: 0.6054 | BJ66: 3 | BK66: 367.43 | BL66: 269.3 | BM66: 324.8523 | BN66: 0.8566 | BO66: =IF(M66=N66,0.5,(J66-N66)/(M66-N66)) | BP66: 33.027 | BQ66: 27.986 | BR66: =100*(0.4*MIN(1,MAX(0,((U66*100)-(0.0))/((2.5)-(0.0))))+0.3*MIN(1,MAX(0,((V66)-(0.6))/((1.0)-(0.6))))+0.3*MIN(1,MAX(0,((BP66)-(0.0))/((15.0)-(0.0))))) | BS66: =100*(0.4*MIN(1,MAX(0,((MIN(ABS(AA66),ABS(AB66)))-(0.75))/((0.0)-(0.75))))+0.3*MIN(1,MAX(0,((BN66)-(1.2))/((0.6)-(1.2))))+0.3*BO66) | BT66: =100*(0.5*MIN(1,MAX(0,((AK66)-(1.0))/((4.0)-(1.0))))+0.3*MIN(1,MAX(0,((IF(ISNUMBER(AO66),AO66,0)*100)-(0.0))/((8.0)-(0.0))))+0.2*MIN(1,MAX(0,((IF(ISNUMBER(AP66),AP66,0))-(25.0))/((5.0)-(25.0))))) | BU66: =100*(0.35*MIN(1,MAX(0,((ABS(BF66))-(0.3))/((0.05)-(0.3))))+0.3*MIN(1,MAX(0,((BG66)-(0.0))/((0.3)-(0.0))))+0.25*MIN(1,MAX(0,((BH66)-(0.4))/((0.7)-(0.4))))+0.1*IF(BJ66>=2,1,0.5)) | BV66: =0.25*BR66+0.25*BS66+0.2*BT66+0.3*BU66 | BW66: C5 MACD慢線向上、C6 MACD柱轉勢
A67: 3 | B67: 5 | C67: LTC | D67: LTC Properties Inc. | E67: NYSE | F67: 房地產 | G67: Real Estate Investment Trusts | H67: 2.311 | I67: 中型 | J67: 43 | K67: 42.67 | L67: =J67/K67-1 | M67: 43.42 | N67: 42.51 | O67: 721700 | P67: 668565 | Q67: =O67/P67 | R67: 42.8817 | S67: 42.5078 | T67: 42.2469 | U67: =S67/T67-1 | V67: 1 | W67: =J67/R67-1 | X67: =J67/S67-1 | Y67: 0.8405 | Z67: =Y67/J67 | AA67: =(J67-R67)/Y67 | AB67: =(J67-S67)/Y67 | AC67: =IF(ABS(AA67)<=ABS(AB67),"9EMA","21EMA") | AD67: 9+21EMA | AE67: 持續在上方 | AH67: ✓ | AI67: 2026-08-20 | AJ67: 30 | AK67: 5 | AL67: 2026-09-21 | AM67: 42.06 | AN67: 40.82 | AO67: =IF(ISNUMBER(AN67),AM67/AN67-1,"") | AP67: 9 | AQ67: =IF(ISNUMBER(AM67),J67/AM67-1,"") | AR67: 43.5 | AS67: =J67/AR67-1 | AT67: 0.4967 | AU67: 0.5871 | AV67: 0.6097 | AW67: =AU67-AV67 | AX67: -0.0904 | AY67: -0.0919 | AZ67: -0.062 | BA67: 淺紅 | BB67: 深紅→淺紅 | BC67: 0 | BD67: 深紅 淺紅 深紅 深紅 深紅 深紅 深紅 淺紅 | BE67: 上升三角（平頂） | BF67: -0.0145 | BG67: 0.3147 | BH67: 0.6892 | BI67: 0.6963 | BJ67: 13 | BK67: 43.6 | BL67: 40.17 | BM67: 42.5341 | BN67: 1.0242 | BO67: =IF(M67=N67,0.5,(J67-N67)/(M67-N67)) | BP67: 8.481 | BQ67: 3.44 | BR67: =100*(0.4*MIN(1,MAX(0,((U67*100)-(0.0))/((2.5)-(0.0))))+0.3*MIN(1,MAX(0,((V67)-(0.6))/((1.0)-(0.6))))+0.3*MIN(1,MAX(0,((BP67)-(0.0))/((15.0)-(0.0))))) | BS67: =100*(0.4*MIN(1,MAX(0,((MIN(ABS(AA67),ABS(AB67)))-(0.75))/((0.0)-(0.75))))+0.3*MIN(1,MAX(0,((BN67)-(1.2))/((0.6)-(1.2))))+0.3*BO67) | BT67: =100*(0.5*MIN(1,MAX(0,((AK67)-(1.0))/((4.0)-(1.0))))+0.3*MIN(1,MAX(0,((IF(ISNUMBER(AO67),AO67,0)*100)-(0.0))/((8.0)-(0.0))))+0.2*MIN(1,MAX(0,((IF(ISNUMBER(AP67),AP67,0))-(25.0))/((5.0)-(25.0))))) | BU67: =100*(0.35*MIN(1,MAX(0,((ABS(BF67))-(0.3))/((0.05)-(0.3))))+0.3*MIN(1,MAX(0,((BG67)-(0.0))/((0.3)-(0.0))))+0.25*MIN(1,MAX(0,((BH67)-(0.4))/((0.7)-(0.4))))+0.1*IF(BJ67>=2,1,0.5)) | BV67: =0.25*BR67+0.25*BS67+0.2*BT67+0.3*BU67 | BW67: C5 MACD慢線向上
A68: 3 | B68: 6 | C68: NVAX | D68: Novavax Inc. | E68: NASDAQ | F68: 醫療保健 | G68: Biotechnology: Biological Products (No Diagnostic Substances) | H68: 1.783 | I68: 小型 | J68: 10.46 | K68: 10.6 | L68: =J68/K68-1 | M68: 10.86 | N68: 10.33 | O68: 4023000 | P68: 5167530 | Q68: =O68/P68 | R68: 10.5454 | S68: 10.1888 | T68: 9.8887 | U68: =S68/T68-1 | V68: 1 | W68: =J68/R68-1 | X68: =J68/S68-1 | Y68: 0.5659 | Z68: =Y68/J68 | AA68: =(J68-R68)/Y68 | AB68: =(J68-S68)/Y68 | AC68: =IF(ABS(AA68)<=ABS(AB68),"9EMA","21EMA") | AD68: 9EMA | AE68: 持續在上方 | AH68: ✓ | AI68: 2026-08-19 | AJ68: 31 | AK68: 5 | AL68: 2026-09-28 | AM68: 10.26 | AN68: 9.11 | AO68: =IF(ISNUMBER(AN68),AM68/AN68-1,"") | AP68: 4 | AQ68: =IF(ISNUMBER(AM68),J68/AM68-1,"") | AR68: 10.83 | AS68: =J68/AR68-1 | AT68: 0.4176 | AU68: 0.4347 | AV68: 0.4389 | AW68: =AU68-AV68 | AX68: -0.017 | AY68: 0.0125 | AZ68: 0.0379 | BA68: 深紅 | BB68: — | BC68: — | BD68: 深綠 淺綠 淺綠 深綠 淺綠 淺綠 淺綠 深紅 | BE68: 上傾收窄（楔形） | BF68: 0.2283 | BG68: 0.6755 | BH68: 0.5588 | BI68: 0.5628 | BJ68: 6 | BK68: 11.11 | BL68: 8.89 | BM68: 10.1305 | BN68: 0.8608 | BO68: =IF(M68=N68,0.5,(J68-N68)/(M68-N68)) | BP68: 6.398 | BQ68: 1.357 | BR68: =100*(0.4*MIN(1,MAX(0,((U68*100)-(0.0))/((2.5)-(0.0))))+0.3*MIN(1,MAX(0,((V68)-(0.6))/((1.0)-(0.6))))+0.3*MIN(1,MAX(0,((BP68)-(0.0))/((15.0)-(0.0))))) | BS68: =100*(0.4*MIN(1,MAX(0,((MIN(ABS(AA68),ABS(AB68)))-(0.75))/((0.0)-(0.75))))+0.3*MIN(1,MAX(0,((BN68)-(1.2))/((0.6)-(1.2))))+0.3*BO68) | BT68: =100*(0.5*MIN(1,MAX(0,((AK68)-(1.0))/((4.0)-(1.0))))+0.3*MIN(1,MAX(0,((IF(ISNUMBER(AO68),AO68,0)*100)-(0.0))/((8.0)-(0.0))))+0.2*MIN(1,MAX(0,((IF(ISNUMBER(AP68),AP68,0))-(25.0))/((5.0)-(25.0))))) | BU68: =100*(0.35*MIN(1,MAX(0,((ABS(BF68))-(0.3))/((0.05)-(0.3))))+0.3*MIN(1,MAX(0,((BG68)-(0.0))/((0.3)-(0.0))))+0.25*MIN(1,MAX(0,((BH68)-(0.4))/((0.7)-(0.4))))+0.1*IF(BJ68>=2,1,0.5)) | BV68: =0.25*BR68+0.25*BS68+0.2*BT68+0.3*BU68 | BW68: C5 MACD慢線向上、C6 MACD柱轉勢
A69: 3 | B69: 7 | C69: NUTX | D69: Nutex Health Inc. | E69: NASDAQ | F69: 非必需消費 | G69: Business Services | H69: 1.449 | I69: 小型 | J69: 216.5 | K69: 212.31 | L69: =J69/K69-1 | M69: 221.01 | N69: 212.59 | O69: 297100 | P69: 161855 | Q69: =O69/P69 | R69: 211.6083 | S69: 206.1376 | T69: 202.0351 | U69: =S69/T69-1 | V69: 1 | W69: =J69/R69-1 | X69: =J69/S69-1 | Y69: 10.4229 | Z69: =Y69/J69 | AA69: =(J69-R69)/Y69 | AB69: =(J69-S69)/Y69 | AC69: =IF(ABS(AA69)<=ABS(AB69),"9EMA","21EMA") | AD69: 9EMA | AE69: 持續在上方 | AH69: ✓ | AI69: 2026-08-10 | AJ69: 38 | AK69: 5 | AL69: 2026-09-24 | AM69: 198.25 | AN69: 184 | AO69: =IF(ISNUMBER(AN69),AM69/AN69-1,"") | AP69: 6 | AQ69: =IF(ISNUMBER(AM69),J69/AM69-1,"") | AR69: 220.11 | AS69: =J69/AR69-1 | AT69: 6.7704 | AU69: 7.2827 | AV69: 7.4108 | AW69: =AU69-AV69 | AX69: -0.5123 | AY69: -0.7208 | AZ69: -0.6743 | BA69: 淺紅 | BB69: 深紅→淺紅 | BC69: 0 | BD69: 深紅 深紅 淺紅 深紅 深紅 深紅 深紅 淺紅 | BE69: 上傾擴張 | BF69: 0.6624 | BG69: 0.4744 | BH69: 0.532 | BI69: 0.5329 | BJ69: 5 | BK69: 224.28 | BL69: 182.66 | BM69: 204.8026 | BN69: 0.7519 | BO69: =IF(M69=N69,0.5,(J69-N69)/(M69-N69)) | BP69: 17.801 | BQ69: 12.76 | BR69: =100*(0.4*MIN(1,MAX(0,((U69*100)-(0.0))/((2.5)-(0.0))))+0.3*MIN(1,MAX(0,((V69)-(0.6))/((1.0)-(0.6))))+0.3*MIN(1,MAX(0,((BP69)-(0.0))/((15.0)-(0.0))))) | BS69: =100*(0.4*MIN(1,MAX(0,((MIN(ABS(AA69),ABS(AB69)))-(0.75))/((0.0)-(0.75))))+0.3*MIN(1,MAX(0,((BN69)-(1.2))/((0.6)-(1.2))))+0.3*BO69) | BT69: =100*(0.5*MIN(1,MAX(0,((AK69)-(1.0))/((4.0)-(1.0))))+0.3*MIN(1,MAX(0,((IF(ISNUMBER(AO69),AO69,0)*100)-(0.0))/((8.0)-(0.0))))+0.2*MIN(1,MAX(0,((IF(ISNUMBER(AP69),AP69,0))-(25.0))/((5.0)-(25.0))))) | BU69: =100*(0.35*MIN(1,MAX(0,((ABS(BF69))-(0.3))/((0.05)-(0.3))))+0.3*MIN(1,MAX(0,((BG69)-(0.0))/((0.3)-(0.0))))+0.25*MIN(1,MAX(0,((BH69)-(0.4))/((0.7)-(0.4))))+0.1*IF(BJ69>=2,1,0.5)) | BV69: =0.25*BR69+0.25*BS69+0.2*BT69+0.3*BU69 | BW69: C5 MACD慢線向上
A70: 3 | B70: 8 | C70: SMMT | D70: Summit Therapeutics Inc. | E70: NASDAQ | F70: 醫療保健 | G70: Biotechnology: Pharmaceutical Preparations | H70: 13.49 | I70: 大型 | J70: 16.755 | K70: 16.69 | L70: =J70/K70-1 | M70: 17.32 | N70: 16.66 | O70: 5190100 | P70: 7425085 | Q70: =O70/P70 | R70: 16.59 | S70: 16.3828 | T70: 16.3132 | U70: =S70/T70-1 | V70: 0.7 | W70: =J70/R70-1 | X70: =J70/S70-1 | Y70: 1.1153 | Z70: =Y70/J70 | AA70: =(J70-R70)/Y70 | AB70: =(J70-S70)/Y70 | AC70: =IF(ABS(AA70)<=ABS(AB70),"9EMA","21EMA") | AD70: 9+21EMA | AE70: 持續在上方 | AH70: ✓ | AI70: 2026-09-01 | AJ70: 22 | AK70: 4 | AL70: 2026-09-28 | AM70: 15.18 | AN70: 13.37 | AO70: =IF(ISNUMBER(AN70),AM70/AN70-1,"") | AP70: 4 | AQ70: =IF(ISNUMBER(AM70),J70/AM70-1,"") | AR70: 18.42 | AS70: =J70/AR70-1 | AT70: 0.3517 | AU70: 0.5012 | AV70: 0.5385 | AW70: =AU70-AV70 | AX70: -0.1495 | AY70: -0.1763 | AZ70: -0.2055 | BA70: 淺紅 | BB70: 深紅→淺紅 | BC70: 3 | BD70: 深紅 深紅 深紅 深紅 淺紅 淺紅 淺紅 淺紅 | BE70: 上傾收窄（楔形） | BF70: 0.1584 | BG70: 0.6002 | BH70: 0.5843 | BI70: 0.6442 | BJ70: 2 | BK70: 19.09 | BL70: 13.37 | BM70: 16.712 | BN70: 0.4324 | BO70: =IF(M70=N70,0.5,(J70-N70)/(M70-N70)) | BP70: 19.801 | BQ70: 14.76 | BR70: =100*(0.4*MIN(1,MAX(0,((U70*100)-(0.0))/((2.5)-(0.0))))+0.3*MIN(1,MAX(0,((V70)-(0.6))/((1.0)-(0.6))))+0.3*MIN(1,MAX(0,((BP70)-(0.0))/((15.0)-(0.0))))) | BS70: =100*(0.4*MIN(1,MAX(0,((MIN(ABS(AA70),ABS(AB70)))-(0.75))/((0.0)-(0.75))))+0.3*MIN(1,MAX(0,((BN70)-(1.2))/((0.6)-(1.2))))+0.3*BO70) | BT70: =100*(0.5*MIN(1,MAX(0,((AK70)-(1.0))/((4.0)-(1.0))))+0.3*MIN(1,MAX(0,((IF(ISNUMBER(AO70),AO70,0)*100)-(0.0))/((8.0)-(0.0))))+0.2*MIN(1,MAX(0,((IF(ISNUMBER(AP70),AP70,0))-(25.0))/((5.0)-(25.0))))) | BU70: =100*(0.35*MIN(1,MAX(0,((ABS(BF70))-(0.3))/((0.05)-(0.3))))+0.3*MIN(1,MAX(0,((BG70)-(0.0))/((0.3)-(0.0))))+0.25*MIN(1,MAX(0,((BH70)-(0.4))/((0.7)-(0.4))))+0.1*IF(BJ70>=2,1,0.5)) | BV70: =0.25*BR70+0.25*BS70+0.2*BT70+0.3*BU70 | BW70: C5 MACD慢線向上
A71: 3 | B71: 9 | C71: FLGT | D71: Fulgent Genetics Inc. | E71: NASDAQ | F71: 醫療保健 | G71: Medical Specialities | H71: 0.606 | I71: 小型 | J71: 21.48 | K71: 21.3 | L71: =J71/K71-1 | M71: 21.64 | N71: 21.065 | O71: 297600 | P71: 330705 | Q71: =O71/P71 | R71: 21.6537 | S71: 21.2219 | T71: 20.8689 | U71: =S71/T71-1 | V71: 1 | W71: =J71/R71-1 | X71: =J71/S71-1 | Y71: 0.6604 | Z71: =Y71/J71 | AA71: =(J71-R71)/Y71 | AB71: =(J71-S71)/Y71 | AC71: =IF(ABS(AA71)<=ABS(AB71),"9EMA","21EMA") | AD71: 9+21EMA | AE71: 持續在上方 | AH71: ✓ | AI71: 2026-08-20 | AJ71: 30 | AK71: 4 | AL71: 2026-09-21 | AM71: 21.01 | AN71: 19.04 | AO71: =IF(ISNUMBER(AN71),AM71/AN71-1,"") | AP71: 9 | AQ71: =IF(ISNUMBER(AM71),J71/AM71-1,"") | AR71: 22.36 | AS71: =J71/AR71-1 | AT71: 0.5189 | AU71: 0.5685 | AV71: 0.581 | AW71: =AU71-AV71 | AX71: -0.0496 | AY71: -0.0119 | AZ71: 0.0593 | BA71: 深紅 | BB71: — | BC71: — | BD71: 淺綠 淺綠 深綠 深綠 淺綠 淺綠 深紅 深紅 | BE71: 上升通道 | BF71: 0.6232 | BG71: 0.6551 | BH71: 0.5294 | BI71: 0.5182 | BJ71: 2 | BK71: 22.59 | BL71: 19.04 | BM71: 20.9193 | BN71: 0.9792 | BO71: =IF(M71=N71,0.5,(J71-N71)/(M71-N71)) | BP71: 12.227 | BQ71: 7.186 | BR71: =100*(0.4*MIN(1,MAX(0,((U71*100)-(0.0))/((2.5)-(0.0))))+0.3*MIN(1,MAX(0,((V71)-(0.6))/((1.0)-(0.6))))+0.3*MIN(1,MAX(0,((BP71)-(0.0))/((15.0)-(0.0))))) | BS71: =100*(0.4*MIN(1,MAX(0,((MIN(ABS(AA71),ABS(AB71)))-(0.75))/((0.0)-(0.75))))+0.3*MIN(1,MAX(0,((BN71)-(1.2))/((0.6)-(1.2))))+0.3*BO71) | BT71: =100*(0.5*MIN(1,MAX(0,((AK71)-(1.0))/((4.0)-(1.0))))+0.3*MIN(1,MAX(0,((IF(ISNUMBER(AO71),AO71,0)*100)-(0.0))/((8.0)-(0.0))))+0.2*MIN(1,MAX(0,((IF(ISNUMBER(AP71),AP71,0))-(25.0))/((5.0)-(25.0))))) | BU71: =100*(0.35*MIN(1,MAX(0,((ABS(BF71))-(0.3))/((0.05)-(0.3))))+0.3*MIN(1,MAX(0,((BG71)-(0.0))/((0.3)-(0.0))))+0.25*MIN(1,MAX(0,((BH71)-(0.4))/((0.7)-(0.4))))+0.1*IF(BJ71>=2,1,0.5)) | BV71: =0.25*BR71+0.25*BS71+0.2*BT71+0.3*BU71 | BW71: C5 MACD慢線向上、C6 MACD柱轉勢
A72: 3 | B72: 10 | C72: HURN | D72: Huron Consulting Group Inc. | E72: NASDAQ | F72: 非必需消費 | G72: Professional Services | H72: 2.495 | I72: 中型 | J72: 162.15 | K72: 168.42 | L72: =J72/K72-1 | M72: 168 | N72: 161.12 | O72: 269900 | P72: 253100 | Q72: =O72/P72 | R72: 159.9353 | S72: 157.5206 | T72: 155.5934 | U72: =S72/T72-1 | V72: 1 | W72: =J72/R72-1 | X72: =J72/S72-1 | Y72: 5.5545 | Z72: =Y72/J72 | AA72: =(J72-R72)/Y72 | AB72: =(J72-S72)/Y72 | AC72: =IF(ABS(AA72)<=ABS(AB72),"9EMA","21EMA") | AD72: 9+21EMA | AE72: 持續在上方 | AH72: ✓ | AI72: 2026-07-13 | AJ72: 58 | AK72: 2 | AL72: 2026-09-29 | AM72: 155.46 | AN72: 144.2 | AO72: =IF(ISNUMBER(AN72),AM72/AN72-1,"") | AP72: 3 | AQ72: =IF(ISNUMBER(AM72),J72/AM72-1,"") | AR72: 168.42 | AS72: =J72/AR72-1 | AT72: 2.8173 | AU72: 2.587 | AV72: 2.5295 | AW72: =AU72-AV72 | AX72: 0.2303 | AY72: 0.2156 | AZ72: -0.501 | BA72: 深綠 | BB72: — | BC72: — | BD72: 淺紅 深紅 深紅 深紅 深紅 深紅 深綠 深綠 | BE72: 上升三角（平頂） | BF72: -0.0116 | BG72: 0.496 | BH72: 0.5459 | BI72: 0.4978 | BJ72: 2 | BK72: 169.45 | BL72: 144.2 | BM72: 157.9837 | BN72: 0.6216 | BO72: =IF(M72=N72,0.5,(J72-N72)/(M72-N72)) | BP72: 8.559 | BQ72: 3.518 | BR72: =100*(0.4*MIN(1,MAX(0,((U72*100)-(0.0))/((2.5)-(0.0))))+0.3*MIN(1,MAX(0,((V72)-(0.6))/((1.0)-(0.6))))+0.3*MIN(1,MAX(0,((BP72)-(0.0))/((15.0)-(0.0))))) | BS72: =100*(0.4*MIN(1,MAX(0,((MIN(ABS(AA72),ABS(AB72)))-(0.75))/((0.0)-(0.75))))+0.3*MIN(1,MAX(0,((BN72)-(1.2))/((0.6)-(1.2))))+0.3*BO72) | BT72: =100*(0.5*MIN(1,MAX(0,((AK72)-(1.0))/((4.0)-(1.0))))+0.3*MIN(1,MAX(0,((IF(ISNUMBER(AO72),AO72,0)*100)-(0.0))/((8.0)-(0.0))))+0.2*MIN(1,MAX(0,((IF(ISNUMBER(AP72),AP72,0))-(25.0))/((5.0)-(25.0))))) | BU72: =100*(0.35*MIN(1,MAX(0,((ABS(BF72))-(0.3))/((0.05)-(0.3))))+0.3*MIN(1,MAX(0,((BG72)-(0.0))/((0.3)-(0.0))))+0.25*MIN(1,MAX(0,((BH72)-(0.4))/((0.7)-(0.4))))+0.1*IF(BJ72>=2,1,0.5)) | BV72: =0.25*BR72+0.25*BS72+0.2*BT72+0.3*BU72 | BW72: C6 MACD柱轉勢
A73: 3 | B73: 11 | C73: MG | D73: Mistras Group Inc | E73: NYSE | F73: 非必需消費 | G73: Military/Government/Technical | H73: 0.671 | I73: 小型 | J73: 20.65 | K73: 20.63 | L73: =J73/K73-1 | M73: 20.85 | N73: 20.6 | O73: 344300 | P73: 519735 | Q73: =O73/P73 | R73: 20.8751 | S73: 20.3491 | T73: 19.9486 | U73: =S73/T73-1 | V73: 1 | W73: =J73/R73-1 | X73: =J73/S73-1 | Y73: 0.6382 | Z73: =Y73/J73 | AA73: =(J73-R73)/Y73 | AB73: =(J73-S73)/Y73 | AC73: =IF(ABS(AA73)<=ABS(AB73),"9EMA","21EMA") | AD73: 9EMA | AE73: 持續在上方 | AH73: ✓ | AI73: 2026-08-11 | AJ73: 37 | AK73: 4 | AL73: 2026-09-23 | AM73: 20.51 | AN73: 19.15 | AO73: =IF(ISNUMBER(AN73),AM73/AN73-1,"") | AP73: 7 | AQ73: =IF(ISNUMBER(AM73),J73/AM73-1,"") | AR73: 21.59 | AS73: =J73/AR73-1 | AT73: 0.6584 | AU73: 0.7375 | AV73: 0.7572 | AW73: =AU73-AV73 | AX73: -0.0791 | AY73: -0.034 | AZ73: 0.0319 | BA73: 深紅 | BB73: — | BC73: — | BD73: 深綠 深綠 深綠 淺綠 淺綠 淺綠 深紅 深紅 | BE73: 上升通道 | BF73: 0.6914 | BG73: 0.6998 | BH73: 0.6298 | BI73: 0.6281 | BJ73: 4 | BK73: 21.77 | BL73: 18.17 | BM73: 20.4371 | BN73: 0.8971 | BO73: =IF(M73=N73,0.5,(J73-N73)/(M73-N73)) | BP73: 11.539 | BQ73: 6.498 | BR73: =100*(0.4*MIN(1,MAX(0,((U73*100)-(0.0))/((2.5)-(0.0))))+0.3*MIN(1,MAX(0,((V73)-(0.6))/((1.0)-(0.6))))+0.3*MIN(1,MAX(0,((BP73)-(0.0))/((15.0)-(0.0))))) | BS73: =100*(0.4*MIN(1,MAX(0,((MIN(ABS(AA73),ABS(AB73)))-(0.75))/((0.0)-(0.75))))+0.3*MIN(1,MAX(0,((BN73)-(1.2))/((0.6)-(1.2))))+0.3*BO73) | BT73: =100*(0.5*MIN(1,MAX(0,((AK73)-(1.0))/((4.0)-(1.0))))+0.3*MIN(1,MAX(0,((IF(ISNUMBER(AO73),AO73,0)*100)-(0.0))/((8.0)-(0.0))))+0.2*MIN(1,MAX(0,((IF(ISNUMBER(AP73),AP73,0))-(25.0))/((5.0)-(25.0))))) | BU73: =100*(0.35*MIN(1,MAX(0,((ABS(BF73))-(0.3))/((0.05)-(0.3))))+0.3*MIN(1,MAX(0,((BG73)-(0.0))/((0.3)-(0.0))))+0.25*MIN(1,MAX(0,((BH73)-(0.4))/((0.7)-(0.4))))+0.1*IF(BJ73>=2,1,0.5)) | BV73: =0.25*BR73+0.25*BS73+0.2*BT73+0.3*BU73 | BW73: C5 MACD慢線向上、C6 MACD柱轉勢
A74: 3 | B74: 12 | C74: PLTR | D74: Palantir Technologies Inc. | E74: NASDAQ | F74: 科技 | G74: Computer Software: Prepackaged Software | H74: 449.304 | I74: 大型 | J74: 188.75 | K74: 190.04 | L74: =J74/K74-1 | M74: 194.78 | N74: 188.26 | O74: 17824100 | P74: 23028005 | Q74: =O74/P74 | R74: 187.0081 | S74: 182.226 | T74: 178.5998 | U74: =S74/T74-1 | V74: 1 | W74: =J74/R74-1 | X74: =J74/S74-1 | Y74: 6.2733 | Z74: =Y74/J74 | AA74: =(J74-R74)/Y74 | AB74: =(J74-S74)/Y74 | AC74: =IF(ABS(AA74)<=ABS(AB74),"9EMA","21EMA") | AD74: 9EMA | AE74: 持續在上方 | AH74: ✓ | AI74: 2026-08-04 | AJ74: 42 | AK74: 2 | AL74: 2026-09-29 | AM74: 184.81 | AN74: 164.55 | AO74: =IF(ISNUMBER(AN74),AM74/AN74-1,"") | AP74: 3 | AQ74: =IF(ISNUMBER(AM74),J74/AM74-1,"") | AR74: 192.59 | AS74: =J74/AR74-1 | AT74: 5.5841 | AU74: 5.5227 | AV74: 5.5073 | AW74: =AU74-AV74 | AX74: 0.0614 | AY74: 0.2214 | AZ74: 0.2468 | BA74: 淺綠 | BB74: — | BC74: — | BD74: 深綠 深綠 淺綠 淺綠 淺綠 淺綠 淺綠 淺綠 | BE74: 上傾收窄（楔形） | BF74: 0.1857 | BG74: 0.6151 | BH74: 0.5064 | BI74: 0.5237 | BJ74: 4 | BK74: 194.78 | BL74: 164.55 | BM74: 179.8582 | BN74: 0.7504 | BO74: =IF(M74=N74,0.5,(J74-N74)/(M74-N74)) | BP74: 16.424 | BQ74: 11.383 | BR74: =100*(0.4*MIN(1,MAX(0,((U74*100)-(0.0))/((2.5)-(0.0))))+0.3*MIN(1,MAX(0,((V74)-(0.6))/((1.0)-(0.6))))+0.3*MIN(1,MAX(0,((BP74)-(0.0))/((15.0)-(0.0))))) | BS74: =100*(0.4*MIN(1,MAX(0,((MIN(ABS(AA74),ABS(AB74)))-(0.75))/((0.0)-(0.75))))+0.3*MIN(1,MAX(0,((BN74)-(1.2))/((0.6)-(1.2))))+0.3*BO74) | BT74: =100*(0.5*MIN(1,MAX(0,((AK74)-(1.0))/((4.0)-(1.0))))+0.3*MIN(1,MAX(0,((IF(ISNUMBER(AO74),AO74,0)*100)-(0.0))/((8.0)-(0.0))))+0.2*MIN(1,MAX(0,((IF(ISNUMBER(AP74),AP74,0))-(25.0))/((5.0)-(25.0))))) | BU74: =100*(0.35*MIN(1,MAX(0,((ABS(BF74))-(0.3))/((0.05)-(0.3))))+0.3*MIN(1,MAX(0,((BG74)-(0.0))/((0.3)-(0.0))))+0.25*MIN(1,MAX(0,((BH74)-(0.4))/((0.7)-(0.4))))+0.1*IF(BJ74>=2,1,0.5)) | BV74: =0.25*BR74+0.25*BS74+0.2*BT74+0.3*BU74 | BW74: C6 MACD柱轉勢
A75: 3 | B75: 13 | C75: ACVA | D75: ACV Auctions Inc. | E75: NYSE | F75: 非必需消費 | G75: Business Services | H75: 1.771 | I75: 小型 | J75: 10.45 | K75: 10.45 | L75: =J75/K75-1 | M75: 10.48 | N75: 10.45 | O75: 2681700 | P75: 15692215 | Q75: =O75/P75 | R75: 10.3545 | S75: 9.7484 | T75: 9.3226 | U75: =S75/T75-1 | V75: 1 | W75: =J75/R75-1 | X75: =J75/S75-1 | Y75: 0.2316 | Z75: =Y75/J75 | AA75: =(J75-R75)/Y75 | AB75: =(J75-S75)/Y75 | AC75: =IF(ABS(AA75)<=ABS(AB75),"9EMA","21EMA") | AD75: — | AE75: 持續在上方 | AH75: ✓ | AI75: 2026-09-11 | AJ75: 15 | AK75: 3 | AL75: 2026-09-29 | AM75: 10.425 | AN75: 10.41 | AO75: =IF(ISNUMBER(AN75),AM75/AN75-1,"") | AP75: 3 | AQ75: =IF(ISNUMBER(AM75),J75/AM75-1,"") | AR75: 10.48 | AS75: =J75/AR75-1 | AT75: 0.7033 | AU75: 0.7394 | AV75: 0.7485 | AW75: =AU75-AV75 | AX75: -0.0361 | AY75: -0.0123 | AZ75: 0.0159 | BA75: 深紅 | BB75: — | BC75: — | BD75: 淺綠 淺綠 淺綠 淺綠 淺綠 淺綠 深紅 深紅 | BE75: 上升三角（平頂） | BF75: 0.0957 | BG75: 2.4609 | BH75: 0.8667 | BI75: 0.8677 | BJ75: 16 | BK75: 10.5 | BL75: 6.6 | BM75: 9.9801 | BN75: 2.1707 | BO75: =IF(M75=N75,0.5,(J75-N75)/(M75-N75)) | BP75: 59.398 | BQ75: 54.357 | BR75: =100*(0.4*MIN(1,MAX(0,((U75*100)-(0.0))/((2.5)-(0.0))))+0.3*MIN(1,MAX(0,((V75)-(0.6))/((1.0)-(0.6))))+0.3*MIN(1,MAX(0,((BP75)-(0.0))/((15.0)-(0.0))))) | BS75: =100*(0.4*MIN(1,MAX(0,((MIN(ABS(AA75),ABS(AB75)))-(0.75))/((0.0)-(0.75))))+0.3*MIN(1,MAX(0,((BN75)-(1.2))/((0.6)-(1.2))))+0.3*BO75) | BT75: =100*(0.5*MIN(1,MAX(0,((AK75)-(1.0))/((4.0)-(1.0))))+0.3*MIN(1,MAX(0,((IF(ISNUMBER(AO75),AO75,0)*100)-(0.0))/((8.0)-(0.0))))+0.2*MIN(1,MAX(0,((IF(ISNUMBER(AP75),AP75,0))-(25.0))/((5.0)-(25.0))))) | BU75: =100*(0.35*MIN(1,MAX(0,((ABS(BF75))-(0.3))/((0.05)-(0.3))))+0.3*MIN(1,MAX(0,((BG75)-(0.0))/((0.3)-(0.0))))+0.25*MIN(1,MAX(0,((BH75)-(0.4))/((0.7)-(0.4))))+0.1*IF(BJ75>=2,1,0.5)) | BV75: =0.25*BR75+0.25*BS75+0.2*BT75+0.3*BU75 | BW75: C5 MACD慢線向上、C6 MACD柱轉勢
A76: 3 | B76: 14 | C76: MNTK | D76: Montauk Renewables Inc. | E76: NASDAQ | F76: 公用事業 | G76: Natural Gas Distribution | H76: 0.389 | I76: 小型 | J76: 2.87 | K76: 2.79 | L76: =J76/K76-1 | M76: 2.91 | N76: 2.79 | O76: 512500 | P76: 773490 | Q76: =O76/P76 | R76: 2.732 | S76: 2.5214 | T76: 2.3355 | U76: =S76/T76-1 | V76: 1 | W76: =J76/R76-1 | X76: =J76/S76-1 | Y76: 0.2234 | Z76: =Y76/J76 | AA76: =(J76-R76)/Y76 | AB76: =(J76-S76)/Y76 | AC76: =IF(ABS(AA76)<=ABS(AB76),"9EMA","21EMA") | AD76: 9EMA | AE76: 持續在上方 | AI76: 2026-09-02 | AJ76: 21 | AK76: 2 | AL76: 2026-09-18 | AM76: 2.16 | AN76: 1.715 | AO76: =IF(ISNUMBER(AN76),AM76/AN76-1,"") | AP76: 10 | AQ76: =IF(ISNUMBER(AM76),J76/AM76-1,"") | AR76: 2.94 | AS76: =J76/AR76-1 | AT76: 0.2223 | AU76: 0.1996 | AV76: 0.1939 | AW76: =AU76-AV76 | AX76: 0.0228 | AY76: 0.0263 | AZ76: 0.035 | BA76: 淺綠 | BB76: — | BC76: — | BD76: 深紅 深綠 深綠 深綠 深綠 淺綠 淺綠 淺綠 | BE76: 上傾收窄（楔形） | BF76: 0.9292 | BG76: 1.1927 | BH76: 0.6628 | BI76: 0.7212 | BJ76: 2 | BK76: 3.05 | BL76: 1.715 | BM76: 2.5999 | BN76: 0.7555 | BO76: =IF(M76=N76,0.5,(J76-N76)/(M76-N76)) | BP76: 39.783 | BQ76: 34.742 | BR76: =100*(0.4*MIN(1,MAX(0,((U76*100)-(0.0))/((2.5)-(0.0))))+0.3*MIN(1,MAX(0,((V76)-(0.6))/((1.0)-(0.6))))+0.3*MIN(1,MAX(0,((BP76)-(0.0))/((15.0)-(0.0))))) | BS76: =100*(0.4*MIN(1,MAX(0,((MIN(ABS(AA76),ABS(AB76)))-(0.75))/((0.0)-(0.75))))+0.3*MIN(1,MAX(0,((BN76)-(1.2))/((0.6)-(1.2))))+0.3*BO76) | BT76: =100*(0.5*MIN(1,MAX(0,((AK76)-(1.0))/((4.0)-(1.0))))+0.3*MIN(1,MAX(0,((IF(ISNUMBER(AO76),AO76,0)*100)-(0.0))/((8.0)-(0.0))))+0.2*MIN(1,MAX(0,((IF(ISNUMBER(AP76),AP76,0))-(25.0))/((5.0)-(25.0))))) | BU76: =100*(0.35*MIN(1,MAX(0,((ABS(BF76))-(0.3))/((0.05)-(0.3))))+0.3*MIN(1,MAX(0,((BG76)-(0.0))/((0.3)-(0.0))))+0.25*MIN(1,MAX(0,((BH76)-(0.4))/((0.7)-(0.4))))+0.1*IF(BJ76>=2,1,0.5)) | BV76: =0.25*BR76+0.25*BS76+0.2*BT76+0.3*BU76 | BW76: C6 MACD柱轉勢
A77: 3 | B77: 15 | C77: OBIO | D77: Orchestra BioMed Holdings Inc. | E77: NASDAQ | F77: 醫療保健 | G77: Medicinal Chemicals and Botanical Products | H77: 0.374 | I77: 小型 | J77: 5.95 | K77: 6.35 | L77: =J77/K77-1 | M77: 6.44 | N77: 5.77 | O77: 421100 | P77: 387300 | Q77: =O77/P77 | R77: 6.0573 | S77: 5.8426 | T77: 5.6827 | U77: =S77/T77-1 | V77: 1 | W77: =J77/R77-1 | X77: =J77/S77-1 | Y77: 0.36 | Z77: =Y77/J77 | AA77: =(J77-R77)/Y77 | AB77: =(J77-S77)/Y77 | AC77: =IF(ABS(AA77)<=ABS(AB77),"9EMA","21EMA") | AD77: 9+21EMA | AE77: 持續在上方 | AH77: ✓ | AI77: 2026-08-03 | AJ77: 43 | AK77: 4 | AL77: 2026-09-24 | AM77: 5.75 | AN77: 5.71 | AO77: =IF(ISNUMBER(AN77),AM77/AN77-1,"") | AP77: 6 | AQ77: =IF(ISNUMBER(AM77),J77/AM77-1,"") | AR77: 6.35 | AS77: =J77/AR77-1 | AT77: 0.2737 | AU77: 0.3071 | AV77: 0.3154 | AW77: =AU77-AV77 | AX77: -0.0333 | AY77: -0.0133 | AZ77: -0.0255 | BA77: 深紅 | BB77: — | BC77: — | BD77: 淺綠 深紅 深紅 深紅 淺紅 淺紅 淺紅 深紅 | BE77: 上傾收窄（楔形） | BF77: 0.9122 | BG77: 1.3316 | BH77: 0.6057 | BI77: 0.6548 | BJ77: 3 | BK77: 6.5 | BL77: 4.71 | BM77: 5.7942 | BN77: 0.9284 | BO77: =IF(M77=N77,0.5,(J77-N77)/(M77-N77)) | BP77: 25.243 | BQ77: 20.202 | BR77: =100*(0.4*MIN(1,MAX(0,((U77*100)-(0.0))/((2.5)-(0.0))))+0.3*MIN(1,MAX(0,((V77)-(0.6))/((1.0)-(0.6))))+0.3*MIN(1,MAX(0,((BP77)-(0.0))/((15.0)-(0.0))))) | BS77: =100*(0.4*MIN(1,MAX(0,((MIN(ABS(AA77),ABS(AB77)))-(0.75))/((0.0)-(0.75))))+0.3*MIN(1,MAX(0,((BN77)-(1.2))/((0.6)-(1.2))))+0.3*BO77) | BT77: =100*(0.5*MIN(1,MAX(0,((AK77)-(1.0))/((4.0)-(1.0))))+0.3*MIN(1,MAX(0,((IF(ISNUMBER(AO77),AO77,0)*100)-(0.0))/((8.0)-(0.0))))+0.2*MIN(1,MAX(0,((IF(ISNUMBER(AP77),AP77,0))-(25.0))/((5.0)-(25.0))))) | BU77: =100*(0.35*MIN(1,MAX(0,((ABS(BF77))-(0.3))/((0.05)-(0.3))))+0.3*MIN(1,MAX(0,((BG77)-(0.0))/((0.3)-(0.0))))+0.25*MIN(1,MAX(0,((BH77)-(0.4))/((0.7)-(0.4))))+0.1*IF(BJ77>=2,1,0.5)) | BV77: =0.25*BR77+0.25*BS77+0.2*BT77+0.3*BU77 | BW77: C5 MACD慢線向上、C6 MACD柱轉勢
A78: 3 | B78: 16 | C78: PSIX | D78: Power Solutions International Inc. | E78: NASDAQ | F78: 工業 | G78: Industrial Machinery/Components | H78: 1.06 | I78: 小型 | J78: 44.85 | K78: 45.4 | L78: =J78/K78-1 | M78: 47.12 | N78: 44.52 | O78: 623000 | P78: 415905 | Q78: =O78/P78 | R78: 45.4263 | S78: 43.6523 | T78: 42.3958 | U78: =S78/T78-1 | V78: 1 | W78: =J78/R78-1 | X78: =J78/S78-1 | Y78: 2.2929 | Z78: =Y78/J78 | AA78: =(J78-R78)/Y78 | AB78: =(J78-S78)/Y78 | AC78: =IF(ABS(AA78)<=ABS(AB78),"9EMA","21EMA") | AD78: 9EMA | AE78: 持續在上方 | AH78: ✓ | AI78: 2026-08-07 | AJ78: 39 | AK78: 3 | AL78: 2026-09-24 | AM78: 44.61 | AN78: 39 | AO78: =IF(ISNUMBER(AN78),AM78/AN78-1,"") | AP78: 6 | AQ78: =IF(ISNUMBER(AM78),J78/AM78-1,"") | AR78: 47.1 | AS78: =J78/AR78-1 | AT78: 2.0917 | AU78: 2.2375 | AV78: 2.2739 | AW78: =AU78-AV78 | AX78: -0.1458 | AY78: 0.0048 | AZ78: 0.1558 | BA78: 深紅 | BB78: — | BC78: — | BD78: 淺綠 淺綠 淺綠 淺綠 淺綠 淺綠 淺綠 深紅 | BE78: 上傾收窄（楔形） | BF78: 0.8175 | BG78: 1.3706 | BH78: 0.622 | BI78: 0.6624 | BJ78: 1 | BK78: 48.32 | BL78: 34.67 | BM78: 43.1608 | BN78: 0.9928 | BO78: =IF(M78=N78,0.5,(J78-N78)/(M78-N78)) | BP78: 30.706 | BQ78: 25.665 | BR78: =100*(0.4*MIN(1,MAX(0,((U78*100)-(0.0))/((2.5)-(0.0))))+0.3*MIN(1,MAX(0,((V78)-(0.6))/((1.0)-(0.6))))+0.3*MIN(1,MAX(0,((BP78)-(0.0))/((15.0)-(0.0))))) | BS78: =100*(0.4*MIN(1,MAX(0,((MIN(ABS(AA78),ABS(AB78)))-(0.75))/((0.0)-(0.75))))+0.3*MIN(1,MAX(0,((BN78)-(1.2))/((0.6)-(1.2))))+0.3*BO78) | BT78: =100*(0.5*MIN(1,MAX(0,((AK78)-(1.0))/((4.0)-(1.0))))+0.3*MIN(1,MAX(0,((IF(ISNUMBER(AO78),AO78,0)*100)-(0.0))/((8.0)-(0.0))))+0.2*MIN(1,MAX(0,((IF(ISNUMBER(AP78),AP78,0))-(25.0))/((5.0)-(25.0))))) | BU78: =100*(0.35*MIN(1,MAX(0,((ABS(BF78))-(0.3))/((0.05)-(0.3))))+0.3*MIN(1,MAX(0,((BG78)-(0.0))/((0.3)-(0.0))))+0.25*MIN(1,MAX(0,((BH78)-(0.4))/((0.7)-(0.4))))+0.1*IF(BJ78>=2,1,0.5)) | BV78: =0.25*BR78+0.25*BS78+0.2*BT78+0.3*BU78 | BW78: C5 MACD慢線向上、C6 MACD柱轉勢
A79: 3 | B79: 17 | C79: DT | D79: Dynatrace Inc. | E79: NYSE | F79: 科技 | G79: Computer Software: Prepackaged Software | H79: 16.687 | I79: 大型 | J79: 59.32 | K79: 59.26 | L79: =J79/K79-1 | M79: 60.24 | N79: 58.91 | O79: 3855100 | P79: 6818060 | Q79: =O79/P79 | R79: 57.9117 | S79: 55.9206 | T79: 54.3892 | U79: =S79/T79-1 | V79: 1 | W79: =J79/R79-1 | X79: =J79/S79-1 | Y79: 1.7233 | Z79: =Y79/J79 | AA79: =(J79-R79)/Y79 | AB79: =(J79-S79)/Y79 | AC79: =IF(ABS(AA79)<=ABS(AB79),"9EMA","21EMA") | AD79: — | AE79: 持續在上方 | AI79: 2026-07-29 | AJ79: 46 | AK79: 4 | AL79: 2026-09-28 | AM79: 55.644 | AN79: 49.56 | AO79: =IF(ISNUMBER(AN79),AM79/AN79-1,"") | AP79: 4 | AQ79: =IF(ISNUMBER(AM79),J79/AM79-1,"") | AR79: 59.32 | AS79: =J79/AR79-1 | AT79: 2.2135 | AU79: 2.1152 | AV79: 2.0906 | AW79: =AU79-AV79 | AX79: 0.0983 | AY79: 0.1037 | AZ79: 0.0794 | BA79: 淺綠 | BB79: — | BC79: — | BD79: 深綠 深綠 淺綠 淺綠 淺綠 淺綠 深綠 淺綠 | BE79: 上傾收窄（楔形） | BF79: 0.4537 | BG79: 0.7889 | BH79: 0.5371 | BI79: 0.5545 | BJ79: 3 | BK79: 60.24 | BL79: 49.56 | BM79: 55.2968 | BN79: 0.8101 | BO79: =IF(M79=N79,0.5,(J79-N79)/(M79-N79)) | BP79: 21.652 | BQ79: 16.611 | BR79: =100*(0.4*MIN(1,MAX(0,((U79*100)-(0.0))/((2.5)-(0.0))))+0.3*MIN(1,MAX(0,((V79)-(0.6))/((1.0)-(0.6))))+0.3*MIN(1,MAX(0,((BP79)-(0.0))/((15.0)-(0.0))))) | BS79: =100*(0.4*MIN(1,MAX(0,((MIN(ABS(AA79),ABS(AB79)))-(0.75))/((0.0)-(0.75))))+0.3*MIN(1,MAX(0,((BN79)-(1.2))/((0.6)-(1.2))))+0.3*BO79) | BT79: =100*(0.5*MIN(1,MAX(0,((AK79)-(1.0))/((4.0)-(1.0))))+0.3*MIN(1,MAX(0,((IF(ISNUMBER(AO79),AO79,0)*100)-(0.0))/((8.0)-(0.0))))+0.2*MIN(1,MAX(0,((IF(ISNUMBER(AP79),AP79,0))-(25.0))/((5.0)-(25.0))))) | BU79: =100*(0.35*MIN(1,MAX(0,((ABS(BF79))-(0.3))/((0.05)-(0.3))))+0.3*MIN(1,MAX(0,((BG79)-(0.0))/((0.3)-(0.0))))+0.25*MIN(1,MAX(0,((BH79)-(0.4))/((0.7)-(0.4))))+0.1*IF(BJ79>=2,1,0.5)) | BV79: =0.25*BR79+0.25*BS79+0.2*BT79+0.3*BU79 | BW79: C6 MACD柱轉勢
A80: 3 | B80: 18 | C80: VRNS | D80: Varonis Systems Inc. | E80: NASDAQ | F80: 科技 | G80: Computer Software: Prepackaged Software | H80: 5.45 | I80: 中型 | J80: 47.57 | K80: 47.45 | L80: =J80/K80-1 | M80: 48.537 | N80: 47.435 | O80: 1012300 | P80: 1745330 | Q80: =O80/P80 | R80: 47.4023 | S80: 46.735 | T80: 46.2708 | U80: =S80/T80-1 | V80: 0.9 | W80: =J80/R80-1 | X80: =J80/S80-1 | Y80: 1.8644 | Z80: =Y80/J80 | AA80: =(J80-R80)/Y80 | AB80: =(J80-S80)/Y80 | AC80: =IF(ABS(AA80)<=ABS(AB80),"9EMA","21EMA") | AD80: 9+21EMA | AE80: 持續在上方 | AH80: ✓ | AI80: 2026-08-31 | AJ80: 23 | AK80: 4 | AL80: 2026-09-28 | AM80: 44.62 | AN80: 44.172 | AO80: =IF(ISNUMBER(AN80),AM80/AN80-1,"") | AP80: 4 | AQ80: =IF(ISNUMBER(AM80),J80/AM80-1,"") | AR80: 48.455 | AS80: =J80/AR80-1 | AT80: 0.8665 | AU80: 1.0035 | AV80: 1.0377 | AW80: =AU80-AV80 | AX80: -0.137 | AY80: -0.1316 | AZ80: -0.1148 | BA80: 深紅 | BB80: — | BC80: — | BD80: 淺綠 淺綠 深紅 淺紅 深紅 深紅 深紅 深紅 | BE80: 上傾收窄（楔形） | BF80: 0.1016 | BG80: 0.4149 | BH80: 0.7213 | BI80: 0.6943 | BJ80: 13 | BK80: 48.79 | BL80: 40.89 | BM80: 46.5884 | BN80: 1.0282 | BO80: =IF(M80=N80,0.5,(J80-N80)/(M80-N80)) | BP80: 6.773 | BQ80: 1.732 | BR80: =100*(0.4*MIN(1,MAX(0,((U80*100)-(0.0))/((2.5)-(0.0))))+0.3*MIN(1,MAX(0,((V80)-(0.6))/((1.0)-(0.6))))+0.3*MIN(1,MAX(0,((BP80)-(0.0))/((15.0)-(0.0))))) | BS80: =100*(0.4*MIN(1,MAX(0,((MIN(ABS(AA80),ABS(AB80)))-(0.75))/((0.0)-(0.75))))+0.3*MIN(1,MAX(0,((BN80)-(1.2))/((0.6)-(1.2))))+0.3*BO80) | BT80: =100*(0.5*MIN(1,MAX(0,((AK80)-(1.0))/((4.0)-(1.0))))+0.3*MIN(1,MAX(0,((IF(ISNUMBER(AO80),AO80,0)*100)-(0.0))/((8.0)-(0.0))))+0.2*MIN(1,MAX(0,((IF(ISNUMBER(AP80),AP80,0))-(25.0))/((5.0)-(25.0))))) | BU80: =100*(0.35*MIN(1,MAX(0,((ABS(BF80))-(0.3))/((0.05)-(0.3))))+0.3*MIN(1,MAX(0,((BG80)-(0.0))/((0.3)-(0.0))))+0.25*MIN(1,MAX(0,((BH80)-(0.4))/((0.7)-(0.4))))+0.1*IF(BJ80>=2,1,0.5)) | BV80: =0.25*BR80+0.25*BS80+0.2*BT80+0.3*BU80 | BW80: C5 MACD慢線向上、C6 MACD柱轉勢
A81: 3 | B81: 19 | C81: AGPU | D81: Axe Compute Inc. | E81: NASDAQ | F81: 醫療保健 | G81: Industrial Specialties | H81: 0.132 | I81: 小型 | J81: 12.08 | K81: 11.42 | L81: =J81/K81-1 | M81: 12.5 | N81: 11.44 | O81: 251300 | P81: 351855 | Q81: =O81/P81 | R81: 11.8277 | S81: 11.4405 | T81: 11.1652 | U81: =S81/T81-1 | V81: 0.9 | W81: =J81/R81-1 | X81: =J81/S81-1 | Y81: 1.0602 | Z81: =Y81/J81 | AA81: =(J81-R81)/Y81 | AB81: =(J81-S81)/Y81 | AC81: =IF(ABS(AA81)<=ABS(AB81),"9EMA","21EMA") | AD81: 9+21EMA | AE81: 持續在上方 | AH81: ✓ | AI81: 2026-07-20 | AJ81: 53 | AK81: 4 | AL81: 2026-09-24 | AM81: 11.03 | AN81: 10.6 | AO81: =IF(ISNUMBER(AN81),AM81/AN81-1,"") | AP81: 6 | AQ81: =IF(ISNUMBER(AM81),J81/AM81-1,"") | AR81: 12.92 | AS81: =J81/AR81-1 | AT81: 0.5224 | AU81: 0.6199 | AV81: 0.6443 | AW81: =AU81-AV81 | AX81: -0.0975 | AY81: -0.1126 | AZ81: -0.0696 | BA81: 淺紅 | BB81: 深紅→淺紅 | BC81: 0 | BD81: 淺綠 深紅 深紅 深紅 深綠 深紅 深紅 淺紅 | BE81: 上傾收窄（楔形） | BF81: 0.8031 | BG81: 1.1074 | BH81: 0.5473 | BI81: 0.5876 | BJ81: 3 | BK81: 13.49 | BL81: 9.07 | BM81: 11.4889 | BN81: 1.171 | BO81: =IF(M81=N81,0.5,(J81-N81)/(M81-N81)) | BP81: 28.432 | BQ81: 23.391 | BR81: =100*(0.4*MIN(1,MAX(0,((U81*100)-(0.0))/((2.5)-(0.0))))+0.3*MIN(1,MAX(0,((V81)-(0.6))/((1.0)-(0.6))))+0.3*MIN(1,MAX(0,((BP81)-(0.0))/((15.0)-(0.0))))) | BS81: =100*(0.4*MIN(1,MAX(0,((MIN(ABS(AA81),ABS(AB81)))-(0.75))/((0.0)-(0.75))))+0.3*MIN(1,MAX(0,((BN81)-(1.2))/((0.6)-(1.2))))+0.3*BO81) | BT81: =100*(0.5*MIN(1,MAX(0,((AK81)-(1.0))/((4.0)-(1.0))))+0.3*MIN(1,MAX(0,((IF(ISNUMBER(AO81),AO81,0)*100)-(0.0))/((8.0)-(0.0))))+0.2*MIN(1,MAX(0,((IF(ISNUMBER(AP81),AP81,0))-(25.0))/((5.0)-(25.0))))) | BU81: =100*(0.35*MIN(1,MAX(0,((ABS(BF81))-(0.3))/((0.05)-(0.3))))+0.3*MIN(1,MAX(0,((BG81)-(0.0))/((0.3)-(0.0))))+0.25*MIN(1,MAX(0,((BH81)-(0.4))/((0.7)-(0.4))))+0.1*IF(BJ81>=2,1,0.5)) | BV81: =0.25*BR81+0.25*BS81+0.2*BT81+0.3*BU81 | BW81: C5 MACD慢線向上
A82: 3 | B82: 20 | C82: BE | D82: Bloom Energy Corporation | E82: NYSE | F82: 能源 | G82: Industrial Machinery/Components | H82: 81.578 | I82: 大型 | J82: 289.15 | K82: 277.58 | L82: =J82/K82-1 | M82: 297.59 | N82: 283.1 | O82: 12862400 | P82: 17788915 | Q82: =O82/P82 | R82: 278.3009 | S82: 266.9409 | T82: 258.7915 | U82: =S82/T82-1 | V82: 1 | W82: =J82/R82-1 | X82: =J82/S82-1 | Y82: 20.9237 | Z82: =Y82/J82 | AA82: =(J82-R82)/Y82 | AB82: =(J82-S82)/Y82 | AC82: =IF(ABS(AA82)<=ABS(AB82),"9EMA","21EMA") | AD82: 9EMA | AE82: 持續在上方 | AI82: 2026-09-03 | AJ82: 20 | AK82: 4 | AL82: 2026-09-24 | AM82: 251.3 | AN82: 249.05 | AO82: =IF(ISNUMBER(AN82),AM82/AN82-1,"") | AP82: 6 | AQ82: =IF(ISNUMBER(AM82),J82/AM82-1,"") | AR82: 291.25 | AS82: =J82/AR82-1 | AT82: 12.6697 | AU82: 12.6184 | AV82: 12.6055 | AW82: =AU82-AV82 | AX82: 0.0514 | AY82: -0.3056 | AZ82: 0.145 | BA82: 深綠 | BB82: — | BC82: — | BD82: 淺綠 淺綠 深綠 深紅 深綠 淺綠 深紅 深綠 | BE82: 上傾收窄（楔形） | BF82: 0.4317 | BG82: 1.1629 | BH82: 0.6379 | BI82: 0.6837 | BJ82: 2 | BK82: 302.354 | BL82: 197.5 | BM82: 264.3821 | BN82: 0.9459 | BO82: =IF(M82=N82,0.5,(J82-N82)/(M82-N82)) | BP82: 38.118 | BQ82: 33.077 | BR82: =100*(0.4*MIN(1,MAX(0,((U82*100)-(0.0))/((2.5)-(0.0))))+0.3*MIN(1,MAX(0,((V82)-(0.6))/((1.0)-(0.6))))+0.3*MIN(1,MAX(0,((BP82)-(0.0))/((15.0)-(0.0))))) | BS82: =100*(0.4*MIN(1,MAX(0,((MIN(ABS(AA82),ABS(AB82)))-(0.75))/((0.0)-(0.75))))+0.3*MIN(1,MAX(0,((BN82)-(1.2))/((0.6)-(1.2))))+0.3*BO82) | BT82: =100*(0.5*MIN(1,MAX(0,((AK82)-(1.0))/((4.0)-(1.0))))+0.3*MIN(1,MAX(0,((IF(ISNUMBER(AO82),AO82,0)*100)-(0.0))/((8.0)-(0.0))))+0.2*MIN(1,MAX(0,((IF(ISNUMBER(AP82),AP82,0))-(25.0))/((5.0)-(25.0))))) | BU82: =100*(0.35*MIN(1,MAX(0,((ABS(BF82))-(0.3))/((0.05)-(0.3))))+0.3*MIN(1,MAX(0,((BG82)-(0.0))/((0.3)-(0.0))))+0.25*MIN(1,MAX(0,((BH82)-(0.4))/((0.7)-(0.4))))+0.1*IF(BJ82>=2,1,0.5)) | BV82: =0.25*BR82+0.25*BS82+0.2*BT82+0.3*BU82 | BW82: C6 MACD柱轉勢
A83: 3 | B83: 21 | C83: CRSR | D83: Corsair Gaming Inc. | E83: NASDAQ | F83: 科技 | G83: Computer peripheral equipment | H83: 1.46 | I83: 小型 | J83: 13.79 | K83: 13.85 | L83: =J83/K83-1 | M83: 14.42 | N83: 13.77 | O83: 1288500 | P83: 1071525 | Q83: =O83/P83 | R83: 13.5806 | S83: 13.2164 | T83: 12.9586 | U83: =S83/T83-1 | V83: 1 | W83: =J83/R83-1 | X83: =J83/S83-1 | Y83: 0.6033 | Z83: =Y83/J83 | AA83: =(J83-R83)/Y83 | AB83: =(J83-S83)/Y83 | AC83: =IF(ABS(AA83)<=ABS(AB83),"9EMA","21EMA") | AD83: 9EMA | AE83: 持續在上方 | AH83: ✓ | AI83: 2026-06-29 | AJ83: 67 | AK83: 6 | AL83: 2026-09-24 | AM83: 13.06 | AN83: 12.05 | AO83: =IF(ISNUMBER(AN83),AM83/AN83-1,"") | AP83: 6 | AQ83: =IF(ISNUMBER(AM83),J83/AM83-1,"") | AR83: 13.85 | AS83: =J83/AR83-1 | AT83: 0.4428 | AU83: 0.468 | AV83: 0.4744 | AW83: =AU83-AV83 | AX83: -0.0253 | AY83: -0.026 | AZ83: -0.0379 | BA83: 淺紅 | BB83: 深紅→淺紅 | BC83: 1 | BD83: 淺綠 淺綠 淺綠 深紅 深紅 深紅 淺紅 淺紅 | BE83: 上傾收窄（楔形） | BF83: 0.5113 | BG83: 0.6893 | BH83: 0.5255 | BI83: 0.645 | BJ83: 2 | BK83: 14.42 | BL83: 11.55 | BM83: 13.0583 | BN83: 0.9491 | BO83: =IF(M83=N83,0.5,(J83-N83)/(M83-N83)) | BP83: 19.008 | BQ83: 13.967 | BR83: =100*(0.4*MIN(1,MAX(0,((U83*100)-(0.0))/((2.5)-(0.0))))+0.3*MIN(1,MAX(0,((V83)-(0.6))/((1.0)-(0.6))))+0.3*MIN(1,MAX(0,((BP83)-(0.0))/((15.0)-(0.0))))) | BS83: =100*(0.4*MIN(1,MAX(0,((MIN(ABS(AA83),ABS(AB83)))-(0.75))/((0.0)-(0.75))))+0.3*MIN(1,MAX(0,((BN83)-(1.2))/((0.6)-(1.2))))+0.3*BO83) | BT83: =100*(0.5*MIN(1,MAX(0,((AK83)-(1.0))/((4.0)-(1.0))))+0.3*MIN(1,MAX(0,((IF(ISNUMBER(AO83),AO83,0)*100)-(0.0))/((8.0)-(0.0))))+0.2*MIN(1,MAX(0,((IF(ISNUMBER(AP83),AP83,0))-(25.0))/((5.0)-(25.0))))) | BU83: =100*(0.35*MIN(1,MAX(0,((ABS(BF83))-(0.3))/((0.05)-(0.3))))+0.3*MIN(1,MAX(0,((BG83)-(0.0))/((0.3)-(0.0))))+0.25*MIN(1,MAX(0,((BH83)-(0.4))/((0.7)-(0.4))))+0.1*IF(BJ83>=2,1,0.5)) | BV83: =0.25*BR83+0.25*BS83+0.2*BT83+0.3*BU83 | BW83: C5 MACD慢線向上
A84: 3 | B84: 22 | C84: SENS | D84: Senseonics Holdings Inc. | E84: NASDAQ | F84: 醫療保健 | G84: Medical/Dental Instruments | H84: 0.538 | I84: 小型 | J84: 9.88 | K84: 9.96 | L84: =J84/K84-1 | M84: 10.09 | N84: 9.78 | O84: 704900 | P84: 717815 | Q84: =O84/P84 | R84: 9.9102 | S84: 9.5826 | T84: 9.3406 | U84: =S84/T84-1 | V84: 1 | W84: =J84/R84-1 | X84: =J84/S84-1 | Y84: 0.4699 | Z84: =Y84/J84 | AA84: =(J84-R84)/Y84 | AB84: =(J84-S84)/Y84 | AC84: =IF(ABS(AA84)<=ABS(AB84),"9EMA","21EMA") | AD84: 9EMA | AE84: 持續在上方 | AH84: ✓ | AI84: 2026-08-07 | AJ84: 39 | AK84: 2 | AL84: 2026-09-29 | AM84: 9.77 | AN84: 8.45 | AO84: =IF(ISNUMBER(AN84),AM84/AN84-1,"") | AP84: 3 | AQ84: =IF(ISNUMBER(AM84),J84/AM84-1,"") | AR84: 10.34 | AS84: =J84/AR84-1 | AT84: 0.428 | AU84: 0.4793 | AV84: 0.4921 | AW84: =AU84-AV84 | AX84: -0.0513 | AY84: -0.0337 | AZ84: -0.0182 | BA84: 深紅 | BB84: — | BC84: — | BD84: 淺紅 深綠 淺綠 深紅 深紅 淺紅 深紅 深紅 | BE84: 上傾收窄（楔形） | BF84: 0.2213 | BG84: 1.0277 | BH84: 0.5319 | BI84: 0.5552 | BJ84: 1 | BK84: 10.64 | BL84: 8.45 | BM84: 9.6149 | BN84: 0.8131 | BO84: =IF(M84=N84,0.5,(J84-N84)/(M84-N84)) | BP84: 4.437 | BQ84: -0.604 | BR84: =100*(0.4*MIN(1,MAX(0,((U84*100)-(0.0))/((2.5)-(0.0))))+0.3*MIN(1,MAX(0,((V84)-(0.6))/((1.0)-(0.6))))+0.3*MIN(1,MAX(0,((BP84)-(0.0))/((15.0)-(0.0))))) | BS84: =100*(0.4*MIN(1,MAX(0,((MIN(ABS(AA84),ABS(AB84)))-(0.75))/((0.0)-(0.75))))+0.3*MIN(1,MAX(0,((BN84)-(1.2))/((0.6)-(1.2))))+0.3*BO84) | BT84: =100*(0.5*MIN(1,MAX(0,((AK84)-(1.0))/((4.0)-(1.0))))+0.3*MIN(1,MAX(0,((IF(ISNUMBER(AO84),AO84,0)*100)-(0.0))/((8.0)-(0.0))))+0.2*MIN(1,MAX(0,((IF(ISNUMBER(AP84),AP84,0))-(25.0))/((5.0)-(25.0))))) | BU84: =100*(0.35*MIN(1,MAX(0,((ABS(BF84))-(0.3))/((0.05)-(0.3))))+0.3*MIN(1,MAX(0,((BG84)-(0.0))/((0.3)-(0.0))))+0.25*MIN(1,MAX(0,((BH84)-(0.4))/((0.7)-(0.4))))+0.1*IF(BJ84>=2,1,0.5)) | BV84: =0.25*BR84+0.25*BS84+0.2*BT84+0.3*BU84 | BW84: C5 MACD慢線向上、C6 MACD柱轉勢
A85: 3 | B85: 23 | C85: SNDK | D85: Sandisk Corporation | E85: NASDAQ | F85: 科技 | G85: Electronic Components | H85: 254.753 | I85: 大型 | J85: 1719.99 | K85: 1787.6899 | L85: =J85/K85-1 | M85: 1774.23 | N85: 1713.47 | O85: 8163600 | P85: 9416170 | Q85: =O85/P85 | R85: 1741.0869 | S85: 1698.1726 | T85: 1673.0694 | U85: =S85/T85-1 | V85: 1 | W85: =J85/R85-1 | X85: =J85/S85-1 | Y85: 100.314 | Z85: =Y85/J85 | AA85: =(J85-R85)/Y85 | AB85: =(J85-S85)/Y85 | AC85: =IF(ABS(AA85)<=ABS(AB85),"9EMA","21EMA") | AD85: 9EMA | AE85: 持續在上方 | AH85: ✓ | AI85: 2026-08-17 | AJ85: 33 | AK85: 5 | AL85: 2026-09-28 | AM85: 1659.02 | AN85: 1504.2 | AO85: =IF(ISNUMBER(AN85),AM85/AN85-1,"") | AP85: 4 | AQ85: =IF(ISNUMBER(AM85),J85/AM85-1,"") | AR85: 1887.04 | AS85: =J85/AR85-1 | AT85: 50.7527 | AU85: 54.8188 | AV85: 55.8353 | AW85: =AU85-AV85 | AX85: -4.0661 | AY85: 0.2068 | AZ85: -0.6985 | BA85: 深紅 | BB85: — | BC85: — | BD85: 深綠 淺綠 淺綠 淺綠 淺綠 深紅 深綠 深紅 | BE85: 上升通道 | BF85: 0.5936 | BG85: 0.6244 | BH85: 0.5169 | BI85: 0.4865 | BJ85: 2 | BK85: 1909.48 | BL85: 1435.61 | BM85: 1680.5625 | BN85: 0.9935 | BO85: =IF(M85=N85,0.5,(J85-N85)/(M85-N85)) | BP85: 15.765 | BQ85: 10.724 | BR85: =100*(0.4*MIN(1,MAX(0,((U85*100)-(0.0))/((2.5)-(0.0))))+0.3*MIN(1,MAX(0,((V85)-(0.6))/((1.0)-(0.6))))+0.3*MIN(1,MAX(0,((BP85)-(0.0))/((15.0)-(0.0))))) | BS85: =100*(0.4*MIN(1,MAX(0,((MIN(ABS(AA85),ABS(AB85)))-(0.75))/((0.0)-(0.75))))+0.3*MIN(1,MAX(0,((BN85)-(1.2))/((0.6)-(1.2))))+0.3*BO85) | BT85: =100*(0.5*MIN(1,MAX(0,((AK85)-(1.0))/((4.0)-(1.0))))+0.3*MIN(1,MAX(0,((IF(ISNUMBER(AO85),AO85,0)*100)-(0.0))/((8.0)-(0.0))))+0.2*MIN(1,MAX(0,((IF(ISNUMBER(AP85),AP85,0))-(25.0))/((5.0)-(25.0))))) | BU85: =100*(0.35*MIN(1,MAX(0,((ABS(BF85))-(0.3))/((0.05)-(0.3))))+0.3*MIN(1,MAX(0,((BG85)-(0.0))/((0.3)-(0.0))))+0.25*MIN(1,MAX(0,((BH85)-(0.4))/((0.7)-(0.4))))+0.1*IF(BJ85>=2,1,0.5)) | BV85: =0.25*BR85+0.25*BS85+0.2*BT85+0.3*BU85 | BW85: C5 MACD慢線向上、C6 MACD柱轉勢
A86: 3 | B86: 24 | C86: CVLT | D86: Commvault Systems Inc. | E86: NASDAQ | F86: 科技 | G86: Computer Software: Prepackaged Software | H86: 6.213 | I86: 中型 | J86: 150.28 | K86: 147.77 | L86: =J86/K86-1 | M86: 153.24 | N86: 148.78 | O86: 471000 | P86: 591635 | Q86: =O86/P86 | R86: 147.643 | S86: 144.3816 | T86: 141.8105 | U86: =S86/T86-1 | V86: 1 | W86: =J86/R86-1 | X86: =J86/S86-1 | Y86: 5.7661 | Z86: =Y86/J86 | AA86: =(J86-R86)/Y86 | AB86: =(J86-S86)/Y86 | AC86: =IF(ABS(AA86)<=ABS(AB86),"9EMA","21EMA") | AD86: 9EMA | AE86: 持續在上方 | AH86: ✓ | AI86: 2026-09-15 | AJ86: 13 | AK86: 3 | AL86: 2026-09-28 | AM86: 141.1 | AN86: 129.5 | AO86: =IF(ISNUMBER(AN86),AM86/AN86-1,"") | AP86: 4 | AQ86: =IF(ISNUMBER(AM86),J86/AM86-1,"") | AR86: 150.28 | AS86: =J86/AR86-1 | AT86: 3.336 | AU86: 2.9186 | AV86: 2.8142 | AW86: =AU86-AV86 | AX86: 0.4175 | AY86: 0.4281 | AZ86: 0.6238 | BA86: 淺綠 | BB86: — | BC86: — | BD86: 深綠 淺綠 淺綠 淺綠 淺綠 淺綠 淺綠 淺綠 | BE86: 上升通道 | BF86: 0.5492 | BG86: 0.6081 | BH86: 0.5966 | BI86: 0.6172 | BJ86: 4 | BK86: 153.24 | BL86: 125.9 | BM86: 142.2108 | BN86: 0.9099 | BO86: =IF(M86=N86,0.5,(J86-N86)/(M86-N86)) | BP86: 19.27 | BQ86: 14.229 | BR86: =100*(0.4*MIN(1,MAX(0,((U86*100)-(0.0))/((2.5)-(0.0))))+0.3*MIN(1,MAX(0,((V86)-(0.6))/((1.0)-(0.6))))+0.3*MIN(1,MAX(0,((BP86)-(0.0))/((15.0)-(0.0))))) | BS86: =100*(0.4*MIN(1,MAX(0,((MIN(ABS(AA86),ABS(AB86)))-(0.75))/((0.0)-(0.75))))+0.3*MIN(1,MAX(0,((BN86)-(1.2))/((0.6)-(1.2))))+0.3*BO86) | BT86: =100*(0.5*MIN(1,MAX(0,((AK86)-(1.0))/((4.0)-(1.0))))+0.3*MIN(1,MAX(0,((IF(ISNUMBER(AO86),AO86,0)*100)-(0.0))/((8.0)-(0.0))))+0.2*MIN(1,MAX(0,((IF(ISNUMBER(AP86),AP86,0))-(25.0))/((5.0)-(25.0))))) | BU86: =100*(0.35*MIN(1,MAX(0,((ABS(BF86))-(0.3))/((0.05)-(0.3))))+0.3*MIN(1,MAX(0,((BG86)-(0.0))/((0.3)-(0.0))))+0.25*MIN(1,MAX(0,((BH86)-(0.4))/((0.7)-(0.4))))+0.1*IF(BJ86>=2,1,0.5)) | BV86: =0.25*BR86+0.25*BS86+0.2*BT86+0.3*BU86 | BW86: C6 MACD柱轉勢
A87: 3 | B87: 25 | C87: DHX | D87: DHI Group Inc. | E87: NYSE | F87: 非必需消費 | G87: Business Services | H87: 0.204 | I87: 小型 | J87: 4.81 | K87: 4.77 | L87: =J87/K87-1 | M87: 4.89 | N87: 4.7 | O87: 146800 | P87: 272790 | Q87: =O87/P87 | R87: 4.7531 | S87: 4.6657 | T87: 4.6066 | U87: =S87/T87-1 | V87: 1 | W87: =J87/R87-1 | X87: =J87/S87-1 | Y87: 0.2427 | Z87: =Y87/J87 | AA87: =(J87-R87)/Y87 | AB87: =(J87-S87)/Y87 | AC87: =IF(ABS(AA87)<=ABS(AB87),"9EMA","21EMA") | AD87: 9+21EMA | AE87: 持續在上方 | AH87: ✓ | AI87: 2026-08-17 | AJ87: 33 | AK87: 4 | AL87: 2026-09-28 | AM87: 4.54 | AN87: 4.06 | AO87: =IF(ISNUMBER(AN87),AM87/AN87-1,"") | AP87: 4 | AQ87: =IF(ISNUMBER(AM87),J87/AM87-1,"") | AR87: 4.99 | AS87: =J87/AR87-1 | AT87: 0.1165 | AU87: 0.1363 | AV87: 0.1413 | AW87: =AU87-AV87 | AX87: -0.0199 | AY87: -0.0229 | AZ87: -0.0239 | BA87: 淺紅 | BB87: 深紅→淺紅 | BC87: 1 | BD87: 深紅 深紅 深紅 深紅 淺紅 深紅 淺紅 淺紅 | BE87: 上傾收窄（楔形） | BF87: 0.2424 | BG87: 0.6944 | BH87: 0.5859 | BI87: 0.6489 | BJ87: 1 | BK87: 5.19 | BL87: 3.91 | BM87: 4.66 | BN87: 1.2624 | BO87: =IF(M87=N87,0.5,(J87-N87)/(M87-N87)) | BP87: 8.705 | BQ87: 3.664 | BR87: =100*(0.4*MIN(1,MAX(0,((U87*100)-(0.0))/((2.5)-(0.0))))+0.3*MIN(1,MAX(0,((V87)-(0.6))/((1.0)-(0.6))))+0.3*MIN(1,MAX(0,((BP87)-(0.0))/((15.0)-(0.0))))) | BS87: =100*(0.4*MIN(1,MAX(0,((MIN(ABS(AA87),ABS(AB87)))-(0.75))/((0.0)-(0.75))))+0.3*MIN(1,MAX(0,((BN87)-(1.2))/((0.6)-(1.2))))+0.3*BO87) | BT87: =100*(0.5*MIN(1,MAX(0,((AK87)-(1.0))/((4.0)-(1.0))))+0.3*MIN(1,MAX(0,((IF(ISNUMBER(AO87),AO87,0)*100)-(0.0))/((8.0)-(0.0))))+0.2*MIN(1,MAX(0,((IF(ISNUMBER(AP87),AP87,0))-(25.0))/((5.0)-(25.0))))) | BU87: =100*(0.35*MIN(1,MAX(0,((ABS(BF87))-(0.3))/((0.05)-(0.3))))+0.3*MIN(1,MAX(0,((BG87)-(0.0))/((0.3)-(0.0))))+0.25*MIN(1,MAX(0,((BH87)-(0.4))/((0.7)-(0.4))))+0.1*IF(BJ87>=2,1,0.5)) | BV87: =0.25*BR87+0.25*BS87+0.2*BT87+0.3*BU87 | BW87: C5 MACD慢線向上
A88: 3 | B88: 26 | C88: LUV | D88: Southwest Airlines Company | E88: NYSE | F88: 非必需消費 | G88: Air Freight/Delivery Services | H88: 20.371 | I88: 大型 | J88: 42.47 | K88: 41.84 | L88: =J88/K88-1 | M88: 42.83 | N88: 41.81 | O88: 6196200 | P88: 6201360 | Q88: =O88/P88 | R88: 41.7883 | S88: 41.3285 | T88: 40.8778 | U88: =S88/T88-1 | V88: 1 | W88: =J88/R88-1 | X88: =J88/S88-1 | Y88: 1.2505 | Z88: =Y88/J88 | AA88: =(J88-R88)/Y88 | AB88: =(J88-S88)/Y88 | AC88: =IF(ABS(AA88)<=ABS(AB88),"9EMA","21EMA") | AD88: 9+21EMA | AE88: 持續在上方 | AH88: ✓ | AI88: 2026-09-23 | AJ88: 7 | AK88: 4 | AL88: 2026-09-24 | AM88: 40.45 | AN88: 38.16 | AO88: =IF(ISNUMBER(AN88),AM88/AN88-1,"") | AP88: 6 | AQ88: =IF(ISNUMBER(AM88),J88/AM88-1,"") | AR88: 42.68 | AS88: =J88/AR88-1 | AT88: 0.2042 | AU88: -0.1436 | AV88: -0.2306 | AW88: =AU88-AV88 | AX88: 0.3478 | AY88: 0.3611 | AZ88: 0.4196 | BA88: 淺綠 | BB88: — | BC88: — | BD88: 淺綠 淺綠 深綠 淺綠 淺綠 淺綠 淺綠 淺綠 | BE88: 上傾擴張 | BF88: 0.5403 | BG88: 0.4101 | BH88: 0.5113 | BI88: 0.5547 | BJ88: 5 | BK88: 43.2 | BL88: 37.58 | BM88: 40.4533 | BN88: 0.8043 | BO88: =IF(M88=N88,0.5,(J88-N88)/(M88-N88)) | BP88: 15.038 | BQ88: 9.997 | BR88: =100*(0.4*MIN(1,MAX(0,((U88*100)-(0.0))/((2.5)-(0.0))))+0.3*MIN(1,MAX(0,((V88)-(0.6))/((1.0)-(0.6))))+0.3*MIN(1,MAX(0,((BP88)-(0.0))/((15.0)-(0.0))))) | BS88: =100*(0.4*MIN(1,MAX(0,((MIN(ABS(AA88),ABS(AB88)))-(0.75))/((0.0)-(0.75))))+0.3*MIN(1,MAX(0,((BN88)-(1.2))/((0.6)-(1.2))))+0.3*BO88) | BT88: =100*(0.5*MIN(1,MAX(0,((AK88)-(1.0))/((4.0)-(1.0))))+0.3*MIN(1,MAX(0,((IF(ISNUMBER(AO88),AO88,0)*100)-(0.0))/((8.0)-(0.0))))+0.2*MIN(1,MAX(0,((IF(ISNUMBER(AP88),AP88,0))-(25.0))/((5.0)-(25.0))))) | BU88: =100*(0.35*MIN(1,MAX(0,((ABS(BF88))-(0.3))/((0.05)-(0.3))))+0.3*MIN(1,MAX(0,((BG88)-(0.0))/((0.3)-(0.0))))+0.25*MIN(1,MAX(0,((BH88)-(0.4))/((0.7)-(0.4))))+0.1*IF(BJ88>=2,1,0.5)) | BV88: =0.25*BR88+0.25*BS88+0.2*BT88+0.3*BU88 | BW88: C6 MACD柱轉勢
A89: 3 | B89: 27 | C89: LQDT | D89: Liquidity Services Inc. | E89: NASDAQ | F89: 非必需消費 | G89: Business Services | H89: 1.342 | I89: 小型 | J89: 43.23 | K89: 43.64 | L89: =J89/K89-1 | M89: 45 | N89: 42.87 | O89: 373400 | P89: 236855 | Q89: =O89/P89 | R89: 43.1855 | S89: 42.7863 | T89: 42.4904 | U89: =S89/T89-1 | V89: 1 | W89: =J89/R89-1 | X89: =J89/S89-1 | Y89: 1.235 | Z89: =Y89/J89 | AA89: =(J89-R89)/Y89 | AB89: =(J89-S89)/Y89 | AC89: =IF(ABS(AA89)<=ABS(AB89),"9EMA","21EMA") | AD89: 9+21EMA | AE89: 持續在上方 | AH89: ✓ | AI89: 2026-09-11 | AJ89: 15 | AK89: 3 | AL89: 2026-09-18 | AM89: 42.1 | AN89: 38.49 | AO89: =IF(ISNUMBER(AN89),AM89/AN89-1,"") | AP89: 10 | AQ89: =IF(ISNUMBER(AM89),J89/AM89-1,"") | AR89: 43.64 | AS89: =J89/AR89-1 | AT89: 0.4833 | AU89: 0.5051 | AV89: 0.5106 | AW89: =AU89-AV89 | AX89: -0.0218 | AY89: -0.0027 | AZ89: -0.0211 | BA89: 深紅 | BB89: — | BC89: — | BD89: 淺綠 深綠 深綠 淺綠 淺綠 深紅 淺紅 深紅 | BE89: 上傾收窄（楔形） | BF89: 0.2776 | BG89: 0.6959 | BH89: 0.5883 | BI89: 0.6937 | BJ89: 2 | BK89: 45 | BL89: 38.49 | BM89: 42.32 | BN89: 0.9417 | BO89: =IF(M89=N89,0.5,(J89-N89)/(M89-N89)) | BP89: 14.79 | BQ89: 9.749 | BR89: =100*(0.4*MIN(1,MAX(0,((U89*100)-(0.0))/((2.5)-(0.0))))+0.3*MIN(1,MAX(0,((V89)-(0.6))/((1.0)-(0.6))))+0.3*MIN(1,MAX(0,((BP89)-(0.0))/((15.0)-(0.0))))) | BS89: =100*(0.4*MIN(1,MAX(0,((MIN(ABS(AA89),ABS(AB89)))-(0.75))/((0.0)-(0.75))))+0.3*MIN(1,MAX(0,((BN89)-(1.2))/((0.6)-(1.2))))+0.3*BO89) | BT89: =100*(0.5*MIN(1,MAX(0,((AK89)-(1.0))/((4.0)-(1.0))))+0.3*MIN(1,MAX(0,((IF(ISNUMBER(AO89),AO89,0)*100)-(0.0))/((8.0)-(0.0))))+0.2*MIN(1,MAX(0,((IF(ISNUMBER(AP89),AP89,0))-(25.0))/((5.0)-(25.0))))) | BU89: =100*(0.35*MIN(1,MAX(0,((ABS(BF89))-(0.3))/((0.05)-(0.3))))+0.3*MIN(1,MAX(0,((BG89)-(0.0))/((0.3)-(0.0))))+0.25*MIN(1,MAX(0,((BH89)-(0.4))/((0.7)-(0.4))))+0.1*IF(BJ89>=2,1,0.5)) | BV89: =0.25*BR89+0.25*BS89+0.2*BT89+0.3*BU89 | BW89: C5 MACD慢線向上、C6 MACD柱轉勢
A90: 3 | B90: 28 | C90: CHPT | D90: ChargePoint Holdings Inc. | E90: NYSE | F90: 其他 | G90: Industrial Machinery/Components | H90: 0.271 | I90: 小型 | J90: 9.29 | K90: 10.2 | L90: =J90/K90-1 | M90: 11.26 | N90: 9.17 | O90: 1658200 | P90: 2297980 | Q90: =O90/P90 | R90: 9.4756 | S90: 8.927 | T90: 8.5184 | U90: =S90/T90-1 | V90: 1 | W90: =J90/R90-1 | X90: =J90/S90-1 | Y90: 0.8102 | Z90: =Y90/J90 | AA90: =(J90-R90)/Y90 | AB90: =(J90-S90)/Y90 | AC90: =IF(ABS(AA90)<=ABS(AB90),"9EMA","21EMA") | AD90: 9EMA | AE90: 持續在上方 | AH90: ✓ | AI90: 2026-09-03 | AJ90: 20 | AK90: 3 | AL90: 2026-09-28 | AM90: 8.65 | AN90: 8.56 | AO90: =IF(ISNUMBER(AN90),AM90/AN90-1,"") | AP90: 4 | AQ90: =IF(ISNUMBER(AM90),J90/AM90-1,"") | AR90: 10.32 | AS90: =J90/AR90-1 | AT90: 0.6746 | AU90: 0.7442 | AV90: 0.7617 | AW90: =AU90-AV90 | AX90: -0.0696 | AY90: -0.0257 | AZ90: -0.0571 | BA90: 深紅 | BB90: — | BC90: — | BD90: 淺綠 深紅 深紅 深紅 淺紅 淺紅 淺紅 深紅 | BE90: 上傾收窄（楔形） | BF90: 0.3902 | BG90: 1.8038 | BH90: 0.6574 | BI90: 0.7779 | BJ90: 1 | BK90: 11.26 | BL90: 5.19 | BM90: 9.1807 | BN90: 1.0268 | BO90: =IF(M90=N90,0.5,(J90-N90)/(M90-N90)) | BP90: 84.039 | BQ90: 78.998 | BR90: =100*(0.4*MIN(1,MAX(0,((U90*100)-(0.0))/((2.5)-(0.0))))+0.3*MIN(1,MAX(0,((V90)-(0.6))/((1.0)-(0.6))))+0.3*MIN(1,MAX(0,((BP90)-(0.0))/((15.0)-(0.0))))) | BS90: =100*(0.4*MIN(1,MAX(0,((MIN(ABS(AA90),ABS(AB90)))-(0.75))/((0.0)-(0.75))))+0.3*MIN(1,MAX(0,((BN90)-(1.2))/((0.6)-(1.2))))+0.3*BO90) | BT90: =100*(0.5*MIN(1,MAX(0,((AK90)-(1.0))/((4.0)-(1.0))))+0.3*MIN(1,MAX(0,((IF(ISNUMBER(AO90),AO90,0)*100)-(0.0))/((8.0)-(0.0))))+0.2*MIN(1,MAX(0,((IF(ISNUMBER(AP90),AP90,0))-(25.0))/((5.0)-(25.0))))) | BU90: =100*(0.35*MIN(1,MAX(0,((ABS(BF90))-(0.3))/((0.05)-(0.3))))+0.3*MIN(1,MAX(0,((BG90)-(0.0))/((0.3)-(0.0))))+0.25*MIN(1,MAX(0,((BH90)-(0.4))/((0.7)-(0.4))))+0.1*IF(BJ90>=2,1,0.5)) | BV90: =0.25*BR90+0.25*BS90+0.2*BT90+0.3*BU90 | BW90: C5 MACD慢線向上、C6 MACD柱轉勢
A91: 3 | B91: 29 | C91: MTW | D91: Manitowoc Company Inc. (The) | E91: NYSE | F91: 工業 | G91: Construction/Ag Equipment/Trucks | H91: 0.774 | I91: 小型 | J91: 23.22 | K91: 22.4 | L91: =J91/K91-1 | M91: 23.56 | N91: 22.86 | O91: 380200 | P91: 499475 | Q91: =O91/P91 | R91: 22.2096 | S91: 21.4944 | T91: 20.989 | U91: =S91/T91-1 | V91: 1 | W91: =J91/R91-1 | X91: =J91/S91-1 | Y91: 0.9726 | Z91: =Y91/J91 | AA91: =(J91-R91)/Y91 | AB91: =(J91-S91)/Y91 | AC91: =IF(ABS(AA91)<=ABS(AB91),"9EMA","21EMA") | AD91: 9+21EMA | AE91: 持續在上方 | AI91: 2026-07-16 | AJ91: 55 | AK91: 5 | AL91: 2026-09-24 | AM91: 21.19 | AN91: 19.63 | AO91: =IF(ISNUMBER(AN91),AM91/AN91-1,"") | AP91: 6 | AQ91: =IF(ISNUMBER(AM91),J91/AM91-1,"") | AR91: 23.22 | AS91: =J91/AR91-1 | AT91: 0.893 | AU91: 0.9551 | AV91: 0.9706 | AW91: =AU91-AV91 | AX91: -0.062 | AY91: -0.1256 | AZ91: -0.1471 | BA91: 淺紅 | BB91: 深紅→淺紅 | BC91: 1 | BD91: 淺綠 深紅 深紅 深紅 深紅 深紅 淺紅 淺紅 | BE91: 上升通道 | BF91: 0.6538 | BG91: 0.6621 | BH91: 0.5626 | BI91: 0.5838 | BJ91: 1 | BK91: 23.56 | BL91: 18.73 | BM91: 21.4472 | BN91: 1.5244 | BO91: =IF(M91=N91,0.5,(J91-N91)/(M91-N91)) | BP91: 19.878 | BQ91: 14.837 | BR91: =100*(0.4*MIN(1,MAX(0,((U91*100)-(0.0))/((2.5)-(0.0))))+0.3*MIN(1,MAX(0,((V91)-(0.6))/((1.0)-(0.6))))+0.3*MIN(1,MAX(0,((BP91)-(0.0))/((15.0)-(0.0))))) | BS91: =100*(0.4*MIN(1,MAX(0,((MIN(ABS(AA91),ABS(AB91)))-(0.75))/((0.0)-(0.75))))+0.3*MIN(1,MAX(0,((BN91)-(1.2))/((0.6)-(1.2))))+0.3*BO91) | BT91: =100*(0.5*MIN(1,MAX(0,((AK91)-(1.0))/((4.0)-(1.0))))+0.3*MIN(1,MAX(0,((IF(ISNUMBER(AO91),AO91,0)*100)-(0.0))/((8.0)-(0.0))))+0.2*MIN(1,MAX(0,((IF(ISNUMBER(AP91),AP91,0))-(25.0))/((5.0)-(25.0))))) | BU91: =100*(0.35*MIN(1,MAX(0,((ABS(BF91))-(0.3))/((0.05)-(0.3))))+0.3*MIN(1,MAX(0,((BG91)-(0.0))/((0.3)-(0.0))))+0.25*MIN(1,MAX(0,((BH91)-(0.4))/((0.7)-(0.4))))+0.1*IF(BJ91>=2,1,0.5)) | BV91: =0.25*BR91+0.25*BS91+0.2*BT91+0.3*BU91 | BW91: C5 MACD慢線向上
A92: 3 | B92: 30 | C92: DELL | D92: Dell Technologies Inc. Class C | E92: NYSE | F92: 科技 | G92: Computer Manufacturing | H92: 342.035 | I92: 大型 | J92: 562.52 | K92: 541.74 | L92: =J92/K92-1 | M92: 568 | N92: 548.01 | O92: 5495400 | P92: 8539980 | Q92: =O92/P92 | R92: 548.5618 | S92: 536.0442 | T92: 530.0505 | U92: =S92/T92-1 | V92: 1 | W92: =J92/R92-1 | X92: =J92/S92-1 | Y92: 28.9582 | Z92: =Y92/J92 | AA92: =(J92-R92)/Y92 | AB92: =(J92-S92)/Y92 | AC92: =IF(ABS(AA92)<=ABS(AB92),"9EMA","21EMA") | AD92: 9+21EMA | AE92: 持續在上方 | AH92: ✓ | AI92: 2026-08-04 | AJ92: 42 | AK92: 3 | AL92: 2026-09-24 | AM92: 530.45 | AN92: 506.25 | AO92: =IF(ISNUMBER(AN92),AM92/AN92-1,"") | AP92: 6 | AQ92: =IF(ISNUMBER(AM92),J92/AM92-1,"") | AR92: 588.4 | AS92: =J92/AR92-1 | AT92: 17.6267 | AU92: 21.7992 | AV92: 22.8424 | AW92: =AU92-AV92 | AX92: -4.1725 | AY92: -5.4178 | AZ92: -5.168 | BA92: 淺紅 | BB92: 深紅→淺紅 | BC92: 0 | BD92: 淺綠 深紅 淺紅 深紅 深紅 深紅 深紅 淺紅 | BE92: 上傾收窄（楔形） | BF92: 0.5881 | BG92: 1.127 | BH92: 0.6064 | BI92: 0.6253 | BJ92: 3 | BK92: 595.51 | BL92: 421.89 | BM92: 527.1796 | BN92: 0.956 | BO92: =IF(M92=N92,0.5,(J92-N92)/(M92-N92)) | BP92: 19.328 | BQ92: 14.287 | BR92: =100*(0.4*MIN(1,MAX(0,((U92*100)-(0.0))/((2.5)-(0.0))))+0.3*MIN(1,MAX(0,((V92)-(0.6))/((1.0)-(0.6))))+0.3*MIN(1,MAX(0,((BP92)-(0.0))/((15.0)-(0.0))))) | BS92: =100*(0.4*MIN(1,MAX(0,((MIN(ABS(AA92),ABS(AB92)))-(0.75))/((0.0)-(0.75))))+0.3*MIN(1,MAX(0,((BN92)-(1.2))/((0.6)-(1.2))))+0.3*BO92) | BT92: =100*(0.5*MIN(1,MAX(0,((AK92)-(1.0))/((4.0)-(1.0))))+0.3*MIN(1,MAX(0,((IF(ISNUMBER(AO92),AO92,0)*100)-(0.0))/((8.0)-(0.0))))+0.2*MIN(1,MAX(0,((IF(ISNUMBER(AP92),AP92,0))-(25.0))/((5.0)-(25.0))))) | BU92: =100*(0.35*MIN(1,MAX(0,((ABS(BF92))-(0.3))/((0.05)-(0.3))))+0.3*MIN(1,MAX(0,((BG92)-(0.0))/((0.3)-(0.0))))+0.25*MIN(1,MAX(0,((BH92)-(0.4))/((0.7)-(0.4))))+0.1*IF(BJ92>=2,1,0.5)) | BV92: =0.25*BR92+0.25*BS92+0.2*BT92+0.3*BU92 | BW92: C5 MACD慢線向上
A93: 3 | B93: 31 | C93: EXEL | D93: Exelixis Inc. | E93: NASDAQ | F93: 醫療保健 | G93: Biotechnology: Biological Products (No Diagnostic Substances) | H93: 14.473 | I93: 大型 | J93: 58.39 | K93: 57.94 | L93: =J93/K93-1 | M93: 58.97 | N93: 57.94 | O93: 1969300 | P93: 2123000 | Q93: =O93/P93 | R93: 58.0968 | S93: 57.5315 | T93: 57.0382 | U93: =S93/T93-1 | V93: 0.9 | W93: =J93/R93-1 | X93: =J93/S93-1 | Y93: 1.6251 | Z93: =Y93/J93 | AA93: =(J93-R93)/Y93 | AB93: =(J93-S93)/Y93 | AC93: =IF(ABS(AA93)<=ABS(AB93),"9EMA","21EMA") | AD93: 9EMA | AE93: 持續在上方 | AH93: ✓ | AI93: 2026-08-25 | AJ93: 27 | AK93: 4 | AL93: 2026-09-23 | AM93: 56.26 | AN93: 54.55 | AO93: =IF(ISNUMBER(AN93),AM93/AN93-1,"") | AP93: 7 | AQ93: =IF(ISNUMBER(AM93),J93/AM93-1,"") | AR93: 58.65 | AS93: =J93/AR93-1 | AT93: 0.6852 | AU93: 0.7313 | AV93: 0.7428 | AW93: =AU93-AV93 | AX93: -0.0461 | AY93: -0.0454 | AZ93: -0.0056 | BA93: 深紅 | BB93: — | BC93: — | BD93: 深紅 淺紅 淺紅 淺紅 淺紅 深紅 深紅 深紅 | BE93: 上升三角（平頂） | BF93: -0.0976 | BG93: 0.3029 | BH93: 0.5428 | BI93: 0.6763 | BJ93: 1 | BK93: 61.14 | BL93: 53.43 | BM93: 57.615 | BN93: 1.0607 | BO93: =IF(M93=N93,0.5,(J93-N93)/(M93-N93)) | BP93: 4.802 | BQ93: -0.239 | BR93: =100*(0.4*MIN(1,MAX(0,((U93*100)-(0.0))/((2.5)-(0.0))))+0.3*MIN(1,MAX(0,((V93)-(0.6))/((1.0)-(0.6))))+0.3*MIN(1,MAX(0,((BP93)-(0.0))/((15.0)-(0.0))))) | BS93: =100*(0.4*MIN(1,MAX(0,((MIN(ABS(AA93),ABS(AB93)))-(0.75))/((0.0)-(0.75))))+0.3*MIN(1,MAX(0,((BN93)-(1.2))/((0.6)-(1.2))))+0.3*BO93) | BT93: =100*(0.5*MIN(1,MAX(0,((AK93)-(1.0))/((4.0)-(1.0))))+0.3*MIN(1,MAX(0,((IF(ISNUMBER(AO93),AO93,0)*100)-(0.0))/((8.0)-(0.0))))+0.2*MIN(1,MAX(0,((IF(ISNUMBER(AP93),AP93,0))-(25.0))/((5.0)-(25.0))))) | BU93: =100*(0.35*MIN(1,MAX(0,((ABS(BF93))-(0.3))/((0.05)-(0.3))))+0.3*MIN(1,MAX(0,((BG93)-(0.0))/((0.3)-(0.0))))+0.25*MIN(1,MAX(0,((BH93)-(0.4))/((0.7)-(0.4))))+0.1*IF(BJ93>=2,1,0.5)) | BV93: =0.25*BR93+0.25*BS93+0.2*BT93+0.3*BU93 | BW93: C5 MACD慢線向上、C6 MACD柱轉勢
A94: 3 | B94: 32 | C94: OSPN | D94: OneSpan Inc. | E94: NASDAQ | F94: 科技 | G94: EDP Services | H94: 0.66 | I94: 小型 | J94: 18.12 | K94: 18.04 | L94: =J94/K94-1 | M94: 18.31 | N94: 17.96 | O94: 318500 | P94: 582100 | Q94: =O94/P94 | R94: 17.8562 | S94: 17.4506 | T94: 17.135 | U94: =S94/T94-1 | V94: 1 | W94: =J94/R94-1 | X94: =J94/S94-1 | Y94: 0.5523 | Z94: =Y94/J94 | AA94: =(J94-R94)/Y94 | AB94: =(J94-S94)/Y94 | AC94: =IF(ABS(AA94)<=ABS(AB94),"9EMA","21EMA") | AD94: 9EMA | AE94: 持續在上方 | AH94: ✓ | AI94: 2026-08-27 | AJ94: 25 | AK94: 3 | AL94: 2026-09-22 | AM94: 17.05 | AN94: 15.97 | AO94: =IF(ISNUMBER(AN94),AM94/AN94-1,"") | AP94: 8 | AQ94: =IF(ISNUMBER(AM94),J94/AM94-1,"") | AR94: 18.12 | AS94: =J94/AR94-1 | AT94: 0.4632 | AU94: 0.4623 | AV94: 0.4621 | AW94: =AU94-AV94 | AX94: 0.0009 | AY94: 0.0012 | AZ94: 0.003 | BA94: 淺綠 | BB94: — | BC94: — | BD94: 深綠 淺綠 淺綠 淺綠 淺綠 淺綠 淺綠 淺綠 | BE94: 上傾收窄（楔形） | BF94: 0.4775 | BG94: 0.745 | BH94: 0.6412 | BI94: 0.6812 | BJ94: 7 | BK94: 18.31 | BL94: 15.79 | BM94: 17.4059 | BN94: 1.3288 | BO94: =IF(M94=N94,0.5,(J94-N94)/(M94-N94)) | BP94: 17.1 | BQ94: 12.059 | BR94: =100*(0.4*MIN(1,MAX(0,((U94*100)-(0.0))/((2.5)-(0.0))))+0.3*MIN(1,MAX(0,((V94)-(0.6))/((1.0)-(0.6))))+0.3*MIN(1,MAX(0,((BP94)-(0.0))/((15.0)-(0.0))))) | BS94: =100*(0.4*MIN(1,MAX(0,((MIN(ABS(AA94),ABS(AB94)))-(0.75))/((0.0)-(0.75))))+0.3*MIN(1,MAX(0,((BN94)-(1.2))/((0.6)-(1.2))))+0.3*BO94) | BT94: =100*(0.5*MIN(1,MAX(0,((AK94)-(1.0))/((4.0)-(1.0))))+0.3*MIN(1,MAX(0,((IF(ISNUMBER(AO94),AO94,0)*100)-(0.0))/((8.0)-(0.0))))+0.2*MIN(1,MAX(0,((IF(ISNUMBER(AP94),AP94,0))-(25.0))/((5.0)-(25.0))))) | BU94: =100*(0.35*MIN(1,MAX(0,((ABS(BF94))-(0.3))/((0.05)-(0.3))))+0.3*MIN(1,MAX(0,((BG94)-(0.0))/((0.3)-(0.0))))+0.25*MIN(1,MAX(0,((BH94)-(0.4))/((0.7)-(0.4))))+0.1*IF(BJ94>=2,1,0.5)) | BV94: =0.25*BR94+0.25*BS94+0.2*BT94+0.3*BU94 | BW94: C6 MACD柱轉勢
A95: 3 | B95: 33 | C95: CSTL | D95: Castle Biosciences Inc. | E95: NASDAQ | F95: 醫療保健 | G95: Medical Specialities | H95: 1.085 | I95: 小型 | J95: 35.56 | K95: 35.255 | L95: =J95/K95-1 | M95: 35.92 | N95: 34.75 | O95: 167700 | P95: 356255 | Q95: =O95/P95 | R95: 35.2921 | S95: 34.5837 | T95: 34.0697 | U95: =S95/T95-1 | V95: 1 | W95: =J95/R95-1 | X95: =J95/S95-1 | Y95: 1.5439 | Z95: =Y95/J95 | AA95: =(J95-R95)/Y95 | AB95: =(J95-S95)/Y95 | AC95: =IF(ABS(AA95)<=ABS(AB95),"9EMA","21EMA") | AD95: 9+21EMA | AE95: 持續在上方 | AH95: ✓ | AI95: 2026-06-23 | AJ95: 71 | AK95: 2 | AL95: 2026-09-24 | AM95: 33.9 | AN95: 31.44 | AO95: =IF(ISNUMBER(AN95),AM95/AN95-1,"") | AP95: 6 | AQ95: =IF(ISNUMBER(AM95),J95/AM95-1,"") | AR95: 36.78 | AS95: =J95/AR95-1 | AT95: 0.9521 | AU95: 1.0923 | AV95: 1.1274 | AW95: =AU95-AV95 | AX95: -0.1402 | AY95: -0.1406 | AZ95: -0.1149 | BA95: 淺紅 | BB95: 深紅→淺紅 | BC95: 0 | BD95: 深紅 深紅 淺紅 淺紅 深紅 深紅 深紅 淺紅 | BE95: 上傾擴張 | BF95: 0.5962 | BG95: 0.2847 | BH95: 0.5766 | BI95: 0.5213 | BJ95: 4 | BK95: 36.99 | BL95: 31.44 | BM95: 34.6402 | BN95: 1.1037 | BO95: =IF(M95=N95,0.5,(J95-N95)/(M95-N95)) | BP95: 11.444 | BQ95: 6.403 | BR95: =100*(0.4*MIN(1,MAX(0,((U95*100)-(0.0))/((2.5)-(0.0))))+0.3*MIN(1,MAX(0,((V95)-(0.6))/((1.0)-(0.6))))+0.3*MIN(1,MAX(0,((BP95)-(0.0))/((15.0)-(0.0))))) | BS95: =100*(0.4*MIN(1,MAX(0,((MIN(ABS(AA95),ABS(AB95)))-(0.75))/((0.0)-(0.75))))+0.3*MIN(1,MAX(0,((BN95)-(1.2))/((0.6)-(1.2))))+0.3*BO95) | BT95: =100*(0.5*MIN(1,MAX(0,((AK95)-(1.0))/((4.0)-(1.0))))+0.3*MIN(1,MAX(0,((IF(ISNUMBER(AO95),AO95,0)*100)-(0.0))/((8.0)-(0.0))))+0.2*MIN(1,MAX(0,((IF(ISNUMBER(AP95),AP95,0))-(25.0))/((5.0)-(25.0))))) | BU95: =100*(0.35*MIN(1,MAX(0,((ABS(BF95))-(0.3))/((0.05)-(0.3))))+0.3*MIN(1,MAX(0,((BG95)-(0.0))/((0.3)-(0.0))))+0.25*MIN(1,MAX(0,((BH95)-(0.4))/((0.7)-(0.4))))+0.1*IF(BJ95>=2,1,0.5)) | BV95: =0.25*BR95+0.25*BS95+0.2*BT95+0.3*BU95 | BW95: C5 MACD慢線向上
A96: 3 | B96: 34 | C96: BRKR | D96: Bruker Corporation | E96: NASDAQ | F96: 工業 | G96: Biotechnology: Laboratory Analytical Instruments | H96: 9.865 | I96: 中型 | J96: 63.24 | K96: 61.94 | L96: =J96/K96-1 | M96: 64.36 | N96: 62.25 | O96: 2227600 | P96: 2353385 | Q96: =O96/P96 | R96: 62.6904 | S96: 61.022 | T96: 59.5145 | U96: =S96/T96-1 | V96: 1 | W96: =J96/R96-1 | X96: =J96/S96-1 | Y96: 2.9441 | Z96: =Y96/J96 | AA96: =(J96-R96)/Y96 | AB96: =(J96-S96)/Y96 | AC96: =IF(ABS(AA96)<=ABS(AB96),"9EMA","21EMA") | AD96: 9EMA | AE96: 持續在上方 | AH96: ✓ | AI96: 2026-09-17 | AJ96: 11 | AK96: 2 | AL96: 2026-09-24 | AM96: 59.17 | AN96: 51.54 | AO96: =IF(ISNUMBER(AN96),AM96/AN96-1,"") | AP96: 6 | AQ96: =IF(ISNUMBER(AM96),J96/AM96-1,"") | AR96: 64.75 | AS96: =J96/AR96-1 | AT96: 1.6201 | AU96: 1.3014 | AV96: 1.2217 | AW96: =AU96-AV96 | AX96: 0.3187 | AY96: 0.4219 | AZ96: 0.6658 | BA96: 淺綠 | BB96: — | BC96: — | BD96: 淺綠 深綠 深綠 淺綠 淺綠 淺綠 淺綠 淺綠 | BE96: 上傾擴張 | BF96: 0.7256 | BG96: 0.3469 | BH96: 0.5235 | BI96: 0.576 | BJ96: 1 | BK96: 66.98 | BL96: 51.54 | BM96: 59.6235 | BN96: 1.1373 | BO96: =IF(M96=N96,0.5,(J96-N96)/(M96-N96)) | BP96: 12.191 | BQ96: 7.15 | BR96: =100*(0.4*MIN(1,MAX(0,((U96*100)-(0.0))/((2.5)-(0.0))))+0.3*MIN(1,MAX(0,((V96)-(0.6))/((1.0)-(0.6))))+0.3*MIN(1,MAX(0,((BP96)-(0.0))/((15.0)-(0.0))))) | BS96: =100*(0.4*MIN(1,MAX(0,((MIN(ABS(AA96),ABS(AB96)))-(0.75))/((0.0)-(0.75))))+0.3*MIN(1,MAX(0,((BN96)-(1.2))/((0.6)-(1.2))))+0.3*BO96) | BT96: =100*(0.5*MIN(1,MAX(0,((AK96)-(1.0))/((4.0)-(1.0))))+0.3*MIN(1,MAX(0,((IF(ISNUMBER(AO96),AO96,0)*100)-(0.0))/((8.0)-(0.0))))+0.2*MIN(1,MAX(0,((IF(ISNUMBER(AP96),AP96,0))-(25.0))/((5.0)-(25.0))))) | BU96: =100*(0.35*MIN(1,MAX(0,((ABS(BF96))-(0.3))/((0.05)-(0.3))))+0.3*MIN(1,MAX(0,((BG96)-(0.0))/((0.3)-(0.0))))+0.25*MIN(1,MAX(0,((BH96)-(0.4))/((0.7)-(0.4))))+0.1*IF(BJ96>=2,1,0.5)) | BV96: =0.25*BR96+0.25*BS96+0.2*BT96+0.3*BU96 | BW96: C6 MACD柱轉勢
A97: 3 | B97: 35 | C97: HYPD | D97: Hyperion DeFi Inc. | E97: NASDAQ | F97: 醫療保健 | G97: Biotechnology: Pharmaceutical Preparations | H97: 0.058 | I97: 小型 | J97: 3.73 | K97: 3.66 | L97: =J97/K97-1 | M97: 3.95 | N97: 3.705 | O97: 530000 | P97: 582245 | Q97: =O97/P97 | R97: 3.8031 | S97: 3.6785 | T97: 3.6075 | U97: =S97/T97-1 | V97: 0.9 | W97: =J97/R97-1 | X97: =J97/S97-1 | Y97: 0.2824 | Z97: =Y97/J97 | AA97: =(J97-R97)/Y97 | AB97: =(J97-S97)/Y97 | AC97: =IF(ABS(AA97)<=ABS(AB97),"9EMA","21EMA") | AD97: 9+21EMA | AE97: 持續在上方 | AG97: ✓ | AI97: 2026-08-19 | AJ97: 31 | AK97: 5 | AL97: 2026-09-16 | AM97: 3.18 | AN97: 3.03 | AO97: =IF(ISNUMBER(AN97),AM97/AN97-1,"") | AP97: 12 | AQ97: =IF(ISNUMBER(AM97),J97/AM97-1,"") | AR97: 4.17 | AS97: =J97/AR97-1 | AT97: 0.1644 | AU97: 0.1978 | AV97: 0.2061 | AW97: =AU97-AV97 | AX97: -0.0334 | AY97: -0.0232 | AZ97: -0.0008 | BA97: 深紅 | BB97: — | BC97: — | BD97: 深綠 深綠 淺綠 淺綠 淺綠 深紅 深紅 深紅 | BE97: 上傾擴張 | BF97: 0.8639 | BG97: 0.4468 | BH97: 0.5478 | BI97: 0.5356 | BJ97: 3 | BK97: 4.17 | BL97: 3.03 | BM97: 3.6545 | BN97: 1.1456 | BO97: =IF(M97=N97,0.5,(J97-N97)/(M97-N97)) | BP97: 26.936 | BQ97: 21.895 | BR97: =100*(0.4*MIN(1,MAX(0,((U97*100)-(0.0))/((2.5)-(0.0))))+0.3*MIN(1,MAX(0,((V97)-(0.6))/((1.0)-(0.6))))+0.3*MIN(1,MAX(0,((BP97)-(0.0))/((15.0)-(0.0))))) | BS97: =100*(0.4*MIN(1,MAX(0,((MIN(ABS(AA97),ABS(AB97)))-(0.75))/((0.0)-(0.75))))+0.3*MIN(1,MAX(0,((BN97)-(1.2))/((0.6)-(1.2))))+0.3*BO97) | BT97: =100*(0.5*MIN(1,MAX(0,((AK97)-(1.0))/((4.0)-(1.0))))+0.3*MIN(1,MAX(0,((IF(ISNUMBER(AO97),AO97,0)*100)-(0.0))/((8.0)-(0.0))))+0.2*MIN(1,MAX(0,((IF(ISNUMBER(AP97),AP97,0))-(25.0))/((5.0)-(25.0))))) | BU97: =100*(0.35*MIN(1,MAX(0,((ABS(BF97))-(0.3))/((0.05)-(0.3))))+0.3*MIN(1,MAX(0,((BG97)-(0.0))/((0.3)-(0.0))))+0.25*MIN(1,MAX(0,((BH97)-(0.4))/((0.7)-(0.4))))+0.1*IF(BJ97>=2,1,0.5)) | BV97: =0.25*BR97+0.25*BS97+0.2*BT97+0.3*BU97 | BW97: C5 MACD慢線向上、C6 MACD柱轉勢
A98: 3 | B98: 36 | C98: NGVC | D98: Natural Grocers by Vitamin Cottage Inc. | E98: NYSE | F98: 必需消費 | G98: Food Chains | H98: 0.702 | I98: 小型 | J98: 30.61 | K98: 30.48 | L98: =J98/K98-1 | M98: 31.34 | N98: 30.31 | O98: 107900 | P98: 157865 | Q98: =O98/P98 | R98: 30.2482 | S98: 29.684 | T98: 29.1693 | U98: =S98/T98-1 | V98: 1 | W98: =J98/R98-1 | X98: =J98/S98-1 | Y98: 1.0498 | Z98: =Y98/J98 | AA98: =(J98-R98)/Y98 | AB98: =(J98-S98)/Y98 | AC98: =IF(ABS(AA98)<=ABS(AB98),"9EMA","21EMA") | AD98: 9EMA | AE98: 持續在上方 | AH98: ✓ | AI98: 2026-09-16 | AJ98: 12 | AK98: 2 | AL98: 2026-09-25 | AM98: 29.48 | AN98: 26.5 | AO98: =IF(ISNUMBER(AN98),AM98/AN98-1,"") | AP98: 5 | AQ98: =IF(ISNUMBER(AM98),J98/AM98-1,"") | AR98: 30.98 | AS98: =J98/AR98-1 | AT98: 0.5075 | AU98: 0.3741 | AV98: 0.3407 | AW98: =AU98-AV98 | AX98: 0.1335 | AY98: 0.1533 | AZ98: 0.1805 | BA98: 淺綠 | BB98: — | BC98: — | BD98: 淺綠 淺綠 淺綠 深綠 淺綠 淺綠 淺綠 淺綠 | BE98: 上傾收窄（楔形） | BF98: 0.4932 | BG98: 0.8113 | BH98: 0.5407 | BI98: 0.5686 | BJ98: 4 | BK98: 31.61 | BL98: 26.5 | BM98: 29.2631 | BN98: 0.9598 | BO98: =IF(M98=N98,0.5,(J98-N98)/(M98-N98)) | BP98: 18.411 | BQ98: 13.37 | BR98: =100*(0.4*MIN(1,MAX(0,((U98*100)-(0.0))/((2.5)-(0.0))))+0.3*MIN(1,MAX(0,((V98)-(0.6))/((1.0)-(0.6))))+0.3*MIN(1,MAX(0,((BP98)-(0.0))/((15.0)-(0.0))))) | BS98: =100*(0.4*MIN(1,MAX(0,((MIN(ABS(AA98),ABS(AB98)))-(0.75))/((0.0)-(0.75))))+0.3*MIN(1,MAX(0,((BN98)-(1.2))/((0.6)-(1.2))))+0.3*BO98) | BT98: =100*(0.5*MIN(1,MAX(0,((AK98)-(1.0))/((4.0)-(1.0))))+0.3*MIN(1,MAX(0,((IF(ISNUMBER(AO98),AO98,0)*100)-(0.0))/((8.0)-(0.0))))+0.2*MIN(1,MAX(0,((IF(ISNUMBER(AP98),AP98,0))-(25.0))/((5.0)-(25.0))))) | BU98: =100*(0.35*MIN(1,MAX(0,((ABS(BF98))-(0.3))/((0.05)-(0.3))))+0.3*MIN(1,MAX(0,((BG98)-(0.0))/((0.3)-(0.0))))+0.25*MIN(1,MAX(0,((BH98)-(0.4))/((0.7)-(0.4))))+0.1*IF(BJ98>=2,1,0.5)) | BV98: =0.25*BR98+0.25*BS98+0.2*BT98+0.3*BU98 | BW98: C6 MACD柱轉勢
A99: 3 | B99: 37 | C99: SMTI | D99: Sanara MedTech Inc. | E99: NASDAQ | F99: 醫療保健 | G99: Industrial Specialties | H99: 0.323 | I99: 小型 | J99: 34.85 | K99: 34.88 | L99: =J99/K99-1 | M99: 34.89 | N99: 34.63 | O99: 341900 | P99: 211730 | Q99: =O99/P99 | R99: 35.014 | S99: 34.8488 | T99: 34.7575 | U99: =S99/T99-1 | V99: 1 | W99: =J99/R99-1 | X99: =J99/S99-1 | Y99: 0.2765 | Z99: =Y99/J99 | AA99: =(J99-R99)/Y99 | AB99: =(J99-S99)/Y99 | AC99: =IF(ABS(AA99)<=ABS(AB99),"9EMA","21EMA") | AD99: 9+21EMA | AE99: 持續在上方 | AG99: ✓ | AI99: 2026-05-12 | AJ99: 99 | AK99: 6 | AL99: 2026-09-25 | AM99: 34.97 | AN99: 34.71 | AO99: =IF(ISNUMBER(AN99),AM99/AN99-1,"") | AP99: 5 | AQ99: =IF(ISNUMBER(AM99),J99/AM99-1,"") | AR99: 35.28 | AS99: =J99/AR99-1 | AT99: 0.3661 | AU99: 0.5353 | AV99: 0.5775 | AW99: =AU99-AV99 | AX99: -0.1691 | AY99: -0.1656 | AZ99: -0.1575 | BA99: 深紅 | BB99: — | BC99: — | BD99: 淺紅 淺紅 淺紅 淺紅 淺紅 淺紅 深紅 深紅 | BE99: 上升三角（平頂） | BF99: 0.041 | BG99: 0.0729 | BH99: 0.5209 | BI99: 0.4907 | BJ99: 23 | BK99: 35.34 | BL99: 34.46 | BM99: 34.9184 | BN99: 1.9993 | BO99: =IF(M99=N99,0.5,(J99-N99)/(M99-N99)) | BP99: 5.185 | BQ99: 0.144 | BR99: =100*(0.4*MIN(1,MAX(0,((U99*100)-(0.0))/((2.5)-(0.0))))+0.3*MIN(1,MAX(0,((V99)-(0.6))/((1.0)-(0.6))))+0.3*MIN(1,MAX(0,((BP99)-(0.0))/((15.0)-(0.0))))) | BS99: =100*(0.4*MIN(1,MAX(0,((MIN(ABS(AA99),ABS(AB99)))-(0.75))/((0.0)-(0.75))))+0.3*MIN(1,MAX(0,((BN99)-(1.2))/((0.6)-(1.2))))+0.3*BO99) | BT99: =100*(0.5*MIN(1,MAX(0,((AK99)-(1.0))/((4.0)-(1.0))))+0.3*MIN(1,MAX(0,((IF(ISNUMBER(AO99),AO99,0)*100)-(0.0))/((8.0)-(0.0))))+0.2*MIN(1,MAX(0,((IF(ISNUMBER(AP99),AP99,0))-(25.0))/((5.0)-(25.0))))) | BU99: =100*(0.35*MIN(1,MAX(0,((ABS(BF99))-(0.3))/((0.05)-(0.3))))+0.3*MIN(1,MAX(0,((BG99)-(0.0))/((0.3)-(0.0))))+0.25*MIN(1,MAX(0,((BH99)-(0.4))/((0.7)-(0.4))))+0.1*IF(BJ99>=2,1,0.5)) | BV99: =0.25*BR99+0.25*BS99+0.2*BT99+0.3*BU99 | BW99: C5 MACD慢線向上、C6 MACD柱轉勢
A100: 3 | B100: 38 | C100: MAZE | D100: Maze Therapeutics Inc. | E100: NASDAQ | F100: 醫療保健 | G100: Biotechnology: Biological Products (No Diagnostic Substances) | H100: 1.51 | I100: 小型 | J100: 26.43 | K100: 26.65 | L100: =J100/K100-1 | M100: 27.49 | N100: 26.36 | O100: 633000 | P100: 883685 | Q100: =O100/P100 | R100: 26.4161 | S100: 26.2458 | T100: 25.9064 | U100: =S100/T100-1 | V100: 0.9 | W100: =J100/R100-1 | X100: =J100/S100-1 | Y100: 1.7578 | Z100: =Y100/J100 | AA100: =(J100-R100)/Y100 | AB100: =(J100-S100)/Y100 | AC100: =IF(ABS(AA100)<=ABS(AB100),"9EMA","21EMA") | AD100: 9+21EMA | AE100: 剛黃金交叉 | AF100: ✓ | AH100: ✓ | AI100: 2026-09-29 | AJ100: 3 | AK100: 2 | AL100: 2026-09-28 | AM100: 24.84 | AN100: 21.95 | AO100: =IF(ISNUMBER(AN100),AM100/AN100-1,"") | AP100: 4 | AQ100: =IF(ISNUMBER(AM100),J100/AM100-1,"") | AR100: 28.38 | AS100: =J100/AR100-1 | AT100: -0.0316 | AU100: -0.322 | AV100: -0.3946 | AW100: =AU100-AV100 | AX100: 0.2904 | AY100: 0.3462 | AZ100: 0.3898 | BA100: 淺綠 | BB100: — | BC100: — | BD100: 深綠 深綠 淺綠 深綠 深綠 深綠 淺綠 淺綠 | BE100: 上升通道 | BF100: 0.1587 | BG100: 0.1965 | BH100: 0.5262 | BI100: 0.6257 | BJ100: 1 | BK100: 29.91 | BL100: 21.95 | BM100: 26.1382 | BN100: 0.5759 | BO100: =IF(M100=N100,0.5,(J100-N100)/(M100-N100)) | BP100: 3.956 | BQ100: -1.085 | BR100: =100*(0.4*MIN(1,MAX(0,((U100*100)-(0.0))/((2.5)-(0.0))))+0.3*MIN(1,MAX(0,((V100)-(0.6))/((1.0)-(0.6))))+0.3*MIN(1,MAX(0,((BP100)-(0.0))/((15.0)-(0.0))))) | BS100: =100*(0.4*MIN(1,MAX(0,((MIN(ABS(AA100),ABS(AB100)))-(0.75))/((0.0)-(0.75))))+0.3*MIN(1,MAX(0,((BN100)-(1.2))/((0.6)-(1.2))))+0.3*BO100) | BT100: =100*(0.5*MIN(1,MAX(0,((AK100)-(1.0))/((4.0)-(1.0))))+0.3*MIN(1,MAX(0,((IF(ISNUMBER(AO100),AO100,0)*100)-(0.0))/((8.0)-(0.0))))+0.2*MIN(1,MAX(0,((IF(ISNUMBER(AP100),AP100,0))-(25.0))/((5.0)-(25.0))))) | BU100: =100*(0.35*MIN(1,MAX(0,((ABS(BF100))-(0.3))/((0.05)-(0.3))))+0.3*MIN(1,MAX(0,((BG100)-(0.0))/((0.3)-(0.0))))+0.25*MIN(1,MAX(0,((BH100)-(0.4))/((0.7)-(0.4))))+0.1*IF(BJ100>=2,1,0.5)) | BV100: =0.25*BR100+0.25*BS100+0.2*BT100+0.3*BU100 | BW100: C6 MACD柱轉勢
A101: 3 | B101: 39 | C101: VLGEA | D101: Village Super Market Inc. | E101: NASDAQ | F101: 必需消費 | G101: Food Chains | H101: 0.673 | I101: 小型 | J101: 46 | K101: 45.53 | L101: =J101/K101-1 | M101: 46.24 | N101: 45.42 | O101: 34000 | P101: 46455 | Q101: =O101/P101 | R101: 45.4199 | S101: 44.7838 | T101: 44.2059 | U101: =S101/T101-1 | V101: 1 | W101: =J101/R101-1 | X101: =J101/S101-1 | Y101: 1.1495 | Z101: =Y101/J101 | AA101: =(J101-R101)/Y101 | AB101: =(J101-S101)/Y101 | AC101: =IF(ABS(AA101)<=ABS(AB101),"9EMA","21EMA") | AD101: 9+21EMA | AE101: 持續在上方 | AH101: ✓ | AI101: 2026-09-14 | AJ101: 14 | AK101: 3 | AL101: 2026-09-18 | AM101: 43.38 | AN101: 42.04 | AO101: =IF(ISNUMBER(AN101),AM101/AN101-1,"") | AP101: 10 | AQ101: =IF(ISNUMBER(AM101),J101/AM101-1,"") | AR101: 46.11 | AS101: =J101/AR101-1 | AT101: 0.6353 | AU101: 0.5261 | AV101: 0.4988 | AW101: =AU101-AV101 | AX101: 0.1092 | AY101: 0.1093 | AZ101: 0.141 | BA101: 淺綠 | BB101: — | BC101: — | BD101: 淺綠 深綠 淺綠 深綠 淺綠 淺綠 淺綠 淺綠 | BE101: 上傾收窄（楔形） | BF101: 0.2098 | BG101: 0.3149 | BH101: 0.5167 | BI101: 0.4827 | BJ101: 3 | BK101: 46.8 | BL101: 41.68 | BM101: 44.3253 | BN101: 1.0663 | BO101: =IF(M101=N101,0.5,(J101-N101)/(M101-N101)) | BP101: 12.292 | BQ101: 7.251 | BR101: =100*(0.4*MIN(1,MAX(0,((U101*100)-(0.0))/((2.5)-(0.0))))+0.3*MIN(1,MAX(0,((V101)-(0.6))/((1.0)-(0.6))))+0.3*MIN(1,MAX(0,((BP101)-(0.0))/((15.0)-(0.0))))) | BS101: =100*(0.4*MIN(1,MAX(0,((MIN(ABS(AA101),ABS(AB101)))-(0.75))/((0.0)-(0.75))))+0.3*MIN(1,MAX(0,((BN101)-(1.2))/((0.6)-(1.2))))+0.3*BO101) | BT101: =100*(0.5*MIN(1,MAX(0,((AK101)-(1.0))/((4.0)-(1.0))))+0.3*MIN(1,MAX(0,((IF(ISNUMBER(AO101),AO101,0)*100)-(0.0))/((8.0)-(0.0))))+0.2*MIN(1,MAX(0,((IF(ISNUMBER(AP101),AP101,0))-(25.0))/((5.0)-(25.0))))) | BU101: =100*(0.35*MIN(1,MAX(0,((ABS(BF101))-(0.3))/((0.05)-(0.3))))+0.3*MIN(1,MAX(0,((BG101)-(0.0))/((0.3)-(0.0))))+0.25*MIN(1,MAX(0,((BH101)-(0.4))/((0.7)-(0.4))))+0.1*IF(BJ101>=2,1,0.5)) | BV101: =0.25*BR101+0.25*BS101+0.2*BT101+0.3*BU101 | BW101: C6 MACD柱轉勢
...

Sheet a 剛黃金交叉
A1: 頁內排名 | B1: 代號 | C1: 公司 | D1: 板塊 | E1: 行業 | F1: 市值組 | G1: 市值(十億美元) | H1: 收市價 | I1: 當日% | J1: EMA9 | K1: EMA21 | L1: 距EMA9% | M1: 距EMA21% | N1: 距EMA9（ATR倍） | O1: 距EMA21（ATR倍） | P1: 近3日低位觸及 | Q1: EMA21 5日斜率% | R1: 9/21狀態 | S1: 金叉日期 | T1: 金叉後日數 | U1: 連續上升底數目 | V1: 最後一底日期 | W1: 距最後一底% | X1: 距15日高% | Y1: 形態（25日） | Z1: 重心 | AA1: RS21% | AB1: 柱顏色 | AC1: 柱轉勢 | AD1: 轉勢幾日前 | AE1: 慢線斜率 | AF1: 趨勢分數 | AG1: 回調質素 | AH1: 底部結構 | AI1: 三角形分數 | AJ1: 綜合分數 | AK1: 梯隊 | AL1: 總表排名 | AM1: 唔過嘅條件
A2: 1 | B2: NEU | C2: ='總表'!D9 | D2: ='總表'!F9 | E2: ='總表'!G9 | F2: ='總表'!I9 | G2: ='總表'!H9 | H2: ='總表'!J9 | I2: ='總表'!L9 | J2: ='總表'!R9 | K2: ='總表'!S9 | L2: ='總表'!W9 | M2: ='總表'!X9 | N2: ='總表'!AA9 | O2: ='總表'!AB9 | P2: ='總表'!AD9 | Q2: ='總表'!U9 | R2: ='總表'!AE9 | S2: ='總表'!AI9 | T2: ='總表'!AJ9 | U2: ='總表'!AK9 | V2: ='總表'!AL9 | W2: ='總表'!AQ9 | X2: ='總表'!AS9 | Y2: ='總表'!BE9 | Z2: ='總表'!BH9 | AA2: ='總表'!BP9 | AB2: ='總表'!BA9 | AC2: ='總表'!BB9 | AD2: ='總表'!BC9 | AE2: ='總表'!AW9 | AF2: ='總表'!BR9 | AG2: ='總表'!BS9 | AH2: ='總表'!BT9 | AI2: ='總表'!BU9 | AJ2: ='總表'!BV9 | AK2: ='總表'!A9 | AL2: ='總表'!B9 | AM2: ='總表'!BW9
A3: 2 | B3: TENB | C3: ='總表'!D16 | D3: ='總表'!F16 | E3: ='總表'!G16 | F3: ='總表'!I16 | G3: ='總表'!H16 | H3: ='總表'!J16 | I3: ='總表'!L16 | J3: ='總表'!R16 | K3: ='總表'!S16 | L3: ='總表'!W16 | M3: ='總表'!X16 | N3: ='總表'!AA16 | O3: ='總表'!AB16 | P3: ='總表'!AD16 | Q3: ='總表'!U16 | R3: ='總表'!AE16 | S3: ='總表'!AI16 | T3: ='總表'!AJ16 | U3: ='總表'!AK16 | V3: ='總表'!AL16 | W3: ='總表'!AQ16 | X3: ='總表'!AS16 | Y3: ='總表'!BE16 | Z3: ='總表'!BH16 | AA3: ='總表'!BP16 | AB3: ='總表'!BA16 | AC3: ='總表'!BB16 | AD3: ='總表'!BC16 | AE3: ='總表'!AW16 | AF3: ='總表'!BR16 | AG3: ='總表'!BS16 | AH3: ='總表'!BT16 | AI3: ='總表'!BU16 | AJ3: ='總表'!BV16 | AK3: ='總表'!A16 | AL3: ='總表'!B16 | AM3: ='總表'!BW16
A4: 3 | B4: NHC | C4: ='總表'!D17 | D4: ='總表'!F17 | E4: ='總表'!G17 | F4: ='總表'!I17 | G4: ='總表'!H17 | H4: ='總表'!J17 | I4: ='總表'!L17 | J4: ='總表'!R17 | K4: ='總表'!S17 | L4: ='總表'!W17 | M4: ='總表'!X17 | N4: ='總表'!AA17 | O4: ='總表'!AB17 | P4: ='總表'!AD17 | Q4: ='總表'!U17 | R4: ='總表'!AE17 | S4: ='總表'!AI17 | T4: ='總表'!AJ17 | U4: ='總表'!AK17 | V4: ='總表'!AL17 | W4: ='總表'!AQ17 | X4: ='總表'!AS17 | Y4: ='總表'!BE17 | Z4: ='總表'!BH17 | AA4: ='總表'!BP17 | AB4: ='總表'!BA17 | AC4: ='總表'!BB17 | AD4: ='總表'!BC17 | AE4: ='總表'!AW17 | AF4: ='總表'!BR17 | AG4: ='總表'!BS17 | AH4: ='總表'!BT17 | AI4: ='總表'!BU17 | AJ4: ='總表'!BV17 | AK4: ='總表'!A17 | AL4: ='總表'!B17 | AM4: ='總表'!BW17
A5: 4 | B5: STRL | C5: ='總表'!D20 | D5: ='總表'!F20 | E5: ='總表'!G20 | F5: ='總表'!I20 | G5: ='總表'!H20 | H5: ='總表'!J20 | I5: ='總表'!L20 | J5: ='總表'!R20 | K5: ='總表'!S20 | L5: ='總表'!W20 | M5: ='總表'!X20 | N5: ='總表'!AA20 | O5: ='總表'!AB20 | P5: ='總表'!AD20 | Q5: ='總表'!U20 | R5: ='總表'!AE20 | S5: ='總表'!AI20 | T5: ='總表'!AJ20 | U5: ='總表'!AK20 | V5: ='總表'!AL20 | W5: ='總表'!AQ20 | X5: ='總表'!AS20 | Y5: ='總表'!BE20 | Z5: ='總表'!BH20 | AA5: ='總表'!BP20 | AB5: ='總表'!BA20 | AC5: ='總表'!BB20 | AD5: ='總表'!BC20 | AE5: ='總表'!AW20 | AF5: ='總表'!BR20 | AG5: ='總表'!BS20 | AH5: ='總表'!BT20 | AI5: ='總表'!BU20 | AJ5: ='總表'!BV20 | AK5: ='總表'!A20 | AL5: ='總表'!B20 | AM5: ='總表'!BW20
A6: 5 | B6: OPY | C6: ='總表'!D25 | D6: ='總表'!F25 | E6: ='總表'!G25 | F6: ='總表'!I25 | G6: ='總表'!H25 | H6: ='總表'!J25 | I6: ='總表'!L25 | J6: ='總表'!R25 | K6: ='總表'!S25 | L6: ='總表'!W25 | M6: ='總表'!X25 | N6: ='總表'!AA25 | O6: ='總表'!AB25 | P6: ='總表'!AD25 | Q6: ='總表'!U25 | R6: ='總表'!AE25 | S6: ='總表'!AI25 | T6: ='總表'!AJ25 | U6: ='總表'!AK25 | V6: ='總表'!AL25 | W6: ='總表'!AQ25 | X6: ='總表'!AS25 | Y6: ='總表'!BE25 | Z6: ='總表'!BH25 | AA6: ='總表'!BP25 | AB6: ='總表'!BA25 | AC6: ='總表'!BB25 | AD6: ='總表'!BC25 | AE6: ='總表'!AW25 | AF6: ='總表'!BR25 | AG6: ='總表'!BS25 | AH6: ='總表'!BT25 | AI6: ='總表'!BU25 | AJ6: ='總表'!BV25 | AK6: ='總表'!A25 | AL6: ='總表'!B25 | AM6: ='總表'!BW25
A7: 6 | B7: BJ | C7: ='總表'!D27 | D7: ='總表'!F27 | E7: ='總表'!G27 | F7: ='總表'!I27 | G7: ='總表'!H27 | H7: ='總表'!J27 | I7: ='總表'!L27 | J7: ='總表'!R27 | K7: ='總表'!S27 | L7: ='總表'!W27 | M7: ='總表'!X27 | N7: ='總表'!AA27 | O7: ='總表'!AB27 | P7: ='總表'!AD27 | Q7: ='總表'!U27 | R7: ='總表'!AE27 | S7: ='總表'!AI27 | T7: ='總表'!AJ27 | U7: ='總表'!AK27 | V7: ='總表'!AL27 | W7: ='總表'!AQ27 | X7: ='總表'!AS27 | Y7: ='總表'!BE27 | Z7: ='總表'!BH27 | AA7: ='總表'!BP27 | AB7: ='總表'!BA27 | AC7: ='總表'!BB27 | AD7: ='總表'!BC27 | AE7: ='總表'!AW27 | AF7: ='總表'!BR27 | AG7: ='總表'!BS27 | AH7: ='總表'!BT27 | AI7: ='總表'!BU27 | AJ7: ='總表'!BV27 | AK7: ='總表'!A27 | AL7: ='總表'!B27 | AM7: ='總表'!BW27
A8: 7 | B8: AIP | C8: ='總表'!D52 | D8: ='總表'!F52 | E8: ='總表'!G52 | F8: ='總表'!I52 | G8: ='總表'!H52 | H8: ='總表'!J52 | I8: ='總表'!L52 | J8: ='總表'!R52 | K8: ='總表'!S52 | L8: ='總表'!W52 | M8: ='總表'!X52 | N8: ='總表'!AA52 | O8: ='總表'!AB52 | P8: ='總表'!AD52 | Q8: ='總表'!U52 | R8: ='總表'!AE52 | S8: ='總表'!AI52 | T8: ='總表'!AJ52 | U8: ='總表'!AK52 | V8: ='總表'!AL52 | W8: ='總表'!AQ52 | X8: ='總表'!AS52 | Y8: ='總表'!BE52 | Z8: ='總表'!BH52 | AA8: ='總表'!BP52 | AB8: ='總表'!BA52 | AC8: ='總表'!BB52 | AD8: ='總表'!BC52 | AE8: ='總表'!AW52 | AF8: ='總表'!BR52 | AG8: ='總表'!BS52 | AH8: ='總表'!BT52 | AI8: ='總表'!BU52 | AJ8: ='總表'!BV52 | AK8: ='總表'!A52 | AL8: ='總表'!B52 | AM8: ='總表'!BW52
A9: 8 | B9: HWKN | C9: ='總表'!D54 | D9: ='總表'!F54 | E9: ='總表'!G54 | F9: ='總表'!I54 | G9: ='總表'!H54 | H9: ='總表'!J54 | I9: ='總表'!L54 | J9: ='總表'!R54 | K9: ='總表'!S54 | L9: ='總表'!W54 | M9: ='總表'!X54 | N9: ='總表'!AA54 | O9: ='總表'!AB54 | P9: ='總表'!AD54 | Q9: ='總表'!U54 | R9: ='總表'!AE54 | S9: ='總表'!AI54 | T9: ='總表'!AJ54 | U9: ='總表'!AK54 | V9: ='總表'!AL54 | W9: ='總表'!AQ54 | X9: ='總表'!AS54 | Y9: ='總表'!BE54 | Z9: ='總表'!BH54 | AA9: ='總表'!BP54 | AB9: ='總表'!BA54 | AC9: ='總表'!BB54 | AD9: ='總表'!BC54 | AE9: ='總表'!AW54 | AF9: ='總表'!BR54 | AG9: ='總表'!BS54 | AH9: ='總表'!BT54 | AI9: ='總表'!BU54 | AJ9: ='總表'!BV54 | AK9: ='總表'!A54 | AL9: ='總表'!B54 | AM9: ='總表'!BW54
A10: 9 | B10: FIX | C10: ='總表'!D55 | D10: ='總表'!F55 | E10: ='總表'!G55 | F10: ='總表'!I55 | G10: ='總表'!H55 | H10: ='總表'!J55 | I10: ='總表'!L55 | J10: ='總表'!R55 | K10: ='總表'!S55 | L10: ='總表'!W55 | M10: ='總表'!X55 | N10: ='總表'!AA55 | O10: ='總表'!AB55 | P10: ='總表'!AD55 | Q10: ='總表'!U55 | R10: ='總表'!AE55 | S10: ='總表'!AI55 | T10: ='總表'!AJ55 | U10: ='總表'!AK55 | V10: ='總表'!AL55 | W10: ='總表'!AQ55 | X10: ='總表'!AS55 | Y10: ='總表'!BE55 | Z10: ='總表'!BH55 | AA10: ='總表'!BP55 | AB10: ='總表'!BA55 | AC10: ='總表'!BB55 | AD10: ='總表'!BC55 | AE10: ='總表'!AW55 | AF10: ='總表'!BR55 | AG10: ='總表'!BS55 | AH10: ='總表'!BT55 | AI10: ='總表'!BU55 | AJ10: ='總表'!BV55 | AK10: ='總表'!A55 | AL10: ='總表'!B55 | AM10: ='總表'!BW55
A11: 10 | B11: NVTS | C11: ='總表'!D56 | D11: ='總表'!F56 | E11: ='總表'!G56 | F11: ='總表'!I56 | G11: ='總表'!H56 | H11: ='總表'!J56 | I11: ='總表'!L56 | J11: ='總表'!R56 | K11: ='總表'!S56 | L11: ='總表'!W56 | M11: ='總表'!X56 | N11: ='總表'!AA56 | O11: ='總表'!AB56 | P11: ='總表'!AD56 | Q11: ='總表'!U56 | R11: ='總表'!AE56 | S11: ='總表'!AI56 | T11: ='總表'!AJ56 | U11: ='總表'!AK56 | V11: ='總表'!AL56 | W11: ='總表'!AQ56 | X11: ='總表'!AS56 | Y11: ='總表'!BE56 | Z11: ='總表'!BH56 | AA11: ='總表'!BP56 | AB11: ='總表'!BA56 | AC11: ='總表'!BB56 | AD11: ='總表'!BC56 | AE11: ='總表'!AW56 | AF11: ='總表'!BR56 | AG11: ='總表'!BS56 | AH11: ='總表'!BT56 | AI11: ='總表'!BU56 | AJ11: ='總表'!BV56 | AK11: ='總表'!A56 | AL11: ='總表'!B56 | AM11: ='總表'!BW56
A12: 11 | B12: PCRX | C12: ='總表'!D57 | D12: ='總表'!F57 | E12: ='總表'!G57 | F12: ='總表'!I57 | G12: ='總表'!H57 | H12: ='總表'!J57 | I12: ='總表'!L57 | J12: ='總表'!R57 | K12: ='總表'!S57 | L12: ='總表'!W57 | M12: ='總表'!X57 | N12: ='總表'!AA57 | O12: ='總表'!AB57 | P12: ='總表'!AD57 | Q12: ='總表'!U57 | R12: ='總表'!AE57 | S12: ='總表'!AI57 | T12: ='總表'!AJ57 | U12: ='總表'!AK57 | V12: ='總表'!AL57 | W12: ='總表'!AQ57 | X12: ='總表'!AS57 | Y12: ='總表'!BE57 | Z12: ='總表'!BH57 | AA12: ='總表'!BP57 | AB12: ='總表'!BA57 | AC12: ='總表'!BB57 | AD12: ='總表'!BC57 | AE12: ='總表'!AW57 | AF12: ='總表'!BR57 | AG12: ='總表'!BS57 | AH12: ='總表'!BT57 | AI12: ='總表'!BU57 | AJ12: ='總表'!BV57 | AK12: ='總表'!A57 | AL12: ='總表'!B57 | AM12: ='總表'!BW57
A13: 12 | B13: GFS | C13: ='總表'!D59 | D13: ='總表'!F59 | E13: ='總表'!G59 | F13: ='總表'!I59 | G13: ='總表'!H59 | H13: ='總表'!J59 | I13: ='總表'!L59 | J13: ='總表'!R59 | K13: ='總表'!S59 | L13: ='總表'!W59 | M13: ='總表'!X59 | N13: ='總表'!AA59 | O13: ='總表'!AB59 | P13: ='總表'!AD59 | Q13: ='總表'!U59 | R13: ='總表'!AE59 | S13: ='總表'!AI59 | T13: ='總表'!AJ59 | U13: ='總表'!AK59 | V13: ='總表'!AL59 | W13: ='總表'!AQ59 | X13: ='總表'!AS59 | Y13: ='總表'!BE59 | Z13: ='總表'!BH59 | AA13: ='總表'!BP59 | AB13: ='總表'!BA59 | AC13: ='總表'!BB59 | AD13: ='總表'!BC59 | AE13: ='總表'!AW59 | AF13: ='總表'!BR59 | AG13: ='總表'!BS59 | AH13: ='總表'!BT59 | AI13: ='總表'!BU59 | AJ13: ='總表'!BV59 | AK13: ='總表'!A59 | AL13: ='總表'!B59 | AM13: ='總表'!BW59
A14: 13 | B14: LYTS | C14: ='總表'!D61 | D14: ='總表'!F61 | E14: ='總表'!G61 | F14: ='總表'!I61 | G14: ='總表'!H61 | H14: ='總表'!J61 | I14: ='總表'!L61 | J14: ='總表'!R61 | K14: ='總表'!S61 | L14: ='總表'!W61 | M14: ='總表'!X61 | N14: ='總表'!AA61 | O14: ='總表'!AB61 | P14: ='總表'!AD61 | Q14: ='總表'!U61 | R14: ='總表'!AE61 | S14: ='總表'!AI61 | T14: ='總表'!AJ61 | U14: ='總表'!AK61 | V14: ='總表'!AL61 | W14: ='總表'!AQ61 | X14: ='總表'!AS61 | Y14: ='總表'!BE61 | Z14: ='總表'!BH61 | AA14: ='總表'!BP61 | AB14: ='總表'!BA61 | AC14: ='總表'!BB61 | AD14: ='總表'!BC61 | AE14: ='總表'!AW61 | AF14: ='總表'!BR61 | AG14: ='總表'!BS61 | AH14: ='總表'!BT61 | AI14: ='總表'!BU61 | AJ14: ='總表'!BV61 | AK14: ='總表'!A61 | AL14: ='總表'!B61 | AM14: ='總表'!BW61
A15: 14 | B15: FLEX | C15: ='總表'!D62 | D15: ='總表'!F62 | E15: ='總表'!G62 | F15: ='總表'!I62 | G15: ='總表'!H62 | H15: ='總表'!J62 | I15: ='總表'!L62 | J15: ='總表'!R62 | K15: ='總表'!S62 | L15: ='總表'!W62 | M15: ='總表'!X62 | N15: ='總表'!AA62 | O15: ='總表'!AB62 | P15: ='總表'!AD62 | Q15: ='總表'!U62 | R15: ='總表'!AE62 | S15: ='總表'!AI62 | T15: ='總表'!AJ62 | U15: ='總表'!AK62 | V15: ='總表'!AL62 | W15: ='總表'!AQ62 | X15: ='總表'!AS62 | Y15: ='總表'!BE62 | Z15: ='總表'!BH62 | AA15: ='總表'!BP62 | AB15: ='總表'!BA62 | AC15: ='總表'!BB62 | AD15: ='總表'!BC62 | AE15: ='總表'!AW62 | AF15: ='總表'!BR62 | AG15: ='總表'!BS62 | AH15: ='總表'!BT62 | AI15: ='總表'!BU62 | AJ15: ='總表'!BV62 | AK15: ='總表'!A62 | AL15: ='總表'!B62 | AM15: ='總表'!BW62
A16: 15 | B16: MAZE | C16: ='總表'!D100 | D16: ='總表'!F100 | E16: ='總表'!G100 | F16: ='總表'!I100 | G16: ='總表'!H100 | H16: ='總表'!J100 | I16: ='總表'!L100 | J16: ='總表'!R100 | K16: ='總表'!S100 | L16: ='總表'!W100 | M16: ='總表'!X100 | N16: ='總表'!AA100 | O16: ='總表'!AB100 | P16: ='總表'!AD100 | Q16: ='總表'!U100 | R16: ='總表'!AE100 | S16: ='總表'!AI100 | T16: ='總表'!AJ100 | U16: ='總表'!AK100 | V16: ='總表'!AL100 | W16: ='總表'!AQ100 | X16: ='總表'!AS100 | Y16: ='總表'!BE100 | Z16: ='總表'!BH100 | AA16: ='總表'!BP100 | AB16: ='總表'!BA100 | AC16: ='總表'!BB100 | AD16: ='總表'!BC100 | AE16: ='總表'!AW100 | AF16: ='總表'!BR100 | AG16: ='總表'!BS100 | AH16: ='總表'!BT100 | AI16: ='總表'!BU100 | AJ16: ='總表'!BV100 | AK16: ='總表'!A100 | AL16: ='總表'!B100 | AM16: ='總表'!BW100
A17: 16 | B17: M | C17: ='總表'!D107 | D17: ='總表'!F107 | E17: ='總表'!G107 | F17: ='總表'!I107 | G17: ='總表'!H107 | H17: ='總表'!J107 | I17: ='總表'!L107 | J17: ='總表'!R107 | K17: ='總表'!S107 | L17: ='總表'!W107 | M17: ='總表'!X107 | N17: ='總表'!AA107 | O17: ='總表'!AB107 | P17: ='總表'!AD107 | Q17: ='總表'!U107 | R17: ='總表'!AE107 | S17: ='總表'!AI107 | T17: ='總表'!AJ107 | U17: ='總表'!AK107 | V17: ='總表'!AL107 | W17: ='總表'!AQ107 | X17: ='總表'!AS107 | Y17: ='總表'!BE107 | Z17: ='總表'!BH107 | AA17: ='總表'!BP107 | AB17: ='總表'!BA107 | AC17: ='總表'!BB107 | AD17: ='總表'!BC107 | AE17: ='總表'!AW107 | AF17: ='總表'!BR107 | AG17: ='總表'!BS107 | AH17: ='總表'!BT107 | AI17: ='總表'!BU107 | AJ17: ='總表'!BV107 | AK17: ='總表'!A107 | AL17: ='總表'!B107 | AM17: ='總表'!BW107
